Workbook

Sheet Lisez_moi
A1: CAPEX e-fuels — données et dimensionnement (Sherpa Engineering, prototype Maroc)
A2: Fichier compagnon de efuels_maroc_base_donnees.xlsx — mêmes hypothèses par défaut.
A4: Élément | B4: Description
A5: Objet | B5: Données de CAPEX (électrolyseurs, synthèse, captage CO2) tirées de l'article [ART] et dimensionnement budgétaire d'une usine e-fuel au Maroc (électrolyse, synthèse, CO2, ENR équivalente, eau).
A6: Format | B6: Livré en .xlsx. Le format .xlsb (binaire Excel) ne peut pas être généré ici : ouvrir le fichier dans Excel puis Fichier > Enregistrer sous > « Classeur Excel binaire (*.xlsb) » (même contenu, formules conservées).
A7: Source [ART] | B7: Colelli et al. (2026), Energy Conversion and Management, doi:10.1016/j.enconman.2025.120529 (Table 4, Table 2, §4.4, Table 5, §2.4).
A8: [HYP] | B8: Hypothèse Sherpa non issue de l'article (fond jaune) : facteur de localisation Maroc, coûts indirects, imprévus, CAPEX FT, CAPEX ENR, part capitalistique du captage CO2. À valider par devis.
A9: Code couleur | B9: Bleu = entrée modifiable · noir = formule · vert = lien inter-feuilles · fond jaune = hypothèse clé.
A10: Portée | B10: Estimation de classe 5 (ordre de grandeur, ±30–50 %). Exclut : terrain, raccordement réseau, stockage H2/batteries, transport/stockage du produit, financement intercalaire, taxes.
A11: Feuilles | B11: Parametres · Capex_Electrolyseurs · Capex_Synthese · Cout_CO2 · Benchmarks_Projets · Dimensionnement · Scenarios_CAPEX · Sources
A12: Utilisation | B12: 1) Régler Parametres (technologie, heures, WACC, facteur Maroc, tonnage cible). 2) Lire Dimensionnement (6 produits à la même capacité). 3) Tester Scenarios_CAPEX. 4) Comparer aux Benchmarks_Projets.

Sheet Parametres
A1: Paramètres généraux de dimensionnement
A2: Bleu = entrée · jaune = hypothèse clé à valider · noir = formule.
A5: Paramètre | B5: Valeur | C5: Unité | D5: Source / note
A6: Technologie d'électrolyse | B6: PEM | C6: AEL / PEM / SOEC | D6: [ART] PEM = la plus utilisée dans les projets
A7: Heures pleine charge électrolyseur | B7: 5000 | C7: h/an | D7: [HYP] article : 3 000–4 000 h/an typiques ; sites Maroc à valider
A8: WACC | B8: 0.08 | C8: % | D8: [HYP] plage 6–12 %
A9: Durée de vie / amortissement | B9: 20 | C9: ans | D9: [HYP]
A10: Facteur de recouvrement du capital (CRF) | B10: =IF(B8=0,1/B9,B8*(1+B8)^B9/((1+B8)^B9-1)) -> 0.10185221 | C10: 1/an | D10: [CALC]
A11: Taux de change €/USD | B11: 0.92 | C11: € par $ | D11: [HYP]
A12: Horizon CAPEX synthèse | B12: Proche terme | C12: Proche terme / Long terme | D12: [ART] Brynolf [100], Lester [248]
A13: Facteur de localisation CAPEX (Maroc vs Europe) | B13: 1 | C13: x | D13: [HYP] 1,0 = niveau Europe/article ; benchmark Chine suggère < 1 (voir Benchmarks_Projets) ; plage 0,5–1,2
A14: Coûts indirects (ingénierie, EPC, propriétaire) | B14: 0.2 | C14: % du direct | D14: [HYP]
A15: Imprévus | B15: 0.15 | C15: % (direct + indirect) | D15: [HYP]
A16: Taux d'utilisation de l'unité de synthèse | B16: 0.9 | C16: % | D16: [HYP]
A17: Rendement matière | B17: 0.95 | C17: % | D17: [HYP]
A18: Densité H2 | B18: 0.08988 | C18: kg/Nm³ | D18: Constante physique
A19: Part capitalistique du coût de captage CO2 | B19: 0.6 | C19: % | D19: [HYP] sert à déduire un CAPEX implicite du coût $/t de l'article
A20: Type de source de CO2 | B20: Point source | C20: Point source / DAC | D20: [ART] Table 2
A21: CAPEX PV | B21: 650 | C21: €/kW | D21: [HYP] hors article
A22: CAPEX éolien terrestre | B22: 1300 | C22: €/kW | D22: [HYP] hors article
A23: Part PV dans la capacité ENR hybride | B23: 0.5 | C23: % | D23: [HYP]
A24: Facteur de charge PV | B24: 0.3 | C24: % | D24: [HYP] Maroc sud, ordre de grandeur
A25: Facteur de charge éolien | B25: 0.45 | C25: % | D25: [HYP] côte atlantique sud, ordre de grandeur
A26: CAPEX ENR hybride (moyenne pondérée) | B26: =B23*B21+(1-B23)*B22 -> 975 | C26: €/kW | D26: [CALC]
A27: Facteur de charge ENR hybride (moyenne pondérée) | B27: =B23*B24+(1-B23)*B25 -> 0.375 | C27: % | D27: [CALC]
A28: Eau stœchiométrique électrolyse | B28: 8.92 | C28: L/kg H2 | D28: [ART] §3.4
A29: Surconsommation d'eau | B29: 0.25 | C29: % | D29: [ART] §3.4
A30: Production annuelle cible | B30: 100000 | C30: t/an | D30: Entrée — même tonnage pour les 6 produits
A31: Produit sélectionné (interface modules) | B31: e-methanol | C31: — | D31: Sert au bloc « Interface » et aux scénarios
A32: Masse molaire H2 | B32: 2.016 | C32: g/mol | D32: Constante
A33: Masse molaire CO2 | B33: 44.01 | C33: g/mol | D33: Constante
A34: Masse molaire N2 | B34: 28.014 | C34: g/mol | D34: Constante
A35: Masse molaire méthanol | B35: 32.04 | C35: g/mol | D35: Constante
A36: Masse molaire DME | B36: 46.07 | C36: g/mol | D36: Constante
A37: Masse molaire NH3 | B37: 17.031 | C37: g/mol | D37: Constante
A38: Masse molaire CH2 (hydrocarbures) | B38: 14.027 | C38: g/mol | D38: Constante (approximation (CH2)n)
A39: CAPEX électrolyseur retenu | B39: =INDEX(Capex_Electrolyseurs!$D$6:$D$8,MATCH(B6,Capex_Electrolyseurs!$A$6:$A$8,0)) -> 1750 | C39: €/kW | D39: [CALC] milieu de fourchette (Table 4)
A40: Consommation électrolyseur retenue | B40: =INDEX(Capex_Electrolyseurs!$G$6:$G$8,MATCH(B6,Capex_Electrolyseurs!$A$6:$A$8,0)) -> 58.967512 | C40: kWh/kg H2 | D40: [CALC] (article : 45–73 kWh/kg)
A41: Eau réelle par kg H2 | B41: =B28*(1+B29) -> 11.15 | C41: L/kg H2 | D41: [CALC]

Sheet Capex_Electrolyseurs
A1: CAPEX et paramètres des électrolyseurs
A2: [ART] Table 4 (réfs [184]–[188]). Bleu = valeur de l'article ; jaune = [HYP].
A5: Technologie | B5: CAPEX min (€/kW) | C5: CAPEX max (€/kW) | D5: CAPEX base (€/kW) | E5: kWh/Nm³ min | F5: kWh/Nm³ max | G5: kWh/kg H2 base | H5: OPEX base (%/an) | I5: Vie min (kh) | J5: Vie max (kh) | K5: Vie min (ans à FLH) | L5: Vie max (ans à FLH) | M5: Note
A6: AEL | B6: 800 | C6: 1500 | D6: =AVERAGE(B6:C6) -> 1150 | E6: 5 | F6: 5.9 | G6: =AVERAGE(E6:F6)/Parametres!$B$18 -> 60.636404 | H6: =AVERAGE(2,3)/100 -> 0.025 | I6: 55 | J6: 120 | K6: =I6*1000/Parametres!$B$7 -> 11 | L6: =J6*1000/Parametres!$B$7 -> 24 | M6: [ART]
A7: PEM | B7: 1400 | C7: 2100 | D7: =AVERAGE(B7:C7) -> 1750 | E7: 5 | F7: 5.6 | G7: =AVERAGE(E7:F7)/Parametres!$B$18 -> 58.967512 | H7: =AVERAGE(3,5)/100 -> 0.04 | I7: 60 | J7: 100 | K7: =I7*1000/Parametres!$B$7 -> 12 | L7: =J7*1000/Parametres!$B$7 -> 20 | M7: [ART]
A8: SOEC | B8: 2000 | C8: 2500 | D8: =AVERAGE(B8:C8) -> 2250 | E8: 3.7 | F8: 3.9 | G8: =AVERAGE(E8:F8)/Parametres!$B$18 -> 42.278594 | H8: =AVERAGE(3,5)/100 -> 0.04 | I8: 8 | J8: 20 | K8: =I8*1000/Parametres!$B$7 -> 1.6 | L8: =J8*1000/Parametres!$B$7 -> 4 | M8: CAPEX max 2 500 et OPEX 3–5 % = [HYP] ; hors coût de la vapeur ; durée de vie très courte
A10: Le remplacement des stacks dépend des heures de fonctionnement : à 5 000 h/an, un SOEC (8–20 kh) doit être remplacé tous les 1,6 à 4 ans → CAPEX de remplacement à ajouter dans une étude détaillée.
A11: Les OPEX (2–3 % AEL, 3–5 % PEM) sont exprimés en % du CAPEX par an (article).

Sheet Capex_Synthese
A1: CAPEX de l'unité de conversion (synthèse) et données produits
A2: CAPEX en €/kW_fuel (puissance PCI du produit). [ART] §4.4 ; CAPEX FT = [HYP]. Stœchiométrie par formules.
A5: Produit | B5: PCI (MJ/kg) | C5: H2 (t/t) | D5: CO2 (t/t) | E5: N2 (t/t) | F5: Proche terme min | G5: Proche terme max | H5: Proche terme base | I5: Long terme min | J5: Long terme max | K5: Long terme base | L5: CAPEX retenu (€/kW_fuel) | M5: Baisse long terme | N5: Source / note
A6: e-methanol | B6: 19.9 | C6: =3*Parametres!$B$32/Parametres!$B$35/Parametres!$B$17 -> 0.19869899 | D6: =Parametres!$B$33/Parametres!$B$35/Parametres!$B$17 -> 1.44589 | E6: 0 | F6: 300 | G6: 1200 | H6: =AVERAGE(F6:G6) -> 750 | I6: 200 | J6: 650 | K6: =IFERROR(AVERAGE(I6:J6),H6) -> 425 | L6: =IF(Parametres!$B$12="Long terme",K6,H6) -> 750 | M6: =IFERROR(1-K6/H6,"n.d.") -> 0.43333333 | N6: [ART] §4.4.3 (réfs [100],[247],[248],[258])
A7: e-DME | B7: 28.4 | C7: =6*Parametres!$B$32/Parametres!$B$36/Parametres!$B$17 -> 0.27637577 | D7: =2*Parametres!$B$33/Parametres!$B$36/Parametres!$B$17 -> 2.0111272 | E7: 0 | F7: 300 | G7: 1200 | H7: =AVERAGE(F7:G7) -> 750 | I7: 200 | J7: 650 | K7: =IFERROR(AVERAGE(I7:J7),H7) -> 425 | L7: =IF(Parametres!$B$12="Long terme",K7,H7) -> 750 | M7: =IFERROR(1-K7/H7,"n.d.") -> 0.43333333 | N7: [ART] §4.4.4
A8: e-kerosene | B8: 43.1 | C8: =3*Parametres!$B$32/Parametres!$B$38/Parametres!$B$17 -> 0.45386154 | D8: =Parametres!$B$33/Parametres!$B$38/Parametres!$B$17 -> 3.3026532 | E8: 0 | F8: 1000 | G8: 1800 | H8: =AVERAGE(F8:G8) -> 1400 | I8: n.d. | J8: n.d. | K8: =IFERROR(AVERAGE(I8:J8),H8) -> 1400 | L8: =IF(Parametres!$B$12="Long terme",K8,H8) -> 1400 | M8: =IFERROR(1-K8/H8,"n.d.") -> 0 | N8: CAPEX FT = [HYP] (non chiffré dans l'article) ; mélange d'hydrocarbures
A9: e-diesel | B9: 43 | C9: =3*Parametres!$B$32/Parametres!$B$38/Parametres!$B$17 -> 0.45386154 | D9: =Parametres!$B$33/Parametres!$B$38/Parametres!$B$17 -> 3.3026532 | E9: 0 | F9: 1000 | G9: 1800 | H9: =AVERAGE(F9:G9) -> 1400 | I9: n.d. | J9: n.d. | K9: =IFERROR(AVERAGE(I9:J9),H9) -> 1400 | L9: =IF(Parametres!$B$12="Long terme",K9,H9) -> 1400 | M9: =IFERROR(1-K9/H9,"n.d.") -> 0 | N9: idem e-kérosène
A10: e-gasoline | B10: 43.4 | C10: =3*Parametres!$B$32/Parametres!$B$38/Parametres!$B$17 -> 0.45386154 | D10: =Parametres!$B$33/Parametres!$B$38/Parametres!$B$17 -> 3.3026532 | E10: 0 | F10: 600 | G10: 600 | H10: =AVERAGE(F10:G10) -> 600 | I10: 250 | J10: 370 | K10: =IFERROR(AVERAGE(I10:J10),H10) -> 310 | L10: =IF(Parametres!$B$12="Long terme",K10,H10) -> 600 | M10: =IFERROR(1-K10/H10,"n.d.") -> 0.48333333 | N10: [ART] §4.4.5 (MTG)
A11: e-ammonia | B11: 18.6 | C11: =3*Parametres!$B$32/(2*Parametres!$B$37)/Parametres!$B$17 -> 0.18690376 | D11: 0 | E11: =Parametres!$B$34/(2*Parametres!$B$37)/Parametres!$B$17 -> 0.86572782 | F11: 1300 | G11: 2200 | H11: =AVERAGE(F11:G11) -> 1750 | I11: 580 | J11: 1100 | K11: =IFERROR(AVERAGE(I11:J11),H11) -> 840 | L11: =IF(Parametres!$B$12="Long terme",K11,H11) -> 1750 | M11: =IFERROR(1-K11/H11,"n.d.") -> 0.52 | N11: [ART] §4.4.6 ; ASU N2 supposé inclus
A12: Si le CAPEX long terme est « n.d. » (voie FT), le calcul reprend le CAPEX proche terme. Les CAPEX sont ceux de la conversion ; électrolyse et captage CO2 sont chiffrés séparément.

Sheet Cout_CO2
A1: Coût du captage de CO2 et CAPEX implicite
A2: [ART] Table 2 (réfs [163]–[167]) et Table 3 (TRL). CAPEX implicite = part capitalistique × coût / CRF [HYP].
A5: Méthode | B5: Coût min ($/t) | C5: Coût max ($/t) | D5: TRL | E5: Coût moyen (€/t) | F5: CAPEX implicite (€ par t/an) | G5: Type
A6: Absorption chimique (amines) | B6: 50 | C6: 100 | D6: 9 | E6: =AVERAGE(B6:C6)*Parametres!$B$11 -> 69 | F6: =Parametres!$B$19*E6/Parametres!$B$10 -> 406.4713 | G6: Point source
A7: Adsorption physique (PSA/TSA…) | B7: 30 | C7: 80 | D7: 7 | E7: =AVERAGE(B7:C7)*Parametres!$B$11 -> 50.6 | F7: =Parametres!$B$19*E7/Parametres!$B$10 -> 298.07896 | G7: Point source
A8: Séparation membranaire | B8: 60 | C8: 120 | D8: 6 | E8: =AVERAGE(B8:C8)*Parametres!$B$11 -> 82.8 | F8: =Parametres!$B$19*E8/Parametres!$B$10 -> 487.76556 | G8: Point source
A9: Captage cryogénique | B9: 70 | C9: 150 | D9: 5 | E9: =AVERAGE(B9:C9)*Parametres!$B$11 -> 101.2 | F9: =Parametres!$B$19*E9/Parametres!$B$10 -> 596.15791 | G9: Point source
A10: Direct Air Capture (DAC) | B10: 235 | C10: 600 | D10: 5 | E10: =AVERAGE(B10:C10)*Parametres!$B$11 -> 384.1 | F10: =Parametres!$B$19*E10/Parametres!$B$10 -> 2262.6903 | G10: DAC
A12: Coût retenu (type de source choisi) | E12: =IF(Parametres!$B$20="DAC",E10,E6) -> 69 | F12: =IF(Parametres!$B$20="DAC",F10,F6) -> 406.4713
A13: Point source = absorption chimique (référence mature, ligne 6). Le CAPEX implicite est une approximation pour budgéter ; remplacer par devis fournisseur.
A14: Le coût DAC ne descend pas sous ~235 $/t dans l'article ; 100–150 $/t seulement avec incitations fortes.

Sheet Benchmarks_Projets
A1: Benchmarks de projets — intensités de CAPEX et d'électrolyse
A2: Données [ART] Table 5 et §2.4 ; réfs [76], [287], [288], [289] (titres/communiqués cités). Calculs = formules.
A5: Projet | B5: Produit | C5: Électrolyse (MW) | D5: Capacité (kt/an) | E5: CAPEX / subvention (M) | F5: Devise | G5: Nature du montant | H5: MW par kt/an | I5: CAPEX par t/an (devise) | J5: MW/kt théorique (modèle) | K5: Écart modèle vs projet | L5: Source / note
A6: Shanxi Intl. Energy (Mongolie int.) | B6: e-kerosene | C6: 1000 | D6: 350 | E6: 1480 | F6: USD | G6: CAPEX annoncé (10,7 Md¥ ≈ 1,48 Md$) | H6: =IFERROR(C6/D6,"n.d.") -> 2.8571429 | I6: =IFERROR(E6*1000000/(D6*1000),"n.d.") -> 4228.5714 | J6: =Capex_Synthese!C8*1000000*Parametres!$B$40/$B$13/1000 -> 3.3453857 | K6: =IFERROR(J6/H6-1,"n.d.") -> 0.170885 | L6: [ART] §2.4 réf. [76] ; périmètre à vérifier (ENR incluse ?)
A7: Texas E-Fuels (HIF) | B7: e-gasoline | C7: 1800 | D7: 630 | E7: n.d. | F7: — | G7: CAPEX n.d. | H7: =IFERROR(C7/D7,"n.d.") -> 2.8571429 | I7: =IFERROR(E7*1000000/(D7*1000),"n.d.") -> n.d. | J7: =Capex_Synthese!C10*1000000*Parametres!$B$40/$B$13/1000 -> 3.3453857 | K7: =IFERROR(J7/H7-1,"n.d.") -> 0.170885 | L7: [ART] Table 5 ; réf. [287] « 1,8 GW » H2
A8: Arcadia eFuels | B8: e-kerosene | C8: 280 | D8: 85 | E8: n.d. | F8: — | G8: CAPEX n.d. | H8: =IFERROR(C8/D8,"n.d.") -> 3.2941176 | I8: =IFERROR(E8*1000000/(D8*1000),"n.d.") -> n.d. | J8: =Capex_Synthese!C8*1000000*Parametres!$B$40/$B$13/1000 -> 3.3453857 | K8: =IFERROR(J8/H8-1,"n.d.") -> 0.015563523 | L8: [ART] Table 5 ; réf. [288] électrolyseur 280 MW (Plug Power)
A9: Herøya SAF (Nordic Electrofuel) | B9: e-kerosene | C9: n.d. | D9: 8 | E9: 40 | F9: EUR | G9: Subvention EU Innovation Fund (pas le CAPEX) | H9: =IFERROR(C9/D9,"n.d.") -> n.d. | I9: =IFERROR(E9*1000000/(D9*1000),"n.d.") -> 5000 | J9: =Capex_Synthese!C8*1000000*Parametres!$B$40/$B$13/1000 -> 3.3453857 | K9: =IFERROR(J9/H9-1,"n.d.") -> n.d. | L9: [ART] réf. [289] ; ne pas assimiler à un CAPEX
A13: Heures de fonctionnement pour le calcul théorique (h/an) | B13: 8000
A14: MW/kt théorique = intensité H2 × kWh/kg ÷ heures. Un projet qui annonce moins de MW par kt/an fonctionne probablement avec plus d'heures ou un rendement meilleur. Ici les trois projets sont à 2,9–3,3 MW par kt/an.
A16: Comparaison avec le modèle (e-kérosène)
A17: CAPEX total modèle e-kérosène (M€ par kt/an) | B17: =INDEX(Dimensionnement!$P$9:$P$14,3) -> 17.712961
A18: CAPEX Shanxi (M€ par kt/an) à partir de M$ | B18: =E6/D6*Parametres!$B$11 -> 3.8902857
A19: Rapport modèle / Shanxi | B19: =B17/B18 -> 4.553126
A20: Le CAPEX annoncé en Chine est plusieurs fois inférieur au modèle (basé sur coûts de l'article, niveau européen) : le périmètre (ENR incluse ou non, électrolyse chinoise) est à vérifier. Utiliser le facteur de localisation (Parametres) pour tester des niveaux de coût plus bas (ex. 0,4–0,6).

Sheet Dimensionnement
A1: Dimensionnement et CAPEX — 6 e-fuels à la même capacité
A2: Entrées : feuille Parametres (tonnage cible, technologie, WACC, facteur Maroc…). ENR équivalente simplifiée (sans stockage ni écrêtage).
A4: Production annuelle cible (t/an) | B4: =Parametres!$B$30 -> 100000
A5: Électrolyseur / heures / facteur Maroc | B5: =Parametres!$B$6 -> PEM | C5: =Parametres!$B$7 -> 5000 | D5: =Parametres!$B$13 -> 1
A8: Produit | B8: Production (t/an) | C8: H2 (t/an) | D8: CO2 (t/an) | E8: N2 (t/an) | F8: Électrolyseur (MW) | G8: Électricité (GWh/an) | H8: Eau (m³/an) | I8: CAPEX électrolyseur (M€) | J8: CAPEX synthèse (M€) | K8: CAPEX captage CO2 (M€) | L8: CAPEX direct (M€) | M8: Indirects (M€) | N8: Imprévus (M€) | O8: CAPEX TOTAL (M€) | P8: CAPEX par kt/an (M€) | Q8: Capacité ENR éq. (MW) | R8: CAPEX ENR (M€) | S8: CAPEX TOTAL + ENR (M€) | T8: Annuité CAPEX hors ENR (M€/an)
A9: =Capex_Synthese!A6 -> e-methanol | B9: =$B$4 -> 100000 | C9: =B9*Capex_Synthese!C6 -> 19869.899 | D9: =B9*Capex_Synthese!D6 -> 144589 | E9: =B9*Capex_Synthese!E6 -> 0 | F9: =C9*1000*Parametres!$B$40/Parametres!$B$7/1000 -> 234.33571 | G9: =C9*1000*Parametres!$B$40/1000000 -> 1171.6785 | H9: =C9*1000*Parametres!$B$41/1000 -> 221549.38 | I9: =F9*1000*Parametres!$B$39*Parametres!$B$13/1000000 -> 410.08749 | J9: =(B9*Capex_Synthese!B6*1000/3.6/8760/Parametres!$B$16)*Capex_Synthese!L6*Parametres!$B$13/1000000 -> 52.585405 | K9: =D9*Cout_CO2!$F$12*Parametres!$B$13/1000000 -> 58.771279 | L9: =I9+J9+K9 -> 521.44417 | M9: =L9*Parametres!$B$14 -> 104.28883 | N9: =(L9+M9)*Parametres!$B$15 -> 93.859951 | O9: =L9+M9+N9 -> 719.59296 | P9: =O9/(B9/1000) -> 7.1959296 | Q9: =G9*1000/(Parametres!$B$27*8760) -> 356.67535 | R9: =Q9*1000*Parametres!$B$26/1000000 -> 347.75847 | S9: =O9+R9 -> 1067.3514 | T9: =O9*Parametres!$B$10 -> 73.292132
A10: =Capex_Synthese!A7 -> e-DME | B10: =$B$4 -> 100000 | C10: =B10*Capex_Synthese!C7 -> 27637.577 | D10: =B10*Capex_Synthese!D7 -> 201112.72 | E10: =B10*Capex_Synthese!E7 -> 0 | F10: =C10*1000*Parametres!$B$40/Parametres!$B$7/1000 -> 325.94383 | G10: =C10*1000*Parametres!$B$40/1000000 -> 1629.7191 | H10: =C10*1000*Parametres!$B$41/1000 -> 308158.98 | I10: =F10*1000*Parametres!$B$39*Parametres!$B$13/1000000 -> 570.4017 | J10: =(B10*Capex_Synthese!B7*1000/3.6/8760/Parametres!$B$16)*Capex_Synthese!L7*Parametres!$B$13/1000000 -> 75.046508 | K10: =D10*Cout_CO2!$F$12*Parametres!$B$13/1000000 -> 81.746551 | L10: =I10+J10+K10 -> 727.19476 | M10: =L10*Parametres!$B$14 -> 145.43895 | N10: =(L10+M10)*Parametres!$B$15 -> 130.89506 | O10: =L10+M10+N10 -> 1003.5288 | P10: =O10/(B10/1000) -> 10.035288 | Q10: =G10*1000/(Parametres!$B$27*8760) -> 496.10933 | R10: =Q10*1000*Parametres!$B$26/1000000 -> 483.70659 | S10: =O10+R10 -> 1487.2354 | T10: =O10*Parametres!$B$10 -> 102.21162
A11: =Capex_Synthese!A8 -> e-kerosene | B11: =$B$4 -> 100000 | C11: =B11*Capex_Synthese!C8 -> 45386.154 | D11: =B11*Capex_Synthese!D8 -> 330265.32 | E11: =B11*Capex_Synthese!E8 -> 0 | F11: =C11*1000*Parametres!$B$40/Parametres!$B$7/1000 -> 535.26172 | G11: =C11*1000*Parametres!$B$40/1000000 -> 2676.3086 | H11: =C11*1000*Parametres!$B$41/1000 -> 506055.61 | I11: =F11*1000*Parametres!$B$39*Parametres!$B$13/1000000 -> 936.708 | J11: =(B11*Capex_Synthese!B8*1000/3.6/8760/Parametres!$B$16)*Capex_Synthese!L8*Parametres!$B$13/1000000 -> 212.59654 | K11: =D11*Cout_CO2!$F$12*Parametres!$B$13/1000000 -> 134.24337 | L11: =I11+J11+K11 -> 1283.5479 | M11: =L11*Parametres!$B$14 -> 256.70958 | N11: =(L11+M11)*Parametres!$B$15 -> 231.03862 | O11: =L11+M11+N11 -> 1771.2961 | P11: =O11/(B11/1000) -> 17.712961 | Q11: =G11*1000/(Parametres!$B$27*8760) -> 814.70581 | R11: =Q11*1000*Parametres!$B$26/1000000 -> 794.33816 | S11: =O11+R11 -> 2565.6343 | T11: =O11*Parametres!$B$10 -> 180.41042
A12: =Capex_Synthese!A9 -> e-diesel | B12: =$B$4 -> 100000 | C12: =B12*Capex_Synthese!C9 -> 45386.154 | D12: =B12*Capex_Synthese!D9 -> 330265.32 | E12: =B12*Capex_Synthese!E9 -> 0 | F12: =C12*1000*Parametres!$B$40/Parametres!$B$7/1000 -> 535.26172 | G12: =C12*1000*Parametres!$B$40/1000000 -> 2676.3086 | H12: =C12*1000*Parametres!$B$41/1000 -> 506055.61 | I12: =F12*1000*Parametres!$B$39*Parametres!$B$13/1000000 -> 936.708 | J12: =(B12*Capex_Synthese!B9*1000/3.6/8760/Parametres!$B$16)*Capex_Synthese!L9*Parametres!$B$13/1000000 -> 212.10328 | K12: =D12*Cout_CO2!$F$12*Parametres!$B$13/1000000 -> 134.24337 | L12: =I12+J12+K12 -> 1283.0547 | M12: =L12*Parametres!$B$14 -> 256.61093 | N12: =(L12+M12)*Parametres!$B$15 -> 230.94984 | O12: =L12+M12+N12 -> 1770.6154 | P12: =O12/(B12/1000) -> 17.706154 | Q12: =G12*1000/(Parametres!$B$27*8760) -> 814.70581 | R12: =Q12*1000*Parametres!$B$26/1000000 -> 794.33816 | S12: =O12+R12 -> 2564.9536 | T12: =O12*Parametres!$B$10 -> 180.34109
A13: =Capex_Synthese!A10 -> e-gasoline | B13: =$B$4 -> 100000 | C13: =B13*Capex_Synthese!C10 -> 45386.154 | D13: =B13*Capex_Synthese!D10 -> 330265.32 | E13: =B13*Capex_Synthese!E10 -> 0 | F13: =C13*1000*Parametres!$B$40/Parametres!$B$7/1000 -> 535.26172 | G13: =C13*1000*Parametres!$B$40/1000000 -> 2676.3086 | H13: =C13*1000*Parametres!$B$41/1000 -> 506055.61 | I13: =F13*1000*Parametres!$B$39*Parametres!$B$13/1000000 -> 936.708 | J13: =(B13*Capex_Synthese!B10*1000/3.6/8760/Parametres!$B$16)*Capex_Synthese!L10*Parametres!$B$13/1000000 -> 91.746998 | K13: =D13*Cout_CO2!$F$12*Parametres!$B$13/1000000 -> 134.24337 | L13: =I13+J13+K13 -> 1162.6984 | M13: =L13*Parametres!$B$14 -> 232.53967 | N13: =(L13+M13)*Parametres!$B$15 -> 209.28571 | O13: =L13+M13+N13 -> 1604.5238 | P13: =O13/(B13/1000) -> 16.045238 | Q13: =G13*1000/(Parametres!$B$27*8760) -> 814.70581 | R13: =Q13*1000*Parametres!$B$26/1000000 -> 794.33816 | S13: =O13+R13 -> 2398.8619 | T13: =O13*Parametres!$B$10 -> 163.42429
A14: =Capex_Synthese!A11 -> e-ammonia | B14: =$B$4 -> 100000 | C14: =B14*Capex_Synthese!C11 -> 18690.376 | D14: =B14*Capex_Synthese!D11 -> 0 | E14: =B14*Capex_Synthese!E11 -> 86572.782 | F14: =C14*1000*Parametres!$B$40/Parametres!$B$7/1000 -> 220.42499 | G14: =C14*1000*Parametres!$B$40/1000000 -> 1102.125 | H14: =C14*1000*Parametres!$B$41/1000 -> 208397.69 | I14: =F14*1000*Parametres!$B$39*Parametres!$B$13/1000000 -> 385.74374 | J14: =(B14*Capex_Synthese!B11*1000/3.6/8760/Parametres!$B$16)*Capex_Synthese!L11*Parametres!$B$13/1000000 -> 114.68375 | K14: =D14*Cout_CO2!$F$12*Parametres!$B$13/1000000 -> 0 | L14: =I14+J14+K14 -> 500.42748 | M14: =L14*Parametres!$B$14 -> 100.0855 | N14: =(L14+M14)*Parametres!$B$15 -> 90.076947 | O14: =L14+M14+N14 -> 690.58993 | P14: =O14/(B14/1000) -> 6.9058993 | Q14: =G14*1000/(Parametres!$B$27*8760) -> 335.50227 | R14: =Q14*1000*Parametres!$B$26/1000000 -> 327.11471 | S14: =O14+R14 -> 1017.7046 | T14: =O14*Parametres!$B$10 -> 70.33811
A15: Électricité = électrolyse seule (l'énergie de synthèse et de captage s'ajoute : +2 à +4 % pour les voies FT/méthanol point source, plus pour le DAC). Les colonnes CAPEX sont en M€.
A16: Le CAPEX de synthèse et de captage est multiplié par le facteur de localisation ; l'ENR est calculée sans écrêtage ni stockage (à remplacer par une simulation horaire).
A18: Interface vers les autres modules du prototype (produit sélectionné dans Parametres)
A19: Produit sélectionné | B19: =Parametres!$B$31 -> e-methanol
A20: Hydrogène à produire | B20: =INDEX($C$9:$C$14,MATCH($B$19,$A$9:$A$14,0))/365 -> 54.438081 | C20: t/jour
A21: CO2 à fournir | B21: =INDEX($D$9:$D$14,MATCH($B$19,$A$9:$A$14,0))/365 -> 396.13425 | C21: t/jour
A22: Azote | B22: =INDEX($E$9:$E$14,MATCH($B$19,$A$9:$A$14,0))/365 -> 0 | C22: t/jour
A23: Puissance électrolyseur | B23: =INDEX($F$9:$F$14,MATCH($B$19,$A$9:$A$14,0)) -> 234.33571 | C23: MW
A24: Charge électrique moyenne (électrolyse) | B24: =INDEX($G$9:$G$14,MATCH($B$19,$A$9:$A$14,0))/8.76 -> 133.75326 | C24: MW
A25: Capacité ENR équivalente (PV+éolien) | B25: =INDEX($Q$9:$Q$14,MATCH($B$19,$A$9:$A$14,0)) -> 356.67535 | C25: MW
A26: Eau dessalée à fournir | B26: =INDEX($H$9:$H$14,MATCH($B$19,$A$9:$A$14,0))/365 -> 606.9846 | C26: m³/jour
A27: CAPEX total hors ENR | B27: =INDEX($O$9:$O$14,MATCH($B$19,$A$9:$A$14,0)) -> 719.59296 | C27: M€
A28: CAPEX total avec ENR | B28: =INDEX($S$9:$S$14,MATCH($B$19,$A$9:$A$14,0)) -> 1067.3514 | C28: M€
A29: CAPEX par kt/an (hors ENR) | B29: =INDEX($P$9:$P$14,MATCH($B$19,$A$9:$A$14,0)) -> 7.1959296 | C29: M€/(kt/an)
A31: Ces sorties alimentent : dessalement (eau), PV/éolien (MW), stockage (charge électrique moyenne, flexibilité), captage CO2 (t/jour).

Sheet Scenarios_CAPEX
A1: Scénarios de CAPEX total (M€, hors ENR) — produit sélectionné
A2: Grille : taille de l'usine (lignes) × CAPEX électrolyseur (colonnes). Formules liées au produit choisi dans Parametres.
A4: Produit sélectionné | B4: =Parametres!$B$31 -> e-methanol
A5: H2 (t/t produit) | B5: =INDEX(Capex_Synthese!$C$6:$C$11,MATCH($B$4,Capex_Synthese!$A$6:$A$11,0)) -> 0.19869899
A6: CAPEX synthèse + CO2 (M€ par t/an) | B6: =(INDEX(Dimensionnement!$J$9:$J$14,MATCH($B$4,Dimensionnement!$A$9:$A$14,0))+INDEX(Dimensionnement!$K$9:$K$14,MATCH($B$4,Dimensionnement!$A$9:$A$14,0)))/INDEX(Dimensionnement!$B$9:$B$14,MATCH($B$4,Dimensionnement!$A$9:$A$14,0)) -> 0.0011135668
A8: t/an \ CAPEX électrolyseur (€/kW) | B8: 500 | C8: 800 | D8: 1200 | E8: 1750 | F8: 2200
A9: 10000 | B9: =(1+Parametres!$B$14)*(1+Parametres!$B$15)*(($A9*$B$5*1000*Parametres!$B$40/Parametres!$B$7/1000)*B$8*Parametres!$B$13/1000+$A9*$B$6) -> 31.536386 | C9: =(1+Parametres!$B$14)*(1+Parametres!$B$15)*(($A9*$B$5*1000*Parametres!$B$40/Parametres!$B$7/1000)*C$8*Parametres!$B$13/1000+$A9*$B$6) -> 41.237885 | D9: =(1+Parametres!$B$14)*(1+Parametres!$B$15)*(($A9*$B$5*1000*Parametres!$B$40/Parametres!$B$7/1000)*D$8*Parametres!$B$13/1000+$A9*$B$6) -> 54.173216 | E9: =(1+Parametres!$B$14)*(1+Parametres!$B$15)*(($A9*$B$5*1000*Parametres!$B$40/Parametres!$B$7/1000)*E$8*Parametres!$B$13/1000+$A9*$B$6) -> 71.959296 | F9: =(1+Parametres!$B$14)*(1+Parametres!$B$15)*(($A9*$B$5*1000*Parametres!$B$40/Parametres!$B$7/1000)*F$8*Parametres!$B$13/1000+$A9*$B$6) -> 86.511543
A10: 50000 | B10: =(1+Parametres!$B$14)*(1+Parametres!$B$15)*(($A10*$B$5*1000*Parametres!$B$40/Parametres!$B$7/1000)*B$8*Parametres!$B$13/1000+$A10*$B$6) -> 157.68193 | C10: =(1+Parametres!$B$14)*(1+Parametres!$B$15)*(($A10*$B$5*1000*Parametres!$B$40/Parametres!$B$7/1000)*C$8*Parametres!$B$13/1000+$A10*$B$6) -> 206.18942 | D10: =(1+Parametres!$B$14)*(1+Parametres!$B$15)*(($A10*$B$5*1000*Parametres!$B$40/Parametres!$B$7/1000)*D$8*Parametres!$B$13/1000+$A10*$B$6) -> 270.86608 | E10: =(1+Parametres!$B$14)*(1+Parametres!$B$15)*(($A10*$B$5*1000*Parametres!$B$40/Parametres!$B$7/1000)*E$8*Parametres!$B$13/1000+$A10*$B$6) -> 359.79648 | F10: =(1+Parametres!$B$14)*(1+Parametres!$B$15)*(($A10*$B$5*1000*Parametres!$B$40/Parametres!$B$7/1000)*F$8*Parametres!$B$13/1000+$A10*$B$6) -> 432.55772
A11: 100000 | B11: =(1+Parametres!$B$14)*(1+Parametres!$B$15)*(($A11*$B$5*1000*Parametres!$B$40/Parametres!$B$7/1000)*B$8*Parametres!$B$13/1000+$A11*$B$6) -> 315.36386 | C11: =(1+Parametres!$B$14)*(1+Parametres!$B$15)*(($A11*$B$5*1000*Parametres!$B$40/Parametres!$B$7/1000)*C$8*Parametres!$B$13/1000+$A11*$B$6) -> 412.37885 | D11: =(1+Parametres!$B$14)*(1+Parametres!$B$15)*(($A11*$B$5*1000*Parametres!$B$40/Parametres!$B$7/1000)*D$8*Parametres!$B$13/1000+$A11*$B$6) -> 541.73216 | E11: =(1+Parametres!$B$14)*(1+Parametres!$B$15)*(($A11*$B$5*1000*Parametres!$B$40/Parametres!$B$7/1000)*E$8*Parametres!$B$13/1000+$A11*$B$6) -> 719.59296 | F11: =(1+Parametres!$B$14)*(1+Parametres!$B$15)*(($A11*$B$5*1000*Parametres!$B$40/Parametres!$B$7/1000)*F$8*Parametres!$B$13/1000+$A11*$B$6) -> 865.11543
A12: 250000 | B12: =(1+Parametres!$B$14)*(1+Parametres!$B$15)*(($A12*$B$5*1000*Parametres!$B$40/Parametres!$B$7/1000)*B$8*Parametres!$B$13/1000+$A12*$B$6) -> 788.40966 | C12: =(1+Parametres!$B$14)*(1+Parametres!$B$15)*(($A12*$B$5*1000*Parametres!$B$40/Parametres!$B$7/1000)*C$8*Parametres!$B$13/1000+$A12*$B$6) -> 1030.9471 | D12: =(1+Parametres!$B$14)*(1+Parametres!$B$15)*(($A12*$B$5*1000*Parametres!$B$40/Parametres!$B$7/1000)*D$8*Parametres!$B$13/1000+$A12*$B$6) -> 1354.3304 | E12: =(1+Parametres!$B$14)*(1+Parametres!$B$15)*(($A12*$B$5*1000*Parametres!$B$40/Parametres!$B$7/1000)*E$8*Parametres!$B$13/1000+$A12*$B$6) -> 1798.9824 | F12: =(1+Parametres!$B$14)*(1+Parametres!$B$15)*(($A12*$B$5*1000*Parametres!$B$40/Parametres!$B$7/1000)*F$8*Parametres!$B$13/1000+$A12*$B$6) -> 2162.7886
A13: 500000 | B13: =(1+Parametres!$B$14)*(1+Parametres!$B$15)*(($A13*$B$5*1000*Parametres!$B$40/Parametres!$B$7/1000)*B$8*Parametres!$B$13/1000+$A13*$B$6) -> 1576.8193 | C13: =(1+Parametres!$B$14)*(1+Parametres!$B$15)*(($A13*$B$5*1000*Parametres!$B$40/Parametres!$B$7/1000)*C$8*Parametres!$B$13/1000+$A13*$B$6) -> 2061.8942 | D13: =(1+Parametres!$B$14)*(1+Parametres!$B$15)*(($A13*$B$5*1000*Parametres!$B$40/Parametres!$B$7/1000)*D$8*Parametres!$B$13/1000+$A13*$B$6) -> 2708.6608 | E13: =(1+Parametres!$B$14)*(1+Parametres!$B$15)*(($A13*$B$5*1000*Parametres!$B$40/Parametres!$B$7/1000)*E$8*Parametres!$B$13/1000+$A13*$B$6) -> 3597.9648 | F13: =(1+Parametres!$B$14)*(1+Parametres!$B$15)*(($A13*$B$5*1000*Parametres!$B$40/Parametres!$B$7/1000)*F$8*Parametres!$B$13/1000+$A13*$B$6) -> 4325.5772
A15: CAPEX électrolyseur de référence (milieu Table 4) : AEL 1 150 · PEM 1 750 · SOEC 2 250 €/kW. Colonne 500 €/kW = scénario « coût chinois » [HYP] à vérifier.
A17: Sensibilité du CAPEX total au facteur de localisation et à la taille (M€)
A18: t/an \ facteur Maroc | B18: 0.5 | C18: 0.75 | D18: 1 | E18: 1.25
A19: 10000 | B19: =(1+Parametres!$B$14)*(1+Parametres!$B$15)*B$18/Parametres!$B$13*(($A19*$B$5*1000*Parametres!$B$40/Parametres!$B$7/1000)*Parametres!$B$39/1000+$A19*$B$6)*Parametres!$B$13 -> 35.979648 | C19: =(1+Parametres!$B$14)*(1+Parametres!$B$15)*C$18/Parametres!$B$13*(($A19*$B$5*1000*Parametres!$B$40/Parametres!$B$7/1000)*Parametres!$B$39/1000+$A19*$B$6)*Parametres!$B$13 -> 53.969472 | D19: =(1+Parametres!$B$14)*(1+Parametres!$B$15)*D$18/Parametres!$B$13*(($A19*$B$5*1000*Parametres!$B$40/Parametres!$B$7/1000)*Parametres!$B$39/1000+$A19*$B$6)*Parametres!$B$13 -> 71.959296 | E19: =(1+Parametres!$B$14)*(1+Parametres!$B$15)*E$18/Parametres!$B$13*(($A19*$B$5*1000*Parametres!$B$40/Parametres!$B$7/1000)*Parametres!$B$39/1000+$A19*$B$6)*Parametres!$B$13 -> 89.94912
A20: 50000 | B20: =(1+Parametres!$B$14)*(1+Parametres!$B$15)*B$18/Parametres!$B$13*(($A20*$B$5*1000*Parametres!$B$40/Parametres!$B$7/1000)*Parametres!$B$39/1000+$A20*$B$6)*Parametres!$B$13 -> 179.89824 | C20: =(1+Parametres!$B$14)*(1+Parametres!$B$15)*C$18/Parametres!$B$13*(($A20*$B$5*1000*Parametres!$B$40/Parametres!$B$7/1000)*Parametres!$B$39/1000+$A20*$B$6)*Parametres!$B$13 -> 269.84736 | D20: =(1+Parametres!$B$14)*(1+Parametres!$B$15)*D$18/Parametres!$B$13*(($A20*$B$5*1000*Parametres!$B$40/Parametres!$B$7/1000)*Parametres!$B$39/1000+$A20*$B$6)*Parametres!$B$13 -> 359.79648 | E20: =(1+Parametres!$B$14)*(1+Parametres!$B$15)*E$18/Parametres!$B$13*(($A20*$B$5*1000*Parametres!$B$40/Parametres!$B$7/1000)*Parametres!$B$39/1000+$A20*$B$6)*Parametres!$B$13 -> 449.7456
A21: 100000 | B21: =(1+Parametres!$B$14)*(1+Parametres!$B$15)*B$18/Parametres!$B$13*(($A21*$B$5*1000*Parametres!$B$40/Parametres!$B$7/1000)*Parametres!$B$39/1000+$A21*$B$6)*Parametres!$B$13 -> 359.79648 | C21: =(1+Parametres!$B$14)*(1+Parametres!$B$15)*C$18/Parametres!$B$13*(($A21*$B$5*1000*Parametres!$B$40/Parametres!$B$7/1000)*Parametres!$B$39/1000+$A21*$B$6)*Parametres!$B$13 -> 539.69472 | D21: =(1+Parametres!$B$14)*(1+Parametres!$B$15)*D$18/Parametres!$B$13*(($A21*$B$5*1000*Parametres!$B$40/Parametres!$B$7/1000)*Parametres!$B$39/1000+$A21*$B$6)*Parametres!$B$13 -> 719.59296 | E21: =(1+Parametres!$B$14)*(1+Parametres!$B$15)*E$18/Parametres!$B$13*(($A21*$B$5*1000*Parametres!$B$40/Parametres!$B$7/1000)*Parametres!$B$39/1000+$A21*$B$6)*Parametres!$B$13 -> 899.4912
A22: 250000 | B22: =(1+Parametres!$B$14)*(1+Parametres!$B$15)*B$18/Parametres!$B$13*(($A22*$B$5*1000*Parametres!$B$40/Parametres!$B$7/1000)*Parametres!$B$39/1000+$A22*$B$6)*Parametres!$B$13 -> 899.4912 | C22: =(1+Parametres!$B$14)*(1+Parametres!$B$15)*C$18/Parametres!$B$13*(($A22*$B$5*1000*Parametres!$B$40/Parametres!$B$7/1000)*Parametres!$B$39/1000+$A22*$B$6)*Parametres!$B$13 -> 1349.2368 | D22: =(1+Parametres!$B$14)*(1+Parametres!$B$15)*D$18/Parametres!$B$13*(($A22*$B$5*1000*Parametres!$B$40/Parametres!$B$7/1000)*Parametres!$B$39/1000+$A22*$B$6)*Parametres!$B$13 -> 1798.9824 | E22: =(1+Parametres!$B$14)*(1+Parametres!$B$15)*E$18/Parametres!$B$13*(($A22*$B$5*1000*Parametres!$B$40/Parametres!$B$7/1000)*Parametres!$B$39/1000+$A22*$B$6)*Parametres!$B$13 -> 2248.728
A23: 500000 | B23: =(1+Parametres!$B$14)*(1+Parametres!$B$15)*B$18/Parametres!$B$13*(($A23*$B$5*1000*Parametres!$B$40/Parametres!$B$7/1000)*Parametres!$B$39/1000+$A23*$B$6)*Parametres!$B$13 -> 1798.9824 | C23: =(1+Parametres!$B$14)*(1+Parametres!$B$15)*C$18/Parametres!$B$13*(($A23*$B$5*1000*Parametres!$B$40/Parametres!$B$7/1000)*Parametres!$B$39/1000+$A23*$B$6)*Parametres!$B$13 -> 2698.4736 | D23: =(1+Parametres!$B$14)*(1+Parametres!$B$15)*D$18/Parametres!$B$13*(($A23*$B$5*1000*Parametres!$B$40/Parametres!$B$7/1000)*Parametres!$B$39/1000+$A23*$B$6)*Parametres!$B$13 -> 3597.9648 | E23: =(1+Parametres!$B$14)*(1+Parametres!$B$15)*E$18/Parametres!$B$13*(($A23*$B$5*1000*Parametres!$B$40/Parametres!$B$7/1000)*Parametres!$B$39/1000+$A23*$B$6)*Parametres!$B$13 -> 4497.456
A25: Pour chaque facteur, CAPEX total = (1+indirects)(1+imprévus) × facteur × (électrolyseur au milieu de Table 4 + synthèse + CO2).

Sheet Sources
A1: Sources
A4: Réf. | B4: Source | C4: Usage
A5: [ART] | B5: Colelli et al. (2026), Energy Conversion and Management, doi:10.1016/j.enconman.2025.120529 | C5: Tables 2, 4, 5 ; §2.4, §3, §4.4
A6: [100] | B6: Brynolf et al. (2018), Electrofuels for the transport sector: a review of production costs | C6: CAPEX méthanol, DME, MTG
A7: [248] | B7: Lester et al. (2020), Analysis on electrofuels in future energy systems | C7: CAPEX ammoniac, efficacités
A8: [76] | B8: Hydrogen Insight (2024), Shanxi — 1,5 Md$ e-SAF | C8: Benchmark Chine
A9: [287] | B9: Hydrogen Insight (2023), HIF Global Texas — 1,8 GW H2 | C9: Benchmark Texas
A10: [288] | B10: Plug Power (2023), Arcadia eFuels — 280 MW | C10: Benchmark Arcadia
A11: [289] | B11: NTB (2023), Nordic Electrofuel — subvention UE 40 M€ | C11: Subvention Herøya
