Workbook

Sheet Lisez_moi
A1: Simulation horaire PV + éolien → électrolyseur (heures pleine charge réelles)
A2: Complément du module e-fuels — Sherpa Engineering
A4: Élément | B4: Description
A5: Objet | B5: Estimer les heures pleine charge réelles de l'électrolyseur, l'énergie écrêtée et le prix effectif de l'électricité à partir de profils horaires PV et éolien. Résultat à reporter dans capex_data.xlsx (Parametres) et dans le Calculateur_LCOE.
A6: ATTENTION — profils synthétiques | B6: Les colonnes pv_cf et wind_cf de Profils_horaires sont des profils SYNTHÉTIQUES (graine fixe, facteurs de charge cibles 30 % PV et 45 % éolien, latitude 28°N). Ils illustrent la méthode ; ils ne représentent pas un site réel. Remplacer les deux colonnes bleues par des séries horaires mesurées/modélisées du site (ERA5, PVGIS, Renewables.ninja, mât de mesure).
A7: Utilisation | B7: 1) Régler Parametres (MW PV, MW éolien, MW électrolyseur, charge minimale). 2) Lire Resultats (FLH, écrêtage, prix effectif, LCOH). 3) Coller vos profils réels dans Profils_horaires (colonnes C et D, 8760 lignes, valeurs 0–1). 4) Consulter Grille_dimensionnement pour l'effet du surdimensionnement ENR.
A8: Logique | B8: Électrolyseur = MIN(production ENR ; puissance nominale), mis à l'arrêt si la production est inférieure à la charge minimale. Écrêtage = production non utilisée. Pas de stockage dans ce classeur (la batterie est dans economics/hourly_sim.py).
A9: Prix effectif | B9: L'énergie écrêtée est payée : prix effectif (€/MWh consommé) = coût total de l'énergie produite ÷ énergie consommée par l'électrolyseur. Il augmente avec le surdimensionnement : le gain d'heures a un coût.
A10: Limites | B10: Pas de rampes, pas de dégradation, pas de pertes réseau, pas de disponibilité des équipements, pas de charge de synthèse/captage. Pas de stockage H2 : à étudier si l'aval (synthèse) exige une charge stable.
A11: Code couleur | B11: Bleu = entrée · noir = formule · vert = lien · jaune = hypothèse.

Sheet Parametres
A1: Paramètres de simulation
A2: Bleu = entrée · jaune = hypothèse à valider.
A4: Paramètre | B4: Valeur | C4: Unité | D4: Source / note
A5: Capacité PV | B5: 300 | C5: MW | D5: [HYP] exemple
A6: Capacité éolienne | B6: 200 | C6: MW | D6: [HYP] exemple
A7: Puissance de l'électrolyseur | B7: 250 | C7: MW | D7: [HYP] exemple (ratio ENR/électrolyseur = 2,0)
A8: Charge minimale de l'électrolyseur | B8: 0.1 | C8: % de la puissance | D8: [HYP] PEM 0–10 % ; AEL ≈ 20 % ([ART] Table 4 : charge nominale)
A9: Consommation système électrolyseur | B9: 58.97 | C9: kWh/kg H2 | D9: [ART] PEM 5,0–5,6 kWh/Nm³ ÷ 0,08988
A10: Coût de production PV (LCOE) | B10: 22 | C10: €/MWh | D10: [HYP]
A11: Coût de production éolien (LCOE) | B11: 30 | C11: €/MWh | D11: [HYP]
A12: CAPEX électrolyseur | B12: 1750 | C12: €/kW | D12: [ART] PEM milieu Table 4
A13: OPEX électrolyseur | B13: 0.04 | C13: % CAPEX/an | D13: [ART] PEM 3–5 %
A14: WACC | B14: 0.08 | C14: % | D14: [HYP]
A15: Durée de vie | B15: 20 | C15: ans | D15: [HYP]
A16: Facteur de recouvrement (CRF) | B16: =B14*(1+B14)^B15/((1+B14)^B15-1) -> 0.10185221 | D16: [CALC]

Sheet Profils_horaires
A1: Profils horaires (8 760 h) — SYNTHÉTIQUES : à remplacer par des séries réelles
A2: Colonnes C et D = entrées (facteur de charge 0–1). Colonnes E à J = formules.
A4: Heure | B4: Mois | C4: PV (facteur de charge) | D4: Éolien (facteur de charge) | E4: PV (MWh) | F4: Éolien (MWh) | G4: Production ENR (MWh) | H4: Électrolyseur (MWh) | I4: Écrêté (MWh) | J4: H2 produit (kg)
A5: 1 | B5: 1 | C5: 0 | D5: 0.0922 | E5: =Parametres!$B$5*C5 -> 0 | F5: =Parametres!$B$6*D5 -> 18.44 | G5: =E5+F5 -> 18.44 | H5: =IF(G5<Parametres!$B$8*Parametres!$B$7,0,MIN(G5,Parametres!$B$7)) -> 0 | I5: =G5-H5 -> 18.44 | J5: =H5*1000/Parametres!$B$9 -> 0
A6: 2 | B6: 1 | C6: 0 | D6: 0.0618 | E6: =Parametres!$B$5*C6 -> 0 | F6: =Parametres!$B$6*D6 -> 12.36 | G6: =E6+F6 -> 12.36 | H6: =IF(G6<Parametres!$B$8*Parametres!$B$7,0,MIN(G6,Parametres!$B$7)) -> 0 | I6: =G6-H6 -> 12.36 | J6: =H6*1000/Parametres!$B$9 -> 0
A7: 3 | B7: 1 | C7: 0 | D7: 0.0441 | E7: =Parametres!$B$5*C7 -> 0 | F7: =Parametres!$B$6*D7 -> 8.82 | G7: =E7+F7 -> 8.82 | H7: =IF(G7<Parametres!$B$8*Parametres!$B$7,0,MIN(G7,Parametres!$B$7)) -> 0 | I7: =G7-H7 -> 8.82 | J7: =H7*1000/Parametres!$B$9 -> 0
A8: 4 | B8: 1 | C8: 0 | D8: 0.0073 | E8: =Parametres!$B$5*C8 -> 0 | F8: =Parametres!$B$6*D8 -> 1.46 | G8: =E8+F8 -> 1.46 | H8: =IF(G8<Parametres!$B$8*Parametres!$B$7,0,MIN(G8,Parametres!$B$7)) -> 0 | I8: =G8-H8 -> 1.46 | J8: =H8*1000/Parametres!$B$9 -> 0
A9: 5 | B9: 1 | C9: 0 | D9: 0.0281 | E9: =Parametres!$B$5*C9 -> 0 | F9: =Parametres!$B$6*D9 -> 5.62 | G9: =E9+F9 -> 5.62 | H9: =IF(G9<Parametres!$B$8*Parametres!$B$7,0,MIN(G9,Parametres!$B$7)) -> 0 | I9: =G9-H9 -> 5.62 | J9: =H9*1000/Parametres!$B$9 -> 0
A10: 6 | B10: 1 | C10: 0 | D10: 0.056 | E10: =Parametres!$B$5*C10 -> 0 | F10: =Parametres!$B$6*D10 -> 11.2 | G10: =E10+F10 -> 11.2 | H10: =IF(G10<Parametres!$B$8*Parametres!$B$7,0,MIN(G10,Parametres!$B$7)) -> 0 | I10: =G10-H10 -> 11.2 | J10: =H10*1000/Parametres!$B$9 -> 0
A11: 7 | B11: 1 | C11: 0 | D11: 0.0511 | E11: =Parametres!$B$5*C11 -> 0 | F11: =Parametres!$B$6*D11 -> 10.22 | G11: =E11+F11 -> 10.22 | H11: =IF(G11<Parametres!$B$8*Parametres!$B$7,0,MIN(G11,Parametres!$B$7)) -> 0 | I11: =G11-H11 -> 10.22 | J11: =H11*1000/Parametres!$B$9 -> 0
A12: 8 | B12: 1 | C12: 0.1196 | D12: 0.085 | E12: =Parametres!$B$5*C12 -> 35.88 | F12: =Parametres!$B$6*D12 -> 17 | G12: =E12+F12 -> 52.88 | H12: =IF(G12<Parametres!$B$8*Parametres!$B$7,0,MIN(G12,Parametres!$B$7)) -> 52.88 | I12: =G12-H12 -> 0 | J12: =H12*1000/Parametres!$B$9 -> 896.72715
A13: 9 | B13: 1 | C13: 0.3606 | D13: 0.111 | E13: =Parametres!$B$5*C13 -> 108.18 | F13: =Parametres!$B$6*D13 -> 22.2 | G13: =E13+F13 -> 130.38 | H13: =IF(G13<Parametres!$B$8*Parametres!$B$7,0,MIN(G13,Parametres!$B$7)) -> 130.38 | I13: =G13-H13 -> 0 | J13: =H13*1000/Parametres!$B$9 -> 2210.9547
A14: 10 | B14: 1 | C14: 0.5095 | D14: 0.1003 | E14: =Parametres!$B$5*C14 -> 152.85 | F14: =Parametres!$B$6*D14 -> 20.06 | G14: =E14+F14 -> 172.91 | H14: =IF(G14<Parametres!$B$8*Parametres!$B$7,0,MIN(G14,Parametres!$B$7)) -> 172.91 | I14: =G14-H14 -> 0 | J14: =H14*1000/Parametres!$B$9 -> 2932.1689
A15: 11 | B15: 1 | C15: 0.6509 | D15: 0.1802 | E15: =Parametres!$B$5*C15 -> 195.27 | F15: =Parametres!$B$6*D15 -> 36.04 | G15: =E15+F15 -> 231.31 | H15: =IF(G15<Parametres!$B$8*Parametres!$B$7,0,MIN(G15,Parametres!$B$7)) -> 231.31 | I15: =G15-H15 -> 0 | J15: =H15*1000/Parametres!$B$9 -> 3922.503
A16: 12 | B16: 1 | C16: 0.7761 | D16: 0.1824 | E16: =Parametres!$B$5*C16 -> 232.83 | F16: =Parametres!$B$6*D16 -> 36.48 | G16: =E16+F16 -> 269.31 | H16: =IF(G16<Parametres!$B$8*Parametres!$B$7,0,MIN(G16,Parametres!$B$7)) -> 250 | I16: =G16-H16 -> 19.31 | J16: =H16*1000/Parametres!$B$9 -> 4239.4438
... A8764: 8760 | B8764: 12 | C8764: 0 | D8764: 0.6094 | E8764: =Parametres!$B$5*C8764 -> 0 | F8764: =Parametres!$B$6*D8764 -> 121.88 | G8764: =E8764+F8764 -> 121.88 | H8764: =IF(G8764<Parametres!$B$8*Parametres!$B$7,0,MIN(G8764,Parametres!$B$7)) -> 121.88 | I8764: =G8764-H8764 -> 0 | J8764: =H8764*1000/Parametres!$B$9 -> 2066.8136

Sheet Resultats
A1: Résultats de la simulation [CALC]
A2: Toutes les valeurs sont des formules liées à Profils_horaires et Parametres.
A4: Indicateur | B4: Valeur | C4: Unité
A5: Production ENR totale | B5: =SUM(Profils_horaires!G5:G8764) -> 1576800.1 | C5: MWh/an
A6: Énergie consommée par l'électrolyseur | B6: =SUM(Profils_horaires!H5:H8764) -> 1256942.2 | C6: MWh/an
A7: Énergie écrêtée | B7: =SUM(Profils_horaires!I5:I8764) -> 319857.91 | C7: MWh/an
A8: Heures pleine charge équivalentes (FLH) | B8: =B6/Parametres!B7 -> 5027.7688 | C8: h/an
A9: Écrêtage | B9: =B7/B5 -> 0.20285254 | C9: % de la production
A10: Facteur de charge ENR hybride | B10: =B5/((Parametres!B5+Parametres!B6)*8760) -> 0.36000002 | C10: %
A11: Rapport capacité ENR / électrolyseur | B11: =(Parametres!B5+Parametres!B6)/Parametres!B7 -> 2 | C11: x
A12: Heures de fonctionnement (> 0) | B12: =COUNTIF(Profils_horaires!H5:H8764,">0") -> 6888 | C12: h/an
A13: Heures à pleine puissance | B13: =COUNTIF(Profils_horaires!H5:H8764,">="&(Parametres!B7-0.000001)) -> 2485 | C13: h/an
A14: Hydrogène produit | B14: =SUM(Profils_horaires!J5:J8764)/1000 -> 21314.943 | C14: t/an
A15: Prix effectif de l'électricité (par MWh consommé) | B15: =(SUM(Profils_horaires!E5:E8764)*Parametres!B10+SUM(Profils_horaires!F5:F8764)*Parametres!B11)/B6 -> 32.616296 | C15: €/MWh
A17: Impact sur le coût de l'hydrogène (LCOH) [CALC]
A18: Cas | B18: FLH (h/an) | C18: Prix électricité (€/MWh) | D18: LCOH (€/kg H2)
A19: Simulation (prix effectif, FLH simulées) | B19: =B8 -> 5027.7688 | C19: =B15 -> 32.616296 | D19: =C19*Parametres!B9/1000+Parametres!B12*(Parametres!B16+Parametres!B13)/(B19/Parametres!B9) -> 4.8349714
A20: Hypothèse par défaut du Calculateur (30 €/MWh ; 5 000 h) | B20: 5000 | C20: 30 | D20: =C20*Parametres!B9/1000+Parametres!B12*(Parametres!B16+Parametres!B13)/(B20/Parametres!B9) -> 4.6968587
A21: LCOH hors eau (≈ 0,02 €/kg). À comparer avec l'article : 3–6 €/kg. Si la simulation donne moins de 5 000 h ou plus de 30 €/MWh, mettre à jour Parametres dans capex_data.xlsx et le Calculateur_LCOE.
A23: Synthèse mensuelle [CALC]
A24: Mois | B24: Production ENR (MWh) | C24: Électrolyseur (MWh) | D24: Écrêté (MWh) | E24: H2 (t) | F24: FLH du mois (h) | G24: Écrêtage (%)
A25: 1 | B25: =SUMIF(Profils_horaires!$B$5:$B$8764,A25,Profils_horaires!$G$5:$G$8764) -> 59866.23 | C25: =SUMIF(Profils_horaires!$B$5:$B$8764,A25,Profils_horaires!$H$5:$H$8764) -> 56791.82 | D25: =SUMIF(Profils_horaires!$B$5:$B$8764,A25,Profils_horaires!$I$5:$I$8764) -> 3074.41 | E25: =SUMIF(Profils_horaires!$B$5:$B$8764,A25,Profils_horaires!$J$5:$J$8764)/1000 -> 963.06291 | F25: =C25/Parametres!$B$7 -> 227.16728 | G25: =IFERROR(D25/B25,0) -> 0.051354662
A26: 2 | B26: =SUMIF(Profils_horaires!$B$5:$B$8764,A26,Profils_horaires!$G$5:$G$8764) -> 71565.74 | C26: =SUMIF(Profils_horaires!$B$5:$B$8764,A26,Profils_horaires!$H$5:$H$8764) -> 65390.69 | D26: =SUMIF(Profils_horaires!$B$5:$B$8764,A26,Profils_horaires!$I$5:$I$8764) -> 6175.05 | E26: =SUMIF(Profils_horaires!$B$5:$B$8764,A26,Profils_horaires!$J$5:$J$8764)/1000 -> 1108.8806 | F26: =C26/Parametres!$B$7 -> 261.56276 | G26: =IFERROR(D26/B26,0) -> 0.086285002
A27: 3 | B27: =SUMIF(Profils_horaires!$B$5:$B$8764,A27,Profils_horaires!$G$5:$G$8764) -> 102978.59 | C27: =SUMIF(Profils_horaires!$B$5:$B$8764,A27,Profils_horaires!$H$5:$H$8764) -> 86267.63 | D27: =SUMIF(Profils_horaires!$B$5:$B$8764,A27,Profils_horaires!$I$5:$I$8764) -> 16710.96 | E27: =SUMIF(Profils_horaires!$B$5:$B$8764,A27,Profils_horaires!$J$5:$J$8764)/1000 -> 1462.9071 | F27: =C27/Parametres!$B$7 -> 345.07052 | G27: =IFERROR(D27/B27,0) -> 0.16227606
A28: 4 | B28: =SUMIF(Profils_horaires!$B$5:$B$8764,A28,Profils_horaires!$G$5:$G$8764) -> 140041.38 | C28: =SUMIF(Profils_horaires!$B$5:$B$8764,A28,Profils_horaires!$H$5:$H$8764) -> 108715.55 | D28: =SUMIF(Profils_horaires!$B$5:$B$8764,A28,Profils_horaires!$I$5:$I$8764) -> 31325.83 | E28: =SUMIF(Profils_horaires!$B$5:$B$8764,A28,Profils_horaires!$J$5:$J$8764)/1000 -> 1843.5739 | F28: =C28/Parametres!$B$7 -> 434.8622 | G28: =IFERROR(D28/B28,0) -> 0.22368981
A29: 5 | B29: =SUMIF(Profils_horaires!$B$5:$B$8764,A29,Profils_horaires!$G$5:$G$8764) -> 181468.24 | C29: =SUMIF(Profils_horaires!$B$5:$B$8764,A29,Profils_horaires!$H$5:$H$8764) -> 134071.97 | D29: =SUMIF(Profils_horaires!$B$5:$B$8764,A29,Profils_horaires!$I$5:$I$8764) -> 47396.27 | E29: =SUMIF(Profils_horaires!$B$5:$B$8764,A29,Profils_horaires!$J$5:$J$8764)/1000 -> 2273.5623 | F29: =C29/Parametres!$B$7 -> 536.28788 | G29: =IFERROR(D29/B29,0) -> 0.26118218
A30: 6 | B30: =SUMIF(Profils_horaires!$B$5:$B$8764,A30,Profils_horaires!$G$5:$G$8764) -> 164782.82 | C30: =SUMIF(Profils_horaires!$B$5:$B$8764,A30,Profils_horaires!$H$5:$H$8764) -> 123290.03 | D30: =SUMIF(Profils_horaires!$B$5:$B$8764,A30,Profils_horaires!$I$5:$I$8764) -> 41492.79 | E30: =SUMIF(Profils_horaires!$B$5:$B$8764,A30,Profils_horaires!$J$5:$J$8764)/1000 -> 2090.7246 | F30: =C30/Parametres!$B$7 -> 493.16012 | G30: =IFERROR(D30/B30,0) -> 0.25180289
A31: 7 | B31: =SUMIF(Profils_horaires!$B$5:$B$8764,A31,Profils_horaires!$G$5:$G$8764) -> 167474.89 | C31: =SUMIF(Profils_horaires!$B$5:$B$8764,A31,Profils_horaires!$H$5:$H$8764) -> 126435.58 | D31: =SUMIF(Profils_horaires!$B$5:$B$8764,A31,Profils_horaires!$I$5:$I$8764) -> 41039.31 | E31: =SUMIF(Profils_horaires!$B$5:$B$8764,A31,Profils_horaires!$J$5:$J$8764)/1000 -> 2144.0661 | F31: =C31/Parametres!$B$7 -> 505.74232 | G31: =IFERROR(D31/B31,0) -> 0.24504754
A32: 8 | B32: =SUMIF(Profils_horaires!$B$5:$B$8764,A32,Profils_horaires!$G$5:$G$8764) -> 190704.94 | C32: =SUMIF(Profils_horaires!$B$5:$B$8764,A32,Profils_horaires!$H$5:$H$8764) -> 139626.01 | D32: =SUMIF(Profils_horaires!$B$5:$B$8764,A32,Profils_horaires!$I$5:$I$8764) -> 51078.93 | E32: =SUMIF(Profils_horaires!$B$5:$B$8764,A32,Profils_horaires!$J$5:$J$8764)/1000 -> 2367.7465 | F32: =C32/Parametres!$B$7 -> 558.50404 | G32: =IFERROR(D32/B32,0) -> 0.26784272
A33: 9 | B33: =SUMIF(Profils_horaires!$B$5:$B$8764,A33,Profils_horaires!$G$5:$G$8764) -> 129326.38 | C33: =SUMIF(Profils_horaires!$B$5:$B$8764,A33,Profils_horaires!$H$5:$H$8764) -> 102833.79 | D33: =SUMIF(Profils_horaires!$B$5:$B$8764,A33,Profils_horaires!$I$5:$I$8764) -> 26492.59 | E33: =SUMIF(Profils_horaires!$B$5:$B$8764,A33,Profils_horaires!$J$5:$J$8764)/1000 -> 1743.8323 | F33: =C33/Parametres!$B$7 -> 411.33516 | G33: =IFERROR(D33/B33,0) -> 0.20485063
A34: 10 | B34: =SUMIF(Profils_horaires!$B$5:$B$8764,A34,Profils_horaires!$G$5:$G$8764) -> 154467.91 | C34: =SUMIF(Profils_horaires!$B$5:$B$8764,A34,Profils_horaires!$H$5:$H$8764) -> 125004.69 | D34: =SUMIF(Profils_horaires!$B$5:$B$8764,A34,Profils_horaires!$I$5:$I$8764) -> 29463.22 | E34: =SUMIF(Profils_horaires!$B$5:$B$8764,A34,Profils_horaires!$J$5:$J$8764)/1000 -> 2119.8014 | F34: =C34/Parametres!$B$7 -> 500.01876 | G34: =IFERROR(D34/B34,0) -> 0.19074007
A35: 11 | B35: =SUMIF(Profils_horaires!$B$5:$B$8764,A35,Profils_horaires!$G$5:$G$8764) -> 127233.66 | C35: =SUMIF(Profils_horaires!$B$5:$B$8764,A35,Profils_horaires!$H$5:$H$8764) -> 108973.61 | D35: =SUMIF(Profils_horaires!$B$5:$B$8764,A35,Profils_horaires!$I$5:$I$8764) -> 18260.05 | E35: =SUMIF(Profils_horaires!$B$5:$B$8764,A35,Profils_horaires!$J$5:$J$8764)/1000 -> 1847.95 | F35: =C35/Parametres!$B$7 -> 435.89444 | G35: =IFERROR(D35/B35,0) -> 0.14351587
A36: 12 | B36: =SUMIF(Profils_horaires!$B$5:$B$8764,A36,Profils_horaires!$G$5:$G$8764) -> 86889.32 | C36: =SUMIF(Profils_horaires!$B$5:$B$8764,A36,Profils_horaires!$H$5:$H$8764) -> 79540.82 | D36: =SUMIF(Profils_horaires!$B$5:$B$8764,A36,Profils_horaires!$I$5:$I$8764) -> 7348.5 | E36: =SUMIF(Profils_horaires!$B$5:$B$8764,A36,Profils_horaires!$J$5:$J$8764)/1000 -> 1348.8353 | F36: =C36/Parametres!$B$7 -> 318.16328 | G36: =IFERROR(D36/B36,0) -> 0.08457311
A37: Total | B37: =SUM(B25:B36) -> 1576800.1 | C37: =SUM(C25:C36) -> 1256942.2 | D37: =SUM(D25:D36) -> 319857.91 | E37: =SUM(E25:E36) -> 21314.943 | F37: =SUM(F25:F36) -> 5027.7688

Sheet Grille_dimensionnement
A1: Effet du surdimensionnement ENR (valeurs figées — calcul Python, profils synthétiques)
A2: Mix PV/éolien et électrolyseur de Parametres au moment de la génération (300/200 MW ; 250 MW). Non recalculé si vous changez Parametres.
A4: Rapport ENR / électrolyseur | B4: FLH (h/an) | C4: Écrêtage | D4: Prix effectif (€/MWh)
A5: 0.8 | B5: 2450.1272 | C5: 0.028837191 | D5: 26.77203
A6: 1 | B6: 3086.01 | C6: 0.021432641 | D6: 26.569454
A7: 1.2 | B7: 3604.6009 | C7: 0.047490473 | D7: 27.296315
A8: 1.5 | B8: 4239.631 | C8: 0.10374789 | D8: 29.009695
A9: 1.8 | B9: 4748.99 | C9: 0.16339175 | D9: 31.077867
A10: 2.2 | B10: 5273.7104 | C10: 0.23987155 | D10: 34.204745
A11: 2.6 | B11: 5652.52 | C11: 0.31061448 | D11: 37.714746
A12: 3 | B12: 5840.7641 | C12: 0.38263528 | D12: 42.11449
A14: Lecture : doubler la capacité ENR par rapport à l'électrolyseur (rapport 2) donne ≈ 5 000 h mais écrête ≈ 20 % ; au-delà de 2,6, chaque heure gagnée coûte de plus en plus cher en prix effectif.
A15: Ces chiffres dépendent entièrement des profils : avec des données réelles du site, relancer economics/hourly_sim.py (sweep_re_ratio) ou la page Streamlit.
