Workbook
Name Analysis_and_Graph: [1]!dd_analysis_graph[Analysis and Graph]
Name Analysis_and_Graph: [1]!dd_analysis_graph[Analysis and Graph]
Name Analysis_and_Graph: dd_analysis_graph[Analysis and Graph]
Name dd_components: [1]!Table3[Component of PtG]
Name dd_components: [1]!Table3[Component of PtG]
Name dd_components: Table3[Component of PtG]
Name temp: Library!$B$1:$F$138

Sheet Cockpit
B2: Economics of Converting Renewable Power to Hydrogen
C4: General Information
C6: Gunther Glenk
C7: TUM School of Management, Technical University of Munich
C9: Stefan Reichelstein
C10: Department of Business Administration, University of Mannheim
C11: Graduate School of Business, Stanford University
C13: December 2018
C15: Structure of this workbook
C17: Sheet | D17: Content
C19: Sources | D19: Overview and categorization of all sources used for the cost review
C21: Database | D21: Collection of all numericals (costs and operating performance measures) for sources used in the analysis
C23: Analysis | D23: Sheet collecting and illustrating the numericals based on filters
C25: Export | D25: Sheet enabling the export of numericals based on filters to use for further analysis in Matlab
C27: Library | D27: Bibliography of all sources
C29: Adjustment Factors | D29: List of conversion and adjustment factors for currencies and consumer price indeces
C31: Dropdowns | D31: List of used dropdowns

Sheet Sources
Z1: Checks | AG1: Secondary references
B2: Citekey | C2: Year | D2: In Library | E2: Type of Publication | F2: Method | G2: Reference to | H2: Analysis and Graph | I2: Type of Source | J2: Comment (temp) | L2: Analysis | T2: Abbreviations | Z2: In Database | AA2: Secondary reference listed | AG2: 1 | AH2: res. String | AI2: 2 | AJ2: res. String | AK2: 3 | AL2: res. String | AM2: 4 | AN2: res. String | AO2: 5
B3: hotellier2014hydrogen | C3: =IFERROR(VALUE(MID(Sources[[#This Row],[Citekey]],FIND("20",Sources[[#This Row],[Citekey]]),4)),"") -> 2014 | D3: yes | E3: Industry Statement | F3: No cost data | H3: =IFERROR(VLOOKUP(Sources[[#This Row],[Method]],dd_analysis_graph[],2,FALSE),"") -> Not in analysis, not in graph | I3: =IFERROR(VLOOKUP(Sources[[#This Row],[Type of Publication]],dd_type_source[],2,FALSE),"") -> Publication | M3: Original analysis, industry data | N3: Original review multiple sources | O3: No reference, unclear method | P3: Secondary source | Q3: No cost data | R3: Total | T3: AEL | U3: Alkaline Electrolyzer | Z3: =IF(OR(Sources[[#This Row],[Analysis and Graph]]="Analysis and Graph",Sources[[#This Row],[Analysis and Graph]]="Not in analysis, but extra in graph"),MATCH(Sources[[#This Row],[Citekey]],Database!$B$4:$B$2385,0),"") | AA3: =IF(AG3<>"",MATCH(AG3,Sources[Citekey],0),"") | AB3: =IF(AI3<>"",MATCH(AI3,Sources[Citekey],0),"") | AC3: =IF(AK3<>"",MATCH(AK3,Sources[Citekey],0),"") | AD3: =IF(AM3<>"",MATCH(AM3,Sources[Citekey],0),"") | AE3: =IF(AO3<>"",MATCH(AO3,Sources[Citekey],0),"") | AG3: =IFERROR(IF(Sources[[#This Row],[Reference to]]<>"",LEFT(Sources[[#This Row],[Reference to]],FIND(",",Sources[[#This Row],[Reference to]])-1),""),Sources[[#This Row],[Reference to]]) | AH3: =IFERROR(RIGHT(Sources[[#This Row],[Reference to]],LEN(Sources[[#This Row],[Reference to]])-LEN($AG3)-2),"") | AI3: =IFERROR(LEFT(AH3,FIND(",",AH3)-1),AH3) | AJ3: =IFERROR(RIGHT(Sources[[#This Row],[Reference to]],LEN(Sources[[#This Row],[Reference to]])-LEN($AG3)-2-LEN($AI3)-2),"") | AK3: =IFERROR(LEFT(AJ3,FIND(",",AJ3)-1),AJ3) | AL3: =IFERROR(RIGHT(Sources[[#This Row],[Reference to]],LEN(Sources[[#This Row],[Reference to]])-LEN($AG3)-2-LEN($AI3)-2-LEN($AK3)-2),"") | AM3: =IFERROR(LEFT(AL3,FIND(",",AL3)-1),AL3) | AN3: =IFERROR(RIGHT(Sources[[#This Row],[Reference to]],LEN(Sources[[#This Row],[Reference to]])-LEN($AG3)-2-LEN($AI3)-2-LEN($AK3)-2-LEN($AM3)-2),"") | AO3: =IFERROR(LEFT(AN3,FIND(",",AN3)-1),AN3)
B4: abbasi2011renewable | C4: =IFERROR(VALUE(MID(Sources[[#This Row],[Citekey]],FIND("20",Sources[[#This Row],[Citekey]]),4)),"") -> 2011 | D4: yes | E4: Journal Article | F4: Secondary source | G4: harrison2009wind | H4: =IFERROR(VLOOKUP(Sources[[#This Row],[Method]],dd_analysis_graph[],2,FALSE),"") -> Not in analysis, not in graph | I4: =IFERROR(VLOOKUP(Sources[[#This Row],[Type of Publication]],dd_type_source[],2,FALSE),"") -> Publication | L4: Report | M4: =COUNTIFS(Sources[Type of Publication],$L4,Sources[Method],M$3) -> 28 | N4: =COUNTIFS(Sources[Type of Publication],$L4,Sources[Method],N$3) -> 3 | O4: =COUNTIFS(Sources[Type of Publication],$L4,Sources[Method],O$3) -> 10 | P4: =COUNTIFS(Sources[Type of Publication],$L4,Sources[Method],P$3) -> 7 | Q4: =COUNTIFS(Sources[Type of Publication],$L4,Sources[Method],Q$3) -> 17 | R4: =SUM(M4:Q4) -> 65 | T4: PEM | U4: Polymer electrolyte membrane | Z4: =IF(OR(Sources[[#This Row],[Analysis and Graph]]="Analysis and Graph",Sources[[#This Row],[Analysis and Graph]]="Not in analysis, but extra in graph"),MATCH(Sources[[#This Row],[Citekey]],Database!$B$4:$B$2385,0),"") | AA4: =IF(AG4<>"",MATCH(AG4,Sources[Citekey],0),"") -> 125 | AB4: =IF(AI4<>"",MATCH(AI4,Sources[Citekey],0),"") | AC4: =IF(AK4<>"",MATCH(AK4,Sources[Citekey],0),"") | AD4: =IF(AM4<>"",MATCH(AM4,Sources[Citekey],0),"") | AE4: =IF(AO4<>"",MATCH(AO4,Sources[Citekey],0),"") | AG4: =IFERROR(IF(Sources[[#This Row],[Reference to]]<>"",LEFT(Sources[[#This Row],[Reference to]],FIND(",",Sources[[#This Row],[Reference to]])-1),""),Sources[[#This Row],[Reference to]]) -> harrison2009wind | AH4: =IFERROR(RIGHT(Sources[[#This Row],[Reference to]],LEN(Sources[[#This Row],[Reference to]])-LEN($AG4)-2),"") | AI4: =IFERROR(LEFT(AH4,FIND(",",AH4)-1),AH4) | AJ4: =IFERROR(RIGHT(Sources[[#This Row],[Reference to]],LEN(Sources[[#This Row],[Reference to]])-LEN($AG4)-2-LEN($AI4)-2),"") | AK4: =IFERROR(LEFT(AJ4,FIND(",",AJ4)-1),AJ4) | AL4: =IFERROR(RIGHT(Sources[[#This Row],[Reference to]],LEN(Sources[[#This Row],[Reference to]])-LEN($AG4)-2-LEN($AI4)-2-LEN($AK4)-2),"") | AM4: =IFERROR(LEFT(AL4,FIND(",",AL4)-1),AL4) | AN4: =IFERROR(RIGHT(Sources[[#This Row],[Reference to]],LEN(Sources[[#This Row],[Reference to]])-LEN($AG4)-2-LEN($AI4)-2-LEN($AK4)-2-LEN($AM4)-2),"") | AO4: =IFERROR(LEFT(AN4,FIND(",",AN4)-1),AN4)
B5: aguado2009economical | C5: 2009 | D5: yes | E5: Journal Article | F5: Secondary source | G5: smith2004low, greiner2007norwegian, lymberopoulos2005hydrogen | H5: =IFERROR(VLOOKUP(Sources[[#This Row],[Method]],dd_analysis_graph[],2,FALSE),"") -> Not in analysis, not in graph | I5: =IFERROR(VLOOKUP(Sources[[#This Row],[Type of Publication]],dd_type_source[],2,FALSE),"") -> Publication | L5: Journal Article | M5: =COUNTIFS(Sources[Type of Publication],$L5,Sources[Method],M$3) -> 18 | N5: =COUNTIFS(Sources[Type of Publication],$L5,Sources[Method],N$3) -> 6 | O5: =COUNTIFS(Sources[Type of Publication],$L5,Sources[Method],O$3) -> 5 | P5: =COUNTIFS(Sources[Type of Publication],$L5,Sources[Method],P$3) -> 29 | Q5: =COUNTIFS(Sources[Type of Publication],$L5,Sources[Method],Q$3) -> 22 | R5: =SUM(M5:Q5) -> 80 | T5: SOEC | U5: Solid oxide electrolyzer cell | Z5: =IF(OR(Sources[[#This Row],[Analysis and Graph]]="Analysis and Graph",Sources[[#This Row],[Analysis and Graph]]="Not in analysis, but extra in graph"),MATCH(Sources[[#This Row],[Citekey]],Database!$B$4:$B$2385,0),"") | AA5: =IF(AG5<>"",MATCH(AG5,Sources[Citekey],0),"") -> 149 | AB5: =IF(AI5<>"",MATCH(AI5,Sources[Citekey],0),"") -> 28 | AC5: =IF(AK5<>"",MATCH(AK5,Sources[Citekey],0),"") -> 135 | AD5: =IF(AM5<>"",MATCH(AM5,Sources[Citekey],0),"") | AE5: =IF(AO5<>"",MATCH(AO5,Sources[Citekey],0),"") | AG5: =IFERROR(IF(Sources[[#This Row],[Reference to]]<>"",LEFT(Sources[[#This Row],[Reference to]],FIND(",",Sources[[#This Row],[Reference to]])-1),""),Sources[[#This Row],[Reference to]]) -> smith2004low | AH5: =IFERROR(RIGHT(Sources[[#This Row],[Reference to]],LEN(Sources[[#This Row],[Reference to]])-LEN($AG5)-2),"") -> greiner2007norwegian, lymberopoulos2005hydrogen | AI5: =IFERROR(LEFT(AH5,FIND(",",AH5)-1),AH5) -> greiner2007norwegian | AJ5: =IFERROR(RIGHT(Sources[[#This Row],[Reference to]],LEN(Sources[[#This Row],[Reference to]])-LEN($AG5)-2-LEN($AI5)-2),"") -> lymberopoulos2005hydrogen | AK5: =IFERROR(LEFT(AJ5,FIND(",",AJ5)-1),AJ5) -> lymberopoulos2005hydrogen | AL5: =IFERROR(RIGHT(Sources[[#This Row],[Reference to]],LEN(Sources[[#This Row],[Reference to]])-LEN($AG5)-2-LEN($AI5)-2-LEN($AK5)-2),"") | AM5: =IFERROR(LEFT(AL5,FIND(",",AL5)-1),AL5) | AN5: =IFERROR(RIGHT(Sources[[#This Row],[Reference to]],LEN(Sources[[#This Row],[Reference to]])-LEN($AG5)-2-LEN($AI5)-2-LEN($AK5)-2-LEN($AM5)-2),"") | AO5: =IFERROR(LEFT(AN5,FIND(",",AN5)-1),AN5)
B6: badwal2013hydrogen | C6: =IFERROR(VALUE(MID(Sources[[#This Row],[Citekey]],FIND("20",Sources[[#This Row],[Citekey]]),4)),"") -> 2013 | D6: yes | E6: Journal Article | F6: Secondary source | G6: genovese2009current | H6: =IFERROR(VLOOKUP(Sources[[#This Row],[Method]],dd_analysis_graph[],2,FALSE),"") -> Not in analysis, not in graph | I6: =IFERROR(VLOOKUP(Sources[[#This Row],[Type of Publication]],dd_type_source[],2,FALSE),"") -> Publication | L6: News Article | M6: =COUNTIFS(Sources[Type of Publication],$L6,Sources[Method],M$3) -> 0 | N6: =COUNTIFS(Sources[Type of Publication],$L6,Sources[Method],N$3) -> 0 | O6: =COUNTIFS(Sources[Type of Publication],$L6,Sources[Method],O$3) -> 0 | P6: =COUNTIFS(Sources[Type of Publication],$L6,Sources[Method],P$3) -> 0 | Q6: =COUNTIFS(Sources[Type of Publication],$L6,Sources[Method],Q$3) -> 1 | R6: =SUM(M6:Q6) -> 1 | Z6: =IF(OR(Sources[[#This Row],[Analysis and Graph]]="Analysis and Graph",Sources[[#This Row],[Analysis and Graph]]="Not in analysis, but extra in graph"),MATCH(Sources[[#This Row],[Citekey]],Database!$B$4:$B$2385,0),"") | AA6: =IF(AG6<>"",MATCH(AG6,Sources[Citekey],0),"") -> 120 | AB6: =IF(AI6<>"",MATCH(AI6,Sources[Citekey],0),"") | AC6: =IF(AK6<>"",MATCH(AK6,Sources[Citekey],0),"") | AD6: =IF(AM6<>"",MATCH(AM6,Sources[Citekey],0),"") | AE6: =IF(AO6<>"",MATCH(AO6,Sources[Citekey],0),"") | AG6: =IFERROR(IF(Sources[[#This Row],[Reference to]]<>"",LEFT(Sources[[#This Row],[Reference to]],FIND(",",Sources[[#This Row],[Reference to]])-1),""),Sources[[#This Row],[Reference to]]) -> genovese2009current | AH6: =IFERROR(RIGHT(Sources[[#This Row],[Reference to]],LEN(Sources[[#This Row],[Reference to]])-LEN($AG6)-2),"") | AI6: =IFERROR(LEFT(AH6,FIND(",",AH6)-1),AH6) | AJ6: =IFERROR(RIGHT(Sources[[#This Row],[Reference to]],LEN(Sources[[#This Row],[Reference to]])-LEN($AG6)-2-LEN($AI6)-2),"") | AK6: =IFERROR(LEFT(AJ6,FIND(",",AJ6)-1),AJ6) | AL6: =IFERROR(RIGHT(Sources[[#This Row],[Reference to]],LEN(Sources[[#This Row],[Reference to]])-LEN($AG6)-2-LEN($AI6)-2-LEN($AK6)-2),"") | AM6: =IFERROR(LEFT(AL6,FIND(",",AL6)-1),AL6) | AN6: =IFERROR(RIGHT(Sources[[#This Row],[Reference to]],LEN(Sources[[#This Row],[Reference to]])-LEN($AG6)-2-LEN($AI6)-2-LEN($AK6)-2-LEN($AM6)-2),"") | AO6: =IFERROR(LEFT(AN6,FIND(",",AN6)-1),AN6)
B7: bajohr2011speicherung | C7: =IFERROR(VALUE(MID(Sources[[#This Row],[Citekey]],FIND("20",Sources[[#This Row],[Citekey]]),4)),"") -> 2011 | D7: yes | E7: Journal Article | F7: Secondary source | G7: wenske2008wasserstoff | H7: =IFERROR(VLOOKUP(Sources[[#This Row],[Method]],dd_analysis_graph[],2,FALSE),"") -> Not in analysis, not in graph | I7: =IFERROR(VLOOKUP(Sources[[#This Row],[Type of Publication]],dd_type_source[],2,FALSE),"") -> Publication | L7: Industry Statement | M7: =COUNTIFS(Sources[Type of Publication],$L7,Sources[Method],M$3) -> 0 | N7: =COUNTIFS(Sources[Type of Publication],$L7,Sources[Method],N$3) -> 0 | O7: =COUNTIFS(Sources[Type of Publication],$L7,Sources[Method],O$3) -> 0 | P7: =COUNTIFS(Sources[Type of Publication],$L7,Sources[Method],P$3) -> 0 | Q7: =COUNTIFS(Sources[Type of Publication],$L7,Sources[Method],Q$3) -> 1 | R7: =SUM(M7:Q7) -> 1 | Z7: =IF(OR(Sources[[#This Row],[Analysis and Graph]]="Analysis and Graph",Sources[[#This Row],[Analysis and Graph]]="Not in analysis, but extra in graph"),MATCH(Sources[[#This Row],[Citekey]],Database!$B$4:$B$2385,0),"") | AA7: =IF(AG7<>"",MATCH(AG7,Sources[Citekey],0),"") -> 164 | AB7: =IF(AI7<>"",MATCH(AI7,Sources[Citekey],0),"") | AC7: =IF(AK7<>"",MATCH(AK7,Sources[Citekey],0),"") | AD7: =IF(AM7<>"",MATCH(AM7,Sources[Citekey],0),"") | AE7: =IF(AO7<>"",MATCH(AO7,Sources[Citekey],0),"") | AG7: =IFERROR(IF(Sources[[#This Row],[Reference to]]<>"",LEFT(Sources[[#This Row],[Reference to]],FIND(",",Sources[[#This Row],[Reference to]])-1),""),Sources[[#This Row],[Reference to]]) -> wenske2008wasserstoff | AH7: =IFERROR(RIGHT(Sources[[#This Row],[Reference to]],LEN(Sources[[#This Row],[Reference to]])-LEN($AG7)-2),"") | AI7: =IFERROR(LEFT(AH7,FIND(",",AH7)-1),AH7) | AJ7: =IFERROR(RIGHT(Sources[[#This Row],[Reference to]],LEN(Sources[[#This Row],[Reference to]])-LEN($AG7)-2-LEN($AI7)-2),"") | AK7: =IFERROR(LEFT(AJ7,FIND(",",AJ7)-1),AJ7) | AL7: =IFERROR(RIGHT(Sources[[#This Row],[Reference to]],LEN(Sources[[#This Row],[Reference to]])-LEN($AG7)-2-LEN($AI7)-2-LEN($AK7)-2),"") | AM7: =IFERROR(LEFT(AL7,FIND(",",AL7)-1),AL7) | AN7: =IFERROR(RIGHT(Sources[[#This Row],[Reference to]],LEN(Sources[[#This Row],[Reference to]])-LEN($AG7)-2-LEN($AI7)-2-LEN($AK7)-2-LEN($AM7)-2),"") | AO7: =IFERROR(LEFT(AN7,FIND(",",AN7)-1),AN7)
B8: balan2016technical | C8: =IFERROR(VALUE(MID(Sources[[#This Row],[Citekey]],FIND("20",Sources[[#This Row],[Citekey]]),4)),"") -> 2016 | D8: yes | E8: Journal Article | F8: Secondary source | G8: bertuccioli2014development | H8: =IFERROR(VLOOKUP(Sources[[#This Row],[Method]],dd_analysis_graph[],2,FALSE),"") -> Not in analysis, not in graph | I8: =IFERROR(VLOOKUP(Sources[[#This Row],[Type of Publication]],dd_type_source[],2,FALSE),"") -> Publication | L8: Manufacturer Interview | M8: =COUNTIFS(Sources[Type of Publication],$L8,Sources[Method],M$3) -> 17 | N8: =COUNTIFS(Sources[Type of Publication],$L8,Sources[Method],N$3) -> 1 | O8: =COUNTIFS(Sources[Type of Publication],$L8,Sources[Method],O$3) -> 0 | P8: =COUNTIFS(Sources[Type of Publication],$L8,Sources[Method],P$3) -> 0 | Q8: =COUNTIFS(Sources[Type of Publication],$L8,Sources[Method],Q$3) -> 0 | R8: =SUM(M8:Q8) -> 18 | Z8: =IF(OR(Sources[[#This Row],[Analysis and Graph]]="Analysis and Graph",Sources[[#This Row],[Analysis and Graph]]="Not in analysis, but extra in graph"),MATCH(Sources[[#This Row],[Citekey]],Database!$B$4:$B$2385,0),"") | AA8: =IF(AG8<>"",MATCH(AG8,Sources[Citekey],0),"") -> 106 | AB8: =IF(AI8<>"",MATCH(AI8,Sources[Citekey],0),"") | AC8: =IF(AK8<>"",MATCH(AK8,Sources[Citekey],0),"") | AD8: =IF(AM8<>"",MATCH(AM8,Sources[Citekey],0),"") | AE8: =IF(AO8<>"",MATCH(AO8,Sources[Citekey],0),"") | AG8: =IFERROR(IF(Sources[[#This Row],[Reference to]]<>"",LEFT(Sources[[#This Row],[Reference to]],FIND(",",Sources[[#This Row],[Reference to]])-1),""),Sources[[#This Row],[Reference to]]) -> bertuccioli2014development | AH8: =IFERROR(RIGHT(Sources[[#This Row],[Reference to]],LEN(Sources[[#This Row],[Reference to]])-LEN($AG8)-2),"") | AI8: =IFERROR(LEFT(AH8,FIND(",",AH8)-1),AH8) | AJ8: =IFERROR(RIGHT(Sources[[#This Row],[Reference to]],LEN(Sources[[#This Row],[Reference to]])-LEN($AG8)-2-LEN($AI8)-2),"") | AK8: =IFERROR(LEFT(AJ8,FIND(",",AJ8)-1),AJ8) | AL8: =IFERROR(RIGHT(Sources[[#This Row],[Reference to]],LEN(Sources[[#This Row],[Reference to]])-LEN($AG8)-2-LEN($AI8)-2-LEN($AK8)-2),"") | AM8: =IFERROR(LEFT(AL8,FIND(",",AL8)-1),AL8) | AN8: =IFERROR(RIGHT(Sources[[#This Row],[Reference to]],LEN(Sources[[#This Row],[Reference to]])-LEN($AG8)-2-LEN($AI8)-2-LEN($AK8)-2-LEN($AM8)-2),"") | AO8: =IFERROR(LEFT(AN8,FIND(",",AN8)-1),AN8)
B9: barbir1997efficiency | C9: 1997 | D9: yes | E9: Journal Article | F9: No cost data | H9: =IFERROR(VLOOKUP(Sources[[#This Row],[Method]],dd_analysis_graph[],2,FALSE),"") -> Not in analysis, not in graph | I9: =IFERROR(VLOOKUP(Sources[[#This Row],[Type of Publication]],dd_type_source[],2,FALSE),"") -> Publication | J9: Excluded due to age | L9: Total | M9: =SUM(M4:M8) -> 63 | N9: =SUM(N4:N8) -> 10 | O9: =SUM(O4:O8) -> 15 | P9: =SUM(P4:P8) -> 36 | Q9: =SUM(Q4:Q8) -> 41 | R9: =SUM(R4:R8) -> 165 | Z9: =IF(OR(Sources[[#This Row],[Analysis and Graph]]="Analysis and Graph",Sources[[#This Row],[Analysis and Graph]]="Not in analysis, but extra in graph"),MATCH(Sources[[#This Row],[Citekey]],Database!$B$4:$B$2385,0),"") | AA9: =IF(AG9<>"",MATCH(AG9,Sources[Citekey],0),"") | AB9: =IF(AI9<>"",MATCH(AI9,Sources[Citekey],0),"") | AC9: =IF(AK9<>"",MATCH(AK9,Sources[Citekey],0),"") | AD9: =IF(AM9<>"",MATCH(AM9,Sources[Citekey],0),"") | AE9: =IF(AO9<>"",MATCH(AO9,Sources[Citekey],0),"") | AG9: =IFERROR(IF(Sources[[#This Row],[Reference to]]<>"",LEFT(Sources[[#This Row],[Reference to]],FIND(",",Sources[[#This Row],[Reference to]])-1),""),Sources[[#This Row],[Reference to]]) | AH9: =IFERROR(RIGHT(Sources[[#This Row],[Reference to]],LEN(Sources[[#This Row],[Reference to]])-LEN($AG9)-2),"") | AI9: =IFERROR(LEFT(AH9,FIND(",",AH9)-1),AH9) | AJ9: =IFERROR(RIGHT(Sources[[#This Row],[Reference to]],LEN(Sources[[#This Row],[Reference to]])-LEN($AG9)-2-LEN($AI9)-2),"") | AK9: =IFERROR(LEFT(AJ9,FIND(",",AJ9)-1),AJ9) | AL9: =IFERROR(RIGHT(Sources[[#This Row],[Reference to]],LEN(Sources[[#This Row],[Reference to]])-LEN($AG9)-2-LEN($AI9)-2-LEN($AK9)-2),"") | AM9: =IFERROR(LEFT(AL9,FIND(",",AL9)-1),AL9) | AN9: =IFERROR(RIGHT(Sources[[#This Row],[Reference to]],LEN(Sources[[#This Row],[Reference to]])-LEN($AG9)-2-LEN($AI9)-2-LEN($AK9)-2-LEN($AM9)-2),"") | AO9: =IFERROR(LEFT(AN9,FIND(",",AN9)-1),AN9)
B10: bernal-agustin2008hourly | C10: =IFERROR(VALUE(MID(Sources[[#This Row],[Citekey]],FIND("20",Sources[[#This Row],[Citekey]]),4)),"") -> 2008 | D10: yes | E10: Journal Article | F10: Secondary source | G10: lipman2004fuel, greiner2007norwegian, lymberopoulos2005hydrogen, briguglio2008new | H10: =IFERROR(VLOOKUP(Sources[[#This Row],[Method]],dd_analysis_graph[],2,FALSE),"") -> Not in analysis, not in graph | I10: =IFERROR(VLOOKUP(Sources[[#This Row],[Type of Publication]],dd_type_source[],2,FALSE),"") -> Publication | Z10: =IF(OR(Sources[[#This Row],[Analysis and Graph]]="Analysis and Graph",Sources[[#This Row],[Analysis and Graph]]="Not in analysis, but extra in graph"),MATCH(Sources[[#This Row],[Citekey]],Database!$B$4:$B$2385,0),"") | AA10: =IF(AG10<>"",MATCH(AG10,Sources[Citekey],0),"") -> 46 | AB10: =IF(AI10<>"",MATCH(AI10,Sources[Citekey],0),"") -> 28 | AC10: =IF(AK10<>"",MATCH(AK10,Sources[Citekey],0),"") -> 135 | AD10: =IF(AM10<>"",MATCH(AM10,Sources[Citekey],0),"") -> 12 | AE10: =IF(AO10<>"",MATCH(AO10,Sources[Citekey],0),"") | AG10: =IFERROR(IF(Sources[[#This Row],[Reference to]]<>"",LEFT(Sources[[#This Row],[Reference to]],FIND(",",Sources[[#This Row],[Reference to]])-1),""),Sources[[#This Row],[Reference to]]) -> lipman2004fuel | AH10: =IFERROR(RIGHT(Sources[[#This Row],[Reference to]],LEN(Sources[[#This Row],[Reference to]])-LEN($AG10)-2),"") -> greiner2007norwegian, lymberopoulos2005hydrogen, briguglio2008new | AI10: =IFERROR(LEFT(AH10,FIND(",",AH10)-1),AH10) -> greiner2007norwegian | AJ10: =IFERROR(RIGHT(Sources[[#This Row],[Reference to]],LEN(Sources[[#This Row],[Reference to]])-LEN($AG10)-2-LEN($AI10)-2),"") -> lymberopoulos2005hydrogen, briguglio2008new | AK10: =IFERROR(LEFT(AJ10,FIND(",",AJ10)-1),AJ10) -> lymberopoulos2005hydrogen | AL10: =IFERROR(RIGHT(Sources[[#This Row],[Reference to]],LEN(Sources[[#This Row],[Reference to]])-LEN($AG10)-2-LEN($AI10)-2-LEN($AK10)-2),"") -> briguglio2008new | AM10: =IFERROR(LEFT(AL10,FIND(",",AL10)-1),AL10) -> briguglio2008new | AN10: =IFERROR(RIGHT(Sources[[#This Row],[Reference to]],LEN(Sources[[#This Row],[Reference to]])-LEN($AG10)-2-LEN($AI10)-2-LEN($AK10)-2-LEN($AM10)-2),"") | AO10: =IFERROR(LEFT(AN10,FIND(",",AN10)-1),AN10)
B11: bernal-agustin2009simulation | C11: =IFERROR(VALUE(MID(Sources[[#This Row],[Citekey]],FIND("20",Sources[[#This Row],[Citekey]]),4)),"") -> 2009 | D11: yes | E11: Journal Article | F11: No cost data | H11: =IFERROR(VLOOKUP(Sources[[#This Row],[Method]],dd_analysis_graph[],2,FALSE),"") -> Not in analysis, not in graph | I11: =IFERROR(VLOOKUP(Sources[[#This Row],[Type of Publication]],dd_type_source[],2,FALSE),"") -> Publication | Z11: =IF(OR(Sources[[#This Row],[Analysis and Graph]]="Analysis and Graph",Sources[[#This Row],[Analysis and Graph]]="Not in analysis, but extra in graph"),MATCH(Sources[[#This Row],[Citekey]],Database!$B$4:$B$2385,0),"") | AA11: =IF(AG11<>"",MATCH(AG11,Sources[Citekey],0),"") | AB11: =IF(AI11<>"",MATCH(AI11,Sources[Citekey],0),"") | AC11: =IF(AK11<>"",MATCH(AK11,Sources[Citekey],0),"") | AD11: =IF(AM11<>"",MATCH(AM11,Sources[Citekey],0),"") | AE11: =IF(AO11<>"",MATCH(AO11,Sources[Citekey],0),"") | AG11: =IFERROR(IF(Sources[[#This Row],[Reference to]]<>"",LEFT(Sources[[#This Row],[Reference to]],FIND(",",Sources[[#This Row],[Reference to]])-1),""),Sources[[#This Row],[Reference to]]) | AH11: =IFERROR(RIGHT(Sources[[#This Row],[Reference to]],LEN(Sources[[#This Row],[Reference to]])-LEN($AG11)-2),"") | AI11: =IFERROR(LEFT(AH11,FIND(",",AH11)-1),AH11) | AJ11: =IFERROR(RIGHT(Sources[[#This Row],[Reference to]],LEN(Sources[[#This Row],[Reference to]])-LEN($AG11)-2-LEN($AI11)-2),"") | AK11: =IFERROR(LEFT(AJ11,FIND(",",AJ11)-1),AJ11) | AL11: =IFERROR(RIGHT(Sources[[#This Row],[Reference to]],LEN(Sources[[#This Row],[Reference to]])-LEN($AG11)-2-LEN($AI11)-2-LEN($AK11)-2),"") | AM11: =IFERROR(LEFT(AL11,FIND(",",AL11)-1),AL11) | AN11: =IFERROR(RIGHT(Sources[[#This Row],[Reference to]],LEN(Sources[[#This Row],[Reference to]])-LEN($AG11)-2-LEN($AI11)-2-LEN($AK11)-2-LEN($AM11)-2),"") | AO11: =IFERROR(LEFT(AN11,FIND(",",AN11)-1),AN11)
B12: bernal-agustin2010techno | C12: =IFERROR(VALUE(MID(Sources[[#This Row],[Citekey]],FIND("20",Sources[[#This Row],[Citekey]]),4)),"") -> 2010 | D12: yes | E12: Journal Article | F12: Secondary source | G12: linnemann2007realistic | H12: =IFERROR(VLOOKUP(Sources[[#This Row],[Method]],dd_analysis_graph[],2,FALSE),"") -> Not in analysis, not in graph | I12: =IFERROR(VLOOKUP(Sources[[#This Row],[Type of Publication]],dd_type_source[],2,FALSE),"") -> Publication | Z12: =IF(OR(Sources[[#This Row],[Analysis and Graph]]="Analysis and Graph",Sources[[#This Row],[Analysis and Graph]]="Not in analysis, but extra in graph"),MATCH(Sources[[#This Row],[Citekey]],Database!$B$4:$B$2385,0),"") | AA12: =IF(AG12<>"",MATCH(AG12,Sources[Citekey],0),"") -> 45 | AB12: =IF(AI12<>"",MATCH(AI12,Sources[Citekey],0),"") | AC12: =IF(AK12<>"",MATCH(AK12,Sources[Citekey],0),"") | AD12: =IF(AM12<>"",MATCH(AM12,Sources[Citekey],0),"") | AE12: =IF(AO12<>"",MATCH(AO12,Sources[Citekey],0),"") | AG12: =IFERROR(IF(Sources[[#This Row],[Reference to]]<>"",LEFT(Sources[[#This Row],[Reference to]],FIND(",",Sources[[#This Row],[Reference to]])-1),""),Sources[[#This Row],[Reference to]]) -> linnemann2007realistic | AH12: =IFERROR(RIGHT(Sources[[#This Row],[Reference to]],LEN(Sources[[#This Row],[Reference to]])-LEN($AG12)-2),"") | AI12: =IFERROR(LEFT(AH12,FIND(",",AH12)-1),AH12) | AJ12: =IFERROR(RIGHT(Sources[[#This Row],[Reference to]],LEN(Sources[[#This Row],[Reference to]])-LEN($AG12)-2-LEN($AI12)-2),"") | AK12: =IFERROR(LEFT(AJ12,FIND(",",AJ12)-1),AJ12) | AL12: =IFERROR(RIGHT(Sources[[#This Row],[Reference to]],LEN(Sources[[#This Row],[Reference to]])-LEN($AG12)-2-LEN($AI12)-2-LEN($AK12)-2),"") | AM12: =IFERROR(LEFT(AL12,FIND(",",AL12)-1),AL12) | AN12: =IFERROR(RIGHT(Sources[[#This Row],[Reference to]],LEN(Sources[[#This Row],[Reference to]])-LEN($AG12)-2-LEN($AI12)-2-LEN($AK12)-2-LEN($AM12)-2),"") | AO12: =IFERROR(LEFT(AN12,FIND(",",AN12)-1),AN12)
B13: bockris2007estimates | C13: =IFERROR(VALUE(MID(Sources[[#This Row],[Citekey]],FIND("20",Sources[[#This Row],[Citekey]]),4)),"") -> 2007 | D13: yes | E13: Journal Article | F13: No cost data | H13: =IFERROR(VLOOKUP(Sources[[#This Row],[Method]],dd_analysis_graph[],2,FALSE),"") -> Not in analysis, not in graph | I13: =IFERROR(VLOOKUP(Sources[[#This Row],[Type of Publication]],dd_type_source[],2,FALSE),"") -> Publication | Z13: =IF(OR(Sources[[#This Row],[Analysis and Graph]]="Analysis and Graph",Sources[[#This Row],[Analysis and Graph]]="Not in analysis, but extra in graph"),MATCH(Sources[[#This Row],[Citekey]],Database!$B$4:$B$2385,0),"") | AA13: =IF(AG13<>"",MATCH(AG13,Sources[Citekey],0),"") | AB13: =IF(AI13<>"",MATCH(AI13,Sources[Citekey],0),"") | AC13: =IF(AK13<>"",MATCH(AK13,Sources[Citekey],0),"") | AD13: =IF(AM13<>"",MATCH(AM13,Sources[Citekey],0),"") | AE13: =IF(AO13<>"",MATCH(AO13,Sources[Citekey],0),"") | AG13: =IFERROR(IF(Sources[[#This Row],[Reference to]]<>"",LEFT(Sources[[#This Row],[Reference to]],FIND(",",Sources[[#This Row],[Reference to]])-1),""),Sources[[#This Row],[Reference to]]) | AH13: =IFERROR(RIGHT(Sources[[#This Row],[Reference to]],LEN(Sources[[#This Row],[Reference to]])-LEN($AG13)-2),"") | AI13: =IFERROR(LEFT(AH13,FIND(",",AH13)-1),AH13) | AJ13: =IFERROR(RIGHT(Sources[[#This Row],[Reference to]],LEN(Sources[[#This Row],[Reference to]])-LEN($AG13)-2-LEN($AI13)-2),"") | AK13: =IFERROR(LEFT(AJ13,FIND(",",AJ13)-1),AJ13) | AL13: =IFERROR(RIGHT(Sources[[#This Row],[Reference to]],LEN(Sources[[#This Row],[Reference to]])-LEN($AG13)-2-LEN($AI13)-2-LEN($AK13)-2),"") | AM13: =IFERROR(LEFT(AL13,FIND(",",AL13)-1),AL13) | AN13: =IFERROR(RIGHT(Sources[[#This Row],[Reference to]],LEN(Sources[[#This Row],[Reference to]])-LEN($AG13)-2-LEN($AI13)-2-LEN($AK13)-2-LEN($AM13)-2),"") | AO13: =IFERROR(LEFT(AN13,FIND(",",AN13)-1),AN13)
B14: briguglio2008new | C14: =IFERROR(VALUE(MID(Sources[[#This Row],[Citekey]],FIND("20",Sources[[#This Row],[Citekey]]),4)),"") -> 2008 | D14: yes | E14: Journal Article | F14: Secondary source | G14: brunetto2007optimal, levene2005economic | H14: =IFERROR(VLOOKUP(Sources[[#This Row],[Method]],dd_analysis_graph[],2,FALSE),"") -> Not in analysis, not in graph | I14: =IFERROR(VLOOKUP(Sources[[#This Row],[Type of Publication]],dd_type_source[],2,FALSE),"") -> Publication | Z14: =IF(OR(Sources[[#This Row],[Analysis and Graph]]="Analysis and Graph",Sources[[#This Row],[Analysis and Graph]]="Not in analysis, but extra in graph"),MATCH(Sources[[#This Row],[Citekey]],Database!$B$4:$B$2385,0),"") | AA14: =IF(AG14<>"",MATCH(AG14,Sources[Citekey],0),"") -> 14 | AB14: =IF(AI14<>"",MATCH(AI14,Sources[Citekey],0),"") -> 133 | AC14: =IF(AK14<>"",MATCH(AK14,Sources[Citekey],0),"") | AD14: =IF(AM14<>"",MATCH(AM14,Sources[Citekey],0),"") | AE14: =IF(AO14<>"",MATCH(AO14,Sources[Citekey],0),"") | AG14: =IFERROR(IF(Sources[[#This Row],[Reference to]]<>"",LEFT(Sources[[#This Row],[Reference to]],FIND(",",Sources[[#This Row],[Reference to]])-1),""),Sources[[#This Row],[Reference to]]) -> brunetto2007optimal | AH14: =IFERROR(RIGHT(Sources[[#This Row],[Reference to]],LEN(Sources[[#This Row],[Reference to]])-LEN($AG14)-2),"") -> levene2005economic | AI14: =IFERROR(LEFT(AH14,FIND(",",AH14)-1),AH14) -> levene2005economic | AJ14: =IFERROR(RIGHT(Sources[[#This Row],[Reference to]],LEN(Sources[[#This Row],[Reference to]])-LEN($AG14)-2-LEN($AI14)-2),"") | AK14: =IFERROR(LEFT(AJ14,FIND(",",AJ14)-1),AJ14) | AL14: =IFERROR(RIGHT(Sources[[#This Row],[Reference to]],LEN(Sources[[#This Row],[Reference to]])-LEN($AG14)-2-LEN($AI14)-2-LEN($AK14)-2),"") | AM14: =IFERROR(LEFT(AL14,FIND(",",AL14)-1),AL14) | AN14: =IFERROR(RIGHT(Sources[[#This Row],[Reference to]],LEN(Sources[[#This Row],[Reference to]])-LEN($AG14)-2-LEN($AI14)-2-LEN($AK14)-2-LEN($AM14)-2),"") | AO14: =IFERROR(LEFT(AN14,FIND(",",AN14)-1),AN14)
B15: brisse2012high | C15: 2012 | D15: yes | E15: Journal Article | F15: Original analysis, industry data | H15: =IFERROR(VLOOKUP(Sources[[#This Row],[Method]],dd_analysis_graph[],2,FALSE),"") -> Analysis and Graph | I15: =IFERROR(VLOOKUP(Sources[[#This Row],[Type of Publication]],dd_type_source[],2,FALSE),"") -> Publication | Z15: =IF(OR(Sources[[#This Row],[Analysis and Graph]]="Analysis and Graph",Sources[[#This Row],[Analysis and Graph]]="Not in analysis, but extra in graph"),MATCH(Sources[[#This Row],[Citekey]],Database!$B$4:$B$2385,0),"") -> 241 | AA15: =IF(AG15<>"",MATCH(AG15,Sources[Citekey],0),"") | AB15: =IF(AI15<>"",MATCH(AI15,Sources[Citekey],0),"") | AC15: =IF(AK15<>"",MATCH(AK15,Sources[Citekey],0),"") | AD15: =IF(AM15<>"",MATCH(AM15,Sources[Citekey],0),"") | AE15: =IF(AO15<>"",MATCH(AO15,Sources[Citekey],0),"") | AG15: =IFERROR(IF(Sources[[#This Row],[Reference to]]<>"",LEFT(Sources[[#This Row],[Reference to]],FIND(",",Sources[[#This Row],[Reference to]])-1),""),Sources[[#This Row],[Reference to]]) | AH15: =IFERROR(RIGHT(Sources[[#This Row],[Reference to]],LEN(Sources[[#This Row],[Reference to]])-LEN($AG15)-2),"") | AI15: =IFERROR(LEFT(AH15,FIND(",",AH15)-1),AH15) | AJ15: =IFERROR(RIGHT(Sources[[#This Row],[Reference to]],LEN(Sources[[#This Row],[Reference to]])-LEN($AG15)-2-LEN($AI15)-2),"") | AK15: =IFERROR(LEFT(AJ15,FIND(",",AJ15)-1),AJ15) | AL15: =IFERROR(RIGHT(Sources[[#This Row],[Reference to]],LEN(Sources[[#This Row],[Reference to]])-LEN($AG15)-2-LEN($AI15)-2-LEN($AK15)-2),"") | AM15: =IFERROR(LEFT(AL15,FIND(",",AL15)-1),AL15) | AN15: =IFERROR(RIGHT(Sources[[#This Row],[Reference to]],LEN(Sources[[#This Row],[Reference to]])-LEN($AG15)-2-LEN($AI15)-2-LEN($AK15)-2-LEN($AM15)-2),"") | AO15: =IFERROR(LEFT(AN15,FIND(",",AN15)-1),AN15)
B16: brunetto2007optimal | C16: 2007 | D16: yes | E16: Journal Article | F16: Original analysis, industry data | H16: =IFERROR(VLOOKUP(Sources[[#This Row],[Method]],dd_analysis_graph[],2,FALSE),"") -> Analysis and Graph | I16: =IFERROR(VLOOKUP(Sources[[#This Row],[Type of Publication]],dd_type_source[],2,FALSE),"") -> Publication | Z16: =IF(OR(Sources[[#This Row],[Analysis and Graph]]="Analysis and Graph",Sources[[#This Row],[Analysis and Graph]]="Not in analysis, but extra in graph"),MATCH(Sources[[#This Row],[Citekey]],Database!$B$4:$B$2385,0),"") -> 193 | AA16: =IF(AG16<>"",MATCH(AG16,Sources[Citekey],0),"") | AB16: =IF(AI16<>"",MATCH(AI16,Sources[Citekey],0),"") | AC16: =IF(AK16<>"",MATCH(AK16,Sources[Citekey],0),"") | AD16: =IF(AM16<>"",MATCH(AM16,Sources[Citekey],0),"") | AE16: =IF(AO16<>"",MATCH(AO16,Sources[Citekey],0),"") | AG16: =IFERROR(IF(Sources[[#This Row],[Reference to]]<>"",LEFT(Sources[[#This Row],[Reference to]],FIND(",",Sources[[#This Row],[Reference to]])-1),""),Sources[[#This Row],[Reference to]]) | AH16: =IFERROR(RIGHT(Sources[[#This Row],[Reference to]],LEN(Sources[[#This Row],[Reference to]])-LEN($AG16)-2),"") | AI16: =IFERROR(LEFT(AH16,FIND(",",AH16)-1),AH16) | AJ16: =IFERROR(RIGHT(Sources[[#This Row],[Reference to]],LEN(Sources[[#This Row],[Reference to]])-LEN($AG16)-2-LEN($AI16)-2),"") | AK16: =IFERROR(LEFT(AJ16,FIND(",",AJ16)-1),AJ16) | AL16: =IFERROR(RIGHT(Sources[[#This Row],[Reference to]],LEN(Sources[[#This Row],[Reference to]])-LEN($AG16)-2-LEN($AI16)-2-LEN($AK16)-2),"") | AM16: =IFERROR(LEFT(AL16,FIND(",",AL16)-1),AL16) | AN16: =IFERROR(RIGHT(Sources[[#This Row],[Reference to]],LEN(Sources[[#This Row],[Reference to]])-LEN($AG16)-2-LEN($AI16)-2-LEN($AK16)-2-LEN($AM16)-2),"") | AO16: =IFERROR(LEFT(AN16,FIND(",",AN16)-1),AN16)
B17: buchholz2014power | C17: =IFERROR(VALUE(MID(Sources[[#This Row],[Citekey]],FIND("20",Sources[[#This Row],[Citekey]]),4)),"") -> 2014 | D17: yes | E17: Journal Article | F17: Secondary source | G17: seider2003product | H17: =IFERROR(VLOOKUP(Sources[[#This Row],[Method]],dd_analysis_graph[],2,FALSE),"") -> Not in analysis, not in graph | I17: =IFERROR(VLOOKUP(Sources[[#This Row],[Type of Publication]],dd_type_source[],2,FALSE),"") -> Publication | Z17: =IF(OR(Sources[[#This Row],[Analysis and Graph]]="Analysis and Graph",Sources[[#This Row],[Analysis and Graph]]="Not in analysis, but extra in graph"),MATCH(Sources[[#This Row],[Citekey]],Database!$B$4:$B$2385,0),"") | AA17: =IF(AG17<>"",MATCH(AG17,Sources[Citekey],0),"") -> 146 | AB17: =IF(AI17<>"",MATCH(AI17,Sources[Citekey],0),"") | AC17: =IF(AK17<>"",MATCH(AK17,Sources[Citekey],0),"") | AD17: =IF(AM17<>"",MATCH(AM17,Sources[Citekey],0),"") | AE17: =IF(AO17<>"",MATCH(AO17,Sources[Citekey],0),"") | AG17: =IFERROR(IF(Sources[[#This Row],[Reference to]]<>"",LEFT(Sources[[#This Row],[Reference to]],FIND(",",Sources[[#This Row],[Reference to]])-1),""),Sources[[#This Row],[Reference to]]) -> seider2003product | AH17: =IFERROR(RIGHT(Sources[[#This Row],[Reference to]],LEN(Sources[[#This Row],[Reference to]])-LEN($AG17)-2),"") | AI17: =IFERROR(LEFT(AH17,FIND(",",AH17)-1),AH17) | AJ17: =IFERROR(RIGHT(Sources[[#This Row],[Reference to]],LEN(Sources[[#This Row],[Reference to]])-LEN($AG17)-2-LEN($AI17)-2),"") | AK17: =IFERROR(LEFT(AJ17,FIND(",",AJ17)-1),AJ17) | AL17: =IFERROR(RIGHT(Sources[[#This Row],[Reference to]],LEN(Sources[[#This Row],[Reference to]])-LEN($AG17)-2-LEN($AI17)-2-LEN($AK17)-2),"") | AM17: =IFERROR(LEFT(AL17,FIND(",",AL17)-1),AL17) | AN17: =IFERROR(RIGHT(Sources[[#This Row],[Reference to]],LEN(Sources[[#This Row],[Reference to]])-LEN($AG17)-2-LEN($AI17)-2-LEN($AK17)-2-LEN($AM17)-2),"") | AO17: =IFERROR(LEFT(AN17,FIND(",",AN17)-1),AN17)
B18: budny2015economic | C18: =IFERROR(VALUE(MID(Sources[[#This Row],[Citekey]],FIND("20",Sources[[#This Row],[Citekey]]),4)),"") -> 2015 | D18: yes | E18: Journal Article | F18: No cost data | H18: =IFERROR(VLOOKUP(Sources[[#This Row],[Method]],dd_analysis_graph[],2,FALSE),"") -> Not in analysis, not in graph | I18: =IFERROR(VLOOKUP(Sources[[#This Row],[Type of Publication]],dd_type_source[],2,FALSE),"") -> Publication | Z18: =IF(OR(Sources[[#This Row],[Analysis and Graph]]="Analysis and Graph",Sources[[#This Row],[Analysis and Graph]]="Not in analysis, but extra in graph"),MATCH(Sources[[#This Row],[Citekey]],Database!$B$4:$B$2385,0),"") | AA18: =IF(AG18<>"",MATCH(AG18,Sources[Citekey],0),"") | AB18: =IF(AI18<>"",MATCH(AI18,Sources[Citekey],0),"") | AC18: =IF(AK18<>"",MATCH(AK18,Sources[Citekey],0),"") | AD18: =IF(AM18<>"",MATCH(AM18,Sources[Citekey],0),"") | AE18: =IF(AO18<>"",MATCH(AO18,Sources[Citekey],0),"") | AG18: =IFERROR(IF(Sources[[#This Row],[Reference to]]<>"",LEFT(Sources[[#This Row],[Reference to]],FIND(",",Sources[[#This Row],[Reference to]])-1),""),Sources[[#This Row],[Reference to]]) | AH18: =IFERROR(RIGHT(Sources[[#This Row],[Reference to]],LEN(Sources[[#This Row],[Reference to]])-LEN($AG18)-2),"") | AI18: =IFERROR(LEFT(AH18,FIND(",",AH18)-1),AH18) | AJ18: =IFERROR(RIGHT(Sources[[#This Row],[Reference to]],LEN(Sources[[#This Row],[Reference to]])-LEN($AG18)-2-LEN($AI18)-2),"") | AK18: =IFERROR(LEFT(AJ18,FIND(",",AJ18)-1),AJ18) | AL18: =IFERROR(RIGHT(Sources[[#This Row],[Reference to]],LEN(Sources[[#This Row],[Reference to]])-LEN($AG18)-2-LEN($AI18)-2-LEN($AK18)-2),"") | AM18: =IFERROR(LEFT(AL18,FIND(",",AL18)-1),AL18) | AN18: =IFERROR(RIGHT(Sources[[#This Row],[Reference to]],LEN(Sources[[#This Row],[Reference to]])-LEN($AG18)-2-LEN($AI18)-2-LEN($AK18)-2-LEN($AM18)-2),"") | AO18: =IFERROR(LEFT(AN18,FIND(",",AN18)-1),AN18)
B19: buttler2015detailed | C19: =IFERROR(VALUE(MID(Sources[[#This Row],[Citekey]],FIND("20",Sources[[#This Row],[Citekey]]),4)),"") -> 2015 | D19: yes | E19: Journal Article | F19: Secondary source | G19: brisse2012high, harvego2008economic, DOE2013solid | H19: =IFERROR(VLOOKUP(Sources[[#This Row],[Method]],dd_analysis_graph[],2,FALSE),"") -> Not in analysis, not in graph | I19: =IFERROR(VLOOKUP(Sources[[#This Row],[Type of Publication]],dd_type_source[],2,FALSE),"") -> Publication | Z19: =IF(OR(Sources[[#This Row],[Analysis and Graph]]="Analysis and Graph",Sources[[#This Row],[Analysis and Graph]]="Not in analysis, but extra in graph"),MATCH(Sources[[#This Row],[Citekey]],Database!$B$4:$B$2385,0),"") | AA19: =IF(AG19<>"",MATCH(AG19,Sources[Citekey],0),"") -> 13 | AB19: =IF(AI19<>"",MATCH(AI19,Sources[Citekey],0),"") -> 126 | AC19: =IF(AK19<>"",MATCH(AK19,Sources[Citekey],0),"") -> 113 | AD19: =IF(AM19<>"",MATCH(AM19,Sources[Citekey],0),"") | AE19: =IF(AO19<>"",MATCH(AO19,Sources[Citekey],0),"") | AG19: =IFERROR(IF(Sources[[#This Row],[Reference to]]<>"",LEFT(Sources[[#This Row],[Reference to]],FIND(",",Sources[[#This Row],[Reference to]])-1),""),Sources[[#This Row],[Reference to]]) -> brisse2012high | AH19: =IFERROR(RIGHT(Sources[[#This Row],[Reference to]],LEN(Sources[[#This Row],[Reference to]])-LEN($AG19)-2),"") -> harvego2008economic, DOE2013solid | AI19: =IFERROR(LEFT(AH19,FIND(",",AH19)-1),AH19) -> harvego2008economic | AJ19: =IFERROR(RIGHT(Sources[[#This Row],[Reference to]],LEN(Sources[[#This Row],[Reference to]])-LEN($AG19)-2-LEN($AI19)-2),"") -> DOE2013solid | AK19: =IFERROR(LEFT(AJ19,FIND(",",AJ19)-1),AJ19) -> DOE2013solid | AL19: =IFERROR(RIGHT(Sources[[#This Row],[Reference to]],LEN(Sources[[#This Row],[Reference to]])-LEN($AG19)-2-LEN($AI19)-2-LEN($AK19)-2),"") | AM19: =IFERROR(LEFT(AL19,FIND(",",AL19)-1),AL19) | AN19: =IFERROR(RIGHT(Sources[[#This Row],[Reference to]],LEN(Sources[[#This Row],[Reference to]])-LEN($AG19)-2-LEN($AI19)-2-LEN($AK19)-2-LEN($AM19)-2),"") | AO19: =IFERROR(LEFT(AN19,FIND(",",AN19)-1),AN19)
B20: DeBoear2014application | C20: =IFERROR(VALUE(MID(Sources[[#This Row],[Citekey]],FIND("20",Sources[[#This Row],[Citekey]]),4)),"") -> 2014 | D20: yes | E20: Journal Article | F20: No cost data | H20: =IFERROR(VLOOKUP(Sources[[#This Row],[Method]],dd_analysis_graph[],2,FALSE),"") -> Not in analysis, not in graph | I20: =IFERROR(VLOOKUP(Sources[[#This Row],[Type of Publication]],dd_type_source[],2,FALSE),"") -> Publication | Z20: =IF(OR(Sources[[#This Row],[Analysis and Graph]]="Analysis and Graph",Sources[[#This Row],[Analysis and Graph]]="Not in analysis, but extra in graph"),MATCH(Sources[[#This Row],[Citekey]],Database!$B$4:$B$2385,0),"") | AA20: =IF(AG20<>"",MATCH(AG20,Sources[Citekey],0),"") | AB20: =IF(AI20<>"",MATCH(AI20,Sources[Citekey],0),"") | AC20: =IF(AK20<>"",MATCH(AK20,Sources[Citekey],0),"") | AD20: =IF(AM20<>"",MATCH(AM20,Sources[Citekey],0),"") | AE20: =IF(AO20<>"",MATCH(AO20,Sources[Citekey],0),"") | AG20: =IFERROR(IF(Sources[[#This Row],[Reference to]]<>"",LEFT(Sources[[#This Row],[Reference to]],FIND(",",Sources[[#This Row],[Reference to]])-1),""),Sources[[#This Row],[Reference to]]) | AH20: =IFERROR(RIGHT(Sources[[#This Row],[Reference to]],LEN(Sources[[#This Row],[Reference to]])-LEN($AG20)-2),"") | AI20: =IFERROR(LEFT(AH20,FIND(",",AH20)-1),AH20) | AJ20: =IFERROR(RIGHT(Sources[[#This Row],[Reference to]],LEN(Sources[[#This Row],[Reference to]])-LEN($AG20)-2-LEN($AI20)-2),"") | AK20: =IFERROR(LEFT(AJ20,FIND(",",AJ20)-1),AJ20) | AL20: =IFERROR(RIGHT(Sources[[#This Row],[Reference to]],LEN(Sources[[#This Row],[Reference to]])-LEN($AG20)-2-LEN($AI20)-2-LEN($AK20)-2),"") | AM20: =IFERROR(LEFT(AL20,FIND(",",AL20)-1),AL20) | AN20: =IFERROR(RIGHT(Sources[[#This Row],[Reference to]],LEN(Sources[[#This Row],[Reference to]])-LEN($AG20)-2-LEN($AI20)-2-LEN($AK20)-2-LEN($AM20)-2),"") | AO20: =IFERROR(LEFT(AN20,FIND(",",AN20)-1),AN20)
B21: DeSaintJean2015economic | C21: =IFERROR(VALUE(MID(Sources[[#This Row],[Citekey]],FIND("20",Sources[[#This Row],[Citekey]]),4)),"") -> 2015 | D21: yes | E21: Journal Article | F21: No cost data | H21: =IFERROR(VLOOKUP(Sources[[#This Row],[Method]],dd_analysis_graph[],2,FALSE),"") -> Not in analysis, not in graph | I21: =IFERROR(VLOOKUP(Sources[[#This Row],[Type of Publication]],dd_type_source[],2,FALSE),"") -> Publication | Z21: =IF(OR(Sources[[#This Row],[Analysis and Graph]]="Analysis and Graph",Sources[[#This Row],[Analysis and Graph]]="Not in analysis, but extra in graph"),MATCH(Sources[[#This Row],[Citekey]],Database!$B$4:$B$2385,0),"") | AA21: =IF(AG21<>"",MATCH(AG21,Sources[Citekey],0),"") | AB21: =IF(AI21<>"",MATCH(AI21,Sources[Citekey],0),"") | AC21: =IF(AK21<>"",MATCH(AK21,Sources[Citekey],0),"") | AD21: =IF(AM21<>"",MATCH(AM21,Sources[Citekey],0),"") | AE21: =IF(AO21<>"",MATCH(AO21,Sources[Citekey],0),"") | AG21: =IFERROR(IF(Sources[[#This Row],[Reference to]]<>"",LEFT(Sources[[#This Row],[Reference to]],FIND(",",Sources[[#This Row],[Reference to]])-1),""),Sources[[#This Row],[Reference to]]) | AH21: =IFERROR(RIGHT(Sources[[#This Row],[Reference to]],LEN(Sources[[#This Row],[Reference to]])-LEN($AG21)-2),"") | AI21: =IFERROR(LEFT(AH21,FIND(",",AH21)-1),AH21) | AJ21: =IFERROR(RIGHT(Sources[[#This Row],[Reference to]],LEN(Sources[[#This Row],[Reference to]])-LEN($AG21)-2-LEN($AI21)-2),"") | AK21: =IFERROR(LEFT(AJ21,FIND(",",AJ21)-1),AJ21) | AL21: =IFERROR(RIGHT(Sources[[#This Row],[Reference to]],LEN(Sources[[#This Row],[Reference to]])-LEN($AG21)-2-LEN($AI21)-2-LEN($AK21)-2),"") | AM21: =IFERROR(LEFT(AL21,FIND(",",AL21)-1),AL21) | AN21: =IFERROR(RIGHT(Sources[[#This Row],[Reference to]],LEN(Sources[[#This Row],[Reference to]])-LEN($AG21)-2-LEN($AI21)-2-LEN($AK21)-2-LEN($AM21)-2),"") | AO21: =IFERROR(LEFT(AN21,FIND(",",AN21)-1),AN21)
B22: edwards2008hydrogen | C22: =IFERROR(VALUE(MID(Sources[[#This Row],[Citekey]],FIND("20",Sources[[#This Row],[Citekey]]),4)),"") -> 2008 | D22: yes | E22: Journal Article | F22: Secondary source | H22: =IFERROR(VLOOKUP(Sources[[#This Row],[Method]],dd_analysis_graph[],2,FALSE),"") -> Not in analysis, not in graph | I22: =IFERROR(VLOOKUP(Sources[[#This Row],[Type of Publication]],dd_type_source[],2,FALSE),"") -> Publication | Z22: =IF(OR(Sources[[#This Row],[Analysis and Graph]]="Analysis and Graph",Sources[[#This Row],[Analysis and Graph]]="Not in analysis, but extra in graph"),MATCH(Sources[[#This Row],[Citekey]],Database!$B$4:$B$2385,0),"") | AA22: =IF(AG22<>"",MATCH(AG22,Sources[Citekey],0),"") | AB22: =IF(AI22<>"",MATCH(AI22,Sources[Citekey],0),"") | AC22: =IF(AK22<>"",MATCH(AK22,Sources[Citekey],0),"") | AD22: =IF(AM22<>"",MATCH(AM22,Sources[Citekey],0),"") | AE22: =IF(AO22<>"",MATCH(AO22,Sources[Citekey],0),"") | AG22: =IFERROR(IF(Sources[[#This Row],[Reference to]]<>"",LEFT(Sources[[#This Row],[Reference to]],FIND(",",Sources[[#This Row],[Reference to]])-1),""),Sources[[#This Row],[Reference to]]) | AH22: =IFERROR(RIGHT(Sources[[#This Row],[Reference to]],LEN(Sources[[#This Row],[Reference to]])-LEN($AG22)-2),"") | AI22: =IFERROR(LEFT(AH22,FIND(",",AH22)-1),AH22) | AJ22: =IFERROR(RIGHT(Sources[[#This Row],[Reference to]],LEN(Sources[[#This Row],[Reference to]])-LEN($AG22)-2-LEN($AI22)-2),"") | AK22: =IFERROR(LEFT(AJ22,FIND(",",AJ22)-1),AJ22) | AL22: =IFERROR(RIGHT(Sources[[#This Row],[Reference to]],LEN(Sources[[#This Row],[Reference to]])-LEN($AG22)-2-LEN($AI22)-2-LEN($AK22)-2),"") | AM22: =IFERROR(LEFT(AL22,FIND(",",AL22)-1),AL22) | AN22: =IFERROR(RIGHT(Sources[[#This Row],[Reference to]],LEN(Sources[[#This Row],[Reference to]])-LEN($AG22)-2-LEN($AI22)-2-LEN($AK22)-2-LEN($AM22)-2),"") | AO22: =IFERROR(LEFT(AN22,FIND(",",AN22)-1),AN22)
B23: felgenhauer2015state | C23: =IFERROR(VALUE(MID(Sources[[#This Row],[Citekey]],FIND("20",Sources[[#This Row],[Citekey]]),4)),"") -> 2015 | D23: yes | E23: Journal Article | F23: No reference, unclear method | H23: =IFERROR(VLOOKUP(Sources[[#This Row],[Method]],dd_analysis_graph[],2,FALSE),"") -> Not in analysis, not in graph | I23: =IFERROR(VLOOKUP(Sources[[#This Row],[Type of Publication]],dd_type_source[],2,FALSE),"") -> Publication | J23: Numbers for complete PtG plant, not only electrolyzer | Z23: =IF(OR(Sources[[#This Row],[Analysis and Graph]]="Analysis and Graph",Sources[[#This Row],[Analysis and Graph]]="Not in analysis, but extra in graph"),MATCH(Sources[[#This Row],[Citekey]],Database!$B$4:$B$2385,0),"") | AA23: =IF(AG23<>"",MATCH(AG23,Sources[Citekey],0),"") | AB23: =IF(AI23<>"",MATCH(AI23,Sources[Citekey],0),"") | AC23: =IF(AK23<>"",MATCH(AK23,Sources[Citekey],0),"") | AD23: =IF(AM23<>"",MATCH(AM23,Sources[Citekey],0),"") | AE23: =IF(AO23<>"",MATCH(AO23,Sources[Citekey],0),"") | AG23: =IFERROR(IF(Sources[[#This Row],[Reference to]]<>"",LEFT(Sources[[#This Row],[Reference to]],FIND(",",Sources[[#This Row],[Reference to]])-1),""),Sources[[#This Row],[Reference to]]) | AH23: =IFERROR(RIGHT(Sources[[#This Row],[Reference to]],LEN(Sources[[#This Row],[Reference to]])-LEN($AG23)-2),"") | AI23: =IFERROR(LEFT(AH23,FIND(",",AH23)-1),AH23) | AJ23: =IFERROR(RIGHT(Sources[[#This Row],[Reference to]],LEN(Sources[[#This Row],[Reference to]])-LEN($AG23)-2-LEN($AI23)-2),"") | AK23: =IFERROR(LEFT(AJ23,FIND(",",AJ23)-1),AJ23) | AL23: =IFERROR(RIGHT(Sources[[#This Row],[Reference to]],LEN(Sources[[#This Row],[Reference to]])-LEN($AG23)-2-LEN($AI23)-2-LEN($AK23)-2),"") | AM23: =IFERROR(LEFT(AL23,FIND(",",AL23)-1),AL23) | AN23: =IFERROR(RIGHT(Sources[[#This Row],[Reference to]],LEN(Sources[[#This Row],[Reference to]])-LEN($AG23)-2-LEN($AI23)-2-LEN($AK23)-2-LEN($AM23)-2),"") | AO23: =IFERROR(LEFT(AN23,FIND(",",AN23)-1),AN23)
B24: floch2007on | C24: =IFERROR(VALUE(MID(Sources[[#This Row],[Citekey]],FIND("20",Sources[[#This Row],[Citekey]]),4)),"") -> 2007 | D24: yes | E24: Journal Article | F24: No reference, unclear method | H24: =IFERROR(VLOOKUP(Sources[[#This Row],[Method]],dd_analysis_graph[],2,FALSE),"") -> Not in analysis, not in graph | I24: =IFERROR(VLOOKUP(Sources[[#This Row],[Type of Publication]],dd_type_source[],2,FALSE),"") -> Publication | Z24: =IF(OR(Sources[[#This Row],[Analysis and Graph]]="Analysis and Graph",Sources[[#This Row],[Analysis and Graph]]="Not in analysis, but extra in graph"),MATCH(Sources[[#This Row],[Citekey]],Database!$B$4:$B$2385,0),"") | AA24: =IF(AG24<>"",MATCH(AG24,Sources[Citekey],0),"") | AB24: =IF(AI24<>"",MATCH(AI24,Sources[Citekey],0),"") | AC24: =IF(AK24<>"",MATCH(AK24,Sources[Citekey],0),"") | AD24: =IF(AM24<>"",MATCH(AM24,Sources[Citekey],0),"") | AE24: =IF(AO24<>"",MATCH(AO24,Sources[Citekey],0),"") | AG24: =IFERROR(IF(Sources[[#This Row],[Reference to]]<>"",LEFT(Sources[[#This Row],[Reference to]],FIND(",",Sources[[#This Row],[Reference to]])-1),""),Sources[[#This Row],[Reference to]]) | AH24: =IFERROR(RIGHT(Sources[[#This Row],[Reference to]],LEN(Sources[[#This Row],[Reference to]])-LEN($AG24)-2),"") | AI24: =IFERROR(LEFT(AH24,FIND(",",AH24)-1),AH24) | AJ24: =IFERROR(RIGHT(Sources[[#This Row],[Reference to]],LEN(Sources[[#This Row],[Reference to]])-LEN($AG24)-2-LEN($AI24)-2),"") | AK24: =IFERROR(LEFT(AJ24,FIND(",",AJ24)-1),AJ24) | AL24: =IFERROR(RIGHT(Sources[[#This Row],[Reference to]],LEN(Sources[[#This Row],[Reference to]])-LEN($AG24)-2-LEN($AI24)-2-LEN($AK24)-2),"") | AM24: =IFERROR(LEFT(AL24,FIND(",",AL24)-1),AL24) | AN24: =IFERROR(RIGHT(Sources[[#This Row],[Reference to]],LEN(Sources[[#This Row],[Reference to]])-LEN($AG24)-2-LEN($AI24)-2-LEN($AK24)-2-LEN($AM24)-2),"") | AO24: =IFERROR(LEFT(AN24,FIND(",",AN24)-1),AN24)
B25: gahleitner2013hydrogen | C25: =IFERROR(VALUE(MID(Sources[[#This Row],[Citekey]],FIND("20",Sources[[#This Row],[Citekey]]),4)),"") -> 2013 | D25: yes | E25: Journal Article | F25: Secondary source | G25: sterner2009bioenergy | H25: =IFERROR(VLOOKUP(Sources[[#This Row],[Method]],dd_analysis_graph[],2,FALSE),"") -> Not in analysis, not in graph | I25: =IFERROR(VLOOKUP(Sources[[#This Row],[Type of Publication]],dd_type_source[],2,FALSE),"") -> Publication | Z25: =IF(OR(Sources[[#This Row],[Analysis and Graph]]="Analysis and Graph",Sources[[#This Row],[Analysis and Graph]]="Not in analysis, but extra in graph"),MATCH(Sources[[#This Row],[Citekey]],Database!$B$4:$B$2385,0),"") | AA25: =IF(AG25<>"",MATCH(AG25,Sources[Citekey],0),"") -> 155 | AB25: =IF(AI25<>"",MATCH(AI25,Sources[Citekey],0),"") | AC25: =IF(AK25<>"",MATCH(AK25,Sources[Citekey],0),"") | AD25: =IF(AM25<>"",MATCH(AM25,Sources[Citekey],0),"") | AE25: =IF(AO25<>"",MATCH(AO25,Sources[Citekey],0),"") | AG25: =IFERROR(IF(Sources[[#This Row],[Reference to]]<>"",LEFT(Sources[[#This Row],[Reference to]],FIND(",",Sources[[#This Row],[Reference to]])-1),""),Sources[[#This Row],[Reference to]]) -> sterner2009bioenergy | AH25: =IFERROR(RIGHT(Sources[[#This Row],[Reference to]],LEN(Sources[[#This Row],[Reference to]])-LEN($AG25)-2),"") | AI25: =IFERROR(LEFT(AH25,FIND(",",AH25)-1),AH25) | AJ25: =IFERROR(RIGHT(Sources[[#This Row],[Reference to]],LEN(Sources[[#This Row],[Reference to]])-LEN($AG25)-2-LEN($AI25)-2),"") | AK25: =IFERROR(LEFT(AJ25,FIND(",",AJ25)-1),AJ25) | AL25: =IFERROR(RIGHT(Sources[[#This Row],[Reference to]],LEN(Sources[[#This Row],[Reference to]])-LEN($AG25)-2-LEN($AI25)-2-LEN($AK25)-2),"") | AM25: =IFERROR(LEFT(AL25,FIND(",",AL25)-1),AL25) | AN25: =IFERROR(RIGHT(Sources[[#This Row],[Reference to]],LEN(Sources[[#This Row],[Reference to]])-LEN($AG25)-2-LEN($AI25)-2-LEN($AK25)-2-LEN($AM25)-2),"") | AO25: =IFERROR(LEFT(AN25,FIND(",",AN25)-1),AN25)
B26: garmsiri2014integration | C26: =IFERROR(VALUE(MID(Sources[[#This Row],[Citekey]],FIND("20",Sources[[#This Row],[Citekey]]),4)),"") -> 2014 | D26: yes | E26: Journal Article | F26: No cost data | H26: =IFERROR(VLOOKUP(Sources[[#This Row],[Method]],dd_analysis_graph[],2,FALSE),"") -> Not in analysis, not in graph | I26: =IFERROR(VLOOKUP(Sources[[#This Row],[Type of Publication]],dd_type_source[],2,FALSE),"") -> Publication | Z26: =IF(OR(Sources[[#This Row],[Analysis and Graph]]="Analysis and Graph",Sources[[#This Row],[Analysis and Graph]]="Not in analysis, but extra in graph"),MATCH(Sources[[#This Row],[Citekey]],Database!$B$4:$B$2385,0),"") | AA26: =IF(AG26<>"",MATCH(AG26,Sources[Citekey],0),"") | AB26: =IF(AI26<>"",MATCH(AI26,Sources[Citekey],0),"") | AC26: =IF(AK26<>"",MATCH(AK26,Sources[Citekey],0),"") | AD26: =IF(AM26<>"",MATCH(AM26,Sources[Citekey],0),"") | AE26: =IF(AO26<>"",MATCH(AO26,Sources[Citekey],0),"") | AG26: =IFERROR(IF(Sources[[#This Row],[Reference to]]<>"",LEFT(Sources[[#This Row],[Reference to]],FIND(",",Sources[[#This Row],[Reference to]])-1),""),Sources[[#This Row],[Reference to]]) | AH26: =IFERROR(RIGHT(Sources[[#This Row],[Reference to]],LEN(Sources[[#This Row],[Reference to]])-LEN($AG26)-2),"") | AI26: =IFERROR(LEFT(AH26,FIND(",",AH26)-1),AH26) | AJ26: =IFERROR(RIGHT(Sources[[#This Row],[Reference to]],LEN(Sources[[#This Row],[Reference to]])-LEN($AG26)-2-LEN($AI26)-2),"") | AK26: =IFERROR(LEFT(AJ26,FIND(",",AJ26)-1),AJ26) | AL26: =IFERROR(RIGHT(Sources[[#This Row],[Reference to]],LEN(Sources[[#This Row],[Reference to]])-LEN($AG26)-2-LEN($AI26)-2-LEN($AK26)-2),"") | AM26: =IFERROR(LEFT(AL26,FIND(",",AL26)-1),AL26) | AN26: =IFERROR(RIGHT(Sources[[#This Row],[Reference to]],LEN(Sources[[#This Row],[Reference to]])-LEN($AG26)-2-LEN($AI26)-2-LEN($AK26)-2-LEN($AM26)-2),"") | AO26: =IFERROR(LEFT(AN26,FIND(",",AN26)-1),AN26)
B27: giglio2015synthetic | C27: =IFERROR(VALUE(MID(Sources[[#This Row],[Citekey]],FIND("20",Sources[[#This Row],[Citekey]]),4)),"") -> 2015 | D27: yes | E27: Journal Article | F27: No cost data | H27: =IFERROR(VLOOKUP(Sources[[#This Row],[Method]],dd_analysis_graph[],2,FALSE),"") -> Not in analysis, not in graph | I27: =IFERROR(VLOOKUP(Sources[[#This Row],[Type of Publication]],dd_type_source[],2,FALSE),"") -> Publication | Z27: =IF(OR(Sources[[#This Row],[Analysis and Graph]]="Analysis and Graph",Sources[[#This Row],[Analysis and Graph]]="Not in analysis, but extra in graph"),MATCH(Sources[[#This Row],[Citekey]],Database!$B$4:$B$2385,0),"") | AA27: =IF(AG27<>"",MATCH(AG27,Sources[Citekey],0),"") | AB27: =IF(AI27<>"",MATCH(AI27,Sources[Citekey],0),"") | AC27: =IF(AK27<>"",MATCH(AK27,Sources[Citekey],0),"") | AD27: =IF(AM27<>"",MATCH(AM27,Sources[Citekey],0),"") | AE27: =IF(AO27<>"",MATCH(AO27,Sources[Citekey],0),"") | AG27: =IFERROR(IF(Sources[[#This Row],[Reference to]]<>"",LEFT(Sources[[#This Row],[Reference to]],FIND(",",Sources[[#This Row],[Reference to]])-1),""),Sources[[#This Row],[Reference to]]) | AH27: =IFERROR(RIGHT(Sources[[#This Row],[Reference to]],LEN(Sources[[#This Row],[Reference to]])-LEN($AG27)-2),"") | AI27: =IFERROR(LEFT(AH27,FIND(",",AH27)-1),AH27) | AJ27: =IFERROR(RIGHT(Sources[[#This Row],[Reference to]],LEN(Sources[[#This Row],[Reference to]])-LEN($AG27)-2-LEN($AI27)-2),"") | AK27: =IFERROR(LEFT(AJ27,FIND(",",AJ27)-1),AJ27) | AL27: =IFERROR(RIGHT(Sources[[#This Row],[Reference to]],LEN(Sources[[#This Row],[Reference to]])-LEN($AG27)-2-LEN($AI27)-2-LEN($AK27)-2),"") | AM27: =IFERROR(LEFT(AL27,FIND(",",AL27)-1),AL27) | AN27: =IFERROR(RIGHT(Sources[[#This Row],[Reference to]],LEN(Sources[[#This Row],[Reference to]])-LEN($AG27)-2-LEN($AI27)-2-LEN($AK27)-2-LEN($AM27)-2),"") | AO27: =IFERROR(LEFT(AN27,FIND(",",AN27)-1),AN27)
B28: gonzalez2004the | C28: =IFERROR(VALUE(MID(Sources[[#This Row],[Citekey]],FIND("20",Sources[[#This Row],[Citekey]]),4)),"") -> 2004 | D28: yes | E28: Journal Article | F28: Original analysis, industry data | H28: =IFERROR(VLOOKUP(Sources[[#This Row],[Method]],dd_analysis_graph[],2,FALSE),"") -> Analysis and Graph | I28: =IFERROR(VLOOKUP(Sources[[#This Row],[Type of Publication]],dd_type_source[],2,FALSE),"") -> Publication | Z28: =IF(OR(Sources[[#This Row],[Analysis and Graph]]="Analysis and Graph",Sources[[#This Row],[Analysis and Graph]]="Not in analysis, but extra in graph"),MATCH(Sources[[#This Row],[Citekey]],Database!$B$4:$B$2385,0),"") -> 433 | AA28: =IF(AG28<>"",MATCH(AG28,Sources[Citekey],0),"") | AB28: =IF(AI28<>"",MATCH(AI28,Sources[Citekey],0),"") | AC28: =IF(AK28<>"",MATCH(AK28,Sources[Citekey],0),"") | AD28: =IF(AM28<>"",MATCH(AM28,Sources[Citekey],0),"") | AE28: =IF(AO28<>"",MATCH(AO28,Sources[Citekey],0),"") | AG28: =IFERROR(IF(Sources[[#This Row],[Reference to]]<>"",LEFT(Sources[[#This Row],[Reference to]],FIND(",",Sources[[#This Row],[Reference to]])-1),""),Sources[[#This Row],[Reference to]]) | AH28: =IFERROR(RIGHT(Sources[[#This Row],[Reference to]],LEN(Sources[[#This Row],[Reference to]])-LEN($AG28)-2),"") | AI28: =IFERROR(LEFT(AH28,FIND(",",AH28)-1),AH28) | AJ28: =IFERROR(RIGHT(Sources[[#This Row],[Reference to]],LEN(Sources[[#This Row],[Reference to]])-LEN($AG28)-2-LEN($AI28)-2),"") | AK28: =IFERROR(LEFT(AJ28,FIND(",",AJ28)-1),AJ28) | AL28: =IFERROR(RIGHT(Sources[[#This Row],[Reference to]],LEN(Sources[[#This Row],[Reference to]])-LEN($AG28)-2-LEN($AI28)-2-LEN($AK28)-2),"") | AM28: =IFERROR(LEFT(AL28,FIND(",",AL28)-1),AL28) | AN28: =IFERROR(RIGHT(Sources[[#This Row],[Reference to]],LEN(Sources[[#This Row],[Reference to]])-LEN($AG28)-2-LEN($AI28)-2-LEN($AK28)-2-LEN($AM28)-2),"") | AO28: =IFERROR(LEFT(AN28,FIND(",",AN28)-1),AN28)
B29: gotz2016renewable | C29: 2016 | D29: yes | E29: Journal Article | F29: Original review multiple sources | G29: buchholz2014power, lehner2014power | H29: =IFERROR(VLOOKUP(Sources[[#This Row],[Method]],dd_analysis_graph[],2,FALSE),"") -> Analysis and Graph | I29: =IFERROR(VLOOKUP(Sources[[#This Row],[Type of Publication]],dd_type_source[],2,FALSE),"") -> Publication | Z29: =IF(OR(Sources[[#This Row],[Analysis and Graph]]="Analysis and Graph",Sources[[#This Row],[Analysis and Graph]]="Not in analysis, but extra in graph"),MATCH(Sources[[#This Row],[Citekey]],Database!$B$4:$B$2385,0),"") -> 1 | AA29: =IF(AG29<>"",MATCH(AG29,Sources[Citekey],0),"") -> 15 | AB29: =IF(AI29<>"",MATCH(AI29,Sources[Citekey],0),"") -> 44 | AC29: =IF(AK29<>"",MATCH(AK29,Sources[Citekey],0),"") | AD29: =IF(AM29<>"",MATCH(AM29,Sources[Citekey],0),"") | AE29: =IF(AO29<>"",MATCH(AO29,Sources[Citekey],0),"") | AG29: =IFERROR(IF(Sources[[#This Row],[Reference to]]<>"",LEFT(Sources[[#This Row],[Reference to]],FIND(",",Sources[[#This Row],[Reference to]])-1),""),Sources[[#This Row],[Reference to]]) -> buchholz2014power | AH29: =IFERROR(RIGHT(Sources[[#This Row],[Reference to]],LEN(Sources[[#This Row],[Reference to]])-LEN($AG29)-2),"") -> lehner2014power | AI29: =IFERROR(LEFT(AH29,FIND(",",AH29)-1),AH29) -> lehner2014power | AJ29: =IFERROR(RIGHT(Sources[[#This Row],[Reference to]],LEN(Sources[[#This Row],[Reference to]])-LEN($AG29)-2-LEN($AI29)-2),"") | AK29: =IFERROR(LEFT(AJ29,FIND(",",AJ29)-1),AJ29) | AL29: =IFERROR(RIGHT(Sources[[#This Row],[Reference to]],LEN(Sources[[#This Row],[Reference to]])-LEN($AG29)-2-LEN($AI29)-2-LEN($AK29)-2),"") | AM29: =IFERROR(LEFT(AL29,FIND(",",AL29)-1),AL29) | AN29: =IFERROR(RIGHT(Sources[[#This Row],[Reference to]],LEN(Sources[[#This Row],[Reference to]])-LEN($AG29)-2-LEN($AI29)-2-LEN($AK29)-2-LEN($AM29)-2),"") | AO29: =IFERROR(LEFT(AN29,FIND(",",AN29)-1),AN29)
B30: greiner2007norwegian | C30: 2007 | D30: yes | E30: Journal Article | F30: Original analysis, industry data | H30: =IFERROR(VLOOKUP(Sources[[#This Row],[Method]],dd_analysis_graph[],2,FALSE),"") -> Analysis and Graph | I30: =IFERROR(VLOOKUP(Sources[[#This Row],[Type of Publication]],dd_type_source[],2,FALSE),"") -> Publication | Z30: =IF(OR(Sources[[#This Row],[Analysis and Graph]]="Analysis and Graph",Sources[[#This Row],[Analysis and Graph]]="Not in analysis, but extra in graph"),MATCH(Sources[[#This Row],[Citekey]],Database!$B$4:$B$2385,0),"") -> 49 | AA30: =IF(AG30<>"",MATCH(AG30,Sources[Citekey],0),"") | AB30: =IF(AI30<>"",MATCH(AI30,Sources[Citekey],0),"") | AC30: =IF(AK30<>"",MATCH(AK30,Sources[Citekey],0),"") | AD30: =IF(AM30<>"",MATCH(AM30,Sources[Citekey],0),"") | AE30: =IF(AO30<>"",MATCH(AO30,Sources[Citekey],0),"") | AG30: =IFERROR(IF(Sources[[#This Row],[Reference to]]<>"",LEFT(Sources[[#This Row],[Reference to]],FIND(",",Sources[[#This Row],[Reference to]])-1),""),Sources[[#This Row],[Reference to]]) | AH30: =IFERROR(RIGHT(Sources[[#This Row],[Reference to]],LEN(Sources[[#This Row],[Reference to]])-LEN($AG30)-2),"") | AI30: =IFERROR(LEFT(AH30,FIND(",",AH30)-1),AH30) | AJ30: =IFERROR(RIGHT(Sources[[#This Row],[Reference to]],LEN(Sources[[#This Row],[Reference to]])-LEN($AG30)-2-LEN($AI30)-2),"") | AK30: =IFERROR(LEFT(AJ30,FIND(",",AJ30)-1),AJ30) | AL30: =IFERROR(RIGHT(Sources[[#This Row],[Reference to]],LEN(Sources[[#This Row],[Reference to]])-LEN($AG30)-2-LEN($AI30)-2-LEN($AK30)-2),"") | AM30: =IFERROR(LEFT(AL30,FIND(",",AL30)-1),AL30) | AN30: =IFERROR(RIGHT(Sources[[#This Row],[Reference to]],LEN(Sources[[#This Row],[Reference to]])-LEN($AG30)-2-LEN($AI30)-2-LEN($AK30)-2-LEN($AM30)-2),"") | AO30: =IFERROR(LEFT(AN30,FIND(",",AN30)-1),AN30)
B31: guandalini2015power | C31: =IFERROR(VALUE(MID(Sources[[#This Row],[Citekey]],FIND("20",Sources[[#This Row],[Citekey]]),4)),"") -> 2015 | D31: yes | E31: Journal Article | F31: Secondary source | G31: bajohr2011speicherung | H31: =IFERROR(VLOOKUP(Sources[[#This Row],[Method]],dd_analysis_graph[],2,FALSE),"") -> Not in analysis, not in graph | I31: =IFERROR(VLOOKUP(Sources[[#This Row],[Type of Publication]],dd_type_source[],2,FALSE),"") -> Publication | Z31: =IF(OR(Sources[[#This Row],[Analysis and Graph]]="Analysis and Graph",Sources[[#This Row],[Analysis and Graph]]="Not in analysis, but extra in graph"),MATCH(Sources[[#This Row],[Citekey]],Database!$B$4:$B$2385,0),"") | AA31: =IF(AG31<>"",MATCH(AG31,Sources[Citekey],0),"") -> 5 | AB31: =IF(AI31<>"",MATCH(AI31,Sources[Citekey],0),"") | AC31: =IF(AK31<>"",MATCH(AK31,Sources[Citekey],0),"") | AD31: =IF(AM31<>"",MATCH(AM31,Sources[Citekey],0),"") | AE31: =IF(AO31<>"",MATCH(AO31,Sources[Citekey],0),"") | AG31: =IFERROR(IF(Sources[[#This Row],[Reference to]]<>"",LEFT(Sources[[#This Row],[Reference to]],FIND(",",Sources[[#This Row],[Reference to]])-1),""),Sources[[#This Row],[Reference to]]) -> bajohr2011speicherung | AH31: =IFERROR(RIGHT(Sources[[#This Row],[Reference to]],LEN(Sources[[#This Row],[Reference to]])-LEN($AG31)-2),"") | AI31: =IFERROR(LEFT(AH31,FIND(",",AH31)-1),AH31) | AJ31: =IFERROR(RIGHT(Sources[[#This Row],[Reference to]],LEN(Sources[[#This Row],[Reference to]])-LEN($AG31)-2-LEN($AI31)-2),"") | AK31: =IFERROR(LEFT(AJ31,FIND(",",AJ31)-1),AJ31) | AL31: =IFERROR(RIGHT(Sources[[#This Row],[Reference to]],LEN(Sources[[#This Row],[Reference to]])-LEN($AG31)-2-LEN($AI31)-2-LEN($AK31)-2),"") | AM31: =IFERROR(LEFT(AL31,FIND(",",AL31)-1),AL31) | AN31: =IFERROR(RIGHT(Sources[[#This Row],[Reference to]],LEN(Sources[[#This Row],[Reference to]])-LEN($AG31)-2-LEN($AI31)-2-LEN($AK31)-2-LEN($AM31)-2),"") | AO31: =IFERROR(LEFT(AN31,FIND(",",AN31)-1),AN31)
B32: guinot2015profitability | C32: =IFERROR(VALUE(MID(Sources[[#This Row],[Citekey]],FIND("20",Sources[[#This Row],[Citekey]]),4)),"") -> 2015 | D32: yes | E32: Journal Article | F32: Original analysis, industry data | H32: =IFERROR(VLOOKUP(Sources[[#This Row],[Method]],dd_analysis_graph[],2,FALSE),"") -> Analysis and Graph | I32: =IFERROR(VLOOKUP(Sources[[#This Row],[Type of Publication]],dd_type_source[],2,FALSE),"") -> Publication | Z32: =IF(OR(Sources[[#This Row],[Analysis and Graph]]="Analysis and Graph",Sources[[#This Row],[Analysis and Graph]]="Not in analysis, but extra in graph"),MATCH(Sources[[#This Row],[Citekey]],Database!$B$4:$B$2385,0),"") -> 577 | AA32: =IF(AG32<>"",MATCH(AG32,Sources[Citekey],0),"") | AB32: =IF(AI32<>"",MATCH(AI32,Sources[Citekey],0),"") | AC32: =IF(AK32<>"",MATCH(AK32,Sources[Citekey],0),"") | AD32: =IF(AM32<>"",MATCH(AM32,Sources[Citekey],0),"") | AE32: =IF(AO32<>"",MATCH(AO32,Sources[Citekey],0),"") | AG32: =IFERROR(IF(Sources[[#This Row],[Reference to]]<>"",LEFT(Sources[[#This Row],[Reference to]],FIND(",",Sources[[#This Row],[Reference to]])-1),""),Sources[[#This Row],[Reference to]]) | AH32: =IFERROR(RIGHT(Sources[[#This Row],[Reference to]],LEN(Sources[[#This Row],[Reference to]])-LEN($AG32)-2),"") | AI32: =IFERROR(LEFT(AH32,FIND(",",AH32)-1),AH32) | AJ32: =IFERROR(RIGHT(Sources[[#This Row],[Reference to]],LEN(Sources[[#This Row],[Reference to]])-LEN($AG32)-2-LEN($AI32)-2),"") | AK32: =IFERROR(LEFT(AJ32,FIND(",",AJ32)-1),AJ32) | AL32: =IFERROR(RIGHT(Sources[[#This Row],[Reference to]],LEN(Sources[[#This Row],[Reference to]])-LEN($AG32)-2-LEN($AI32)-2-LEN($AK32)-2),"") | AM32: =IFERROR(LEFT(AL32,FIND(",",AL32)-1),AL32) | AN32: =IFERROR(RIGHT(Sources[[#This Row],[Reference to]],LEN(Sources[[#This Row],[Reference to]])-LEN($AG32)-2-LEN($AI32)-2-LEN($AK32)-2-LEN($AM32)-2),"") | AO32: =IFERROR(LEFT(AN32,FIND(",",AN32)-1),AN32)
B33: hocevar2008hydrogen | C33: 2008 | D33: yes | E33: Journal Article | F33: Original analysis, industry data | H33: =IFERROR(VLOOKUP(Sources[[#This Row],[Method]],dd_analysis_graph[],2,FALSE),"") -> Analysis and Graph | I33: =IFERROR(VLOOKUP(Sources[[#This Row],[Type of Publication]],dd_type_source[],2,FALSE),"") -> Publication | Z33: =IF(OR(Sources[[#This Row],[Analysis and Graph]]="Analysis and Graph",Sources[[#This Row],[Analysis and Graph]]="Not in analysis, but extra in graph"),MATCH(Sources[[#This Row],[Citekey]],Database!$B$4:$B$2385,0),"") -> 313 | AA33: =IF(AG33<>"",MATCH(AG33,Sources[Citekey],0),"") | AB33: =IF(AI33<>"",MATCH(AI33,Sources[Citekey],0),"") | AC33: =IF(AK33<>"",MATCH(AK33,Sources[Citekey],0),"") | AD33: =IF(AM33<>"",MATCH(AM33,Sources[Citekey],0),"") | AE33: =IF(AO33<>"",MATCH(AO33,Sources[Citekey],0),"") | AG33: =IFERROR(IF(Sources[[#This Row],[Reference to]]<>"",LEFT(Sources[[#This Row],[Reference to]],FIND(",",Sources[[#This Row],[Reference to]])-1),""),Sources[[#This Row],[Reference to]]) | AH33: =IFERROR(RIGHT(Sources[[#This Row],[Reference to]],LEN(Sources[[#This Row],[Reference to]])-LEN($AG33)-2),"") | AI33: =IFERROR(LEFT(AH33,FIND(",",AH33)-1),AH33) | AJ33: =IFERROR(RIGHT(Sources[[#This Row],[Reference to]],LEN(Sources[[#This Row],[Reference to]])-LEN($AG33)-2-LEN($AI33)-2),"") | AK33: =IFERROR(LEFT(AJ33,FIND(",",AJ33)-1),AJ33) | AL33: =IFERROR(RIGHT(Sources[[#This Row],[Reference to]],LEN(Sources[[#This Row],[Reference to]])-LEN($AG33)-2-LEN($AI33)-2-LEN($AK33)-2),"") | AM33: =IFERROR(LEFT(AL33,FIND(",",AL33)-1),AL33) | AN33: =IFERROR(RIGHT(Sources[[#This Row],[Reference to]],LEN(Sources[[#This Row],[Reference to]])-LEN($AG33)-2-LEN($AI33)-2-LEN($AK33)-2-LEN($AM33)-2),"") | AO33: =IFERROR(LEFT(AN33,FIND(",",AN33)-1),AN33)
B34: holladay2009an | C34: =IFERROR(VALUE(MID(Sources[[#This Row],[Citekey]],FIND("20",Sources[[#This Row],[Citekey]]),4)),"") -> 2009 | D34: yes | E34: Journal Article | F34: Secondary source | G34: turner2008renewable | H34: =IFERROR(VLOOKUP(Sources[[#This Row],[Method]],dd_analysis_graph[],2,FALSE),"") -> Not in analysis, not in graph | I34: =IFERROR(VLOOKUP(Sources[[#This Row],[Type of Publication]],dd_type_source[],2,FALSE),"") -> Publication | Z34: =IF(OR(Sources[[#This Row],[Analysis and Graph]]="Analysis and Graph",Sources[[#This Row],[Analysis and Graph]]="Not in analysis, but extra in graph"),MATCH(Sources[[#This Row],[Citekey]],Database!$B$4:$B$2385,0),"") | AA34: =IF(AG34<>"",MATCH(AG34,Sources[Citekey],0),"") -> 71 | AB34: =IF(AI34<>"",MATCH(AI34,Sources[Citekey],0),"") | AC34: =IF(AK34<>"",MATCH(AK34,Sources[Citekey],0),"") | AD34: =IF(AM34<>"",MATCH(AM34,Sources[Citekey],0),"") | AE34: =IF(AO34<>"",MATCH(AO34,Sources[Citekey],0),"") | AG34: =IFERROR(IF(Sources[[#This Row],[Reference to]]<>"",LEFT(Sources[[#This Row],[Reference to]],FIND(",",Sources[[#This Row],[Reference to]])-1),""),Sources[[#This Row],[Reference to]]) -> turner2008renewable | AH34: =IFERROR(RIGHT(Sources[[#This Row],[Reference to]],LEN(Sources[[#This Row],[Reference to]])-LEN($AG34)-2),"") | AI34: =IFERROR(LEFT(AH34,FIND(",",AH34)-1),AH34) | AJ34: =IFERROR(RIGHT(Sources[[#This Row],[Reference to]],LEN(Sources[[#This Row],[Reference to]])-LEN($AG34)-2-LEN($AI34)-2),"") | AK34: =IFERROR(LEFT(AJ34,FIND(",",AJ34)-1),AJ34) | AL34: =IFERROR(RIGHT(Sources[[#This Row],[Reference to]],LEN(Sources[[#This Row],[Reference to]])-LEN($AG34)-2-LEN($AI34)-2-LEN($AK34)-2),"") | AM34: =IFERROR(LEFT(AL34,FIND(",",AL34)-1),AL34) | AN34: =IFERROR(RIGHT(Sources[[#This Row],[Reference to]],LEN(Sources[[#This Row],[Reference to]])-LEN($AG34)-2-LEN($AI34)-2-LEN($AK34)-2-LEN($AM34)-2),"") | AO34: =IFERROR(LEFT(AN34,FIND(",",AN34)-1),AN34)
B35: jensen2007hydrogen | C35: =IFERROR(VALUE(MID(Sources[[#This Row],[Citekey]],FIND("20",Sources[[#This Row],[Citekey]]),4)),"") -> 2007 | D35: yes | E35: Journal Article | F35: No cost data | H35: =IFERROR(VLOOKUP(Sources[[#This Row],[Method]],dd_analysis_graph[],2,FALSE),"") -> Not in analysis, not in graph | I35: =IFERROR(VLOOKUP(Sources[[#This Row],[Type of Publication]],dd_type_source[],2,FALSE),"") -> Publication | Z35: =IF(OR(Sources[[#This Row],[Analysis and Graph]]="Analysis and Graph",Sources[[#This Row],[Analysis and Graph]]="Not in analysis, but extra in graph"),MATCH(Sources[[#This Row],[Citekey]],Database!$B$4:$B$2385,0),"") | AA35: =IF(AG35<>"",MATCH(AG35,Sources[Citekey],0),"") | AB35: =IF(AI35<>"",MATCH(AI35,Sources[Citekey],0),"") | AC35: =IF(AK35<>"",MATCH(AK35,Sources[Citekey],0),"") | AD35: =IF(AM35<>"",MATCH(AM35,Sources[Citekey],0),"") | AE35: =IF(AO35<>"",MATCH(AO35,Sources[Citekey],0),"") | AG35: =IFERROR(IF(Sources[[#This Row],[Reference to]]<>"",LEFT(Sources[[#This Row],[Reference to]],FIND(",",Sources[[#This Row],[Reference to]])-1),""),Sources[[#This Row],[Reference to]]) | AH35: =IFERROR(RIGHT(Sources[[#This Row],[Reference to]],LEN(Sources[[#This Row],[Reference to]])-LEN($AG35)-2),"") | AI35: =IFERROR(LEFT(AH35,FIND(",",AH35)-1),AH35) | AJ35: =IFERROR(RIGHT(Sources[[#This Row],[Reference to]],LEN(Sources[[#This Row],[Reference to]])-LEN($AG35)-2-LEN($AI35)-2),"") | AK35: =IFERROR(LEFT(AJ35,FIND(",",AJ35)-1),AJ35) | AL35: =IFERROR(RIGHT(Sources[[#This Row],[Reference to]],LEN(Sources[[#This Row],[Reference to]])-LEN($AG35)-2-LEN($AI35)-2-LEN($AK35)-2),"") | AM35: =IFERROR(LEFT(AL35,FIND(",",AL35)-1),AL35) | AN35: =IFERROR(RIGHT(Sources[[#This Row],[Reference to]],LEN(Sources[[#This Row],[Reference to]])-LEN($AG35)-2-LEN($AI35)-2-LEN($AK35)-2-LEN($AM35)-2),"") | AO35: =IFERROR(LEFT(AN35,FIND(",",AN35)-1),AN35)
B36: jensen2015large | C36: =IFERROR(VALUE(MID(Sources[[#This Row],[Citekey]],FIND("20",Sources[[#This Row],[Citekey]]),4)),"") -> 2015 | D36: yes | E36: Journal Article | F36: Secondary source | H36: =IFERROR(VLOOKUP(Sources[[#This Row],[Method]],dd_analysis_graph[],2,FALSE),"") -> Not in analysis, not in graph | I36: =IFERROR(VLOOKUP(Sources[[#This Row],[Type of Publication]],dd_type_source[],2,FALSE),"") -> Publication | Z36: =IF(OR(Sources[[#This Row],[Analysis and Graph]]="Analysis and Graph",Sources[[#This Row],[Analysis and Graph]]="Not in analysis, but extra in graph"),MATCH(Sources[[#This Row],[Citekey]],Database!$B$4:$B$2385,0),"") | AA36: =IF(AG36<>"",MATCH(AG36,Sources[Citekey],0),"") | AB36: =IF(AI36<>"",MATCH(AI36,Sources[Citekey],0),"") | AC36: =IF(AK36<>"",MATCH(AK36,Sources[Citekey],0),"") | AD36: =IF(AM36<>"",MATCH(AM36,Sources[Citekey],0),"") | AE36: =IF(AO36<>"",MATCH(AO36,Sources[Citekey],0),"") | AG36: =IFERROR(IF(Sources[[#This Row],[Reference to]]<>"",LEFT(Sources[[#This Row],[Reference to]],FIND(",",Sources[[#This Row],[Reference to]])-1),""),Sources[[#This Row],[Reference to]]) | AH36: =IFERROR(RIGHT(Sources[[#This Row],[Reference to]],LEN(Sources[[#This Row],[Reference to]])-LEN($AG36)-2),"") | AI36: =IFERROR(LEFT(AH36,FIND(",",AH36)-1),AH36) | AJ36: =IFERROR(RIGHT(Sources[[#This Row],[Reference to]],LEN(Sources[[#This Row],[Reference to]])-LEN($AG36)-2-LEN($AI36)-2),"") | AK36: =IFERROR(LEFT(AJ36,FIND(",",AJ36)-1),AJ36) | AL36: =IFERROR(RIGHT(Sources[[#This Row],[Reference to]],LEN(Sources[[#This Row],[Reference to]])-LEN($AG36)-2-LEN($AI36)-2-LEN($AK36)-2),"") | AM36: =IFERROR(LEFT(AL36,FIND(",",AL36)-1),AL36) | AN36: =IFERROR(RIGHT(Sources[[#This Row],[Reference to]],LEN(Sources[[#This Row],[Reference to]])-LEN($AG36)-2-LEN($AI36)-2-LEN($AK36)-2-LEN($AM36)-2),"") | AO36: =IFERROR(LEFT(AN36,FIND(",",AN36)-1),AN36)
B37: jentsch2014optimal | C37: =IFERROR(VALUE(MID(Sources[[#This Row],[Citekey]],FIND("20",Sources[[#This Row],[Citekey]]),4)),"") -> 2014 | D37: yes | E37: Journal Article | F37: Original analysis, industry data | H37: =IFERROR(VLOOKUP(Sources[[#This Row],[Method]],dd_analysis_graph[],2,FALSE),"") -> Analysis and Graph | I37: =IFERROR(VLOOKUP(Sources[[#This Row],[Type of Publication]],dd_type_source[],2,FALSE),"") -> Publication | Z37: =IF(OR(Sources[[#This Row],[Analysis and Graph]]="Analysis and Graph",Sources[[#This Row],[Analysis and Graph]]="Not in analysis, but extra in graph"),MATCH(Sources[[#This Row],[Citekey]],Database!$B$4:$B$2385,0),"") -> 601 | AA37: =IF(AG37<>"",MATCH(AG37,Sources[Citekey],0),"") | AB37: =IF(AI37<>"",MATCH(AI37,Sources[Citekey],0),"") | AC37: =IF(AK37<>"",MATCH(AK37,Sources[Citekey],0),"") | AD37: =IF(AM37<>"",MATCH(AM37,Sources[Citekey],0),"") | AE37: =IF(AO37<>"",MATCH(AO37,Sources[Citekey],0),"") | AG37: =IFERROR(IF(Sources[[#This Row],[Reference to]]<>"",LEFT(Sources[[#This Row],[Reference to]],FIND(",",Sources[[#This Row],[Reference to]])-1),""),Sources[[#This Row],[Reference to]]) | AH37: =IFERROR(RIGHT(Sources[[#This Row],[Reference to]],LEN(Sources[[#This Row],[Reference to]])-LEN($AG37)-2),"") | AI37: =IFERROR(LEFT(AH37,FIND(",",AH37)-1),AH37) | AJ37: =IFERROR(RIGHT(Sources[[#This Row],[Reference to]],LEN(Sources[[#This Row],[Reference to]])-LEN($AG37)-2-LEN($AI37)-2),"") | AK37: =IFERROR(LEFT(AJ37,FIND(",",AJ37)-1),AJ37) | AL37: =IFERROR(RIGHT(Sources[[#This Row],[Reference to]],LEN(Sources[[#This Row],[Reference to]])-LEN($AG37)-2-LEN($AI37)-2-LEN($AK37)-2),"") | AM37: =IFERROR(LEFT(AL37,FIND(",",AL37)-1),AL37) | AN37: =IFERROR(RIGHT(Sources[[#This Row],[Reference to]],LEN(Sources[[#This Row],[Reference to]])-LEN($AG37)-2-LEN($AI37)-2-LEN($AK37)-2-LEN($AM37)-2),"") | AO37: =IFERROR(LEFT(AN37,FIND(",",AN37)-1),AN37)
B38: jorgensen2008production | C38: =IFERROR(VALUE(MID(Sources[[#This Row],[Citekey]],FIND("20",Sources[[#This Row],[Citekey]]),4)),"") -> 2008 | D38: yes | E38: Journal Article | F38: Secondary source | G38: sorensen2008comparative, linnemann2007realistic, saxe2007advantages, floch2007on, ivy2004summary, gonzalez2004role, greiner2007norwegian, bockris2007estimates | H38: =IFERROR(VLOOKUP(Sources[[#This Row],[Method]],dd_analysis_graph[],2,FALSE),"") -> Not in analysis, not in graph | I38: =IFERROR(VLOOKUP(Sources[[#This Row],[Type of Publication]],dd_type_source[],2,FALSE),"") -> Publication | Z38: =IF(OR(Sources[[#This Row],[Analysis and Graph]]="Analysis and Graph",Sources[[#This Row],[Analysis and Graph]]="Not in analysis, but extra in graph"),MATCH(Sources[[#This Row],[Citekey]],Database!$B$4:$B$2385,0),"") | AA38: =IF(AG38<>"",MATCH(AG38,Sources[Citekey],0),"") -> 152 | AB38: =IF(AI38<>"",MATCH(AI38,Sources[Citekey],0),"") -> 45 | AC38: =IF(AK38<>"",MATCH(AK38,Sources[Citekey],0),"") -> 64 | AD38: =IF(AM38<>"",MATCH(AM38,Sources[Citekey],0),"") -> 22 | AE38: =IF(AO38<>"",MATCH(AO38,Sources[Citekey],0),"") -> 130 | AG38: =IFERROR(IF(Sources[[#This Row],[Reference to]]<>"",LEFT(Sources[[#This Row],[Reference to]],FIND(",",Sources[[#This Row],[Reference to]])-1),""),Sources[[#This Row],[Reference to]]) -> sorensen2008comparative | AH38: =IFERROR(RIGHT(Sources[[#This Row],[Reference to]],LEN(Sources[[#This Row],[Reference to]])-LEN($AG38)-2),"") -> linnemann2007realistic, saxe2007advantages, floch2007on, ivy2004summary, gonzalez2004role, greiner2007norwegian, bockris2007estimates | AI38: =IFERROR(LEFT(AH38,FIND(",",AH38)-1),AH38) -> linnemann2007realistic | AJ38: =IFERROR(RIGHT(Sources[[#This Row],[Reference to]],LEN(Sources[[#This Row],[Reference to]])-LEN($AG38)-2-LEN($AI38)-2),"") -> saxe2007advantages, floch2007on, ivy2004summary, gonzalez2004role, greiner2007norwegian, bockris2007estimates | AK38: =IFERROR(LEFT(AJ38,FIND(",",AJ38)-1),AJ38) -> saxe2007advantages | AL38: =IFERROR(RIGHT(Sources[[#This Row],[Reference to]],LEN(Sources[[#This Row],[Reference to]])-LEN($AG38)-2-LEN($AI38)-2-LEN($AK38)-2),"") -> floch2007on, ivy2004summary, gonzalez2004role, greiner2007norwegian, bockris2007estimates | AM38: =IFERROR(LEFT(AL38,FIND(",",AL38)-1),AL38) -> floch2007on | AN38: =IFERROR(RIGHT(Sources[[#This Row],[Reference to]],LEN(Sources[[#This Row],[Reference to]])-LEN($AG38)-2-LEN($AI38)-2-LEN($AK38)-2-LEN($AM38)-2),"") -> ivy2004summary, gonzalez2004role, greiner2007norwegian, bockris2007estimates | AO38: =IFERROR(LEFT(AN38,FIND(",",AN38)-1),AN38) -> ivy2004summary
B39: julch2016comparison | C39: 2016 | D39: yes | E39: Journal Article | F39: Original analysis, industry data | H39: =IFERROR(VLOOKUP(Sources[[#This Row],[Method]],dd_analysis_graph[],2,FALSE),"") -> Analysis and Graph | I39: =IFERROR(VLOOKUP(Sources[[#This Row],[Type of Publication]],dd_type_source[],2,FALSE),"") -> Publication | Z39: =IF(OR(Sources[[#This Row],[Analysis and Graph]]="Analysis and Graph",Sources[[#This Row],[Analysis and Graph]]="Not in analysis, but extra in graph"),MATCH(Sources[[#This Row],[Citekey]],Database!$B$4:$B$2385,0),"") -> 1105 | AA39: =IF(AG39<>"",MATCH(AG39,Sources[Citekey],0),"") | AB39: =IF(AI39<>"",MATCH(AI39,Sources[Citekey],0),"") | AC39: =IF(AK39<>"",MATCH(AK39,Sources[Citekey],0),"") | AD39: =IF(AM39<>"",MATCH(AM39,Sources[Citekey],0),"") | AE39: =IF(AO39<>"",MATCH(AO39,Sources[Citekey],0),"") | AG39: =IFERROR(IF(Sources[[#This Row],[Reference to]]<>"",LEFT(Sources[[#This Row],[Reference to]],FIND(",",Sources[[#This Row],[Reference to]])-1),""),Sources[[#This Row],[Reference to]]) | AH39: =IFERROR(RIGHT(Sources[[#This Row],[Reference to]],LEN(Sources[[#This Row],[Reference to]])-LEN($AG39)-2),"") | AI39: =IFERROR(LEFT(AH39,FIND(",",AH39)-1),AH39) | AJ39: =IFERROR(RIGHT(Sources[[#This Row],[Reference to]],LEN(Sources[[#This Row],[Reference to]])-LEN($AG39)-2-LEN($AI39)-2),"") | AK39: =IFERROR(LEFT(AJ39,FIND(",",AJ39)-1),AJ39) | AL39: =IFERROR(RIGHT(Sources[[#This Row],[Reference to]],LEN(Sources[[#This Row],[Reference to]])-LEN($AG39)-2-LEN($AI39)-2-LEN($AK39)-2),"") | AM39: =IFERROR(LEFT(AL39,FIND(",",AL39)-1),AL39) | AN39: =IFERROR(RIGHT(Sources[[#This Row],[Reference to]],LEN(Sources[[#This Row],[Reference to]])-LEN($AG39)-2-LEN($AI39)-2-LEN($AK39)-2-LEN($AM39)-2),"") | AO39: =IFERROR(LEFT(AN39,FIND(",",AN39)-1),AN39)
B40: karlsson2008optimal | C40: =IFERROR(VALUE(MID(Sources[[#This Row],[Citekey]],FIND("20",Sources[[#This Row],[Citekey]]),4)),"") -> 2008 | D40: yes | E40: Journal Article | F40: Secondary source | G40: sorensen2008comparative | H40: =IFERROR(VLOOKUP(Sources[[#This Row],[Method]],dd_analysis_graph[],2,FALSE),"") -> Not in analysis, not in graph | I40: =IFERROR(VLOOKUP(Sources[[#This Row],[Type of Publication]],dd_type_source[],2,FALSE),"") -> Publication | Z40: =IF(OR(Sources[[#This Row],[Analysis and Graph]]="Analysis and Graph",Sources[[#This Row],[Analysis and Graph]]="Not in analysis, but extra in graph"),MATCH(Sources[[#This Row],[Citekey]],Database!$B$4:$B$2385,0),"") | AA40: =IF(AG40<>"",MATCH(AG40,Sources[Citekey],0),"") -> 152 | AB40: =IF(AI40<>"",MATCH(AI40,Sources[Citekey],0),"") | AC40: =IF(AK40<>"",MATCH(AK40,Sources[Citekey],0),"") | AD40: =IF(AM40<>"",MATCH(AM40,Sources[Citekey],0),"") | AE40: =IF(AO40<>"",MATCH(AO40,Sources[Citekey],0),"") | AG40: =IFERROR(IF(Sources[[#This Row],[Reference to]]<>"",LEFT(Sources[[#This Row],[Reference to]],FIND(",",Sources[[#This Row],[Reference to]])-1),""),Sources[[#This Row],[Reference to]]) -> sorensen2008comparative | AH40: =IFERROR(RIGHT(Sources[[#This Row],[Reference to]],LEN(Sources[[#This Row],[Reference to]])-LEN($AG40)-2),"") | AI40: =IFERROR(LEFT(AH40,FIND(",",AH40)-1),AH40) | AJ40: =IFERROR(RIGHT(Sources[[#This Row],[Reference to]],LEN(Sources[[#This Row],[Reference to]])-LEN($AG40)-2-LEN($AI40)-2),"") | AK40: =IFERROR(LEFT(AJ40,FIND(",",AJ40)-1),AJ40) | AL40: =IFERROR(RIGHT(Sources[[#This Row],[Reference to]],LEN(Sources[[#This Row],[Reference to]])-LEN($AG40)-2-LEN($AI40)-2-LEN($AK40)-2),"") | AM40: =IFERROR(LEFT(AL40,FIND(",",AL40)-1),AL40) | AN40: =IFERROR(RIGHT(Sources[[#This Row],[Reference to]],LEN(Sources[[#This Row],[Reference to]])-LEN($AG40)-2-LEN($AI40)-2-LEN($AK40)-2-LEN($AM40)-2),"") | AO40: =IFERROR(LEFT(AN40,FIND(",",AN40)-1),AN40)
B41: kato2005effective | C41: =IFERROR(VALUE(MID(Sources[[#This Row],[Citekey]],FIND("20",Sources[[#This Row],[Citekey]]),4)),"") -> 2005 | D41: yes | E41: Journal Article | F41: No reference, unclear method | H41: =IFERROR(VLOOKUP(Sources[[#This Row],[Method]],dd_analysis_graph[],2,FALSE),"") -> Not in analysis, not in graph | I41: =IFERROR(VLOOKUP(Sources[[#This Row],[Type of Publication]],dd_type_source[],2,FALSE),"") -> Publication | Z41: =IF(OR(Sources[[#This Row],[Analysis and Graph]]="Analysis and Graph",Sources[[#This Row],[Analysis and Graph]]="Not in analysis, but extra in graph"),MATCH(Sources[[#This Row],[Citekey]],Database!$B$4:$B$2385,0),"") | AA41: =IF(AG41<>"",MATCH(AG41,Sources[Citekey],0),"") | AB41: =IF(AI41<>"",MATCH(AI41,Sources[Citekey],0),"") | AC41: =IF(AK41<>"",MATCH(AK41,Sources[Citekey],0),"") | AD41: =IF(AM41<>"",MATCH(AM41,Sources[Citekey],0),"") | AE41: =IF(AO41<>"",MATCH(AO41,Sources[Citekey],0),"") | AG41: =IFERROR(IF(Sources[[#This Row],[Reference to]]<>"",LEFT(Sources[[#This Row],[Reference to]],FIND(",",Sources[[#This Row],[Reference to]])-1),""),Sources[[#This Row],[Reference to]]) | AH41: =IFERROR(RIGHT(Sources[[#This Row],[Reference to]],LEN(Sources[[#This Row],[Reference to]])-LEN($AG41)-2),"") | AI41: =IFERROR(LEFT(AH41,FIND(",",AH41)-1),AH41) | AJ41: =IFERROR(RIGHT(Sources[[#This Row],[Reference to]],LEN(Sources[[#This Row],[Reference to]])-LEN($AG41)-2-LEN($AI41)-2),"") | AK41: =IFERROR(LEFT(AJ41,FIND(",",AJ41)-1),AJ41) | AL41: =IFERROR(RIGHT(Sources[[#This Row],[Reference to]],LEN(Sources[[#This Row],[Reference to]])-LEN($AG41)-2-LEN($AI41)-2-LEN($AK41)-2),"") | AM41: =IFERROR(LEFT(AL41,FIND(",",AL41)-1),AL41) | AN41: =IFERROR(RIGHT(Sources[[#This Row],[Reference to]],LEN(Sources[[#This Row],[Reference to]])-LEN($AG41)-2-LEN($AI41)-2-LEN($AK41)-2-LEN($AM41)-2),"") | AO41: =IFERROR(LEFT(AN41,FIND(",",AN41)-1),AN41)
B42: klumpp2016comparison | C42: =IFERROR(VALUE(MID(Sources[[#This Row],[Citekey]],FIND("20",Sources[[#This Row],[Citekey]]),4)),"") -> 2016 | D42: yes | E42: Journal Article | F42: No reference, unclear method | H42: =IFERROR(VLOOKUP(Sources[[#This Row],[Method]],dd_analysis_graph[],2,FALSE),"") -> Not in analysis, not in graph | I42: =IFERROR(VLOOKUP(Sources[[#This Row],[Type of Publication]],dd_type_source[],2,FALSE),"") -> Publication | Z42: =IF(OR(Sources[[#This Row],[Analysis and Graph]]="Analysis and Graph",Sources[[#This Row],[Analysis and Graph]]="Not in analysis, but extra in graph"),MATCH(Sources[[#This Row],[Citekey]],Database!$B$4:$B$2385,0),"") | AA42: =IF(AG42<>"",MATCH(AG42,Sources[Citekey],0),"") | AB42: =IF(AI42<>"",MATCH(AI42,Sources[Citekey],0),"") | AC42: =IF(AK42<>"",MATCH(AK42,Sources[Citekey],0),"") | AD42: =IF(AM42<>"",MATCH(AM42,Sources[Citekey],0),"") | AE42: =IF(AO42<>"",MATCH(AO42,Sources[Citekey],0),"") | AG42: =IFERROR(IF(Sources[[#This Row],[Reference to]]<>"",LEFT(Sources[[#This Row],[Reference to]],FIND(",",Sources[[#This Row],[Reference to]])-1),""),Sources[[#This Row],[Reference to]]) | AH42: =IFERROR(RIGHT(Sources[[#This Row],[Reference to]],LEN(Sources[[#This Row],[Reference to]])-LEN($AG42)-2),"") | AI42: =IFERROR(LEFT(AH42,FIND(",",AH42)-1),AH42) | AJ42: =IFERROR(RIGHT(Sources[[#This Row],[Reference to]],LEN(Sources[[#This Row],[Reference to]])-LEN($AG42)-2-LEN($AI42)-2),"") | AK42: =IFERROR(LEFT(AJ42,FIND(",",AJ42)-1),AJ42) | AL42: =IFERROR(RIGHT(Sources[[#This Row],[Reference to]],LEN(Sources[[#This Row],[Reference to]])-LEN($AG42)-2-LEN($AI42)-2-LEN($AK42)-2),"") | AM42: =IFERROR(LEFT(AL42,FIND(",",AL42)-1),AL42) | AN42: =IFERROR(RIGHT(Sources[[#This Row],[Reference to]],LEN(Sources[[#This Row],[Reference to]])-LEN($AG42)-2-LEN($AI42)-2-LEN($AK42)-2-LEN($AM42)-2),"") | AO42: =IFERROR(LEFT(AN42,FIND(",",AN42)-1),AN42)
B43: kotter2015sensitivities | C43: =IFERROR(VALUE(MID(Sources[[#This Row],[Citekey]],FIND("20",Sources[[#This Row],[Citekey]]),4)),"") -> 2015 | D43: yes | E43: Journal Article | F43: Secondary source | G43: edwards2008hydrogen, ivy2004summary, sterner2009bioenergy, orhan2012integrated, miltner2010renewable | H43: =IFERROR(VLOOKUP(Sources[[#This Row],[Method]],dd_analysis_graph[],2,FALSE),"") -> Not in analysis, not in graph | I43: =IFERROR(VLOOKUP(Sources[[#This Row],[Type of Publication]],dd_type_source[],2,FALSE),"") -> Publication | Z43: =IF(OR(Sources[[#This Row],[Analysis and Graph]]="Analysis and Graph",Sources[[#This Row],[Analysis and Graph]]="Not in analysis, but extra in graph"),MATCH(Sources[[#This Row],[Citekey]],Database!$B$4:$B$2385,0),"") | AA43: =IF(AG43<>"",MATCH(AG43,Sources[Citekey],0),"") -> 20 | AB43: =IF(AI43<>"",MATCH(AI43,Sources[Citekey],0),"") -> 130 | AC43: =IF(AK43<>"",MATCH(AK43,Sources[Citekey],0),"") -> 155 | AD43: =IF(AM43<>"",MATCH(AM43,Sources[Citekey],0),"") -> 58 | AE43: =IF(AO43<>"",MATCH(AO43,Sources[Citekey],0),"") -> 55 | AG43: =IFERROR(IF(Sources[[#This Row],[Reference to]]<>"",LEFT(Sources[[#This Row],[Reference to]],FIND(",",Sources[[#This Row],[Reference to]])-1),""),Sources[[#This Row],[Reference to]]) -> edwards2008hydrogen | AH43: =IFERROR(RIGHT(Sources[[#This Row],[Reference to]],LEN(Sources[[#This Row],[Reference to]])-LEN($AG43)-2),"") -> ivy2004summary, sterner2009bioenergy, orhan2012integrated, miltner2010renewable | AI43: =IFERROR(LEFT(AH43,FIND(",",AH43)-1),AH43) -> ivy2004summary | AJ43: =IFERROR(RIGHT(Sources[[#This Row],[Reference to]],LEN(Sources[[#This Row],[Reference to]])-LEN($AG43)-2-LEN($AI43)-2),"") -> sterner2009bioenergy, orhan2012integrated, miltner2010renewable | AK43: =IFERROR(LEFT(AJ43,FIND(",",AJ43)-1),AJ43) -> sterner2009bioenergy | AL43: =IFERROR(RIGHT(Sources[[#This Row],[Reference to]],LEN(Sources[[#This Row],[Reference to]])-LEN($AG43)-2-LEN($AI43)-2-LEN($AK43)-2),"") -> orhan2012integrated, miltner2010renewable | AM43: =IFERROR(LEFT(AL43,FIND(",",AL43)-1),AL43) -> orhan2012integrated | AN43: =IFERROR(RIGHT(Sources[[#This Row],[Reference to]],LEN(Sources[[#This Row],[Reference to]])-LEN($AG43)-2-LEN($AI43)-2-LEN($AK43)-2-LEN($AM43)-2),"") -> miltner2010renewable | AO43: =IFERROR(LEFT(AN43,FIND(",",AN43)-1),AN43) -> miltner2010renewable
B44: kotter2016future | C44: =IFERROR(VALUE(MID(Sources[[#This Row],[Citekey]],FIND("20",Sources[[#This Row],[Citekey]]),4)),"") -> 2016 | D44: yes | E44: Journal Article | F44: Secondary source | H44: =IFERROR(VLOOKUP(Sources[[#This Row],[Method]],dd_analysis_graph[],2,FALSE),"") -> Not in analysis, not in graph | I44: =IFERROR(VLOOKUP(Sources[[#This Row],[Type of Publication]],dd_type_source[],2,FALSE),"") -> Publication | Z44: =IF(OR(Sources[[#This Row],[Analysis and Graph]]="Analysis and Graph",Sources[[#This Row],[Analysis and Graph]]="Not in analysis, but extra in graph"),MATCH(Sources[[#This Row],[Citekey]],Database!$B$4:$B$2385,0),"") | AA44: =IF(AG44<>"",MATCH(AG44,Sources[Citekey],0),"") | AB44: =IF(AI44<>"",MATCH(AI44,Sources[Citekey],0),"") | AC44: =IF(AK44<>"",MATCH(AK44,Sources[Citekey],0),"") | AD44: =IF(AM44<>"",MATCH(AM44,Sources[Citekey],0),"") | AE44: =IF(AO44<>"",MATCH(AO44,Sources[Citekey],0),"") | AG44: =IFERROR(IF(Sources[[#This Row],[Reference to]]<>"",LEFT(Sources[[#This Row],[Reference to]],FIND(",",Sources[[#This Row],[Reference to]])-1),""),Sources[[#This Row],[Reference to]]) | AH44: =IFERROR(RIGHT(Sources[[#This Row],[Reference to]],LEN(Sources[[#This Row],[Reference to]])-LEN($AG44)-2),"") | AI44: =IFERROR(LEFT(AH44,FIND(",",AH44)-1),AH44) | AJ44: =IFERROR(RIGHT(Sources[[#This Row],[Reference to]],LEN(Sources[[#This Row],[Reference to]])-LEN($AG44)-2-LEN($AI44)-2),"") | AK44: =IFERROR(LEFT(AJ44,FIND(",",AJ44)-1),AJ44) | AL44: =IFERROR(RIGHT(Sources[[#This Row],[Reference to]],LEN(Sources[[#This Row],[Reference to]])-LEN($AG44)-2-LEN($AI44)-2-LEN($AK44)-2),"") | AM44: =IFERROR(LEFT(AL44,FIND(",",AL44)-1),AL44) | AN44: =IFERROR(RIGHT(Sources[[#This Row],[Reference to]],LEN(Sources[[#This Row],[Reference to]])-LEN($AG44)-2-LEN($AI44)-2-LEN($AK44)-2-LEN($AM44)-2),"") | AO44: =IFERROR(LEFT(AN44,FIND(",",AN44)-1),AN44)
B45: kroniger2014hydrogen | C45: =IFERROR(VALUE(MID(Sources[[#This Row],[Citekey]],FIND("20",Sources[[#This Row],[Citekey]]),4)),"") -> 2014 | D45: yes | E45: Journal Article | F45: Secondary source | G45: smolinka2010stand | H45: =IFERROR(VLOOKUP(Sources[[#This Row],[Method]],dd_analysis_graph[],2,FALSE),"") -> Not in analysis, not in graph | I45: =IFERROR(VLOOKUP(Sources[[#This Row],[Type of Publication]],dd_type_source[],2,FALSE),"") -> Publication | Z45: =IF(OR(Sources[[#This Row],[Analysis and Graph]]="Analysis and Graph",Sources[[#This Row],[Analysis and Graph]]="Not in analysis, but extra in graph"),MATCH(Sources[[#This Row],[Citekey]],Database!$B$4:$B$2385,0),"") | AA45: =IF(AG45<>"",MATCH(AG45,Sources[Citekey],0),"") -> 150 | AB45: =IF(AI45<>"",MATCH(AI45,Sources[Citekey],0),"") | AC45: =IF(AK45<>"",MATCH(AK45,Sources[Citekey],0),"") | AD45: =IF(AM45<>"",MATCH(AM45,Sources[Citekey],0),"") | AE45: =IF(AO45<>"",MATCH(AO45,Sources[Citekey],0),"") | AG45: =IFERROR(IF(Sources[[#This Row],[Reference to]]<>"",LEFT(Sources[[#This Row],[Reference to]],FIND(",",Sources[[#This Row],[Reference to]])-1),""),Sources[[#This Row],[Reference to]]) -> smolinka2010stand | AH45: =IFERROR(RIGHT(Sources[[#This Row],[Reference to]],LEN(Sources[[#This Row],[Reference to]])-LEN($AG45)-2),"") | AI45: =IFERROR(LEFT(AH45,FIND(",",AH45)-1),AH45) | AJ45: =IFERROR(RIGHT(Sources[[#This Row],[Reference to]],LEN(Sources[[#This Row],[Reference to]])-LEN($AG45)-2-LEN($AI45)-2),"") | AK45: =IFERROR(LEFT(AJ45,FIND(",",AJ45)-1),AJ45) | AL45: =IFERROR(RIGHT(Sources[[#This Row],[Reference to]],LEN(Sources[[#This Row],[Reference to]])-LEN($AG45)-2-LEN($AI45)-2-LEN($AK45)-2),"") | AM45: =IFERROR(LEFT(AL45,FIND(",",AL45)-1),AL45) | AN45: =IFERROR(RIGHT(Sources[[#This Row],[Reference to]],LEN(Sources[[#This Row],[Reference to]])-LEN($AG45)-2-LEN($AI45)-2-LEN($AK45)-2-LEN($AM45)-2),"") | AO45: =IFERROR(LEFT(AN45,FIND(",",AN45)-1),AN45)
B46: lehner2014power | C46: 2014 | D46: yes | E46: Journal Article | F46: Original analysis, industry data | H46: =IFERROR(VLOOKUP(Sources[[#This Row],[Method]],dd_analysis_graph[],2,FALSE),"") -> Analysis and Graph | I46: =IFERROR(VLOOKUP(Sources[[#This Row],[Type of Publication]],dd_type_source[],2,FALSE),"") -> Publication | Z46: =IF(OR(Sources[[#This Row],[Analysis and Graph]]="Analysis and Graph",Sources[[#This Row],[Analysis and Graph]]="Not in analysis, but extra in graph"),MATCH(Sources[[#This Row],[Citekey]],Database!$B$4:$B$2385,0),"") -> 73 | AA46: =IF(AG46<>"",MATCH(AG46,Sources[Citekey],0),"") | AB46: =IF(AI46<>"",MATCH(AI46,Sources[Citekey],0),"") | AC46: =IF(AK46<>"",MATCH(AK46,Sources[Citekey],0),"") | AD46: =IF(AM46<>"",MATCH(AM46,Sources[Citekey],0),"") | AE46: =IF(AO46<>"",MATCH(AO46,Sources[Citekey],0),"") | AG46: =IFERROR(IF(Sources[[#This Row],[Reference to]]<>"",LEFT(Sources[[#This Row],[Reference to]],FIND(",",Sources[[#This Row],[Reference to]])-1),""),Sources[[#This Row],[Reference to]]) | AH46: =IFERROR(RIGHT(Sources[[#This Row],[Reference to]],LEN(Sources[[#This Row],[Reference to]])-LEN($AG46)-2),"") | AI46: =IFERROR(LEFT(AH46,FIND(",",AH46)-1),AH46) | AJ46: =IFERROR(RIGHT(Sources[[#This Row],[Reference to]],LEN(Sources[[#This Row],[Reference to]])-LEN($AG46)-2-LEN($AI46)-2),"") | AK46: =IFERROR(LEFT(AJ46,FIND(",",AJ46)-1),AJ46) | AL46: =IFERROR(RIGHT(Sources[[#This Row],[Reference to]],LEN(Sources[[#This Row],[Reference to]])-LEN($AG46)-2-LEN($AI46)-2-LEN($AK46)-2),"") | AM46: =IFERROR(LEFT(AL46,FIND(",",AL46)-1),AL46) | AN46: =IFERROR(RIGHT(Sources[[#This Row],[Reference to]],LEN(Sources[[#This Row],[Reference to]])-LEN($AG46)-2-LEN($AI46)-2-LEN($AK46)-2-LEN($AM46)-2),"") | AO46: =IFERROR(LEFT(AN46,FIND(",",AN46)-1),AN46)
B47: linnemann2007realistic | C47: =IFERROR(VALUE(MID(Sources[[#This Row],[Citekey]],FIND("20",Sources[[#This Row],[Citekey]]),4)),"") -> 2007 | D47: yes | E47: Journal Article | F47: Original analysis, industry data | H47: =IFERROR(VLOOKUP(Sources[[#This Row],[Method]],dd_analysis_graph[],2,FALSE),"") -> Analysis and Graph | I47: =IFERROR(VLOOKUP(Sources[[#This Row],[Type of Publication]],dd_type_source[],2,FALSE),"") -> Publication | Z47: =IF(OR(Sources[[#This Row],[Analysis and Graph]]="Analysis and Graph",Sources[[#This Row],[Analysis and Graph]]="Not in analysis, but extra in graph"),MATCH(Sources[[#This Row],[Citekey]],Database!$B$4:$B$2385,0),"") -> 361 | AA47: =IF(AG47<>"",MATCH(AG47,Sources[Citekey],0),"") | AB47: =IF(AI47<>"",MATCH(AI47,Sources[Citekey],0),"") | AC47: =IF(AK47<>"",MATCH(AK47,Sources[Citekey],0),"") | AD47: =IF(AM47<>"",MATCH(AM47,Sources[Citekey],0),"") | AE47: =IF(AO47<>"",MATCH(AO47,Sources[Citekey],0),"") | AG47: =IFERROR(IF(Sources[[#This Row],[Reference to]]<>"",LEFT(Sources[[#This Row],[Reference to]],FIND(",",Sources[[#This Row],[Reference to]])-1),""),Sources[[#This Row],[Reference to]]) | AH47: =IFERROR(RIGHT(Sources[[#This Row],[Reference to]],LEN(Sources[[#This Row],[Reference to]])-LEN($AG47)-2),"") | AI47: =IFERROR(LEFT(AH47,FIND(",",AH47)-1),AH47) | AJ47: =IFERROR(RIGHT(Sources[[#This Row],[Reference to]],LEN(Sources[[#This Row],[Reference to]])-LEN($AG47)-2-LEN($AI47)-2),"") | AK47: =IFERROR(LEFT(AJ47,FIND(",",AJ47)-1),AJ47) | AL47: =IFERROR(RIGHT(Sources[[#This Row],[Reference to]],LEN(Sources[[#This Row],[Reference to]])-LEN($AG47)-2-LEN($AI47)-2-LEN($AK47)-2),"") | AM47: =IFERROR(LEFT(AL47,FIND(",",AL47)-1),AL47) | AN47: =IFERROR(RIGHT(Sources[[#This Row],[Reference to]],LEN(Sources[[#This Row],[Reference to]])-LEN($AG47)-2-LEN($AI47)-2-LEN($AK47)-2-LEN($AM47)-2),"") | AO47: =IFERROR(LEFT(AN47,FIND(",",AN47)-1),AN47)
B48: lipman2004fuel | C48: =IFERROR(VALUE(MID(Sources[[#This Row],[Citekey]],FIND("20",Sources[[#This Row],[Citekey]]),4)),"") -> 2004 | D48: yes | E48: Journal Article | F48: Original review multiple sources | H48: =IFERROR(VLOOKUP(Sources[[#This Row],[Method]],dd_analysis_graph[],2,FALSE),"") -> Analysis and Graph | I48: =IFERROR(VLOOKUP(Sources[[#This Row],[Type of Publication]],dd_type_source[],2,FALSE),"") -> Publication | Z48: =IF(OR(Sources[[#This Row],[Analysis and Graph]]="Analysis and Graph",Sources[[#This Row],[Analysis and Graph]]="Not in analysis, but extra in graph"),MATCH(Sources[[#This Row],[Citekey]],Database!$B$4:$B$2385,0),"") -> 1417 | AA48: =IF(AG48<>"",MATCH(AG48,Sources[Citekey],0),"") | AB48: =IF(AI48<>"",MATCH(AI48,Sources[Citekey],0),"") | AC48: =IF(AK48<>"",MATCH(AK48,Sources[Citekey],0),"") | AD48: =IF(AM48<>"",MATCH(AM48,Sources[Citekey],0),"") | AE48: =IF(AO48<>"",MATCH(AO48,Sources[Citekey],0),"") | AG48: =IFERROR(IF(Sources[[#This Row],[Reference to]]<>"",LEFT(Sources[[#This Row],[Reference to]],FIND(",",Sources[[#This Row],[Reference to]])-1),""),Sources[[#This Row],[Reference to]]) | AH48: =IFERROR(RIGHT(Sources[[#This Row],[Reference to]],LEN(Sources[[#This Row],[Reference to]])-LEN($AG48)-2),"") | AI48: =IFERROR(LEFT(AH48,FIND(",",AH48)-1),AH48) | AJ48: =IFERROR(RIGHT(Sources[[#This Row],[Reference to]],LEN(Sources[[#This Row],[Reference to]])-LEN($AG48)-2-LEN($AI48)-2),"") | AK48: =IFERROR(LEFT(AJ48,FIND(",",AJ48)-1),AJ48) | AL48: =IFERROR(RIGHT(Sources[[#This Row],[Reference to]],LEN(Sources[[#This Row],[Reference to]])-LEN($AG48)-2-LEN($AI48)-2-LEN($AK48)-2),"") | AM48: =IFERROR(LEFT(AL48,FIND(",",AL48)-1),AL48) | AN48: =IFERROR(RIGHT(Sources[[#This Row],[Reference to]],LEN(Sources[[#This Row],[Reference to]])-LEN($AG48)-2-LEN($AI48)-2-LEN($AK48)-2-LEN($AM48)-2),"") | AO48: =IFERROR(LEFT(AN48,FIND(",",AN48)-1),AN48)
B49: loisel2015economic | C49: =IFERROR(VALUE(MID(Sources[[#This Row],[Citekey]],FIND("20",Sources[[#This Row],[Citekey]]),4)),"") -> 2015 | D49: yes | E49: Journal Article | F49: Secondary source | G49: menanteau2010une | H49: =IFERROR(VLOOKUP(Sources[[#This Row],[Method]],dd_analysis_graph[],2,FALSE),"") -> Not in analysis, not in graph | I49: =IFERROR(VLOOKUP(Sources[[#This Row],[Type of Publication]],dd_type_source[],2,FALSE),"") -> Publication | Z49: =IF(OR(Sources[[#This Row],[Analysis and Graph]]="Analysis and Graph",Sources[[#This Row],[Analysis and Graph]]="Not in analysis, but extra in graph"),MATCH(Sources[[#This Row],[Citekey]],Database!$B$4:$B$2385,0),"") | AA49: =IF(AG49<>"",MATCH(AG49,Sources[Citekey],0),"") -> 136 | AB49: =IF(AI49<>"",MATCH(AI49,Sources[Citekey],0),"") | AC49: =IF(AK49<>"",MATCH(AK49,Sources[Citekey],0),"") | AD49: =IF(AM49<>"",MATCH(AM49,Sources[Citekey],0),"") | AE49: =IF(AO49<>"",MATCH(AO49,Sources[Citekey],0),"") | AG49: =IFERROR(IF(Sources[[#This Row],[Reference to]]<>"",LEFT(Sources[[#This Row],[Reference to]],FIND(",",Sources[[#This Row],[Reference to]])-1),""),Sources[[#This Row],[Reference to]]) -> menanteau2010une | AH49: =IFERROR(RIGHT(Sources[[#This Row],[Reference to]],LEN(Sources[[#This Row],[Reference to]])-LEN($AG49)-2),"") | AI49: =IFERROR(LEFT(AH49,FIND(",",AH49)-1),AH49) | AJ49: =IFERROR(RIGHT(Sources[[#This Row],[Reference to]],LEN(Sources[[#This Row],[Reference to]])-LEN($AG49)-2-LEN($AI49)-2),"") | AK49: =IFERROR(LEFT(AJ49,FIND(",",AJ49)-1),AJ49) | AL49: =IFERROR(RIGHT(Sources[[#This Row],[Reference to]],LEN(Sources[[#This Row],[Reference to]])-LEN($AG49)-2-LEN($AI49)-2-LEN($AK49)-2),"") | AM49: =IFERROR(LEFT(AL49,FIND(",",AL49)-1),AL49) | AN49: =IFERROR(RIGHT(Sources[[#This Row],[Reference to]],LEN(Sources[[#This Row],[Reference to]])-LEN($AG49)-2-LEN($AI49)-2-LEN($AK49)-2-LEN($AM49)-2),"") | AO49: =IFERROR(LEFT(AN49,FIND(",",AN49)-1),AN49)
B50: manage2011techno | C50: =IFERROR(VALUE(MID(Sources[[#This Row],[Citekey]],FIND("20",Sources[[#This Row],[Citekey]]),4)),"") -> 2011 | D50: yes | E50: Journal Article | F50: Secondary source | G50: mueller-langer2007techno, sorensen2004hydrogen, jorgensen2008production, holladay2009an, jensen2007hydrogen | H50: =IFERROR(VLOOKUP(Sources[[#This Row],[Method]],dd_analysis_graph[],2,FALSE),"") -> Not in analysis, not in graph | I50: =IFERROR(VLOOKUP(Sources[[#This Row],[Type of Publication]],dd_type_source[],2,FALSE),"") -> Publication | Z50: =IF(OR(Sources[[#This Row],[Analysis and Graph]]="Analysis and Graph",Sources[[#This Row],[Analysis and Graph]]="Not in analysis, but extra in graph"),MATCH(Sources[[#This Row],[Citekey]],Database!$B$4:$B$2385,0),"") | AA50: =IF(AG50<>"",MATCH(AG50,Sources[Citekey],0),"") -> 56 | AB50: =IF(AI50<>"",MATCH(AI50,Sources[Citekey],0),"") -> 67 | AC50: =IF(AK50<>"",MATCH(AK50,Sources[Citekey],0),"") -> 36 | AD50: =IF(AM50<>"",MATCH(AM50,Sources[Citekey],0),"") -> 32 | AE50: =IF(AO50<>"",MATCH(AO50,Sources[Citekey],0),"") -> 33 | AG50: =IFERROR(IF(Sources[[#This Row],[Reference to]]<>"",LEFT(Sources[[#This Row],[Reference to]],FIND(",",Sources[[#This Row],[Reference to]])-1),""),Sources[[#This Row],[Reference to]]) -> mueller-langer2007techno | AH50: =IFERROR(RIGHT(Sources[[#This Row],[Reference to]],LEN(Sources[[#This Row],[Reference to]])-LEN($AG50)-2),"") -> sorensen2004hydrogen, jorgensen2008production, holladay2009an, jensen2007hydrogen | AI50: =IFERROR(LEFT(AH50,FIND(",",AH50)-1),AH50) -> sorensen2004hydrogen | AJ50: =IFERROR(RIGHT(Sources[[#This Row],[Reference to]],LEN(Sources[[#This Row],[Reference to]])-LEN($AG50)-2-LEN($AI50)-2),"") -> jorgensen2008production, holladay2009an, jensen2007hydrogen | AK50: =IFERROR(LEFT(AJ50,FIND(",",AJ50)-1),AJ50) -> jorgensen2008production | AL50: =IFERROR(RIGHT(Sources[[#This Row],[Reference to]],LEN(Sources[[#This Row],[Reference to]])-LEN($AG50)-2-LEN($AI50)-2-LEN($AK50)-2),"") -> holladay2009an, jensen2007hydrogen | AM50: =IFERROR(LEFT(AL50,FIND(",",AL50)-1),AL50) -> holladay2009an | AN50: =IFERROR(RIGHT(Sources[[#This Row],[Reference to]],LEN(Sources[[#This Row],[Reference to]])-LEN($AG50)-2-LEN($AI50)-2-LEN($AK50)-2-LEN($AM50)-2),"") -> jensen2007hydrogen | AO50: =IFERROR(LEFT(AN50,FIND(",",AN50)-1),AN50) -> jensen2007hydrogen
B51: mansilla2011reducing | C51: 2011 | D51: yes | E51: Journal Article | F51: Original analysis, industry data | H51: =IFERROR(VLOOKUP(Sources[[#This Row],[Method]],dd_analysis_graph[],2,FALSE),"") -> Analysis and Graph | I51: =IFERROR(VLOOKUP(Sources[[#This Row],[Type of Publication]],dd_type_source[],2,FALSE),"") -> Publication | Z51: =IF(OR(Sources[[#This Row],[Analysis and Graph]]="Analysis and Graph",Sources[[#This Row],[Analysis and Graph]]="Not in analysis, but extra in graph"),MATCH(Sources[[#This Row],[Citekey]],Database!$B$4:$B$2385,0),"") -> 97 | AA51: =IF(AG51<>"",MATCH(AG51,Sources[Citekey],0),"") | AB51: =IF(AI51<>"",MATCH(AI51,Sources[Citekey],0),"") | AC51: =IF(AK51<>"",MATCH(AK51,Sources[Citekey],0),"") | AD51: =IF(AM51<>"",MATCH(AM51,Sources[Citekey],0),"") | AE51: =IF(AO51<>"",MATCH(AO51,Sources[Citekey],0),"") | AG51: =IFERROR(IF(Sources[[#This Row],[Reference to]]<>"",LEFT(Sources[[#This Row],[Reference to]],FIND(",",Sources[[#This Row],[Reference to]])-1),""),Sources[[#This Row],[Reference to]]) | AH51: =IFERROR(RIGHT(Sources[[#This Row],[Reference to]],LEN(Sources[[#This Row],[Reference to]])-LEN($AG51)-2),"") | AI51: =IFERROR(LEFT(AH51,FIND(",",AH51)-1),AH51) | AJ51: =IFERROR(RIGHT(Sources[[#This Row],[Reference to]],LEN(Sources[[#This Row],[Reference to]])-LEN($AG51)-2-LEN($AI51)-2),"") | AK51: =IFERROR(LEFT(AJ51,FIND(",",AJ51)-1),AJ51) | AL51: =IFERROR(RIGHT(Sources[[#This Row],[Reference to]],LEN(Sources[[#This Row],[Reference to]])-LEN($AG51)-2-LEN($AI51)-2-LEN($AK51)-2),"") | AM51: =IFERROR(LEFT(AL51,FIND(",",AL51)-1),AL51) | AN51: =IFERROR(RIGHT(Sources[[#This Row],[Reference to]],LEN(Sources[[#This Row],[Reference to]])-LEN($AG51)-2-LEN($AI51)-2-LEN($AK51)-2-LEN($AM51)-2),"") | AO51: =IFERROR(LEFT(AN51,FIND(",",AN51)-1),AN51)
B52: mansilla2013economic | C52: 2013 | D52: yes | E52: Journal Article | F52: Original analysis, industry data | H52: =IFERROR(VLOOKUP(Sources[[#This Row],[Method]],dd_analysis_graph[],2,FALSE),"") -> Analysis and Graph | I52: =IFERROR(VLOOKUP(Sources[[#This Row],[Type of Publication]],dd_type_source[],2,FALSE),"") -> Publication | Z52: =IF(OR(Sources[[#This Row],[Analysis and Graph]]="Analysis and Graph",Sources[[#This Row],[Analysis and Graph]]="Not in analysis, but extra in graph"),MATCH(Sources[[#This Row],[Citekey]],Database!$B$4:$B$2385,0),"") -> 121 | AA52: =IF(AG52<>"",MATCH(AG52,Sources[Citekey],0),"") | AB52: =IF(AI52<>"",MATCH(AI52,Sources[Citekey],0),"") | AC52: =IF(AK52<>"",MATCH(AK52,Sources[Citekey],0),"") | AD52: =IF(AM52<>"",MATCH(AM52,Sources[Citekey],0),"") | AE52: =IF(AO52<>"",MATCH(AO52,Sources[Citekey],0),"") | AG52: =IFERROR(IF(Sources[[#This Row],[Reference to]]<>"",LEFT(Sources[[#This Row],[Reference to]],FIND(",",Sources[[#This Row],[Reference to]])-1),""),Sources[[#This Row],[Reference to]]) | AH52: =IFERROR(RIGHT(Sources[[#This Row],[Reference to]],LEN(Sources[[#This Row],[Reference to]])-LEN($AG52)-2),"") | AI52: =IFERROR(LEFT(AH52,FIND(",",AH52)-1),AH52) | AJ52: =IFERROR(RIGHT(Sources[[#This Row],[Reference to]],LEN(Sources[[#This Row],[Reference to]])-LEN($AG52)-2-LEN($AI52)-2),"") | AK52: =IFERROR(LEFT(AJ52,FIND(",",AJ52)-1),AJ52) | AL52: =IFERROR(RIGHT(Sources[[#This Row],[Reference to]],LEN(Sources[[#This Row],[Reference to]])-LEN($AG52)-2-LEN($AI52)-2-LEN($AK52)-2),"") | AM52: =IFERROR(LEFT(AL52,FIND(",",AL52)-1),AL52) | AN52: =IFERROR(RIGHT(Sources[[#This Row],[Reference to]],LEN(Sources[[#This Row],[Reference to]])-LEN($AG52)-2-LEN($AI52)-2-LEN($AK52)-2-LEN($AM52)-2),"") | AO52: =IFERROR(LEFT(AN52,FIND(",",AN52)-1),AN52)
B53: mantz2008hydrogen | C53: =IFERROR(VALUE(MID(Sources[[#This Row],[Citekey]],FIND("20",Sources[[#This Row],[Citekey]]),4)),"") -> 2008 | D53: yes | E53: Journal Article | F53: No cost data | H53: =IFERROR(VLOOKUP(Sources[[#This Row],[Method]],dd_analysis_graph[],2,FALSE),"") -> Not in analysis, not in graph | I53: =IFERROR(VLOOKUP(Sources[[#This Row],[Type of Publication]],dd_type_source[],2,FALSE),"") -> Publication | Z53: =IF(OR(Sources[[#This Row],[Analysis and Graph]]="Analysis and Graph",Sources[[#This Row],[Analysis and Graph]]="Not in analysis, but extra in graph"),MATCH(Sources[[#This Row],[Citekey]],Database!$B$4:$B$2385,0),"") | AA53: =IF(AG53<>"",MATCH(AG53,Sources[Citekey],0),"") | AB53: =IF(AI53<>"",MATCH(AI53,Sources[Citekey],0),"") | AC53: =IF(AK53<>"",MATCH(AK53,Sources[Citekey],0),"") | AD53: =IF(AM53<>"",MATCH(AM53,Sources[Citekey],0),"") | AE53: =IF(AO53<>"",MATCH(AO53,Sources[Citekey],0),"") | AG53: =IFERROR(IF(Sources[[#This Row],[Reference to]]<>"",LEFT(Sources[[#This Row],[Reference to]],FIND(",",Sources[[#This Row],[Reference to]])-1),""),Sources[[#This Row],[Reference to]]) | AH53: =IFERROR(RIGHT(Sources[[#This Row],[Reference to]],LEN(Sources[[#This Row],[Reference to]])-LEN($AG53)-2),"") | AI53: =IFERROR(LEFT(AH53,FIND(",",AH53)-1),AH53) | AJ53: =IFERROR(RIGHT(Sources[[#This Row],[Reference to]],LEN(Sources[[#This Row],[Reference to]])-LEN($AG53)-2-LEN($AI53)-2),"") | AK53: =IFERROR(LEFT(AJ53,FIND(",",AJ53)-1),AJ53) | AL53: =IFERROR(RIGHT(Sources[[#This Row],[Reference to]],LEN(Sources[[#This Row],[Reference to]])-LEN($AG53)-2-LEN($AI53)-2-LEN($AK53)-2),"") | AM53: =IFERROR(LEFT(AL53,FIND(",",AL53)-1),AL53) | AN53: =IFERROR(RIGHT(Sources[[#This Row],[Reference to]],LEN(Sources[[#This Row],[Reference to]])-LEN($AG53)-2-LEN($AI53)-2-LEN($AK53)-2-LEN($AM53)-2),"") | AO53: =IFERROR(LEFT(AN53,FIND(",",AN53)-1),AN53)
B54: marcelo2008economical | C54: =IFERROR(VALUE(MID(Sources[[#This Row],[Citekey]],FIND("20",Sources[[#This Row],[Citekey]]),4)),"") -> 2008 | D54: yes | E54: Journal Article | F54: No cost data | H54: =IFERROR(VLOOKUP(Sources[[#This Row],[Method]],dd_analysis_graph[],2,FALSE),"") -> Not in analysis, not in graph | I54: =IFERROR(VLOOKUP(Sources[[#This Row],[Type of Publication]],dd_type_source[],2,FALSE),"") -> Publication | Z54: =IF(OR(Sources[[#This Row],[Analysis and Graph]]="Analysis and Graph",Sources[[#This Row],[Analysis and Graph]]="Not in analysis, but extra in graph"),MATCH(Sources[[#This Row],[Citekey]],Database!$B$4:$B$2385,0),"") | AA54: =IF(AG54<>"",MATCH(AG54,Sources[Citekey],0),"") | AB54: =IF(AI54<>"",MATCH(AI54,Sources[Citekey],0),"") | AC54: =IF(AK54<>"",MATCH(AK54,Sources[Citekey],0),"") | AD54: =IF(AM54<>"",MATCH(AM54,Sources[Citekey],0),"") | AE54: =IF(AO54<>"",MATCH(AO54,Sources[Citekey],0),"") | AG54: =IFERROR(IF(Sources[[#This Row],[Reference to]]<>"",LEFT(Sources[[#This Row],[Reference to]],FIND(",",Sources[[#This Row],[Reference to]])-1),""),Sources[[#This Row],[Reference to]]) | AH54: =IFERROR(RIGHT(Sources[[#This Row],[Reference to]],LEN(Sources[[#This Row],[Reference to]])-LEN($AG54)-2),"") | AI54: =IFERROR(LEFT(AH54,FIND(",",AH54)-1),AH54) | AJ54: =IFERROR(RIGHT(Sources[[#This Row],[Reference to]],LEN(Sources[[#This Row],[Reference to]])-LEN($AG54)-2-LEN($AI54)-2),"") | AK54: =IFERROR(LEFT(AJ54,FIND(",",AJ54)-1),AJ54) | AL54: =IFERROR(RIGHT(Sources[[#This Row],[Reference to]],LEN(Sources[[#This Row],[Reference to]])-LEN($AG54)-2-LEN($AI54)-2-LEN($AK54)-2),"") | AM54: =IFERROR(LEFT(AL54,FIND(",",AL54)-1),AL54) | AN54: =IFERROR(RIGHT(Sources[[#This Row],[Reference to]],LEN(Sources[[#This Row],[Reference to]])-LEN($AG54)-2-LEN($AI54)-2-LEN($AK54)-2-LEN($AM54)-2),"") | AO54: =IFERROR(LEFT(AN54,FIND(",",AN54)-1),AN54)
B55: mathiesen2013technology | C55: =IFERROR(VALUE(MID(Sources[[#This Row],[Citekey]],FIND("20",Sources[[#This Row],[Citekey]]),4)),"") -> 2013 | D55: yes | E55: Journal Article | F55: Original analysis, industry data | H55: =IFERROR(VLOOKUP(Sources[[#This Row],[Method]],dd_analysis_graph[],2,FALSE),"") -> Analysis and Graph | I55: =IFERROR(VLOOKUP(Sources[[#This Row],[Type of Publication]],dd_type_source[],2,FALSE),"") -> Publication | Z55: =IF(OR(Sources[[#This Row],[Analysis and Graph]]="Analysis and Graph",Sources[[#This Row],[Analysis and Graph]]="Not in analysis, but extra in graph"),MATCH(Sources[[#This Row],[Citekey]],Database!$B$4:$B$2385,0),"") -> 1369 | AA55: =IF(AG55<>"",MATCH(AG55,Sources[Citekey],0),"") | AB55: =IF(AI55<>"",MATCH(AI55,Sources[Citekey],0),"") | AC55: =IF(AK55<>"",MATCH(AK55,Sources[Citekey],0),"") | AD55: =IF(AM55<>"",MATCH(AM55,Sources[Citekey],0),"") | AE55: =IF(AO55<>"",MATCH(AO55,Sources[Citekey],0),"") | AG55: =IFERROR(IF(Sources[[#This Row],[Reference to]]<>"",LEFT(Sources[[#This Row],[Reference to]],FIND(",",Sources[[#This Row],[Reference to]])-1),""),Sources[[#This Row],[Reference to]]) | AH55: =IFERROR(RIGHT(Sources[[#This Row],[Reference to]],LEN(Sources[[#This Row],[Reference to]])-LEN($AG55)-2),"") | AI55: =IFERROR(LEFT(AH55,FIND(",",AH55)-1),AH55) | AJ55: =IFERROR(RIGHT(Sources[[#This Row],[Reference to]],LEN(Sources[[#This Row],[Reference to]])-LEN($AG55)-2-LEN($AI55)-2),"") | AK55: =IFERROR(LEFT(AJ55,FIND(",",AJ55)-1),AJ55) | AL55: =IFERROR(RIGHT(Sources[[#This Row],[Reference to]],LEN(Sources[[#This Row],[Reference to]])-LEN($AG55)-2-LEN($AI55)-2-LEN($AK55)-2),"") | AM55: =IFERROR(LEFT(AL55,FIND(",",AL55)-1),AL55) | AN55: =IFERROR(RIGHT(Sources[[#This Row],[Reference to]],LEN(Sources[[#This Row],[Reference to]])-LEN($AG55)-2-LEN($AI55)-2-LEN($AK55)-2-LEN($AM55)-2),"") | AO55: =IFERROR(LEFT(AN55,FIND(",",AN55)-1),AN55)
B56: michaelis2014evaluation | C56: =IFERROR(VALUE(MID(Sources[[#This Row],[Citekey]],FIND("20",Sources[[#This Row],[Citekey]]),4)),"") -> 2014 | D56: yes | E56: Journal Article | F56: No cost data | H56: =IFERROR(VLOOKUP(Sources[[#This Row],[Method]],dd_analysis_graph[],2,FALSE),"") -> Not in analysis, not in graph | I56: =IFERROR(VLOOKUP(Sources[[#This Row],[Type of Publication]],dd_type_source[],2,FALSE),"") -> Publication | Z56: =IF(OR(Sources[[#This Row],[Analysis and Graph]]="Analysis and Graph",Sources[[#This Row],[Analysis and Graph]]="Not in analysis, but extra in graph"),MATCH(Sources[[#This Row],[Citekey]],Database!$B$4:$B$2385,0),"") | AA56: =IF(AG56<>"",MATCH(AG56,Sources[Citekey],0),"") | AB56: =IF(AI56<>"",MATCH(AI56,Sources[Citekey],0),"") | AC56: =IF(AK56<>"",MATCH(AK56,Sources[Citekey],0),"") | AD56: =IF(AM56<>"",MATCH(AM56,Sources[Citekey],0),"") | AE56: =IF(AO56<>"",MATCH(AO56,Sources[Citekey],0),"") | AG56: =IFERROR(IF(Sources[[#This Row],[Reference to]]<>"",LEFT(Sources[[#This Row],[Reference to]],FIND(",",Sources[[#This Row],[Reference to]])-1),""),Sources[[#This Row],[Reference to]]) | AH56: =IFERROR(RIGHT(Sources[[#This Row],[Reference to]],LEN(Sources[[#This Row],[Reference to]])-LEN($AG56)-2),"") | AI56: =IFERROR(LEFT(AH56,FIND(",",AH56)-1),AH56) | AJ56: =IFERROR(RIGHT(Sources[[#This Row],[Reference to]],LEN(Sources[[#This Row],[Reference to]])-LEN($AG56)-2-LEN($AI56)-2),"") | AK56: =IFERROR(LEFT(AJ56,FIND(",",AJ56)-1),AJ56) | AL56: =IFERROR(RIGHT(Sources[[#This Row],[Reference to]],LEN(Sources[[#This Row],[Reference to]])-LEN($AG56)-2-LEN($AI56)-2-LEN($AK56)-2),"") | AM56: =IFERROR(LEFT(AL56,FIND(",",AL56)-1),AL56) | AN56: =IFERROR(RIGHT(Sources[[#This Row],[Reference to]],LEN(Sources[[#This Row],[Reference to]])-LEN($AG56)-2-LEN($AI56)-2-LEN($AK56)-2-LEN($AM56)-2),"") | AO56: =IFERROR(LEFT(AN56,FIND(",",AN56)-1),AN56)
B57: miltner2010renewable | C57: =IFERROR(VALUE(MID(Sources[[#This Row],[Citekey]],FIND("20",Sources[[#This Row],[Citekey]]),4)),"") -> 2010 | D57: yes | E57: Journal Article | F57: No cost data | H57: =IFERROR(VLOOKUP(Sources[[#This Row],[Method]],dd_analysis_graph[],2,FALSE),"") -> Not in analysis, not in graph | I57: =IFERROR(VLOOKUP(Sources[[#This Row],[Type of Publication]],dd_type_source[],2,FALSE),"") -> Publication | Z57: =IF(OR(Sources[[#This Row],[Analysis and Graph]]="Analysis and Graph",Sources[[#This Row],[Analysis and Graph]]="Not in analysis, but extra in graph"),MATCH(Sources[[#This Row],[Citekey]],Database!$B$4:$B$2385,0),"") | AA57: =IF(AG57<>"",MATCH(AG57,Sources[Citekey],0),"") | AB57: =IF(AI57<>"",MATCH(AI57,Sources[Citekey],0),"") | AC57: =IF(AK57<>"",MATCH(AK57,Sources[Citekey],0),"") | AD57: =IF(AM57<>"",MATCH(AM57,Sources[Citekey],0),"") | AE57: =IF(AO57<>"",MATCH(AO57,Sources[Citekey],0),"") | AG57: =IFERROR(IF(Sources[[#This Row],[Reference to]]<>"",LEFT(Sources[[#This Row],[Reference to]],FIND(",",Sources[[#This Row],[Reference to]])-1),""),Sources[[#This Row],[Reference to]]) | AH57: =IFERROR(RIGHT(Sources[[#This Row],[Reference to]],LEN(Sources[[#This Row],[Reference to]])-LEN($AG57)-2),"") | AI57: =IFERROR(LEFT(AH57,FIND(",",AH57)-1),AH57) | AJ57: =IFERROR(RIGHT(Sources[[#This Row],[Reference to]],LEN(Sources[[#This Row],[Reference to]])-LEN($AG57)-2-LEN($AI57)-2),"") | AK57: =IFERROR(LEFT(AJ57,FIND(",",AJ57)-1),AJ57) | AL57: =IFERROR(RIGHT(Sources[[#This Row],[Reference to]],LEN(Sources[[#This Row],[Reference to]])-LEN($AG57)-2-LEN($AI57)-2-LEN($AK57)-2),"") | AM57: =IFERROR(LEFT(AL57,FIND(",",AL57)-1),AL57) | AN57: =IFERROR(RIGHT(Sources[[#This Row],[Reference to]],LEN(Sources[[#This Row],[Reference to]])-LEN($AG57)-2-LEN($AI57)-2-LEN($AK57)-2-LEN($AM57)-2),"") | AO57: =IFERROR(LEFT(AN57,FIND(",",AN57)-1),AN57)
B58: mueller-langer2007techno | C58: =IFERROR(VALUE(MID(Sources[[#This Row],[Citekey]],FIND("20",Sources[[#This Row],[Citekey]]),4)),"") -> 2007 | D58: yes | E58: Journal Article | F58: Original review multiple sources | H58: =IFERROR(VLOOKUP(Sources[[#This Row],[Method]],dd_analysis_graph[],2,FALSE),"") -> Analysis and Graph | I58: =IFERROR(VLOOKUP(Sources[[#This Row],[Type of Publication]],dd_type_source[],2,FALSE),"") -> Publication | Z58: =IF(OR(Sources[[#This Row],[Analysis and Graph]]="Analysis and Graph",Sources[[#This Row],[Analysis and Graph]]="Not in analysis, but extra in graph"),MATCH(Sources[[#This Row],[Citekey]],Database!$B$4:$B$2385,0),"") -> 1153 | AA58: =IF(AG58<>"",MATCH(AG58,Sources[Citekey],0),"") | AB58: =IF(AI58<>"",MATCH(AI58,Sources[Citekey],0),"") | AC58: =IF(AK58<>"",MATCH(AK58,Sources[Citekey],0),"") | AD58: =IF(AM58<>"",MATCH(AM58,Sources[Citekey],0),"") | AE58: =IF(AO58<>"",MATCH(AO58,Sources[Citekey],0),"") | AG58: =IFERROR(IF(Sources[[#This Row],[Reference to]]<>"",LEFT(Sources[[#This Row],[Reference to]],FIND(",",Sources[[#This Row],[Reference to]])-1),""),Sources[[#This Row],[Reference to]]) | AH58: =IFERROR(RIGHT(Sources[[#This Row],[Reference to]],LEN(Sources[[#This Row],[Reference to]])-LEN($AG58)-2),"") | AI58: =IFERROR(LEFT(AH58,FIND(",",AH58)-1),AH58) | AJ58: =IFERROR(RIGHT(Sources[[#This Row],[Reference to]],LEN(Sources[[#This Row],[Reference to]])-LEN($AG58)-2-LEN($AI58)-2),"") | AK58: =IFERROR(LEFT(AJ58,FIND(",",AJ58)-1),AJ58) | AL58: =IFERROR(RIGHT(Sources[[#This Row],[Reference to]],LEN(Sources[[#This Row],[Reference to]])-LEN($AG58)-2-LEN($AI58)-2-LEN($AK58)-2),"") | AM58: =IFERROR(LEFT(AL58,FIND(",",AL58)-1),AL58) | AN58: =IFERROR(RIGHT(Sources[[#This Row],[Reference to]],LEN(Sources[[#This Row],[Reference to]])-LEN($AG58)-2-LEN($AI58)-2-LEN($AK58)-2-LEN($AM58)-2),"") | AO58: =IFERROR(LEFT(AN58,FIND(",",AN58)-1),AN58)
B59: ni2008technological | C59: =IFERROR(VALUE(MID(Sources[[#This Row],[Citekey]],FIND("20",Sources[[#This Row],[Citekey]]),4)),"") -> 2008 | D59: yes | E59: Journal Article | F59: No cost data | H59: =IFERROR(VLOOKUP(Sources[[#This Row],[Method]],dd_analysis_graph[],2,FALSE),"") -> Not in analysis, not in graph | I59: =IFERROR(VLOOKUP(Sources[[#This Row],[Type of Publication]],dd_type_source[],2,FALSE),"") -> Publication | Z59: =IF(OR(Sources[[#This Row],[Analysis and Graph]]="Analysis and Graph",Sources[[#This Row],[Analysis and Graph]]="Not in analysis, but extra in graph"),MATCH(Sources[[#This Row],[Citekey]],Database!$B$4:$B$2385,0),"") | AA59: =IF(AG59<>"",MATCH(AG59,Sources[Citekey],0),"") | AB59: =IF(AI59<>"",MATCH(AI59,Sources[Citekey],0),"") | AC59: =IF(AK59<>"",MATCH(AK59,Sources[Citekey],0),"") | AD59: =IF(AM59<>"",MATCH(AM59,Sources[Citekey],0),"") | AE59: =IF(AO59<>"",MATCH(AO59,Sources[Citekey],0),"") | AG59: =IFERROR(IF(Sources[[#This Row],[Reference to]]<>"",LEFT(Sources[[#This Row],[Reference to]],FIND(",",Sources[[#This Row],[Reference to]])-1),""),Sources[[#This Row],[Reference to]]) | AH59: =IFERROR(RIGHT(Sources[[#This Row],[Reference to]],LEN(Sources[[#This Row],[Reference to]])-LEN($AG59)-2),"") | AI59: =IFERROR(LEFT(AH59,FIND(",",AH59)-1),AH59) | AJ59: =IFERROR(RIGHT(Sources[[#This Row],[Reference to]],LEN(Sources[[#This Row],[Reference to]])-LEN($AG59)-2-LEN($AI59)-2),"") | AK59: =IFERROR(LEFT(AJ59,FIND(",",AJ59)-1),AJ59) | AL59: =IFERROR(RIGHT(Sources[[#This Row],[Reference to]],LEN(Sources[[#This Row],[Reference to]])-LEN($AG59)-2-LEN($AI59)-2-LEN($AK59)-2),"") | AM59: =IFERROR(LEFT(AL59,FIND(",",AL59)-1),AL59) | AN59: =IFERROR(RIGHT(Sources[[#This Row],[Reference to]],LEN(Sources[[#This Row],[Reference to]])-LEN($AG59)-2-LEN($AI59)-2-LEN($AK59)-2-LEN($AM59)-2),"") | AO59: =IFERROR(LEFT(AN59,FIND(",",AN59)-1),AN59)
B60: orhan2012integrated | C60: =IFERROR(VALUE(MID(Sources[[#This Row],[Citekey]],FIND("20",Sources[[#This Row],[Citekey]]),4)),"") -> 2012 | D60: yes | E60: Journal Article | F60: Secondary source | G60: edwards2008hydrogen | H60: =IFERROR(VLOOKUP(Sources[[#This Row],[Method]],dd_analysis_graph[],2,FALSE),"") -> Not in analysis, not in graph | I60: =IFERROR(VLOOKUP(Sources[[#This Row],[Type of Publication]],dd_type_source[],2,FALSE),"") -> Publication | Z60: =IF(OR(Sources[[#This Row],[Analysis and Graph]]="Analysis and Graph",Sources[[#This Row],[Analysis and Graph]]="Not in analysis, but extra in graph"),MATCH(Sources[[#This Row],[Citekey]],Database!$B$4:$B$2385,0),"") | AA60: =IF(AG60<>"",MATCH(AG60,Sources[Citekey],0),"") -> 20 | AB60: =IF(AI60<>"",MATCH(AI60,Sources[Citekey],0),"") | AC60: =IF(AK60<>"",MATCH(AK60,Sources[Citekey],0),"") | AD60: =IF(AM60<>"",MATCH(AM60,Sources[Citekey],0),"") | AE60: =IF(AO60<>"",MATCH(AO60,Sources[Citekey],0),"") | AG60: =IFERROR(IF(Sources[[#This Row],[Reference to]]<>"",LEFT(Sources[[#This Row],[Reference to]],FIND(",",Sources[[#This Row],[Reference to]])-1),""),Sources[[#This Row],[Reference to]]) -> edwards2008hydrogen | AH60: =IFERROR(RIGHT(Sources[[#This Row],[Reference to]],LEN(Sources[[#This Row],[Reference to]])-LEN($AG60)-2),"") | AI60: =IFERROR(LEFT(AH60,FIND(",",AH60)-1),AH60) | AJ60: =IFERROR(RIGHT(Sources[[#This Row],[Reference to]],LEN(Sources[[#This Row],[Reference to]])-LEN($AG60)-2-LEN($AI60)-2),"") | AK60: =IFERROR(LEFT(AJ60,FIND(",",AJ60)-1),AJ60) | AL60: =IFERROR(RIGHT(Sources[[#This Row],[Reference to]],LEN(Sources[[#This Row],[Reference to]])-LEN($AG60)-2-LEN($AI60)-2-LEN($AK60)-2),"") | AM60: =IFERROR(LEFT(AL60,FIND(",",AL60)-1),AL60) | AN60: =IFERROR(RIGHT(Sources[[#This Row],[Reference to]],LEN(Sources[[#This Row],[Reference to]])-LEN($AG60)-2-LEN($AI60)-2-LEN($AK60)-2-LEN($AM60)-2),"") | AO60: =IFERROR(LEFT(AN60,FIND(",",AN60)-1),AN60)
B61: palzer2014comprehensive | C61: =IFERROR(VALUE(MID(Sources[[#This Row],[Citekey]],FIND("20",Sources[[#This Row],[Citekey]]),4)),"") -> 2014 | D61: yes | E61: Journal Article | F61: No cost data | H61: =IFERROR(VLOOKUP(Sources[[#This Row],[Method]],dd_analysis_graph[],2,FALSE),"") -> Not in analysis, not in graph | I61: =IFERROR(VLOOKUP(Sources[[#This Row],[Type of Publication]],dd_type_source[],2,FALSE),"") -> Publication | Z61: =IF(OR(Sources[[#This Row],[Analysis and Graph]]="Analysis and Graph",Sources[[#This Row],[Analysis and Graph]]="Not in analysis, but extra in graph"),MATCH(Sources[[#This Row],[Citekey]],Database!$B$4:$B$2385,0),"") | AA61: =IF(AG61<>"",MATCH(AG61,Sources[Citekey],0),"") | AB61: =IF(AI61<>"",MATCH(AI61,Sources[Citekey],0),"") | AC61: =IF(AK61<>"",MATCH(AK61,Sources[Citekey],0),"") | AD61: =IF(AM61<>"",MATCH(AM61,Sources[Citekey],0),"") | AE61: =IF(AO61<>"",MATCH(AO61,Sources[Citekey],0),"") | AG61: =IFERROR(IF(Sources[[#This Row],[Reference to]]<>"",LEFT(Sources[[#This Row],[Reference to]],FIND(",",Sources[[#This Row],[Reference to]])-1),""),Sources[[#This Row],[Reference to]]) | AH61: =IFERROR(RIGHT(Sources[[#This Row],[Reference to]],LEN(Sources[[#This Row],[Reference to]])-LEN($AG61)-2),"") | AI61: =IFERROR(LEFT(AH61,FIND(",",AH61)-1),AH61) | AJ61: =IFERROR(RIGHT(Sources[[#This Row],[Reference to]],LEN(Sources[[#This Row],[Reference to]])-LEN($AG61)-2-LEN($AI61)-2),"") | AK61: =IFERROR(LEFT(AJ61,FIND(",",AJ61)-1),AJ61) | AL61: =IFERROR(RIGHT(Sources[[#This Row],[Reference to]],LEN(Sources[[#This Row],[Reference to]])-LEN($AG61)-2-LEN($AI61)-2-LEN($AK61)-2),"") | AM61: =IFERROR(LEFT(AL61,FIND(",",AL61)-1),AL61) | AN61: =IFERROR(RIGHT(Sources[[#This Row],[Reference to]],LEN(Sources[[#This Row],[Reference to]])-LEN($AG61)-2-LEN($AI61)-2-LEN($AK61)-2-LEN($AM61)-2),"") | AO61: =IFERROR(LEFT(AN61,FIND(",",AN61)-1),AN61)
B62: parra2016techno | C62: =IFERROR(VALUE(MID(Sources[[#This Row],[Citekey]],FIND("20",Sources[[#This Row],[Citekey]]),4)),"") -> 2016 | D62: yes | E62: Journal Article | F62: Secondary source | G62: bertuccioli2014development | H62: =IFERROR(VLOOKUP(Sources[[#This Row],[Method]],dd_analysis_graph[],2,FALSE),"") -> Not in analysis, not in graph | I62: =IFERROR(VLOOKUP(Sources[[#This Row],[Type of Publication]],dd_type_source[],2,FALSE),"") -> Publication | Z62: =IF(OR(Sources[[#This Row],[Analysis and Graph]]="Analysis and Graph",Sources[[#This Row],[Analysis and Graph]]="Not in analysis, but extra in graph"),MATCH(Sources[[#This Row],[Citekey]],Database!$B$4:$B$2385,0),"") | AA62: =IF(AG62<>"",MATCH(AG62,Sources[Citekey],0),"") -> 106 | AB62: =IF(AI62<>"",MATCH(AI62,Sources[Citekey],0),"") | AC62: =IF(AK62<>"",MATCH(AK62,Sources[Citekey],0),"") | AD62: =IF(AM62<>"",MATCH(AM62,Sources[Citekey],0),"") | AE62: =IF(AO62<>"",MATCH(AO62,Sources[Citekey],0),"") | AG62: =IFERROR(IF(Sources[[#This Row],[Reference to]]<>"",LEFT(Sources[[#This Row],[Reference to]],FIND(",",Sources[[#This Row],[Reference to]])-1),""),Sources[[#This Row],[Reference to]]) -> bertuccioli2014development | AH62: =IFERROR(RIGHT(Sources[[#This Row],[Reference to]],LEN(Sources[[#This Row],[Reference to]])-LEN($AG62)-2),"") | AI62: =IFERROR(LEFT(AH62,FIND(",",AH62)-1),AH62) | AJ62: =IFERROR(RIGHT(Sources[[#This Row],[Reference to]],LEN(Sources[[#This Row],[Reference to]])-LEN($AG62)-2-LEN($AI62)-2),"") | AK62: =IFERROR(LEFT(AJ62,FIND(",",AJ62)-1),AJ62) | AL62: =IFERROR(RIGHT(Sources[[#This Row],[Reference to]],LEN(Sources[[#This Row],[Reference to]])-LEN($AG62)-2-LEN($AI62)-2-LEN($AK62)-2),"") | AM62: =IFERROR(LEFT(AL62,FIND(",",AL62)-1),AL62) | AN62: =IFERROR(RIGHT(Sources[[#This Row],[Reference to]],LEN(Sources[[#This Row],[Reference to]])-LEN($AG62)-2-LEN($AI62)-2-LEN($AK62)-2-LEN($AM62)-2),"") | AO62: =IFERROR(LEFT(AN62,FIND(",",AN62)-1),AN62)
B63: plessmann2014global | C63: =IFERROR(VALUE(MID(Sources[[#This Row],[Citekey]],FIND("20",Sources[[#This Row],[Citekey]]),4)),"") -> 2014 | D63: yes | E63: Journal Article | F63: Original analysis, industry data | H63: =IFERROR(VLOOKUP(Sources[[#This Row],[Method]],dd_analysis_graph[],2,FALSE),"") -> Analysis and Graph | I63: =IFERROR(VLOOKUP(Sources[[#This Row],[Type of Publication]],dd_type_source[],2,FALSE),"") -> Publication | Z63: =IF(OR(Sources[[#This Row],[Analysis and Graph]]="Analysis and Graph",Sources[[#This Row],[Analysis and Graph]]="Not in analysis, but extra in graph"),MATCH(Sources[[#This Row],[Citekey]],Database!$B$4:$B$2385,0),"") -> 1177 | AA63: =IF(AG63<>"",MATCH(AG63,Sources[Citekey],0),"") | AB63: =IF(AI63<>"",MATCH(AI63,Sources[Citekey],0),"") | AC63: =IF(AK63<>"",MATCH(AK63,Sources[Citekey],0),"") | AD63: =IF(AM63<>"",MATCH(AM63,Sources[Citekey],0),"") | AE63: =IF(AO63<>"",MATCH(AO63,Sources[Citekey],0),"") | AG63: =IFERROR(IF(Sources[[#This Row],[Reference to]]<>"",LEFT(Sources[[#This Row],[Reference to]],FIND(",",Sources[[#This Row],[Reference to]])-1),""),Sources[[#This Row],[Reference to]]) | AH63: =IFERROR(RIGHT(Sources[[#This Row],[Reference to]],LEN(Sources[[#This Row],[Reference to]])-LEN($AG63)-2),"") | AI63: =IFERROR(LEFT(AH63,FIND(",",AH63)-1),AH63) | AJ63: =IFERROR(RIGHT(Sources[[#This Row],[Reference to]],LEN(Sources[[#This Row],[Reference to]])-LEN($AG63)-2-LEN($AI63)-2),"") | AK63: =IFERROR(LEFT(AJ63,FIND(",",AJ63)-1),AJ63) | AL63: =IFERROR(RIGHT(Sources[[#This Row],[Reference to]],LEN(Sources[[#This Row],[Reference to]])-LEN($AG63)-2-LEN($AI63)-2-LEN($AK63)-2),"") | AM63: =IFERROR(LEFT(AL63,FIND(",",AL63)-1),AL63) | AN63: =IFERROR(RIGHT(Sources[[#This Row],[Reference to]],LEN(Sources[[#This Row],[Reference to]])-LEN($AG63)-2-LEN($AI63)-2-LEN($AK63)-2-LEN($AM63)-2),"") | AO63: =IFERROR(LEFT(AN63,FIND(",",AN63)-1),AN63)
B64: qadrdan2015role | C64: =IFERROR(VALUE(MID(Sources[[#This Row],[Citekey]],FIND("20",Sources[[#This Row],[Citekey]]),4)),"") -> 2015 | D64: yes | E64: Journal Article | F64: No cost data | H64: =IFERROR(VLOOKUP(Sources[[#This Row],[Method]],dd_analysis_graph[],2,FALSE),"") -> Not in analysis, not in graph | I64: =IFERROR(VLOOKUP(Sources[[#This Row],[Type of Publication]],dd_type_source[],2,FALSE),"") -> Publication | Z64: =IF(OR(Sources[[#This Row],[Analysis and Graph]]="Analysis and Graph",Sources[[#This Row],[Analysis and Graph]]="Not in analysis, but extra in graph"),MATCH(Sources[[#This Row],[Citekey]],Database!$B$4:$B$2385,0),"") | AA64: =IF(AG64<>"",MATCH(AG64,Sources[Citekey],0),"") | AB64: =IF(AI64<>"",MATCH(AI64,Sources[Citekey],0),"") | AC64: =IF(AK64<>"",MATCH(AK64,Sources[Citekey],0),"") | AD64: =IF(AM64<>"",MATCH(AM64,Sources[Citekey],0),"") | AE64: =IF(AO64<>"",MATCH(AO64,Sources[Citekey],0),"") | AG64: =IFERROR(IF(Sources[[#This Row],[Reference to]]<>"",LEFT(Sources[[#This Row],[Reference to]],FIND(",",Sources[[#This Row],[Reference to]])-1),""),Sources[[#This Row],[Reference to]]) | AH64: =IFERROR(RIGHT(Sources[[#This Row],[Reference to]],LEN(Sources[[#This Row],[Reference to]])-LEN($AG64)-2),"") | AI64: =IFERROR(LEFT(AH64,FIND(",",AH64)-1),AH64) | AJ64: =IFERROR(RIGHT(Sources[[#This Row],[Reference to]],LEN(Sources[[#This Row],[Reference to]])-LEN($AG64)-2-LEN($AI64)-2),"") | AK64: =IFERROR(LEFT(AJ64,FIND(",",AJ64)-1),AJ64) | AL64: =IFERROR(RIGHT(Sources[[#This Row],[Reference to]],LEN(Sources[[#This Row],[Reference to]])-LEN($AG64)-2-LEN($AI64)-2-LEN($AK64)-2),"") | AM64: =IFERROR(LEFT(AL64,FIND(",",AL64)-1),AL64) | AN64: =IFERROR(RIGHT(Sources[[#This Row],[Reference to]],LEN(Sources[[#This Row],[Reference to]])-LEN($AG64)-2-LEN($AI64)-2-LEN($AK64)-2-LEN($AM64)-2),"") | AO64: =IFERROR(LEFT(AN64,FIND(",",AN64)-1),AN64)
B65: samsatli2016optimal | C65: =IFERROR(VALUE(MID(Sources[[#This Row],[Citekey]],FIND("20",Sources[[#This Row],[Citekey]]),4)),"") -> 2016 | D65: yes | E65: Journal Article | F65: No cost data | H65: =IFERROR(VLOOKUP(Sources[[#This Row],[Method]],dd_analysis_graph[],2,FALSE),"") -> Not in analysis, not in graph | I65: =IFERROR(VLOOKUP(Sources[[#This Row],[Type of Publication]],dd_type_source[],2,FALSE),"") -> Publication | Z65: =IF(OR(Sources[[#This Row],[Analysis and Graph]]="Analysis and Graph",Sources[[#This Row],[Analysis and Graph]]="Not in analysis, but extra in graph"),MATCH(Sources[[#This Row],[Citekey]],Database!$B$4:$B$2385,0),"") | AA65: =IF(AG65<>"",MATCH(AG65,Sources[Citekey],0),"") | AB65: =IF(AI65<>"",MATCH(AI65,Sources[Citekey],0),"") | AC65: =IF(AK65<>"",MATCH(AK65,Sources[Citekey],0),"") | AD65: =IF(AM65<>"",MATCH(AM65,Sources[Citekey],0),"") | AE65: =IF(AO65<>"",MATCH(AO65,Sources[Citekey],0),"") | AG65: =IFERROR(IF(Sources[[#This Row],[Reference to]]<>"",LEFT(Sources[[#This Row],[Reference to]],FIND(",",Sources[[#This Row],[Reference to]])-1),""),Sources[[#This Row],[Reference to]]) | AH65: =IFERROR(RIGHT(Sources[[#This Row],[Reference to]],LEN(Sources[[#This Row],[Reference to]])-LEN($AG65)-2),"") | AI65: =IFERROR(LEFT(AH65,FIND(",",AH65)-1),AH65) | AJ65: =IFERROR(RIGHT(Sources[[#This Row],[Reference to]],LEN(Sources[[#This Row],[Reference to]])-LEN($AG65)-2-LEN($AI65)-2),"") | AK65: =IFERROR(LEFT(AJ65,FIND(",",AJ65)-1),AJ65) | AL65: =IFERROR(RIGHT(Sources[[#This Row],[Reference to]],LEN(Sources[[#This Row],[Reference to]])-LEN($AG65)-2-LEN($AI65)-2-LEN($AK65)-2),"") | AM65: =IFERROR(LEFT(AL65,FIND(",",AL65)-1),AL65) | AN65: =IFERROR(RIGHT(Sources[[#This Row],[Reference to]],LEN(Sources[[#This Row],[Reference to]])-LEN($AG65)-2-LEN($AI65)-2-LEN($AK65)-2-LEN($AM65)-2),"") | AO65: =IFERROR(LEFT(AN65,FIND(",",AN65)-1),AN65)
B66: saxe2007advantages | C66: =IFERROR(VALUE(MID(Sources[[#This Row],[Citekey]],FIND("20",Sources[[#This Row],[Citekey]]),4)),"") -> 2007 | D66: yes | E66: Journal Article | F66: Secondary source | G66: simbeck2002hydrogen, kato2005effective | H66: =IFERROR(VLOOKUP(Sources[[#This Row],[Method]],dd_analysis_graph[],2,FALSE),"") -> Not in analysis, not in graph | I66: =IFERROR(VLOOKUP(Sources[[#This Row],[Type of Publication]],dd_type_source[],2,FALSE),"") -> Publication | Z66: =IF(OR(Sources[[#This Row],[Analysis and Graph]]="Analysis and Graph",Sources[[#This Row],[Analysis and Graph]]="Not in analysis, but extra in graph"),MATCH(Sources[[#This Row],[Citekey]],Database!$B$4:$B$2385,0),"") | AA66: =IF(AG66<>"",MATCH(AG66,Sources[Citekey],0),"") -> 148 | AB66: =IF(AI66<>"",MATCH(AI66,Sources[Citekey],0),"") -> 39 | AC66: =IF(AK66<>"",MATCH(AK66,Sources[Citekey],0),"") | AD66: =IF(AM66<>"",MATCH(AM66,Sources[Citekey],0),"") | AE66: =IF(AO66<>"",MATCH(AO66,Sources[Citekey],0),"") | AG66: =IFERROR(IF(Sources[[#This Row],[Reference to]]<>"",LEFT(Sources[[#This Row],[Reference to]],FIND(",",Sources[[#This Row],[Reference to]])-1),""),Sources[[#This Row],[Reference to]]) -> simbeck2002hydrogen | AH66: =IFERROR(RIGHT(Sources[[#This Row],[Reference to]],LEN(Sources[[#This Row],[Reference to]])-LEN($AG66)-2),"") -> kato2005effective | AI66: =IFERROR(LEFT(AH66,FIND(",",AH66)-1),AH66) -> kato2005effective | AJ66: =IFERROR(RIGHT(Sources[[#This Row],[Reference to]],LEN(Sources[[#This Row],[Reference to]])-LEN($AG66)-2-LEN($AI66)-2),"") | AK66: =IFERROR(LEFT(AJ66,FIND(",",AJ66)-1),AJ66) | AL66: =IFERROR(RIGHT(Sources[[#This Row],[Reference to]],LEN(Sources[[#This Row],[Reference to]])-LEN($AG66)-2-LEN($AI66)-2-LEN($AK66)-2),"") | AM66: =IFERROR(LEFT(AL66,FIND(",",AL66)-1),AL66) | AN66: =IFERROR(RIGHT(Sources[[#This Row],[Reference to]],LEN(Sources[[#This Row],[Reference to]])-LEN($AG66)-2-LEN($AI66)-2-LEN($AK66)-2-LEN($AM66)-2),"") | AO66: =IFERROR(LEFT(AN66,FIND(",",AN66)-1),AN66)
B67: schiebahn2015pwoer | C67: =IFERROR(VALUE(MID(Sources[[#This Row],[Citekey]],FIND("20",Sources[[#This Row],[Citekey]]),4)),"") -> 2015 | D67: yes | E67: Journal Article | F67: Original review multiple sources | H67: =IFERROR(VLOOKUP(Sources[[#This Row],[Method]],dd_analysis_graph[],2,FALSE),"") -> Analysis and Graph | I67: =IFERROR(VLOOKUP(Sources[[#This Row],[Type of Publication]],dd_type_source[],2,FALSE),"") -> Publication | Z67: =IF(OR(Sources[[#This Row],[Analysis and Graph]]="Analysis and Graph",Sources[[#This Row],[Analysis and Graph]]="Not in analysis, but extra in graph"),MATCH(Sources[[#This Row],[Citekey]],Database!$B$4:$B$2385,0),"") -> 1201 | AA67: =IF(AG67<>"",MATCH(AG67,Sources[Citekey],0),"") | AB67: =IF(AI67<>"",MATCH(AI67,Sources[Citekey],0),"") | AC67: =IF(AK67<>"",MATCH(AK67,Sources[Citekey],0),"") | AD67: =IF(AM67<>"",MATCH(AM67,Sources[Citekey],0),"") | AE67: =IF(AO67<>"",MATCH(AO67,Sources[Citekey],0),"") | AG67: =IFERROR(IF(Sources[[#This Row],[Reference to]]<>"",LEFT(Sources[[#This Row],[Reference to]],FIND(",",Sources[[#This Row],[Reference to]])-1),""),Sources[[#This Row],[Reference to]]) | AH67: =IFERROR(RIGHT(Sources[[#This Row],[Reference to]],LEN(Sources[[#This Row],[Reference to]])-LEN($AG67)-2),"") | AI67: =IFERROR(LEFT(AH67,FIND(",",AH67)-1),AH67) | AJ67: =IFERROR(RIGHT(Sources[[#This Row],[Reference to]],LEN(Sources[[#This Row],[Reference to]])-LEN($AG67)-2-LEN($AI67)-2),"") | AK67: =IFERROR(LEFT(AJ67,FIND(",",AJ67)-1),AJ67) | AL67: =IFERROR(RIGHT(Sources[[#This Row],[Reference to]],LEN(Sources[[#This Row],[Reference to]])-LEN($AG67)-2-LEN($AI67)-2-LEN($AK67)-2),"") | AM67: =IFERROR(LEFT(AL67,FIND(",",AL67)-1),AL67) | AN67: =IFERROR(RIGHT(Sources[[#This Row],[Reference to]],LEN(Sources[[#This Row],[Reference to]])-LEN($AG67)-2-LEN($AI67)-2-LEN($AK67)-2-LEN($AM67)-2),"") | AO67: =IFERROR(LEFT(AN67,FIND(",",AN67)-1),AN67)
B68: simon2015hyunder | C68: =IFERROR(VALUE(MID(Sources[[#This Row],[Citekey]],FIND("20",Sources[[#This Row],[Citekey]]),4)),"") -> 2015 | D68: yes | E68: Journal Article | F68: No cost data | H68: =IFERROR(VLOOKUP(Sources[[#This Row],[Method]],dd_analysis_graph[],2,FALSE),"") -> Not in analysis, not in graph | I68: =IFERROR(VLOOKUP(Sources[[#This Row],[Type of Publication]],dd_type_source[],2,FALSE),"") -> Publication | Z68: =IF(OR(Sources[[#This Row],[Analysis and Graph]]="Analysis and Graph",Sources[[#This Row],[Analysis and Graph]]="Not in analysis, but extra in graph"),MATCH(Sources[[#This Row],[Citekey]],Database!$B$4:$B$2385,0),"") | AA68: =IF(AG68<>"",MATCH(AG68,Sources[Citekey],0),"") | AB68: =IF(AI68<>"",MATCH(AI68,Sources[Citekey],0),"") | AC68: =IF(AK68<>"",MATCH(AK68,Sources[Citekey],0),"") | AD68: =IF(AM68<>"",MATCH(AM68,Sources[Citekey],0),"") | AE68: =IF(AO68<>"",MATCH(AO68,Sources[Citekey],0),"") | AG68: =IFERROR(IF(Sources[[#This Row],[Reference to]]<>"",LEFT(Sources[[#This Row],[Reference to]],FIND(",",Sources[[#This Row],[Reference to]])-1),""),Sources[[#This Row],[Reference to]]) | AH68: =IFERROR(RIGHT(Sources[[#This Row],[Reference to]],LEN(Sources[[#This Row],[Reference to]])-LEN($AG68)-2),"") | AI68: =IFERROR(LEFT(AH68,FIND(",",AH68)-1),AH68) | AJ68: =IFERROR(RIGHT(Sources[[#This Row],[Reference to]],LEN(Sources[[#This Row],[Reference to]])-LEN($AG68)-2-LEN($AI68)-2),"") | AK68: =IFERROR(LEFT(AJ68,FIND(",",AJ68)-1),AJ68) | AL68: =IFERROR(RIGHT(Sources[[#This Row],[Reference to]],LEN(Sources[[#This Row],[Reference to]])-LEN($AG68)-2-LEN($AI68)-2-LEN($AK68)-2),"") | AM68: =IFERROR(LEFT(AL68,FIND(",",AL68)-1),AL68) | AN68: =IFERROR(RIGHT(Sources[[#This Row],[Reference to]],LEN(Sources[[#This Row],[Reference to]])-LEN($AG68)-2-LEN($AI68)-2-LEN($AK68)-2-LEN($AM68)-2),"") | AO68: =IFERROR(LEFT(AN68,FIND(",",AN68)-1),AN68)
B69: sorensen2004hydrogen | C69: =IFERROR(VALUE(MID(Sources[[#This Row],[Citekey]],FIND("20",Sources[[#This Row],[Citekey]]),4)),"") -> 2004 | D69: yes | E69: Journal Article | F69: Original analysis, industry data | H69: =IFERROR(VLOOKUP(Sources[[#This Row],[Method]],dd_analysis_graph[],2,FALSE),"") -> Analysis and Graph | I69: =IFERROR(VLOOKUP(Sources[[#This Row],[Type of Publication]],dd_type_source[],2,FALSE),"") -> Publication | Z69: =IF(OR(Sources[[#This Row],[Analysis and Graph]]="Analysis and Graph",Sources[[#This Row],[Analysis and Graph]]="Not in analysis, but extra in graph"),MATCH(Sources[[#This Row],[Citekey]],Database!$B$4:$B$2385,0),"") -> 1225 | AA69: =IF(AG69<>"",MATCH(AG69,Sources[Citekey],0),"") | AB69: =IF(AI69<>"",MATCH(AI69,Sources[Citekey],0),"") | AC69: =IF(AK69<>"",MATCH(AK69,Sources[Citekey],0),"") | AD69: =IF(AM69<>"",MATCH(AM69,Sources[Citekey],0),"") | AE69: =IF(AO69<>"",MATCH(AO69,Sources[Citekey],0),"") | AG69: =IFERROR(IF(Sources[[#This Row],[Reference to]]<>"",LEFT(Sources[[#This Row],[Reference to]],FIND(",",Sources[[#This Row],[Reference to]])-1),""),Sources[[#This Row],[Reference to]]) | AH69: =IFERROR(RIGHT(Sources[[#This Row],[Reference to]],LEN(Sources[[#This Row],[Reference to]])-LEN($AG69)-2),"") | AI69: =IFERROR(LEFT(AH69,FIND(",",AH69)-1),AH69) | AJ69: =IFERROR(RIGHT(Sources[[#This Row],[Reference to]],LEN(Sources[[#This Row],[Reference to]])-LEN($AG69)-2-LEN($AI69)-2),"") | AK69: =IFERROR(LEFT(AJ69,FIND(",",AJ69)-1),AJ69) | AL69: =IFERROR(RIGHT(Sources[[#This Row],[Reference to]],LEN(Sources[[#This Row],[Reference to]])-LEN($AG69)-2-LEN($AI69)-2-LEN($AK69)-2),"") | AM69: =IFERROR(LEFT(AL69,FIND(",",AL69)-1),AL69) | AN69: =IFERROR(RIGHT(Sources[[#This Row],[Reference to]],LEN(Sources[[#This Row],[Reference to]])-LEN($AG69)-2-LEN($AI69)-2-LEN($AK69)-2-LEN($AM69)-2),"") | AO69: =IFERROR(LEFT(AN69,FIND(",",AN69)-1),AN69)
B70: sternberg2016life | C70: =IFERROR(VALUE(MID(Sources[[#This Row],[Citekey]],FIND("20",Sources[[#This Row],[Citekey]]),4)),"") -> 2016 | D70: yes | E70: Journal Article | F70: No cost data | H70: =IFERROR(VLOOKUP(Sources[[#This Row],[Method]],dd_analysis_graph[],2,FALSE),"") -> Not in analysis, not in graph | I70: =IFERROR(VLOOKUP(Sources[[#This Row],[Type of Publication]],dd_type_source[],2,FALSE),"") -> Publication | Z70: =IF(OR(Sources[[#This Row],[Analysis and Graph]]="Analysis and Graph",Sources[[#This Row],[Analysis and Graph]]="Not in analysis, but extra in graph"),MATCH(Sources[[#This Row],[Citekey]],Database!$B$4:$B$2385,0),"") | AA70: =IF(AG70<>"",MATCH(AG70,Sources[Citekey],0),"") | AB70: =IF(AI70<>"",MATCH(AI70,Sources[Citekey],0),"") | AC70: =IF(AK70<>"",MATCH(AK70,Sources[Citekey],0),"") | AD70: =IF(AM70<>"",MATCH(AM70,Sources[Citekey],0),"") | AE70: =IF(AO70<>"",MATCH(AO70,Sources[Citekey],0),"") | AG70: =IFERROR(IF(Sources[[#This Row],[Reference to]]<>"",LEFT(Sources[[#This Row],[Reference to]],FIND(",",Sources[[#This Row],[Reference to]])-1),""),Sources[[#This Row],[Reference to]]) | AH70: =IFERROR(RIGHT(Sources[[#This Row],[Reference to]],LEN(Sources[[#This Row],[Reference to]])-LEN($AG70)-2),"") | AI70: =IFERROR(LEFT(AH70,FIND(",",AH70)-1),AH70) | AJ70: =IFERROR(RIGHT(Sources[[#This Row],[Reference to]],LEN(Sources[[#This Row],[Reference to]])-LEN($AG70)-2-LEN($AI70)-2),"") | AK70: =IFERROR(LEFT(AJ70,FIND(",",AJ70)-1),AJ70) | AL70: =IFERROR(RIGHT(Sources[[#This Row],[Reference to]],LEN(Sources[[#This Row],[Reference to]])-LEN($AG70)-2-LEN($AI70)-2-LEN($AK70)-2),"") | AM70: =IFERROR(LEFT(AL70,FIND(",",AL70)-1),AL70) | AN70: =IFERROR(RIGHT(Sources[[#This Row],[Reference to]],LEN(Sources[[#This Row],[Reference to]])-LEN($AG70)-2-LEN($AI70)-2-LEN($AK70)-2-LEN($AM70)-2),"") | AO70: =IFERROR(LEFT(AN70,FIND(",",AN70)-1),AN70)
B71: sterner2014energiespeicher | C71: =IFERROR(VALUE(MID(Sources[[#This Row],[Citekey]],FIND("20",Sources[[#This Row],[Citekey]]),4)),"") -> 2014 | D71: yes | E71: Journal Article | F71: Original analysis, industry data | H71: =IFERROR(VLOOKUP(Sources[[#This Row],[Method]],dd_analysis_graph[],2,FALSE),"") -> Analysis and Graph | I71: =IFERROR(VLOOKUP(Sources[[#This Row],[Type of Publication]],dd_type_source[],2,FALSE),"") -> Publication | Z71: =IF(OR(Sources[[#This Row],[Analysis and Graph]]="Analysis and Graph",Sources[[#This Row],[Analysis and Graph]]="Not in analysis, but extra in graph"),MATCH(Sources[[#This Row],[Citekey]],Database!$B$4:$B$2385,0),"") -> 1249 | AA71: =IF(AG71<>"",MATCH(AG71,Sources[Citekey],0),"") | AB71: =IF(AI71<>"",MATCH(AI71,Sources[Citekey],0),"") | AC71: =IF(AK71<>"",MATCH(AK71,Sources[Citekey],0),"") | AD71: =IF(AM71<>"",MATCH(AM71,Sources[Citekey],0),"") | AE71: =IF(AO71<>"",MATCH(AO71,Sources[Citekey],0),"") | AG71: =IFERROR(IF(Sources[[#This Row],[Reference to]]<>"",LEFT(Sources[[#This Row],[Reference to]],FIND(",",Sources[[#This Row],[Reference to]])-1),""),Sources[[#This Row],[Reference to]]) | AH71: =IFERROR(RIGHT(Sources[[#This Row],[Reference to]],LEN(Sources[[#This Row],[Reference to]])-LEN($AG71)-2),"") | AI71: =IFERROR(LEFT(AH71,FIND(",",AH71)-1),AH71) | AJ71: =IFERROR(RIGHT(Sources[[#This Row],[Reference to]],LEN(Sources[[#This Row],[Reference to]])-LEN($AG71)-2-LEN($AI71)-2),"") | AK71: =IFERROR(LEFT(AJ71,FIND(",",AJ71)-1),AJ71) | AL71: =IFERROR(RIGHT(Sources[[#This Row],[Reference to]],LEN(Sources[[#This Row],[Reference to]])-LEN($AG71)-2-LEN($AI71)-2-LEN($AK71)-2),"") | AM71: =IFERROR(LEFT(AL71,FIND(",",AL71)-1),AL71) | AN71: =IFERROR(RIGHT(Sources[[#This Row],[Reference to]],LEN(Sources[[#This Row],[Reference to]])-LEN($AG71)-2-LEN($AI71)-2-LEN($AK71)-2-LEN($AM71)-2),"") | AO71: =IFERROR(LEFT(AN71,FIND(",",AN71)-1),AN71)
B72: tsupari2016economic | C72: =IFERROR(VALUE(MID(Sources[[#This Row],[Citekey]],FIND("20",Sources[[#This Row],[Citekey]]),4)),"") -> 2016 | D72: yes | E72: Journal Article | F72: Secondary source | G72: bertuccioli2014development | H72: =IFERROR(VLOOKUP(Sources[[#This Row],[Method]],dd_analysis_graph[],2,FALSE),"") -> Not in analysis, not in graph | I72: =IFERROR(VLOOKUP(Sources[[#This Row],[Type of Publication]],dd_type_source[],2,FALSE),"") -> Publication | Z72: =IF(OR(Sources[[#This Row],[Analysis and Graph]]="Analysis and Graph",Sources[[#This Row],[Analysis and Graph]]="Not in analysis, but extra in graph"),MATCH(Sources[[#This Row],[Citekey]],Database!$B$4:$B$2385,0),"") | AA72: =IF(AG72<>"",MATCH(AG72,Sources[Citekey],0),"") -> 106 | AB72: =IF(AI72<>"",MATCH(AI72,Sources[Citekey],0),"") | AC72: =IF(AK72<>"",MATCH(AK72,Sources[Citekey],0),"") | AD72: =IF(AM72<>"",MATCH(AM72,Sources[Citekey],0),"") | AE72: =IF(AO72<>"",MATCH(AO72,Sources[Citekey],0),"") | AG72: =IFERROR(IF(Sources[[#This Row],[Reference to]]<>"",LEFT(Sources[[#This Row],[Reference to]],FIND(",",Sources[[#This Row],[Reference to]])-1),""),Sources[[#This Row],[Reference to]]) -> bertuccioli2014development | AH72: =IFERROR(RIGHT(Sources[[#This Row],[Reference to]],LEN(Sources[[#This Row],[Reference to]])-LEN($AG72)-2),"") | AI72: =IFERROR(LEFT(AH72,FIND(",",AH72)-1),AH72) | AJ72: =IFERROR(RIGHT(Sources[[#This Row],[Reference to]],LEN(Sources[[#This Row],[Reference to]])-LEN($AG72)-2-LEN($AI72)-2),"") | AK72: =IFERROR(LEFT(AJ72,FIND(",",AJ72)-1),AJ72) | AL72: =IFERROR(RIGHT(Sources[[#This Row],[Reference to]],LEN(Sources[[#This Row],[Reference to]])-LEN($AG72)-2-LEN($AI72)-2-LEN($AK72)-2),"") | AM72: =IFERROR(LEFT(AL72,FIND(",",AL72)-1),AL72) | AN72: =IFERROR(RIGHT(Sources[[#This Row],[Reference to]],LEN(Sources[[#This Row],[Reference to]])-LEN($AG72)-2-LEN($AI72)-2-LEN($AK72)-2-LEN($AM72)-2),"") | AO72: =IFERROR(LEFT(AN72,FIND(",",AN72)-1),AN72)
B73: turner2008renewable | C73: =IFERROR(VALUE(MID(Sources[[#This Row],[Citekey]],FIND("20",Sources[[#This Row],[Citekey]]),4)),"") -> 2008 | D73: yes | E73: Journal Article | F73: No cost data | H73: =IFERROR(VLOOKUP(Sources[[#This Row],[Method]],dd_analysis_graph[],2,FALSE),"") -> Not in analysis, not in graph | I73: =IFERROR(VLOOKUP(Sources[[#This Row],[Type of Publication]],dd_type_source[],2,FALSE),"") -> Publication | Z73: =IF(OR(Sources[[#This Row],[Analysis and Graph]]="Analysis and Graph",Sources[[#This Row],[Analysis and Graph]]="Not in analysis, but extra in graph"),MATCH(Sources[[#This Row],[Citekey]],Database!$B$4:$B$2385,0),"") | AA73: =IF(AG73<>"",MATCH(AG73,Sources[Citekey],0),"") | AB73: =IF(AI73<>"",MATCH(AI73,Sources[Citekey],0),"") | AC73: =IF(AK73<>"",MATCH(AK73,Sources[Citekey],0),"") | AD73: =IF(AM73<>"",MATCH(AM73,Sources[Citekey],0),"") | AE73: =IF(AO73<>"",MATCH(AO73,Sources[Citekey],0),"") | AG73: =IFERROR(IF(Sources[[#This Row],[Reference to]]<>"",LEFT(Sources[[#This Row],[Reference to]],FIND(",",Sources[[#This Row],[Reference to]])-1),""),Sources[[#This Row],[Reference to]]) | AH73: =IFERROR(RIGHT(Sources[[#This Row],[Reference to]],LEN(Sources[[#This Row],[Reference to]])-LEN($AG73)-2),"") | AI73: =IFERROR(LEFT(AH73,FIND(",",AH73)-1),AH73) | AJ73: =IFERROR(RIGHT(Sources[[#This Row],[Reference to]],LEN(Sources[[#This Row],[Reference to]])-LEN($AG73)-2-LEN($AI73)-2),"") | AK73: =IFERROR(LEFT(AJ73,FIND(",",AJ73)-1),AJ73) | AL73: =IFERROR(RIGHT(Sources[[#This Row],[Reference to]],LEN(Sources[[#This Row],[Reference to]])-LEN($AG73)-2-LEN($AI73)-2-LEN($AK73)-2),"") | AM73: =IFERROR(LEFT(AL73,FIND(",",AL73)-1),AL73) | AN73: =IFERROR(RIGHT(Sources[[#This Row],[Reference to]],LEN(Sources[[#This Row],[Reference to]])-LEN($AG73)-2-LEN($AI73)-2-LEN($AK73)-2-LEN($AM73)-2),"") | AO73: =IFERROR(LEFT(AN73,FIND(",",AN73)-1),AN73)
B74: ursua2012hydrogen | C74: =IFERROR(VALUE(MID(Sources[[#This Row],[Citekey]],FIND("20",Sources[[#This Row],[Citekey]]),4)),"") -> 2012 | D74: yes | E74: Journal Article | F74: Secondary source | G74: rajeshwar2008solar | H74: =IFERROR(VLOOKUP(Sources[[#This Row],[Method]],dd_analysis_graph[],2,FALSE),"") -> Not in analysis, not in graph | I74: =IFERROR(VLOOKUP(Sources[[#This Row],[Type of Publication]],dd_type_source[],2,FALSE),"") -> Publication | Z74: =IF(OR(Sources[[#This Row],[Analysis and Graph]]="Analysis and Graph",Sources[[#This Row],[Analysis and Graph]]="Not in analysis, but extra in graph"),MATCH(Sources[[#This Row],[Citekey]],Database!$B$4:$B$2385,0),"") | AA74: =IF(AG74<>"",MATCH(AG74,Sources[Citekey],0),"") -> 142 | AB74: =IF(AI74<>"",MATCH(AI74,Sources[Citekey],0),"") | AC74: =IF(AK74<>"",MATCH(AK74,Sources[Citekey],0),"") | AD74: =IF(AM74<>"",MATCH(AM74,Sources[Citekey],0),"") | AE74: =IF(AO74<>"",MATCH(AO74,Sources[Citekey],0),"") | AG74: =IFERROR(IF(Sources[[#This Row],[Reference to]]<>"",LEFT(Sources[[#This Row],[Reference to]],FIND(",",Sources[[#This Row],[Reference to]])-1),""),Sources[[#This Row],[Reference to]]) -> rajeshwar2008solar | AH74: =IFERROR(RIGHT(Sources[[#This Row],[Reference to]],LEN(Sources[[#This Row],[Reference to]])-LEN($AG74)-2),"") | AI74: =IFERROR(LEFT(AH74,FIND(",",AH74)-1),AH74) | AJ74: =IFERROR(RIGHT(Sources[[#This Row],[Reference to]],LEN(Sources[[#This Row],[Reference to]])-LEN($AG74)-2-LEN($AI74)-2),"") | AK74: =IFERROR(LEFT(AJ74,FIND(",",AJ74)-1),AJ74) | AL74: =IFERROR(RIGHT(Sources[[#This Row],[Reference to]],LEN(Sources[[#This Row],[Reference to]])-LEN($AG74)-2-LEN($AI74)-2-LEN($AK74)-2),"") | AM74: =IFERROR(LEFT(AL74,FIND(",",AL74)-1),AL74) | AN74: =IFERROR(RIGHT(Sources[[#This Row],[Reference to]],LEN(Sources[[#This Row],[Reference to]])-LEN($AG74)-2-LEN($AI74)-2-LEN($AK74)-2-LEN($AM74)-2),"") | AO74: =IFERROR(LEFT(AN74,FIND(",",AN74)-1),AN74)
B75: vandewalle2015effects | C75: =IFERROR(VALUE(MID(Sources[[#This Row],[Citekey]],FIND("20",Sources[[#This Row],[Citekey]]),4)),"") -> 2015 | D75: yes | E75: Journal Article | F75: Secondary source | G75: jentsch2014optimal | H75: =IFERROR(VLOOKUP(Sources[[#This Row],[Method]],dd_analysis_graph[],2,FALSE),"") -> Not in analysis, not in graph | I75: =IFERROR(VLOOKUP(Sources[[#This Row],[Type of Publication]],dd_type_source[],2,FALSE),"") -> Publication | Z75: =IF(OR(Sources[[#This Row],[Analysis and Graph]]="Analysis and Graph",Sources[[#This Row],[Analysis and Graph]]="Not in analysis, but extra in graph"),MATCH(Sources[[#This Row],[Citekey]],Database!$B$4:$B$2385,0),"") | AA75: =IF(AG75<>"",MATCH(AG75,Sources[Citekey],0),"") -> 35 | AB75: =IF(AI75<>"",MATCH(AI75,Sources[Citekey],0),"") | AC75: =IF(AK75<>"",MATCH(AK75,Sources[Citekey],0),"") | AD75: =IF(AM75<>"",MATCH(AM75,Sources[Citekey],0),"") | AE75: =IF(AO75<>"",MATCH(AO75,Sources[Citekey],0),"") | AG75: =IFERROR(IF(Sources[[#This Row],[Reference to]]<>"",LEFT(Sources[[#This Row],[Reference to]],FIND(",",Sources[[#This Row],[Reference to]])-1),""),Sources[[#This Row],[Reference to]]) -> jentsch2014optimal | AH75: =IFERROR(RIGHT(Sources[[#This Row],[Reference to]],LEN(Sources[[#This Row],[Reference to]])-LEN($AG75)-2),"") | AI75: =IFERROR(LEFT(AH75,FIND(",",AH75)-1),AH75) | AJ75: =IFERROR(RIGHT(Sources[[#This Row],[Reference to]],LEN(Sources[[#This Row],[Reference to]])-LEN($AG75)-2-LEN($AI75)-2),"") | AK75: =IFERROR(LEFT(AJ75,FIND(",",AJ75)-1),AJ75) | AL75: =IFERROR(RIGHT(Sources[[#This Row],[Reference to]],LEN(Sources[[#This Row],[Reference to]])-LEN($AG75)-2-LEN($AI75)-2-LEN($AK75)-2),"") | AM75: =IFERROR(LEFT(AL75,FIND(",",AL75)-1),AL75) | AN75: =IFERROR(RIGHT(Sources[[#This Row],[Reference to]],LEN(Sources[[#This Row],[Reference to]])-LEN($AG75)-2-LEN($AI75)-2-LEN($AK75)-2-LEN($AM75)-2),"") | AO75: =IFERROR(LEFT(AN75,FIND(",",AN75)-1),AN75)
B76: varone2015power | C76: =IFERROR(VALUE(MID(Sources[[#This Row],[Citekey]],FIND("20",Sources[[#This Row],[Citekey]]),4)),"") -> 2015 | D76: yes | E76: Journal Article | F76: Original analysis, industry data | H76: =IFERROR(VLOOKUP(Sources[[#This Row],[Method]],dd_analysis_graph[],2,FALSE),"") -> Analysis and Graph | I76: =IFERROR(VLOOKUP(Sources[[#This Row],[Type of Publication]],dd_type_source[],2,FALSE),"") -> Publication | Z76: =IF(OR(Sources[[#This Row],[Analysis and Graph]]="Analysis and Graph",Sources[[#This Row],[Analysis and Graph]]="Not in analysis, but extra in graph"),MATCH(Sources[[#This Row],[Citekey]],Database!$B$4:$B$2385,0),"") -> 1297 | AA76: =IF(AG76<>"",MATCH(AG76,Sources[Citekey],0),"") | AB76: =IF(AI76<>"",MATCH(AI76,Sources[Citekey],0),"") | AC76: =IF(AK76<>"",MATCH(AK76,Sources[Citekey],0),"") | AD76: =IF(AM76<>"",MATCH(AM76,Sources[Citekey],0),"") | AE76: =IF(AO76<>"",MATCH(AO76,Sources[Citekey],0),"") | AG76: =IFERROR(IF(Sources[[#This Row],[Reference to]]<>"",LEFT(Sources[[#This Row],[Reference to]],FIND(",",Sources[[#This Row],[Reference to]])-1),""),Sources[[#This Row],[Reference to]]) | AH76: =IFERROR(RIGHT(Sources[[#This Row],[Reference to]],LEN(Sources[[#This Row],[Reference to]])-LEN($AG76)-2),"") | AI76: =IFERROR(LEFT(AH76,FIND(",",AH76)-1),AH76) | AJ76: =IFERROR(RIGHT(Sources[[#This Row],[Reference to]],LEN(Sources[[#This Row],[Reference to]])-LEN($AG76)-2-LEN($AI76)-2),"") | AK76: =IFERROR(LEFT(AJ76,FIND(",",AJ76)-1),AJ76) | AL76: =IFERROR(RIGHT(Sources[[#This Row],[Reference to]],LEN(Sources[[#This Row],[Reference to]])-LEN($AG76)-2-LEN($AI76)-2-LEN($AK76)-2),"") | AM76: =IFERROR(LEFT(AL76,FIND(",",AL76)-1),AL76) | AN76: =IFERROR(RIGHT(Sources[[#This Row],[Reference to]],LEN(Sources[[#This Row],[Reference to]])-LEN($AG76)-2-LEN($AI76)-2-LEN($AK76)-2-LEN($AM76)-2),"") | AO76: =IFERROR(LEFT(AN76,FIND(",",AN76)-1),AN76)
B77: walker2016benchmarking | C77: =IFERROR(VALUE(MID(Sources[[#This Row],[Citekey]],FIND("20",Sources[[#This Row],[Citekey]]),4)),"") -> 2016 | D77: yes | E77: Journal Article | F77: Original review multiple sources | G77: guandalini2015power | H77: =IFERROR(VLOOKUP(Sources[[#This Row],[Method]],dd_analysis_graph[],2,FALSE),"") -> Analysis and Graph | I77: =IFERROR(VLOOKUP(Sources[[#This Row],[Type of Publication]],dd_type_source[],2,FALSE),"") -> Publication | Z77: =IF(OR(Sources[[#This Row],[Analysis and Graph]]="Analysis and Graph",Sources[[#This Row],[Analysis and Graph]]="Not in analysis, but extra in graph"),MATCH(Sources[[#This Row],[Citekey]],Database!$B$4:$B$2385,0),"") -> 1465 | AA77: =IF(AG77<>"",MATCH(AG77,Sources[Citekey],0),"") -> 29 | AB77: =IF(AI77<>"",MATCH(AI77,Sources[Citekey],0),"") | AC77: =IF(AK77<>"",MATCH(AK77,Sources[Citekey],0),"") | AD77: =IF(AM77<>"",MATCH(AM77,Sources[Citekey],0),"") | AE77: =IF(AO77<>"",MATCH(AO77,Sources[Citekey],0),"") | AG77: =IFERROR(IF(Sources[[#This Row],[Reference to]]<>"",LEFT(Sources[[#This Row],[Reference to]],FIND(",",Sources[[#This Row],[Reference to]])-1),""),Sources[[#This Row],[Reference to]]) -> guandalini2015power | AH77: =IFERROR(RIGHT(Sources[[#This Row],[Reference to]],LEN(Sources[[#This Row],[Reference to]])-LEN($AG77)-2),"") | AI77: =IFERROR(LEFT(AH77,FIND(",",AH77)-1),AH77) | AJ77: =IFERROR(RIGHT(Sources[[#This Row],[Reference to]],LEN(Sources[[#This Row],[Reference to]])-LEN($AG77)-2-LEN($AI77)-2),"") | AK77: =IFERROR(LEFT(AJ77,FIND(",",AJ77)-1),AJ77) | AL77: =IFERROR(RIGHT(Sources[[#This Row],[Reference to]],LEN(Sources[[#This Row],[Reference to]])-LEN($AG77)-2-LEN($AI77)-2-LEN($AK77)-2),"") | AM77: =IFERROR(LEFT(AL77,FIND(",",AL77)-1),AL77) | AN77: =IFERROR(RIGHT(Sources[[#This Row],[Reference to]],LEN(Sources[[#This Row],[Reference to]])-LEN($AG77)-2-LEN($AI77)-2-LEN($AK77)-2-LEN($AM77)-2),"") | AO77: =IFERROR(LEFT(AN77,FIND(",",AN77)-1),AN77)
B78: walker2016economic | C78: =IFERROR(VALUE(MID(Sources[[#This Row],[Citekey]],FIND("20",Sources[[#This Row],[Citekey]]),4)),"") -> 2016 | D78: yes | E78: Journal Article | F78: No cost data | H78: =IFERROR(VLOOKUP(Sources[[#This Row],[Method]],dd_analysis_graph[],2,FALSE),"") -> Not in analysis, not in graph | I78: =IFERROR(VLOOKUP(Sources[[#This Row],[Type of Publication]],dd_type_source[],2,FALSE),"") -> Publication | Z78: =IF(OR(Sources[[#This Row],[Analysis and Graph]]="Analysis and Graph",Sources[[#This Row],[Analysis and Graph]]="Not in analysis, but extra in graph"),MATCH(Sources[[#This Row],[Citekey]],Database!$B$4:$B$2385,0),"") | AA78: =IF(AG78<>"",MATCH(AG78,Sources[Citekey],0),"") | AB78: =IF(AI78<>"",MATCH(AI78,Sources[Citekey],0),"") | AC78: =IF(AK78<>"",MATCH(AK78,Sources[Citekey],0),"") | AD78: =IF(AM78<>"",MATCH(AM78,Sources[Citekey],0),"") | AE78: =IF(AO78<>"",MATCH(AO78,Sources[Citekey],0),"") | AG78: =IFERROR(IF(Sources[[#This Row],[Reference to]]<>"",LEFT(Sources[[#This Row],[Reference to]],FIND(",",Sources[[#This Row],[Reference to]])-1),""),Sources[[#This Row],[Reference to]]) | AH78: =IFERROR(RIGHT(Sources[[#This Row],[Reference to]],LEN(Sources[[#This Row],[Reference to]])-LEN($AG78)-2),"") | AI78: =IFERROR(LEFT(AH78,FIND(",",AH78)-1),AH78) | AJ78: =IFERROR(RIGHT(Sources[[#This Row],[Reference to]],LEN(Sources[[#This Row],[Reference to]])-LEN($AG78)-2-LEN($AI78)-2),"") | AK78: =IFERROR(LEFT(AJ78,FIND(",",AJ78)-1),AJ78) | AL78: =IFERROR(RIGHT(Sources[[#This Row],[Reference to]],LEN(Sources[[#This Row],[Reference to]])-LEN($AG78)-2-LEN($AI78)-2-LEN($AK78)-2),"") | AM78: =IFERROR(LEFT(AL78,FIND(",",AL78)-1),AL78) | AN78: =IFERROR(RIGHT(Sources[[#This Row],[Reference to]],LEN(Sources[[#This Row],[Reference to]])-LEN($AG78)-2-LEN($AI78)-2-LEN($AK78)-2-LEN($AM78)-2),"") | AO78: =IFERROR(LEFT(AN78,FIND(",",AN78)-1),AN78)
B79: winkler2013power | C79: =IFERROR(VALUE(MID(Sources[[#This Row],[Citekey]],FIND("20",Sources[[#This Row],[Citekey]]),4)),"") -> 2013 | D79: yes | E79: Journal Article | F79: Original analysis, industry data | H79: =IFERROR(VLOOKUP(Sources[[#This Row],[Method]],dd_analysis_graph[],2,FALSE),"") -> Analysis and Graph | I79: =IFERROR(VLOOKUP(Sources[[#This Row],[Type of Publication]],dd_type_source[],2,FALSE),"") -> Publication | Z79: =IF(OR(Sources[[#This Row],[Analysis and Graph]]="Analysis and Graph",Sources[[#This Row],[Analysis and Graph]]="Not in analysis, but extra in graph"),MATCH(Sources[[#This Row],[Citekey]],Database!$B$4:$B$2385,0),"") -> 1321 | AA79: =IF(AG79<>"",MATCH(AG79,Sources[Citekey],0),"") | AB79: =IF(AI79<>"",MATCH(AI79,Sources[Citekey],0),"") | AC79: =IF(AK79<>"",MATCH(AK79,Sources[Citekey],0),"") | AD79: =IF(AM79<>"",MATCH(AM79,Sources[Citekey],0),"") | AE79: =IF(AO79<>"",MATCH(AO79,Sources[Citekey],0),"") | AG79: =IFERROR(IF(Sources[[#This Row],[Reference to]]<>"",LEFT(Sources[[#This Row],[Reference to]],FIND(",",Sources[[#This Row],[Reference to]])-1),""),Sources[[#This Row],[Reference to]]) | AH79: =IFERROR(RIGHT(Sources[[#This Row],[Reference to]],LEN(Sources[[#This Row],[Reference to]])-LEN($AG79)-2),"") | AI79: =IFERROR(LEFT(AH79,FIND(",",AH79)-1),AH79) | AJ79: =IFERROR(RIGHT(Sources[[#This Row],[Reference to]],LEN(Sources[[#This Row],[Reference to]])-LEN($AG79)-2-LEN($AI79)-2),"") | AK79: =IFERROR(LEFT(AJ79,FIND(",",AJ79)-1),AJ79) | AL79: =IFERROR(RIGHT(Sources[[#This Row],[Reference to]],LEN(Sources[[#This Row],[Reference to]])-LEN($AG79)-2-LEN($AI79)-2-LEN($AK79)-2),"") | AM79: =IFERROR(LEFT(AL79,FIND(",",AL79)-1),AL79) | AN79: =IFERROR(RIGHT(Sources[[#This Row],[Reference to]],LEN(Sources[[#This Row],[Reference to]])-LEN($AG79)-2-LEN($AI79)-2-LEN($AK79)-2-LEN($AM79)-2),"") | AO79: =IFERROR(LEFT(AN79,FIND(",",AN79)-1),AN79)
B80: yang2007determining | C80: =IFERROR(VALUE(MID(Sources[[#This Row],[Citekey]],FIND("20",Sources[[#This Row],[Citekey]]),4)),"") -> 2007 | D80: yes | E80: Journal Article | F80: No cost data | H80: =IFERROR(VLOOKUP(Sources[[#This Row],[Method]],dd_analysis_graph[],2,FALSE),"") -> Not in analysis, not in graph | I80: =IFERROR(VLOOKUP(Sources[[#This Row],[Type of Publication]],dd_type_source[],2,FALSE),"") -> Publication | Z80: =IF(OR(Sources[[#This Row],[Analysis and Graph]]="Analysis and Graph",Sources[[#This Row],[Analysis and Graph]]="Not in analysis, but extra in graph"),MATCH(Sources[[#This Row],[Citekey]],Database!$B$4:$B$2385,0),"") | AA80: =IF(AG80<>"",MATCH(AG80,Sources[Citekey],0),"") | AB80: =IF(AI80<>"",MATCH(AI80,Sources[Citekey],0),"") | AC80: =IF(AK80<>"",MATCH(AK80,Sources[Citekey],0),"") | AD80: =IF(AM80<>"",MATCH(AM80,Sources[Citekey],0),"") | AE80: =IF(AO80<>"",MATCH(AO80,Sources[Citekey],0),"") | AG80: =IFERROR(IF(Sources[[#This Row],[Reference to]]<>"",LEFT(Sources[[#This Row],[Reference to]],FIND(",",Sources[[#This Row],[Reference to]])-1),""),Sources[[#This Row],[Reference to]]) | AH80: =IFERROR(RIGHT(Sources[[#This Row],[Reference to]],LEN(Sources[[#This Row],[Reference to]])-LEN($AG80)-2),"") | AI80: =IFERROR(LEFT(AH80,FIND(",",AH80)-1),AH80) | AJ80: =IFERROR(RIGHT(Sources[[#This Row],[Reference to]],LEN(Sources[[#This Row],[Reference to]])-LEN($AG80)-2-LEN($AI80)-2),"") | AK80: =IFERROR(LEFT(AJ80,FIND(",",AJ80)-1),AJ80) | AL80: =IFERROR(RIGHT(Sources[[#This Row],[Reference to]],LEN(Sources[[#This Row],[Reference to]])-LEN($AG80)-2-LEN($AI80)-2-LEN($AK80)-2),"") | AM80: =IFERROR(LEFT(AL80,FIND(",",AL80)-1),AL80) | AN80: =IFERROR(RIGHT(Sources[[#This Row],[Reference to]],LEN(Sources[[#This Row],[Reference to]])-LEN($AG80)-2-LEN($AI80)-2-LEN($AK80)-2-LEN($AM80)-2),"") | AO80: =IFERROR(LEFT(AN80,FIND(",",AN80)-1),AN80)
B81: you2016value | C81: =IFERROR(VALUE(MID(Sources[[#This Row],[Citekey]],FIND("20",Sources[[#This Row],[Citekey]]),4)),"") -> 2016 | D81: yes | E81: Journal Article | F81: Secondary source | G81: CopenHydrogen2014project | H81: =IFERROR(VLOOKUP(Sources[[#This Row],[Method]],dd_analysis_graph[],2,FALSE),"") -> Not in analysis, not in graph | I81: =IFERROR(VLOOKUP(Sources[[#This Row],[Type of Publication]],dd_type_source[],2,FALSE),"") -> Publication | Z81: =IF(OR(Sources[[#This Row],[Analysis and Graph]]="Analysis and Graph",Sources[[#This Row],[Analysis and Graph]]="Not in analysis, but extra in graph"),MATCH(Sources[[#This Row],[Citekey]],Database!$B$4:$B$2385,0),"") | AA81: =IF(AG81<>"",MATCH(AG81,Sources[Citekey],0),"") -> 110 | AB81: =IF(AI81<>"",MATCH(AI81,Sources[Citekey],0),"") | AC81: =IF(AK81<>"",MATCH(AK81,Sources[Citekey],0),"") | AD81: =IF(AM81<>"",MATCH(AM81,Sources[Citekey],0),"") | AE81: =IF(AO81<>"",MATCH(AO81,Sources[Citekey],0),"") | AG81: =IFERROR(IF(Sources[[#This Row],[Reference to]]<>"",LEFT(Sources[[#This Row],[Reference to]],FIND(",",Sources[[#This Row],[Reference to]])-1),""),Sources[[#This Row],[Reference to]]) -> CopenHydrogen2014project | AH81: =IFERROR(RIGHT(Sources[[#This Row],[Reference to]],LEN(Sources[[#This Row],[Reference to]])-LEN($AG81)-2),"") | AI81: =IFERROR(LEFT(AH81,FIND(",",AH81)-1),AH81) | AJ81: =IFERROR(RIGHT(Sources[[#This Row],[Reference to]],LEN(Sources[[#This Row],[Reference to]])-LEN($AG81)-2-LEN($AI81)-2),"") | AK81: =IFERROR(LEFT(AJ81,FIND(",",AJ81)-1),AJ81) | AL81: =IFERROR(RIGHT(Sources[[#This Row],[Reference to]],LEN(Sources[[#This Row],[Reference to]])-LEN($AG81)-2-LEN($AI81)-2-LEN($AK81)-2),"") | AM81: =IFERROR(LEFT(AL81,FIND(",",AL81)-1),AL81) | AN81: =IFERROR(RIGHT(Sources[[#This Row],[Reference to]],LEN(Sources[[#This Row],[Reference to]])-LEN($AG81)-2-LEN($AI81)-2-LEN($AK81)-2-LEN($AM81)-2),"") | AO81: =IFERROR(LEFT(AN81,FIND(",",AN81)-1),AN81)
B82: zakeri2015electrical | C82: =IFERROR(VALUE(MID(Sources[[#This Row],[Citekey]],FIND("20",Sources[[#This Row],[Citekey]]),4)),"") -> 2015 | D82: yes | E82: Journal Article | F82: Original review multiple sources | H82: =IFERROR(VLOOKUP(Sources[[#This Row],[Method]],dd_analysis_graph[],2,FALSE),"") -> Analysis and Graph | I82: =IFERROR(VLOOKUP(Sources[[#This Row],[Type of Publication]],dd_type_source[],2,FALSE),"") -> Publication | Z82: =IF(OR(Sources[[#This Row],[Analysis and Graph]]="Analysis and Graph",Sources[[#This Row],[Analysis and Graph]]="Not in analysis, but extra in graph"),MATCH(Sources[[#This Row],[Citekey]],Database!$B$4:$B$2385,0),"") -> 673 | AA82: =IF(AG82<>"",MATCH(AG82,Sources[Citekey],0),"") | AB82: =IF(AI82<>"",MATCH(AI82,Sources[Citekey],0),"") | AC82: =IF(AK82<>"",MATCH(AK82,Sources[Citekey],0),"") | AD82: =IF(AM82<>"",MATCH(AM82,Sources[Citekey],0),"") | AE82: =IF(AO82<>"",MATCH(AO82,Sources[Citekey],0),"") | AG82: =IFERROR(IF(Sources[[#This Row],[Reference to]]<>"",LEFT(Sources[[#This Row],[Reference to]],FIND(",",Sources[[#This Row],[Reference to]])-1),""),Sources[[#This Row],[Reference to]]) | AH82: =IFERROR(RIGHT(Sources[[#This Row],[Reference to]],LEN(Sources[[#This Row],[Reference to]])-LEN($AG82)-2),"") | AI82: =IFERROR(LEFT(AH82,FIND(",",AH82)-1),AH82) | AJ82: =IFERROR(RIGHT(Sources[[#This Row],[Reference to]],LEN(Sources[[#This Row],[Reference to]])-LEN($AG82)-2-LEN($AI82)-2),"") | AK82: =IFERROR(LEFT(AJ82,FIND(",",AJ82)-1),AJ82) | AL82: =IFERROR(RIGHT(Sources[[#This Row],[Reference to]],LEN(Sources[[#This Row],[Reference to]])-LEN($AG82)-2-LEN($AI82)-2-LEN($AK82)-2),"") | AM82: =IFERROR(LEFT(AL82,FIND(",",AL82)-1),AL82) | AN82: =IFERROR(RIGHT(Sources[[#This Row],[Reference to]],LEN(Sources[[#This Row],[Reference to]])-LEN($AG82)-2-LEN($AI82)-2-LEN($AK82)-2-LEN($AM82)-2),"") | AO82: =IFERROR(LEFT(AN82,FIND(",",AN82)-1),AN82)
B83: zhang2014a | C83: =IFERROR(VALUE(MID(Sources[[#This Row],[Citekey]],FIND("20",Sources[[#This Row],[Citekey]]),4)),"") -> 2014 | D83: yes | E83: Journal Article | F83: No reference, unclear method | H83: =IFERROR(VLOOKUP(Sources[[#This Row],[Method]],dd_analysis_graph[],2,FALSE),"") -> Not in analysis, not in graph | I83: =IFERROR(VLOOKUP(Sources[[#This Row],[Type of Publication]],dd_type_source[],2,FALSE),"") -> Publication | Z83: =IF(OR(Sources[[#This Row],[Analysis and Graph]]="Analysis and Graph",Sources[[#This Row],[Analysis and Graph]]="Not in analysis, but extra in graph"),MATCH(Sources[[#This Row],[Citekey]],Database!$B$4:$B$2385,0),"") | AA83: =IF(AG83<>"",MATCH(AG83,Sources[Citekey],0),"") | AB83: =IF(AI83<>"",MATCH(AI83,Sources[Citekey],0),"") | AC83: =IF(AK83<>"",MATCH(AK83,Sources[Citekey],0),"") | AD83: =IF(AM83<>"",MATCH(AM83,Sources[Citekey],0),"") | AE83: =IF(AO83<>"",MATCH(AO83,Sources[Citekey],0),"") | AG83: =IFERROR(IF(Sources[[#This Row],[Reference to]]<>"",LEFT(Sources[[#This Row],[Reference to]],FIND(",",Sources[[#This Row],[Reference to]])-1),""),Sources[[#This Row],[Reference to]]) | AH83: =IFERROR(RIGHT(Sources[[#This Row],[Reference to]],LEN(Sources[[#This Row],[Reference to]])-LEN($AG83)-2),"") | AI83: =IFERROR(LEFT(AH83,FIND(",",AH83)-1),AH83) | AJ83: =IFERROR(RIGHT(Sources[[#This Row],[Reference to]],LEN(Sources[[#This Row],[Reference to]])-LEN($AG83)-2-LEN($AI83)-2),"") | AK83: =IFERROR(LEFT(AJ83,FIND(",",AJ83)-1),AJ83) | AL83: =IFERROR(RIGHT(Sources[[#This Row],[Reference to]],LEN(Sources[[#This Row],[Reference to]])-LEN($AG83)-2-LEN($AI83)-2-LEN($AK83)-2),"") | AM83: =IFERROR(LEFT(AL83,FIND(",",AL83)-1),AL83) | AN83: =IFERROR(RIGHT(Sources[[#This Row],[Reference to]],LEN(Sources[[#This Row],[Reference to]])-LEN($AG83)-2-LEN($AI83)-2-LEN($AK83)-2-LEN($AM83)-2),"") | AO83: =IFERROR(LEFT(AN83,FIND(",",AN83)-1),AN83)
B84: Anonymous2014-1 | C84: =IFERROR(VALUE(MID(Sources[[#This Row],[Citekey]],FIND("20",Sources[[#This Row],[Citekey]]),4)),"") -> 2014 | D84: no | E84: Manufacturer Interview | F84: Original analysis, industry data | H84: =IFERROR(VLOOKUP(Sources[[#This Row],[Method]],dd_analysis_graph[],2,FALSE),"") -> Analysis and Graph | I84: =IFERROR(VLOOKUP(Sources[[#This Row],[Type of Publication]],dd_type_source[],2,FALSE),"") -> Manufacturer Interview | Z84: =IF(OR(Sources[[#This Row],[Analysis and Graph]]="Analysis and Graph",Sources[[#This Row],[Analysis and Graph]]="Not in analysis, but extra in graph"),MATCH(Sources[[#This Row],[Citekey]],Database!$B$4:$B$2385,0),"") -> 1898 | AA84: =IF(AG84<>"",MATCH(AG84,Sources[Citekey],0),"") | AB84: =IF(AI84<>"",MATCH(AI84,Sources[Citekey],0),"") | AC84: =IF(AK84<>"",MATCH(AK84,Sources[Citekey],0),"") | AD84: =IF(AM84<>"",MATCH(AM84,Sources[Citekey],0),"") | AE84: =IF(AO84<>"",MATCH(AO84,Sources[Citekey],0),"") | AG84: =IFERROR(IF(Sources[[#This Row],[Reference to]]<>"",LEFT(Sources[[#This Row],[Reference to]],FIND(",",Sources[[#This Row],[Reference to]])-1),""),Sources[[#This Row],[Reference to]]) | AH84: =IFERROR(RIGHT(Sources[[#This Row],[Reference to]],LEN(Sources[[#This Row],[Reference to]])-LEN($AG84)-2),"") | AI84: =IFERROR(LEFT(AH84,FIND(",",AH84)-1),AH84) | AJ84: =IFERROR(RIGHT(Sources[[#This Row],[Reference to]],LEN(Sources[[#This Row],[Reference to]])-LEN($AG84)-2-LEN($AI84)-2),"") | AK84: =IFERROR(LEFT(AJ84,FIND(",",AJ84)-1),AJ84) | AL84: =IFERROR(RIGHT(Sources[[#This Row],[Reference to]],LEN(Sources[[#This Row],[Reference to]])-LEN($AG84)-2-LEN($AI84)-2-LEN($AK84)-2),"") | AM84: =IFERROR(LEFT(AL84,FIND(",",AL84)-1),AL84) | AN84: =IFERROR(RIGHT(Sources[[#This Row],[Reference to]],LEN(Sources[[#This Row],[Reference to]])-LEN($AG84)-2-LEN($AI84)-2-LEN($AK84)-2-LEN($AM84)-2),"") | AO84: =IFERROR(LEFT(AN84,FIND(",",AN84)-1),AN84)
B85: Anonymous2015-1 | C85: =IFERROR(VALUE(MID(Sources[[#This Row],[Citekey]],FIND("20",Sources[[#This Row],[Citekey]]),4)),"") -> 2015 | D85: no | E85: Manufacturer Interview | F85: Original analysis, industry data | H85: =IFERROR(VLOOKUP(Sources[[#This Row],[Method]],dd_analysis_graph[],2,FALSE),"") -> Analysis and Graph | I85: =IFERROR(VLOOKUP(Sources[[#This Row],[Type of Publication]],dd_type_source[],2,FALSE),"") -> Manufacturer Interview | Z85: =IF(OR(Sources[[#This Row],[Analysis and Graph]]="Analysis and Graph",Sources[[#This Row],[Analysis and Graph]]="Not in analysis, but extra in graph"),MATCH(Sources[[#This Row],[Citekey]],Database!$B$4:$B$2385,0),"") -> 1826 | AA85: =IF(AG85<>"",MATCH(AG85,Sources[Citekey],0),"") | AB85: =IF(AI85<>"",MATCH(AI85,Sources[Citekey],0),"") | AC85: =IF(AK85<>"",MATCH(AK85,Sources[Citekey],0),"") | AD85: =IF(AM85<>"",MATCH(AM85,Sources[Citekey],0),"") | AE85: =IF(AO85<>"",MATCH(AO85,Sources[Citekey],0),"") | AG85: =IFERROR(IF(Sources[[#This Row],[Reference to]]<>"",LEFT(Sources[[#This Row],[Reference to]],FIND(",",Sources[[#This Row],[Reference to]])-1),""),Sources[[#This Row],[Reference to]]) | AH85: =IFERROR(RIGHT(Sources[[#This Row],[Reference to]],LEN(Sources[[#This Row],[Reference to]])-LEN($AG85)-2),"") | AI85: =IFERROR(LEFT(AH85,FIND(",",AH85)-1),AH85) | AJ85: =IFERROR(RIGHT(Sources[[#This Row],[Reference to]],LEN(Sources[[#This Row],[Reference to]])-LEN($AG85)-2-LEN($AI85)-2),"") | AK85: =IFERROR(LEFT(AJ85,FIND(",",AJ85)-1),AJ85) | AL85: =IFERROR(RIGHT(Sources[[#This Row],[Reference to]],LEN(Sources[[#This Row],[Reference to]])-LEN($AG85)-2-LEN($AI85)-2-LEN($AK85)-2),"") | AM85: =IFERROR(LEFT(AL85,FIND(",",AL85)-1),AL85) | AN85: =IFERROR(RIGHT(Sources[[#This Row],[Reference to]],LEN(Sources[[#This Row],[Reference to]])-LEN($AG85)-2-LEN($AI85)-2-LEN($AK85)-2-LEN($AM85)-2),"") | AO85: =IFERROR(LEFT(AN85,FIND(",",AN85)-1),AN85)
B86: Anonymous2015-10 | C86: =IFERROR(VALUE(MID(Sources[[#This Row],[Citekey]],FIND("20",Sources[[#This Row],[Citekey]]),4)),"") -> 2015 | D86: no | E86: Manufacturer Interview | F86: Original analysis, industry data | H86: =IFERROR(VLOOKUP(Sources[[#This Row],[Method]],dd_analysis_graph[],2,FALSE),"") -> Analysis and Graph | I86: =IFERROR(VLOOKUP(Sources[[#This Row],[Type of Publication]],dd_type_source[],2,FALSE),"") -> Manufacturer Interview | Z86: =IF(OR(Sources[[#This Row],[Analysis and Graph]]="Analysis and Graph",Sources[[#This Row],[Analysis and Graph]]="Not in analysis, but extra in graph"),MATCH(Sources[[#This Row],[Citekey]],Database!$B$4:$B$2385,0),"") -> 2066 | AA86: =IF(AG86<>"",MATCH(AG86,Sources[Citekey],0),"") | AB86: =IF(AI86<>"",MATCH(AI86,Sources[Citekey],0),"") | AC86: =IF(AK86<>"",MATCH(AK86,Sources[Citekey],0),"") | AD86: =IF(AM86<>"",MATCH(AM86,Sources[Citekey],0),"") | AE86: =IF(AO86<>"",MATCH(AO86,Sources[Citekey],0),"") | AG86: =IFERROR(IF(Sources[[#This Row],[Reference to]]<>"",LEFT(Sources[[#This Row],[Reference to]],FIND(",",Sources[[#This Row],[Reference to]])-1),""),Sources[[#This Row],[Reference to]]) | AH86: =IFERROR(RIGHT(Sources[[#This Row],[Reference to]],LEN(Sources[[#This Row],[Reference to]])-LEN($AG86)-2),"") | AI86: =IFERROR(LEFT(AH86,FIND(",",AH86)-1),AH86) | AJ86: =IFERROR(RIGHT(Sources[[#This Row],[Reference to]],LEN(Sources[[#This Row],[Reference to]])-LEN($AG86)-2-LEN($AI86)-2),"") | AK86: =IFERROR(LEFT(AJ86,FIND(",",AJ86)-1),AJ86) | AL86: =IFERROR(RIGHT(Sources[[#This Row],[Reference to]],LEN(Sources[[#This Row],[Reference to]])-LEN($AG86)-2-LEN($AI86)-2-LEN($AK86)-2),"") | AM86: =IFERROR(LEFT(AL86,FIND(",",AL86)-1),AL86) | AN86: =IFERROR(RIGHT(Sources[[#This Row],[Reference to]],LEN(Sources[[#This Row],[Reference to]])-LEN($AG86)-2-LEN($AI86)-2-LEN($AK86)-2-LEN($AM86)-2),"") | AO86: =IFERROR(LEFT(AN86,FIND(",",AN86)-1),AN86)
B87: Anonymous2015-2 | C87: =IFERROR(VALUE(MID(Sources[[#This Row],[Citekey]],FIND("20",Sources[[#This Row],[Citekey]]),4)),"") -> 2015 | D87: no | E87: Manufacturer Interview | F87: Original analysis, industry data | H87: =IFERROR(VLOOKUP(Sources[[#This Row],[Method]],dd_analysis_graph[],2,FALSE),"") -> Analysis and Graph | I87: =IFERROR(VLOOKUP(Sources[[#This Row],[Type of Publication]],dd_type_source[],2,FALSE),"") -> Manufacturer Interview | Z87: =IF(OR(Sources[[#This Row],[Analysis and Graph]]="Analysis and Graph",Sources[[#This Row],[Analysis and Graph]]="Not in analysis, but extra in graph"),MATCH(Sources[[#This Row],[Citekey]],Database!$B$4:$B$2385,0),"") -> 1850 | AA87: =IF(AG87<>"",MATCH(AG87,Sources[Citekey],0),"") | AB87: =IF(AI87<>"",MATCH(AI87,Sources[Citekey],0),"") | AC87: =IF(AK87<>"",MATCH(AK87,Sources[Citekey],0),"") | AD87: =IF(AM87<>"",MATCH(AM87,Sources[Citekey],0),"") | AE87: =IF(AO87<>"",MATCH(AO87,Sources[Citekey],0),"") | AG87: =IFERROR(IF(Sources[[#This Row],[Reference to]]<>"",LEFT(Sources[[#This Row],[Reference to]],FIND(",",Sources[[#This Row],[Reference to]])-1),""),Sources[[#This Row],[Reference to]]) | AH87: =IFERROR(RIGHT(Sources[[#This Row],[Reference to]],LEN(Sources[[#This Row],[Reference to]])-LEN($AG87)-2),"") | AI87: =IFERROR(LEFT(AH87,FIND(",",AH87)-1),AH87) | AJ87: =IFERROR(RIGHT(Sources[[#This Row],[Reference to]],LEN(Sources[[#This Row],[Reference to]])-LEN($AG87)-2-LEN($AI87)-2),"") | AK87: =IFERROR(LEFT(AJ87,FIND(",",AJ87)-1),AJ87) | AL87: =IFERROR(RIGHT(Sources[[#This Row],[Reference to]],LEN(Sources[[#This Row],[Reference to]])-LEN($AG87)-2-LEN($AI87)-2-LEN($AK87)-2),"") | AM87: =IFERROR(LEFT(AL87,FIND(",",AL87)-1),AL87) | AN87: =IFERROR(RIGHT(Sources[[#This Row],[Reference to]],LEN(Sources[[#This Row],[Reference to]])-LEN($AG87)-2-LEN($AI87)-2-LEN($AK87)-2-LEN($AM87)-2),"") | AO87: =IFERROR(LEFT(AN87,FIND(",",AN87)-1),AN87)
B88: Anonymous2015-3 | C88: =IFERROR(VALUE(MID(Sources[[#This Row],[Citekey]],FIND("20",Sources[[#This Row],[Citekey]]),4)),"") -> 2015 | D88: no | E88: Manufacturer Interview | F88: Original analysis, industry data | H88: =IFERROR(VLOOKUP(Sources[[#This Row],[Method]],dd_analysis_graph[],2,FALSE),"") -> Analysis and Graph | I88: =IFERROR(VLOOKUP(Sources[[#This Row],[Type of Publication]],dd_type_source[],2,FALSE),"") -> Manufacturer Interview | Z88: =IF(OR(Sources[[#This Row],[Analysis and Graph]]="Analysis and Graph",Sources[[#This Row],[Analysis and Graph]]="Not in analysis, but extra in graph"),MATCH(Sources[[#This Row],[Citekey]],Database!$B$4:$B$2385,0),"") -> 1874 | AA88: =IF(AG88<>"",MATCH(AG88,Sources[Citekey],0),"") | AB88: =IF(AI88<>"",MATCH(AI88,Sources[Citekey],0),"") | AC88: =IF(AK88<>"",MATCH(AK88,Sources[Citekey],0),"") | AD88: =IF(AM88<>"",MATCH(AM88,Sources[Citekey],0),"") | AE88: =IF(AO88<>"",MATCH(AO88,Sources[Citekey],0),"") | AG88: =IFERROR(IF(Sources[[#This Row],[Reference to]]<>"",LEFT(Sources[[#This Row],[Reference to]],FIND(",",Sources[[#This Row],[Reference to]])-1),""),Sources[[#This Row],[Reference to]]) | AH88: =IFERROR(RIGHT(Sources[[#This Row],[Reference to]],LEN(Sources[[#This Row],[Reference to]])-LEN($AG88)-2),"") | AI88: =IFERROR(LEFT(AH88,FIND(",",AH88)-1),AH88) | AJ88: =IFERROR(RIGHT(Sources[[#This Row],[Reference to]],LEN(Sources[[#This Row],[Reference to]])-LEN($AG88)-2-LEN($AI88)-2),"") | AK88: =IFERROR(LEFT(AJ88,FIND(",",AJ88)-1),AJ88) | AL88: =IFERROR(RIGHT(Sources[[#This Row],[Reference to]],LEN(Sources[[#This Row],[Reference to]])-LEN($AG88)-2-LEN($AI88)-2-LEN($AK88)-2),"") | AM88: =IFERROR(LEFT(AL88,FIND(",",AL88)-1),AL88) | AN88: =IFERROR(RIGHT(Sources[[#This Row],[Reference to]],LEN(Sources[[#This Row],[Reference to]])-LEN($AG88)-2-LEN($AI88)-2-LEN($AK88)-2-LEN($AM88)-2),"") | AO88: =IFERROR(LEFT(AN88,FIND(",",AN88)-1),AN88)
B89: Anonymous2015-4 | C89: =IFERROR(VALUE(MID(Sources[[#This Row],[Citekey]],FIND("20",Sources[[#This Row],[Citekey]]),4)),"") -> 2015 | D89: no | E89: Manufacturer Interview | F89: Original analysis, industry data | H89: =IFERROR(VLOOKUP(Sources[[#This Row],[Method]],dd_analysis_graph[],2,FALSE),"") -> Analysis and Graph | I89: =IFERROR(VLOOKUP(Sources[[#This Row],[Type of Publication]],dd_type_source[],2,FALSE),"") -> Manufacturer Interview | Z89: =IF(OR(Sources[[#This Row],[Analysis and Graph]]="Analysis and Graph",Sources[[#This Row],[Analysis and Graph]]="Not in analysis, but extra in graph"),MATCH(Sources[[#This Row],[Citekey]],Database!$B$4:$B$2385,0),"") -> 1922 | AA89: =IF(AG89<>"",MATCH(AG89,Sources[Citekey],0),"") | AB89: =IF(AI89<>"",MATCH(AI89,Sources[Citekey],0),"") | AC89: =IF(AK89<>"",MATCH(AK89,Sources[Citekey],0),"") | AD89: =IF(AM89<>"",MATCH(AM89,Sources[Citekey],0),"") | AE89: =IF(AO89<>"",MATCH(AO89,Sources[Citekey],0),"") | AG89: =IFERROR(IF(Sources[[#This Row],[Reference to]]<>"",LEFT(Sources[[#This Row],[Reference to]],FIND(",",Sources[[#This Row],[Reference to]])-1),""),Sources[[#This Row],[Reference to]]) | AH89: =IFERROR(RIGHT(Sources[[#This Row],[Reference to]],LEN(Sources[[#This Row],[Reference to]])-LEN($AG89)-2),"") | AI89: =IFERROR(LEFT(AH89,FIND(",",AH89)-1),AH89) | AJ89: =IFERROR(RIGHT(Sources[[#This Row],[Reference to]],LEN(Sources[[#This Row],[Reference to]])-LEN($AG89)-2-LEN($AI89)-2),"") | AK89: =IFERROR(LEFT(AJ89,FIND(",",AJ89)-1),AJ89) | AL89: =IFERROR(RIGHT(Sources[[#This Row],[Reference to]],LEN(Sources[[#This Row],[Reference to]])-LEN($AG89)-2-LEN($AI89)-2-LEN($AK89)-2),"") | AM89: =IFERROR(LEFT(AL89,FIND(",",AL89)-1),AL89) | AN89: =IFERROR(RIGHT(Sources[[#This Row],[Reference to]],LEN(Sources[[#This Row],[Reference to]])-LEN($AG89)-2-LEN($AI89)-2-LEN($AK89)-2-LEN($AM89)-2),"") | AO89: =IFERROR(LEFT(AN89,FIND(",",AN89)-1),AN89)
B90: Anonymous2015-5 | C90: =IFERROR(VALUE(MID(Sources[[#This Row],[Citekey]],FIND("20",Sources[[#This Row],[Citekey]]),4)),"") -> 2015 | D90: no | E90: Manufacturer Interview | F90: Original analysis, industry data | H90: =IFERROR(VLOOKUP(Sources[[#This Row],[Method]],dd_analysis_graph[],2,FALSE),"") -> Analysis and Graph | I90: =IFERROR(VLOOKUP(Sources[[#This Row],[Type of Publication]],dd_type_source[],2,FALSE),"") -> Manufacturer Interview | Z90: =IF(OR(Sources[[#This Row],[Analysis and Graph]]="Analysis and Graph",Sources[[#This Row],[Analysis and Graph]]="Not in analysis, but extra in graph"),MATCH(Sources[[#This Row],[Citekey]],Database!$B$4:$B$2385,0),"") -> 1946 | AA90: =IF(AG90<>"",MATCH(AG90,Sources[Citekey],0),"") | AB90: =IF(AI90<>"",MATCH(AI90,Sources[Citekey],0),"") | AC90: =IF(AK90<>"",MATCH(AK90,Sources[Citekey],0),"") | AD90: =IF(AM90<>"",MATCH(AM90,Sources[Citekey],0),"") | AE90: =IF(AO90<>"",MATCH(AO90,Sources[Citekey],0),"") | AG90: =IFERROR(IF(Sources[[#This Row],[Reference to]]<>"",LEFT(Sources[[#This Row],[Reference to]],FIND(",",Sources[[#This Row],[Reference to]])-1),""),Sources[[#This Row],[Reference to]]) | AH90: =IFERROR(RIGHT(Sources[[#This Row],[Reference to]],LEN(Sources[[#This Row],[Reference to]])-LEN($AG90)-2),"") | AI90: =IFERROR(LEFT(AH90,FIND(",",AH90)-1),AH90) | AJ90: =IFERROR(RIGHT(Sources[[#This Row],[Reference to]],LEN(Sources[[#This Row],[Reference to]])-LEN($AG90)-2-LEN($AI90)-2),"") | AK90: =IFERROR(LEFT(AJ90,FIND(",",AJ90)-1),AJ90) | AL90: =IFERROR(RIGHT(Sources[[#This Row],[Reference to]],LEN(Sources[[#This Row],[Reference to]])-LEN($AG90)-2-LEN($AI90)-2-LEN($AK90)-2),"") | AM90: =IFERROR(LEFT(AL90,FIND(",",AL90)-1),AL90) | AN90: =IFERROR(RIGHT(Sources[[#This Row],[Reference to]],LEN(Sources[[#This Row],[Reference to]])-LEN($AG90)-2-LEN($AI90)-2-LEN($AK90)-2-LEN($AM90)-2),"") | AO90: =IFERROR(LEFT(AN90,FIND(",",AN90)-1),AN90)
B91: Anonymous2015-6 | C91: =IFERROR(VALUE(MID(Sources[[#This Row],[Citekey]],FIND("20",Sources[[#This Row],[Citekey]]),4)),"") -> 2015 | D91: no | E91: Manufacturer Interview | F91: Original analysis, industry data | H91: =IFERROR(VLOOKUP(Sources[[#This Row],[Method]],dd_analysis_graph[],2,FALSE),"") -> Analysis and Graph | I91: =IFERROR(VLOOKUP(Sources[[#This Row],[Type of Publication]],dd_type_source[],2,FALSE),"") -> Manufacturer Interview | Z91: =IF(OR(Sources[[#This Row],[Analysis and Graph]]="Analysis and Graph",Sources[[#This Row],[Analysis and Graph]]="Not in analysis, but extra in graph"),MATCH(Sources[[#This Row],[Citekey]],Database!$B$4:$B$2385,0),"") -> 1970 | AA91: =IF(AG91<>"",MATCH(AG91,Sources[Citekey],0),"") | AB91: =IF(AI91<>"",MATCH(AI91,Sources[Citekey],0),"") | AC91: =IF(AK91<>"",MATCH(AK91,Sources[Citekey],0),"") | AD91: =IF(AM91<>"",MATCH(AM91,Sources[Citekey],0),"") | AE91: =IF(AO91<>"",MATCH(AO91,Sources[Citekey],0),"") | AG91: =IFERROR(IF(Sources[[#This Row],[Reference to]]<>"",LEFT(Sources[[#This Row],[Reference to]],FIND(",",Sources[[#This Row],[Reference to]])-1),""),Sources[[#This Row],[Reference to]]) | AH91: =IFERROR(RIGHT(Sources[[#This Row],[Reference to]],LEN(Sources[[#This Row],[Reference to]])-LEN($AG91)-2),"") | AI91: =IFERROR(LEFT(AH91,FIND(",",AH91)-1),AH91) | AJ91: =IFERROR(RIGHT(Sources[[#This Row],[Reference to]],LEN(Sources[[#This Row],[Reference to]])-LEN($AG91)-2-LEN($AI91)-2),"") | AK91: =IFERROR(LEFT(AJ91,FIND(",",AJ91)-1),AJ91) | AL91: =IFERROR(RIGHT(Sources[[#This Row],[Reference to]],LEN(Sources[[#This Row],[Reference to]])-LEN($AG91)-2-LEN($AI91)-2-LEN($AK91)-2),"") | AM91: =IFERROR(LEFT(AL91,FIND(",",AL91)-1),AL91) | AN91: =IFERROR(RIGHT(Sources[[#This Row],[Reference to]],LEN(Sources[[#This Row],[Reference to]])-LEN($AG91)-2-LEN($AI91)-2-LEN($AK91)-2-LEN($AM91)-2),"") | AO91: =IFERROR(LEFT(AN91,FIND(",",AN91)-1),AN91)
B92: Anonymous2015-7 | C92: =IFERROR(VALUE(MID(Sources[[#This Row],[Citekey]],FIND("20",Sources[[#This Row],[Citekey]]),4)),"") -> 2015 | D92: no | E92: Manufacturer Interview | F92: Original analysis, industry data | H92: =IFERROR(VLOOKUP(Sources[[#This Row],[Method]],dd_analysis_graph[],2,FALSE),"") -> Analysis and Graph | I92: =IFERROR(VLOOKUP(Sources[[#This Row],[Type of Publication]],dd_type_source[],2,FALSE),"") -> Manufacturer Interview | Z92: =IF(OR(Sources[[#This Row],[Analysis and Graph]]="Analysis and Graph",Sources[[#This Row],[Analysis and Graph]]="Not in analysis, but extra in graph"),MATCH(Sources[[#This Row],[Citekey]],Database!$B$4:$B$2385,0),"") -> 1994 | AA92: =IF(AG92<>"",MATCH(AG92,Sources[Citekey],0),"") | AB92: =IF(AI92<>"",MATCH(AI92,Sources[Citekey],0),"") | AC92: =IF(AK92<>"",MATCH(AK92,Sources[Citekey],0),"") | AD92: =IF(AM92<>"",MATCH(AM92,Sources[Citekey],0),"") | AE92: =IF(AO92<>"",MATCH(AO92,Sources[Citekey],0),"") | AG92: =IFERROR(IF(Sources[[#This Row],[Reference to]]<>"",LEFT(Sources[[#This Row],[Reference to]],FIND(",",Sources[[#This Row],[Reference to]])-1),""),Sources[[#This Row],[Reference to]]) | AH92: =IFERROR(RIGHT(Sources[[#This Row],[Reference to]],LEN(Sources[[#This Row],[Reference to]])-LEN($AG92)-2),"") | AI92: =IFERROR(LEFT(AH92,FIND(",",AH92)-1),AH92) | AJ92: =IFERROR(RIGHT(Sources[[#This Row],[Reference to]],LEN(Sources[[#This Row],[Reference to]])-LEN($AG92)-2-LEN($AI92)-2),"") | AK92: =IFERROR(LEFT(AJ92,FIND(",",AJ92)-1),AJ92) | AL92: =IFERROR(RIGHT(Sources[[#This Row],[Reference to]],LEN(Sources[[#This Row],[Reference to]])-LEN($AG92)-2-LEN($AI92)-2-LEN($AK92)-2),"") | AM92: =IFERROR(LEFT(AL92,FIND(",",AL92)-1),AL92) | AN92: =IFERROR(RIGHT(Sources[[#This Row],[Reference to]],LEN(Sources[[#This Row],[Reference to]])-LEN($AG92)-2-LEN($AI92)-2-LEN($AK92)-2-LEN($AM92)-2),"") | AO92: =IFERROR(LEFT(AN92,FIND(",",AN92)-1),AN92)
B93: Anonymous2015-8 | C93: =IFERROR(VALUE(MID(Sources[[#This Row],[Citekey]],FIND("20",Sources[[#This Row],[Citekey]]),4)),"") -> 2015 | D93: no | E93: Manufacturer Interview | F93: Original analysis, industry data | H93: =IFERROR(VLOOKUP(Sources[[#This Row],[Method]],dd_analysis_graph[],2,FALSE),"") -> Analysis and Graph | I93: =IFERROR(VLOOKUP(Sources[[#This Row],[Type of Publication]],dd_type_source[],2,FALSE),"") -> Manufacturer Interview | Z93: =IF(OR(Sources[[#This Row],[Analysis and Graph]]="Analysis and Graph",Sources[[#This Row],[Analysis and Graph]]="Not in analysis, but extra in graph"),MATCH(Sources[[#This Row],[Citekey]],Database!$B$4:$B$2385,0),"") -> 2018 | AA93: =IF(AG93<>"",MATCH(AG93,Sources[Citekey],0),"") | AB93: =IF(AI93<>"",MATCH(AI93,Sources[Citekey],0),"") | AC93: =IF(AK93<>"",MATCH(AK93,Sources[Citekey],0),"") | AD93: =IF(AM93<>"",MATCH(AM93,Sources[Citekey],0),"") | AE93: =IF(AO93<>"",MATCH(AO93,Sources[Citekey],0),"") | AG93: =IFERROR(IF(Sources[[#This Row],[Reference to]]<>"",LEFT(Sources[[#This Row],[Reference to]],FIND(",",Sources[[#This Row],[Reference to]])-1),""),Sources[[#This Row],[Reference to]]) | AH93: =IFERROR(RIGHT(Sources[[#This Row],[Reference to]],LEN(Sources[[#This Row],[Reference to]])-LEN($AG93)-2),"") | AI93: =IFERROR(LEFT(AH93,FIND(",",AH93)-1),AH93) | AJ93: =IFERROR(RIGHT(Sources[[#This Row],[Reference to]],LEN(Sources[[#This Row],[Reference to]])-LEN($AG93)-2-LEN($AI93)-2),"") | AK93: =IFERROR(LEFT(AJ93,FIND(",",AJ93)-1),AJ93) | AL93: =IFERROR(RIGHT(Sources[[#This Row],[Reference to]],LEN(Sources[[#This Row],[Reference to]])-LEN($AG93)-2-LEN($AI93)-2-LEN($AK93)-2),"") | AM93: =IFERROR(LEFT(AL93,FIND(",",AL93)-1),AL93) | AN93: =IFERROR(RIGHT(Sources[[#This Row],[Reference to]],LEN(Sources[[#This Row],[Reference to]])-LEN($AG93)-2-LEN($AI93)-2-LEN($AK93)-2-LEN($AM93)-2),"") | AO93: =IFERROR(LEFT(AN93,FIND(",",AN93)-1),AN93)
... B101: wind-wasserstoff2016 | C101: =IFERROR(VALUE(MID(Sources[[#This Row],[Citekey]],FIND("20",Sources[[#This Row],[Citekey]]),4)),"") -> 2016 | D101: no | E101: Manufacturer Interview | F101: Original analysis, industry data | H101: =IFERROR(VLOOKUP(Sources[[#This Row],[Method]],dd_analysis_graph[],2,FALSE),"") -> Analysis and Graph | I101: =IFERROR(VLOOKUP(Sources[[#This Row],[Type of Publication]],dd_type_source[],2,FALSE),"") -> Manufacturer Interview | Z101: =IF(OR(Sources[[#This Row],[Analysis and Graph]]="Analysis and Graph",Sources[[#This Row],[Analysis and Graph]]="Not in analysis, but extra in graph"),MATCH(Sources[[#This Row],[Citekey]],Database!$B$4:$B$2385,0),"") -> 1777 | AA101: =IF(AG101<>"",MATCH(AG101,Sources[Citekey],0),"") | AB101: =IF(AI101<>"",MATCH(AI101,Sources[Citekey],0),"") | AC101: =IF(AK101<>"",MATCH(AK101,Sources[Citekey],0),"") | AD101: =IF(AM101<>"",MATCH(AM101,Sources[Citekey],0),"") | AE101: =IF(AO101<>"",MATCH(AO101,Sources[Citekey],0),"") | AG101: =IFERROR(IF(Sources[[#This Row],[Reference to]]<>"",LEFT(Sources[[#This Row],[Reference to]],FIND(",",Sources[[#This Row],[Reference to]])-1),""),Sources[[#This Row],[Reference to]]) | AH101: =IFERROR(RIGHT(Sources[[#This Row],[Reference to]],LEN(Sources[[#This Row],[Reference to]])-LEN($AG101)-2),"") | AI101: =IFERROR(LEFT(AH101,FIND(",",AH101)-1),AH101) | AJ101: =IFERROR(RIGHT(Sources[[#This Row],[Reference to]],LEN(Sources[[#This Row],[Reference to]])-LEN($AG101)-2-LEN($AI101)-2),"") | AK101: =IFERROR(LEFT(AJ101,FIND(",",AJ101)-1),AJ101) | AL101: =IFERROR(RIGHT(Sources[[#This Row],[Reference to]],LEN(Sources[[#This Row],[Reference to]])-LEN($AG101)-2-LEN($AI101)-2-LEN($AK101)-2),"") | AM101: =IFERROR(LEFT(AL101,FIND(",",AL101)-1),AL101) | AN101: =IFERROR(RIGHT(Sources[[#This Row],[Reference to]],LEN(Sources[[#This Row],[Reference to]])-LEN($AG101)-2-LEN($AI101)-2-LEN($AK101)-2-LEN($AM101)-2),"") | AO101: =IFERROR(LEFT(AN101,FIND(",",AN101)-1),AN101)
B102: flint1999flint | C102: 1999 | D102: yes | E102: News Article | F102: No cost data | H102: =IFERROR(VLOOKUP(Sources[[#This Row],[Method]],dd_analysis_graph[],2,FALSE),"") -> Not in analysis, not in graph | I102: =IFERROR(VLOOKUP(Sources[[#This Row],[Type of Publication]],dd_type_source[],2,FALSE),"") -> Publication | J102: Excluded due to age | Z102: =IF(OR(Sources[[#This Row],[Analysis and Graph]]="Analysis and Graph",Sources[[#This Row],[Analysis and Graph]]="Not in analysis, but extra in graph"),MATCH(Sources[[#This Row],[Citekey]],Database!$B$4:$B$2385,0),"") | AA102: =IF(AG102<>"",MATCH(AG102,Sources[Citekey],0),"") | AB102: =IF(AI102<>"",MATCH(AI102,Sources[Citekey],0),"") | AC102: =IF(AK102<>"",MATCH(AK102,Sources[Citekey],0),"") | AD102: =IF(AM102<>"",MATCH(AM102,Sources[Citekey],0),"") | AE102: =IF(AO102<>"",MATCH(AO102,Sources[Citekey],0),"") | AG102: =IFERROR(IF(Sources[[#This Row],[Reference to]]<>"",LEFT(Sources[[#This Row],[Reference to]],FIND(",",Sources[[#This Row],[Reference to]])-1),""),Sources[[#This Row],[Reference to]]) | AH102: =IFERROR(RIGHT(Sources[[#This Row],[Reference to]],LEN(Sources[[#This Row],[Reference to]])-LEN($AG102)-2),"") | AI102: =IFERROR(LEFT(AH102,FIND(",",AH102)-1),AH102) | AJ102: =IFERROR(RIGHT(Sources[[#This Row],[Reference to]],LEN(Sources[[#This Row],[Reference to]])-LEN($AG102)-2-LEN($AI102)-2),"") | AK102: =IFERROR(LEFT(AJ102,FIND(",",AJ102)-1),AJ102) | AL102: =IFERROR(RIGHT(Sources[[#This Row],[Reference to]],LEN(Sources[[#This Row],[Reference to]])-LEN($AG102)-2-LEN($AI102)-2-LEN($AK102)-2),"") | AM102: =IFERROR(LEFT(AL102,FIND(",",AL102)-1),AL102) | AN102: =IFERROR(RIGHT(Sources[[#This Row],[Reference to]],LEN(Sources[[#This Row],[Reference to]])-LEN($AG102)-2-LEN($AI102)-2-LEN($AK102)-2-LEN($AM102)-2),"") | AO102: =IFERROR(LEFT(AN102,FIND(",",AN102)-1),AN102)
B103: aicher2014arbeitspaket | C103: =IFERROR(VALUE(MID(Sources[[#This Row],[Citekey]],FIND("20",Sources[[#This Row],[Citekey]]),4)),"") -> 2014 | D103: yes | E103: Report | F103: Original analysis, industry data | H103: =IFERROR(VLOOKUP(Sources[[#This Row],[Method]],dd_analysis_graph[],2,FALSE),"") -> Analysis and Graph | I103: =IFERROR(VLOOKUP(Sources[[#This Row],[Type of Publication]],dd_type_source[],2,FALSE),"") -> Publication | Z103: =IF(OR(Sources[[#This Row],[Analysis and Graph]]="Analysis and Graph",Sources[[#This Row],[Analysis and Graph]]="Not in analysis, but extra in graph"),MATCH(Sources[[#This Row],[Citekey]],Database!$B$4:$B$2385,0),"") -> 265 | AA103: =IF(AG103<>"",MATCH(AG103,Sources[Citekey],0),"") | AB103: =IF(AI103<>"",MATCH(AI103,Sources[Citekey],0),"") | AC103: =IF(AK103<>"",MATCH(AK103,Sources[Citekey],0),"") | AD103: =IF(AM103<>"",MATCH(AM103,Sources[Citekey],0),"") | AE103: =IF(AO103<>"",MATCH(AO103,Sources[Citekey],0),"") | AG103: =IFERROR(IF(Sources[[#This Row],[Reference to]]<>"",LEFT(Sources[[#This Row],[Reference to]],FIND(",",Sources[[#This Row],[Reference to]])-1),""),Sources[[#This Row],[Reference to]]) | AH103: =IFERROR(RIGHT(Sources[[#This Row],[Reference to]],LEN(Sources[[#This Row],[Reference to]])-LEN($AG103)-2),"") | AI103: =IFERROR(LEFT(AH103,FIND(",",AH103)-1),AH103) | AJ103: =IFERROR(RIGHT(Sources[[#This Row],[Reference to]],LEN(Sources[[#This Row],[Reference to]])-LEN($AG103)-2-LEN($AI103)-2),"") | AK103: =IFERROR(LEFT(AJ103,FIND(",",AJ103)-1),AJ103) | AL103: =IFERROR(RIGHT(Sources[[#This Row],[Reference to]],LEN(Sources[[#This Row],[Reference to]])-LEN($AG103)-2-LEN($AI103)-2-LEN($AK103)-2),"") | AM103: =IFERROR(LEFT(AL103,FIND(",",AL103)-1),AL103) | AN103: =IFERROR(RIGHT(Sources[[#This Row],[Reference to]],LEN(Sources[[#This Row],[Reference to]])-LEN($AG103)-2-LEN($AI103)-2-LEN($AK103)-2-LEN($AM103)-2),"") | AO103: =IFERROR(LEFT(AN103,FIND(",",AN103)-1),AN103)
B104: ainscough2014hydrogen | C104: =IFERROR(VALUE(MID(Sources[[#This Row],[Citekey]],FIND("20",Sources[[#This Row],[Citekey]]),4)),"") -> 2014 | D104: yes | E104: Report | F104: Original analysis, industry data | H104: =IFERROR(VLOOKUP(Sources[[#This Row],[Method]],dd_analysis_graph[],2,FALSE),"") -> Analysis and Graph | I104: =IFERROR(VLOOKUP(Sources[[#This Row],[Type of Publication]],dd_type_source[],2,FALSE),"") -> Publication | Z104: =IF(OR(Sources[[#This Row],[Analysis and Graph]]="Analysis and Graph",Sources[[#This Row],[Analysis and Graph]]="Not in analysis, but extra in graph"),MATCH(Sources[[#This Row],[Citekey]],Database!$B$4:$B$2385,0),"") -> 1489 | AA104: =IF(AG104<>"",MATCH(AG104,Sources[Citekey],0),"") | AB104: =IF(AI104<>"",MATCH(AI104,Sources[Citekey],0),"") | AC104: =IF(AK104<>"",MATCH(AK104,Sources[Citekey],0),"") | AD104: =IF(AM104<>"",MATCH(AM104,Sources[Citekey],0),"") | AE104: =IF(AO104<>"",MATCH(AO104,Sources[Citekey],0),"") | AG104: =IFERROR(IF(Sources[[#This Row],[Reference to]]<>"",LEFT(Sources[[#This Row],[Reference to]],FIND(",",Sources[[#This Row],[Reference to]])-1),""),Sources[[#This Row],[Reference to]]) | AH104: =IFERROR(RIGHT(Sources[[#This Row],[Reference to]],LEN(Sources[[#This Row],[Reference to]])-LEN($AG104)-2),"") | AI104: =IFERROR(LEFT(AH104,FIND(",",AH104)-1),AH104) | AJ104: =IFERROR(RIGHT(Sources[[#This Row],[Reference to]],LEN(Sources[[#This Row],[Reference to]])-LEN($AG104)-2-LEN($AI104)-2),"") | AK104: =IFERROR(LEFT(AJ104,FIND(",",AJ104)-1),AJ104) | AL104: =IFERROR(RIGHT(Sources[[#This Row],[Reference to]],LEN(Sources[[#This Row],[Reference to]])-LEN($AG104)-2-LEN($AI104)-2-LEN($AK104)-2),"") | AM104: =IFERROR(LEFT(AL104,FIND(",",AL104)-1),AL104) | AN104: =IFERROR(RIGHT(Sources[[#This Row],[Reference to]],LEN(Sources[[#This Row],[Reference to]])-LEN($AG104)-2-LEN($AI104)-2-LEN($AK104)-2-LEN($AM104)-2),"") | AO104: =IFERROR(LEFT(AN104,FIND(",",AN104)-1),AN104)
B105: akhil2013DOE | C105: =IFERROR(VALUE(MID(Sources[[#This Row],[Citekey]],FIND("20",Sources[[#This Row],[Citekey]]),4)),"") -> 2013 | D105: yes | E105: Report | F105: No cost data | H105: =IFERROR(VLOOKUP(Sources[[#This Row],[Method]],dd_analysis_graph[],2,FALSE),"") -> Not in analysis, not in graph | I105: =IFERROR(VLOOKUP(Sources[[#This Row],[Type of Publication]],dd_type_source[],2,FALSE),"") -> Publication | Z105: =IF(OR(Sources[[#This Row],[Analysis and Graph]]="Analysis and Graph",Sources[[#This Row],[Analysis and Graph]]="Not in analysis, but extra in graph"),MATCH(Sources[[#This Row],[Citekey]],Database!$B$4:$B$2385,0),"") | AA105: =IF(AG105<>"",MATCH(AG105,Sources[Citekey],0),"") | AB105: =IF(AI105<>"",MATCH(AI105,Sources[Citekey],0),"") | AC105: =IF(AK105<>"",MATCH(AK105,Sources[Citekey],0),"") | AD105: =IF(AM105<>"",MATCH(AM105,Sources[Citekey],0),"") | AE105: =IF(AO105<>"",MATCH(AO105,Sources[Citekey],0),"") | AG105: =IFERROR(IF(Sources[[#This Row],[Reference to]]<>"",LEFT(Sources[[#This Row],[Reference to]],FIND(",",Sources[[#This Row],[Reference to]])-1),""),Sources[[#This Row],[Reference to]]) | AH105: =IFERROR(RIGHT(Sources[[#This Row],[Reference to]],LEN(Sources[[#This Row],[Reference to]])-LEN($AG105)-2),"") | AI105: =IFERROR(LEFT(AH105,FIND(",",AH105)-1),AH105) | AJ105: =IFERROR(RIGHT(Sources[[#This Row],[Reference to]],LEN(Sources[[#This Row],[Reference to]])-LEN($AG105)-2-LEN($AI105)-2),"") | AK105: =IFERROR(LEFT(AJ105,FIND(",",AJ105)-1),AJ105) | AL105: =IFERROR(RIGHT(Sources[[#This Row],[Reference to]],LEN(Sources[[#This Row],[Reference to]])-LEN($AG105)-2-LEN($AI105)-2-LEN($AK105)-2),"") | AM105: =IFERROR(LEFT(AL105,FIND(",",AL105)-1),AL105) | AN105: =IFERROR(RIGHT(Sources[[#This Row],[Reference to]],LEN(Sources[[#This Row],[Reference to]])-LEN($AG105)-2-LEN($AI105)-2-LEN($AK105)-2-LEN($AM105)-2),"") | AO105: =IFERROR(LEFT(AN105,FIND(",",AN105)-1),AN105)
B106: albrecht2013analyse | C106: =IFERROR(VALUE(MID(Sources[[#This Row],[Citekey]],FIND("20",Sources[[#This Row],[Citekey]]),4)),"") -> 2013 | D106: yes | E106: Report | F106: Original review multiple sources | H106: =IFERROR(VLOOKUP(Sources[[#This Row],[Method]],dd_analysis_graph[],2,FALSE),"") -> Analysis and Graph | I106: =IFERROR(VLOOKUP(Sources[[#This Row],[Type of Publication]],dd_type_source[],2,FALSE),"") -> Publication | Z106: =IF(OR(Sources[[#This Row],[Analysis and Graph]]="Analysis and Graph",Sources[[#This Row],[Analysis and Graph]]="Not in analysis, but extra in graph"),MATCH(Sources[[#This Row],[Citekey]],Database!$B$4:$B$2385,0),"") -> 1537 | AA106: =IF(AG106<>"",MATCH(AG106,Sources[Citekey],0),"") | AB106: =IF(AI106<>"",MATCH(AI106,Sources[Citekey],0),"") | AC106: =IF(AK106<>"",MATCH(AK106,Sources[Citekey],0),"") | AD106: =IF(AM106<>"",MATCH(AM106,Sources[Citekey],0),"") | AE106: =IF(AO106<>"",MATCH(AO106,Sources[Citekey],0),"") | AG106: =IFERROR(IF(Sources[[#This Row],[Reference to]]<>"",LEFT(Sources[[#This Row],[Reference to]],FIND(",",Sources[[#This Row],[Reference to]])-1),""),Sources[[#This Row],[Reference to]]) | AH106: =IFERROR(RIGHT(Sources[[#This Row],[Reference to]],LEN(Sources[[#This Row],[Reference to]])-LEN($AG106)-2),"") | AI106: =IFERROR(LEFT(AH106,FIND(",",AH106)-1),AH106) | AJ106: =IFERROR(RIGHT(Sources[[#This Row],[Reference to]],LEN(Sources[[#This Row],[Reference to]])-LEN($AG106)-2-LEN($AI106)-2),"") | AK106: =IFERROR(LEFT(AJ106,FIND(",",AJ106)-1),AJ106) | AL106: =IFERROR(RIGHT(Sources[[#This Row],[Reference to]],LEN(Sources[[#This Row],[Reference to]])-LEN($AG106)-2-LEN($AI106)-2-LEN($AK106)-2),"") | AM106: =IFERROR(LEFT(AL106,FIND(",",AL106)-1),AL106) | AN106: =IFERROR(RIGHT(Sources[[#This Row],[Reference to]],LEN(Sources[[#This Row],[Reference to]])-LEN($AG106)-2-LEN($AI106)-2-LEN($AK106)-2-LEN($AM106)-2),"") | AO106: =IFERROR(LEFT(AN106,FIND(",",AN106)-1),AN106)
B107: benjaminsson2013power | C107: =IFERROR(VALUE(MID(Sources[[#This Row],[Citekey]],FIND("20",Sources[[#This Row],[Citekey]]),4)),"") -> 2013 | D107: yes | E107: Report | F107: No cost data | H107: =IFERROR(VLOOKUP(Sources[[#This Row],[Method]],dd_analysis_graph[],2,FALSE),"") -> Not in analysis, not in graph | I107: =IFERROR(VLOOKUP(Sources[[#This Row],[Type of Publication]],dd_type_source[],2,FALSE),"") -> Publication | Z107: =IF(OR(Sources[[#This Row],[Analysis and Graph]]="Analysis and Graph",Sources[[#This Row],[Analysis and Graph]]="Not in analysis, but extra in graph"),MATCH(Sources[[#This Row],[Citekey]],Database!$B$4:$B$2385,0),"") | AA107: =IF(AG107<>"",MATCH(AG107,Sources[Citekey],0),"") | AB107: =IF(AI107<>"",MATCH(AI107,Sources[Citekey],0),"") | AC107: =IF(AK107<>"",MATCH(AK107,Sources[Citekey],0),"") | AD107: =IF(AM107<>"",MATCH(AM107,Sources[Citekey],0),"") | AE107: =IF(AO107<>"",MATCH(AO107,Sources[Citekey],0),"") | AG107: =IFERROR(IF(Sources[[#This Row],[Reference to]]<>"",LEFT(Sources[[#This Row],[Reference to]],FIND(",",Sources[[#This Row],[Reference to]])-1),""),Sources[[#This Row],[Reference to]]) | AH107: =IFERROR(RIGHT(Sources[[#This Row],[Reference to]],LEN(Sources[[#This Row],[Reference to]])-LEN($AG107)-2),"") | AI107: =IFERROR(LEFT(AH107,FIND(",",AH107)-1),AH107) | AJ107: =IFERROR(RIGHT(Sources[[#This Row],[Reference to]],LEN(Sources[[#This Row],[Reference to]])-LEN($AG107)-2-LEN($AI107)-2),"") | AK107: =IFERROR(LEFT(AJ107,FIND(",",AJ107)-1),AJ107) | AL107: =IFERROR(RIGHT(Sources[[#This Row],[Reference to]],LEN(Sources[[#This Row],[Reference to]])-LEN($AG107)-2-LEN($AI107)-2-LEN($AK107)-2),"") | AM107: =IFERROR(LEFT(AL107,FIND(",",AL107)-1),AL107) | AN107: =IFERROR(RIGHT(Sources[[#This Row],[Reference to]],LEN(Sources[[#This Row],[Reference to]])-LEN($AG107)-2-LEN($AI107)-2-LEN($AK107)-2-LEN($AM107)-2),"") | AO107: =IFERROR(LEFT(AN107,FIND(",",AN107)-1),AN107)
...

Sheet Database
A2: Database | B2: Citekey | C2: Component of PtG | D2: Year | E2: Unit | F2: 2000 | I2: 2001 | L2: 2002 | O2: 2003 | R2: 2004 | U2: 2005 | X2: 2006 | AA2: 2007 | AD2: 2008 | AG2: 2009 | AJ2: 2010 | AM2: 2011 | AP2: 2012 | AS2: 2013 | AV2: 2014 | AY2: 2015 | BB2: 2016 | BE2: 2017 | BH2: 2018 | BK2: 2019 | BN2: 2020 | BQ2: 2025 | BT2: 2030 | BX2: Comment | BY2: Location in source
F3: mean | G3: low | H3: high | I3: mean | J3: low | K3: high | L3: mean | M3: low | N3: high | O3: mean | P3: low | Q3: high | R3: mean | S3: low | T3: high | U3: mean | V3: low | W3: high | X3: mean | Y3: low | Z3: high | AA3: mean | AB3: low | AC3: high | AD3: mean | AE3: low | AF3: high | AG3: mean | AH3: low | AI3: high | AJ3: mean | AK3: low | AL3: high | AM3: mean | AN3: low | AO3: high | AP3: mean | AQ3: low | AR3: high | AS3: mean | AT3: low | AU3: high | AV3: mean | AW3: low | AX3: high | AY3: mean | AZ3: low | BA3: high | BB3: mean | BC3: low | BD3: high | BE3: mean | BF3: low | BG3: high | BH3: mean | BI3: low | BJ3: high | BK3: mean | BL3: low | BM3: high | BN3: mean | BO3: low | BP3: high | BQ3: mean | BR3: low | BS3: high | BT3: mean | BU3: low | BV3: high
A4: =MATCH(B4,Sources[Citekey],0) -> 27 | B4: gotz2016renewable | D4: =VLOOKUP(B4,Sources[],2,FALSE) -> 2016
B5: =B4 -> gotz2016renewable | C5: Electrolyzer (AEL) | D5: =D4 -> 2016 | E5: EUR/kW | F5: =IFERROR(AVERAGE(G5:H5),"") | I5: =IFERROR(AVERAGE(J5:K5),"") | L5: =IFERROR(AVERAGE(M5:N5),"") | O5: =IFERROR(AVERAGE(P5:Q5),"") | R5: =IFERROR(AVERAGE(S5:T5),"") | U5: =IFERROR(AVERAGE(V5:W5),"") | X5: =IFERROR(AVERAGE(Y5:Z5),"") | AA5: =IFERROR(AVERAGE(AB5:AC5),"") | AD5: =IFERROR(AVERAGE(AE5:AF5),"") | AG5: =IFERROR(AVERAGE(AH5:AI5),"") | AJ5: =IFERROR(AVERAGE(AK5:AL5),"") | AM5: =IFERROR(AVERAGE(AN5:AO5),"") | AP5: =IFERROR(AVERAGE(AQ5:AR5),"") | AS5: =IFERROR(AVERAGE(AT5:AU5),"") | AV5: =IFERROR(AVERAGE(AW5:AX5),"") | AY5: =IFERROR(AVERAGE(AZ5:BA5),"") | BB5: =IFERROR(AVERAGE(BC5:BD5),"") -> 1000 | BC5: 1000 | BD5: 1000 | BE5: =IFERROR(AVERAGE(BF5:BG5),"") | BH5: =IFERROR(AVERAGE(BI5:BJ5),"") | BK5: =IFERROR(AVERAGE(BL5:BM5),"") | BN5: =IFERROR(AVERAGE(BO5:BP5),"") | BQ5: =IFERROR(AVERAGE(BR5:BS5),"") | BT5: =IFERROR(AVERAGE(BU5:BV5),"") | BY5: pp. 1373-1374
B6: =B5 -> gotz2016renewable | C6: Electrolyzer (PEM) | D6: =D5 -> 2016 | E6: =E5 -> EUR/kW | F6: =IFERROR(AVERAGE(G6:H6),"") | I6: =IFERROR(AVERAGE(J6:K6),"") | L6: =IFERROR(AVERAGE(M6:N6),"") | O6: =IFERROR(AVERAGE(P6:Q6),"") | R6: =IFERROR(AVERAGE(S6:T6),"") | U6: =IFERROR(AVERAGE(V6:W6),"") | X6: =IFERROR(AVERAGE(Y6:Z6),"") | AA6: =IFERROR(AVERAGE(AB6:AC6),"") | AD6: =IFERROR(AVERAGE(AE6:AF6),"") | AG6: =IFERROR(AVERAGE(AH6:AI6),"") | AJ6: =IFERROR(AVERAGE(AK6:AL6),"") | AM6: =IFERROR(AVERAGE(AN6:AO6),"") | AP6: =IFERROR(AVERAGE(AQ6:AR6),"") | AS6: =IFERROR(AVERAGE(AT6:AU6),"") | AV6: =IFERROR(AVERAGE(AW6:AX6),"") | AY6: =IFERROR(AVERAGE(AZ6:BA6),"") | BB6: =IFERROR(AVERAGE(BC6:BD6),"") -> 2000 | BC6: 2000 | BD6: 2000 | BE6: =IFERROR(AVERAGE(BF6:BG6),"") | BH6: =IFERROR(AVERAGE(BI6:BJ6),"") -> 1000 | BI6: 1000 | BJ6: 1000 | BK6: =IFERROR(AVERAGE(BL6:BM6),"") | BN6: =IFERROR(AVERAGE(BO6:BP6),"") -> 1250 | BO6: 1250 | BP6: 1250 | BQ6: =IFERROR(AVERAGE(BR6:BS6),"") | BT6: =IFERROR(AVERAGE(BU6:BV6),"") | BY6: pp. 1373-1374
B7: =B6 -> gotz2016renewable | C7: Electrolyzer (SOEC) | D7: =D6 -> 2016 | E7: =E6 -> EUR/kW | F7: =IFERROR(AVERAGE(G7:H7),"") | I7: =IFERROR(AVERAGE(J7:K7),"") | L7: =IFERROR(AVERAGE(M7:N7),"") | O7: =IFERROR(AVERAGE(P7:Q7),"") | R7: =IFERROR(AVERAGE(S7:T7),"") | U7: =IFERROR(AVERAGE(V7:W7),"") | X7: =IFERROR(AVERAGE(Y7:Z7),"") | AA7: =IFERROR(AVERAGE(AB7:AC7),"") | AD7: =IFERROR(AVERAGE(AE7:AF7),"") | AG7: =IFERROR(AVERAGE(AH7:AI7),"") | AJ7: =IFERROR(AVERAGE(AK7:AL7),"") | AM7: =IFERROR(AVERAGE(AN7:AO7),"") | AP7: =IFERROR(AVERAGE(AQ7:AR7),"") | AS7: =IFERROR(AVERAGE(AT7:AU7),"") | AV7: =IFERROR(AVERAGE(AW7:AX7),"") | AY7: =IFERROR(AVERAGE(AZ7:BA7),"") | BB7: =IFERROR(AVERAGE(BC7:BD7),"") | BE7: =IFERROR(AVERAGE(BF7:BG7),"") | BH7: =IFERROR(AVERAGE(BI7:BJ7),"") | BK7: =IFERROR(AVERAGE(BL7:BM7),"") | BN7: =IFERROR(AVERAGE(BO7:BP7),"") | BQ7: =IFERROR(AVERAGE(BR7:BS7),"") | BT7: =IFERROR(AVERAGE(BU7:BV7),"") -> 1000 | BU7: 1000 | BV7: 1000 | BY7: pp. 1373-1374
B9: =B7 -> gotz2016renewable | C9: Balance of System | D9: =D4 -> 2016 | E9: =E5 -> EUR/kW | F9: =IFERROR(SUM(F11:F16)/F10,0) -> 0 | G9: =IFERROR(SUM(G11:G16)/G10,0) -> 0 | H9: =IFERROR(SUM(H11:H16)/H10,0) -> 0 | I9: =IFERROR(SUM(I11:I16)/I10,0) -> 0 | J9: =IFERROR(SUM(J11:J16)/J10,0) -> 0 | K9: =IFERROR(SUM(K11:K16)/K10,0) -> 0 | L9: =IFERROR(SUM(L11:L16)/L10,0) -> 0 | M9: =IFERROR(SUM(M11:M16)/M10,0) -> 0 | ... BV9: =IFERROR(SUM(BV11:BV16)/BV10,0) -> 0
B10: =B9 -> gotz2016renewable | C10: Size of example | D10: =D9 -> 2016 | E10: kW | F10: =IFERROR(AVERAGE(G10:H10),"") | I10: =IFERROR(AVERAGE(J10:K10),"") | L10: =IFERROR(AVERAGE(M10:N10),"") | O10: =IFERROR(AVERAGE(P10:Q10),"") | R10: =IFERROR(AVERAGE(S10:T10),"") | U10: =IFERROR(AVERAGE(V10:W10),"") | X10: =IFERROR(AVERAGE(Y10:Z10),"") | AA10: =IFERROR(AVERAGE(AB10:AC10),"") | AD10: =IFERROR(AVERAGE(AE10:AF10),"") | AG10: =IFERROR(AVERAGE(AH10:AI10),"") | AJ10: =IFERROR(AVERAGE(AK10:AL10),"") | AM10: =IFERROR(AVERAGE(AN10:AO10),"") | AP10: =IFERROR(AVERAGE(AQ10:AR10),"") | AS10: =IFERROR(AVERAGE(AT10:AU10),"") | AV10: =IFERROR(AVERAGE(AW10:AX10),"") | AY10: =IFERROR(AVERAGE(AZ10:BA10),"") | BB10: =IFERROR(AVERAGE(BC10:BD10),"") | BE10: =IFERROR(AVERAGE(BF10:BG10),"") | BH10: =IFERROR(AVERAGE(BI10:BJ10),"") | BK10: =IFERROR(AVERAGE(BL10:BM10),"") | BN10: =IFERROR(AVERAGE(BO10:BP10),"") | BQ10: =IFERROR(AVERAGE(BR10:BS10),"") | BT10: =IFERROR(AVERAGE(BU10:BV10),"")
B11: =B10 -> gotz2016renewable | C11: Fundament | D11: =D9 -> 2016 | E11: =LEFT(E9,3) -> EUR | F11: =IFERROR(AVERAGE(G11:H11),"") | I11: =IFERROR(AVERAGE(J11:K11),"") | L11: =IFERROR(AVERAGE(M11:N11),"") | O11: =IFERROR(AVERAGE(P11:Q11),"") | R11: =IFERROR(AVERAGE(S11:T11),"") | U11: =IFERROR(AVERAGE(V11:W11),"") | X11: =IFERROR(AVERAGE(Y11:Z11),"") | AA11: =IFERROR(AVERAGE(AB11:AC11),"") | AD11: =IFERROR(AVERAGE(AE11:AF11),"") | AG11: =IFERROR(AVERAGE(AH11:AI11),"") | AJ11: =IFERROR(AVERAGE(AK11:AL11),"") | AM11: =IFERROR(AVERAGE(AN11:AO11),"") | AP11: =IFERROR(AVERAGE(AQ11:AR11),"") | AS11: =IFERROR(AVERAGE(AT11:AU11),"") | AV11: =IFERROR(AVERAGE(AW11:AX11),"") | AY11: =IFERROR(AVERAGE(AZ11:BA11),"") | BB11: =IFERROR(AVERAGE(BC11:BD11),"") | BE11: =IFERROR(AVERAGE(BF11:BG11),"") | BH11: =IFERROR(AVERAGE(BI11:BJ11),"") | BK11: =IFERROR(AVERAGE(BL11:BM11),"") | BN11: =IFERROR(AVERAGE(BO11:BP11),"") | BQ11: =IFERROR(AVERAGE(BR11:BS11),"") | BT11: =IFERROR(AVERAGE(BU11:BV11),"")
B12: =B11 -> gotz2016renewable | C12: Energy Access | D12: =D11 -> 2016 | E12: =E11 -> EUR | F12: =IFERROR(AVERAGE(G12:H12),"") | I12: =IFERROR(AVERAGE(J12:K12),"") | L12: =IFERROR(AVERAGE(M12:N12),"") | O12: =IFERROR(AVERAGE(P12:Q12),"") | R12: =IFERROR(AVERAGE(S12:T12),"") | U12: =IFERROR(AVERAGE(V12:W12),"") | X12: =IFERROR(AVERAGE(Y12:Z12),"") | AA12: =IFERROR(AVERAGE(AB12:AC12),"") | AD12: =IFERROR(AVERAGE(AE12:AF12),"") | AG12: =IFERROR(AVERAGE(AH12:AI12),"") | AJ12: =IFERROR(AVERAGE(AK12:AL12),"") | AM12: =IFERROR(AVERAGE(AN12:AO12),"") | AP12: =IFERROR(AVERAGE(AQ12:AR12),"") | AS12: =IFERROR(AVERAGE(AT12:AU12),"") | AV12: =IFERROR(AVERAGE(AW12:AX12),"") | AY12: =IFERROR(AVERAGE(AZ12:BA12),"") | BB12: =IFERROR(AVERAGE(BC12:BD12),"") | BE12: =IFERROR(AVERAGE(BF12:BG12),"") | BH12: =IFERROR(AVERAGE(BI12:BJ12),"") | BK12: =IFERROR(AVERAGE(BL12:BM12),"") | BN12: =IFERROR(AVERAGE(BO12:BP12),"") | BQ12: =IFERROR(AVERAGE(BR12:BS12),"") | BT12: =IFERROR(AVERAGE(BU12:BV12),"")
