Workbook

Sheet Lisez-moi
A1: Classeur maître « Électrolyseurs » : CAPEX, rendement et paramètres (alcalin / PEM / SOEC)
A3: Onglets
A4: • Hypothèses : taux de change, inflation, définition de l'horizon « actuel ». Cellules bleues sur fond jaune = à modifier ; tout se recalcule.
A5: • Données : une ligne par valeur (table à charger dans Power BI). Colonnes Facteur, Min/Typique/Max normalisés et Horizon = formules.
A6: • Sources : une ligne par base et par étude/source (auteur, titre, année, DOI ou lien, licence, date de consultation).
A7: • Synthèse : CAPEX et rendement par technologie et horizon (actuel, 2030, 2050) : min, médiane, max, nombre de valeurs et de sources. Formules MEDIAN / MIN / MAX / SUMPRODUCT, mises à jour dès qu'on ajoute des lignes dans Données.
A8: • Déploiement : capacités IEA par année, statut et technologie (alcalin, PEM), à charger en table séparée dans Power BI.
A9: • Lacunes : nombre de sources par paramètre et par technologie (objectif : au moins 2).
A10: • Interface : tableau d'interface du bloc électrolyseur (entrées, sorties, paramètres) pour Capella et le modèle Python.
A12: Contenu importé
A13: • Ghadim et al. 2025 (CAPEX et LCOH, alcalin et PEM, USD 2024) : valeurs observées et projections, min / moyenne / max par étude et par année.
A14: • Delft (CAPEX_DATA, onglet CAPEX) : CAPEX alcalin et PEM 2003-2023 en EUR/kW.
... A27: • Données observées et projections sont mélangées pour un même horizon : filtrer sur la colonne Type si besoin.

Sheet Hypothèses
A1: Hypothèses de conversion et d'horizon
A2: Cellules bleues sur fond jaune = modifiables. Unité cible du CAPEX : USD 2024 par kW.
A4: Paramètre | B4: Valeur | C4: Source / commentaire | D4: Année | E4: Coef. USD→USD 2024
A5: Taux EUR → USD (2024) | B5: 1.082 | C5: Ghadim et al. 2025, onglet « Conversion rates » : 1 EUR = 1,082 USD en 2024 | D5: 2001 | E5: 1.77
A6: Année de référence des EUR de Delft | B6: 2018 | C6: Hypothèse : les valeurs 2019-2023 de Delft sont ajustées de l'inflation vers ≈2018 ; avant 2019 ce sont des EUR de l'année. À vérifier auprès de Glenk & Reichelstein / Delft. | D6: 2002 | E6: 1.74
A7: Coefficient d'inflation USD vers USD 2024 (année de réf. Delft) | B7: =INDEX($E$5:$E$40,MATCH(B6,$D$5:$D$40,0)) -> 1.25 | C7: Lu dans le tableau ci-dessous (Ghadim, « Conversion rates »). Approximation : on applique l'inflation USD aux EUR de Delft. | D7: 2003 | E7: 1.7
A8: Facteur Delft : EUR → USD 2024 | B8: =B5*B7 -> 1.3525 | C8: Taux EUR/USD × coefficient d'inflation (calculé) | D8: 2004 | E8: 1.66
A9: Début de la plage « actuel » | B9: 2020 | C9: Choix de l'utilisateur : horizon « actuel » = valeurs datées de cette année à la suivante | D9: 2005 | E9: 1.61
A10: Fin de la plage « actuel » | B10: 2025 | C10: idem | D10: 2006 | E10: 1.56
A11: Année de réf. des EUR du micro-réseau | B11: 2024 | C11: Muñoz-Peña : « EUR courants 2024 » (facteur d'inflation = 1) | D11: 2007 | E11: 1.51
A12: Exclure les lignes Secondary_Source de Potsdam (1 = oui, 0 = non) | B12: 1 | C12: Potsdam recommande de privilégier Original_Review_Multiple_Sources et Original_Analysis_w_Industry_Sources | D12: 2008 | E12: 1.46
A13: Clé de conversion | B13: Facteur vers USD 2024 | C13: Usage | D13: 2009 | E13: 1.46
A14: USD2024 | B14: =1 -> 1 | C14: Ghadim (déjà en USD 2024) | D14: 2010 | E14: 1.44
A15: EUR_DELFT | B15: =B8 -> 1.3525 | C15: Delft (EUR de réf. ≈2018) | D15: 2011 | E15: 1.39
A16: EUR2024 | B16: =B5*1 -> 1.082 | C16: Micro-réseau (EUR courants 2024) | D16: 2012 | E16: 1.37
A17: aucune | B17: =1 -> 1 | C17: Paramètres non monétaires | D17: 2013 | E17: 1.35
A18: EUR_2015 | B18: =$B$5*INDEX($E$5:$E$40,MATCH(2015,$D$5:$D$40,0)) -> 1.42824 | C18: Potsdam : EUR de 2015 vers USD 2024 (taux 2024 × inflation USD 2015→2024) | D18: 2014 | E18: 1.32
A19: EUR_2016 | B19: =$B$5*INDEX($E$5:$E$40,MATCH(2016,$D$5:$D$40,0)) -> 1.41742 | C19: Potsdam : EUR de 2016 vers USD 2024 (taux 2024 × inflation USD 2016→2024) | D19: 2015 | E19: 1.32
A20: EUR_2017 | B20: =$B$5*INDEX($E$5:$E$40,MATCH(2017,$D$5:$D$40,0)) -> 1.38496 | C20: Potsdam : EUR de 2017 vers USD 2024 (taux 2024 × inflation USD 2017→2024) | D20: 2016 | E20: 1.31
A21: EUR_2018 | B21: =$B$5*INDEX($E$5:$E$40,MATCH(2018,$D$5:$D$40,0)) -> 1.3525 | C21: Potsdam : EUR de 2018 vers USD 2024 (taux 2024 × inflation USD 2018→2024) | D21: 2017 | E21: 1.28
A22: EUR_2019 | B22: =$B$5*INDEX($E$5:$E$40,MATCH(2019,$D$5:$D$40,0)) -> 1.33086 | C22: Potsdam : EUR de 2019 vers USD 2024 (taux 2024 × inflation USD 2019→2024) | D22: 2018 | E22: 1.25
D23: 2019 | E23: 1.23
A24: Remarque : l'inflation EUR 2018→2024 est probablement différente de l'inflation USD ; la conversion Delft est donc une approximation, à documenter dans la réunion. | D24: 2020 | E24: 1.21
D25: 2021 | E25: 1.16
D26: 2022 | E26: 1.07
D27: 2023 | E27: 1.03
D28: 2024 | E28: 1

Sheet Sources
A1: Source | B1: Base | C1: Auteur(s) | D1: Titre | E1: Année | F1: DOI ou lien | G1: Licence | H1: Date de consultation | I1: Statut | J1: Remarque
A2: Actual CAPEX | B2: Ghadim | C2: Actual CAPEX (étude compilée par Ghadim et al.) | D2: Voir Supplementary Table 1 de Ghadim et al. 2025 | F2: 10.1038/s41597-025-05951-4 (article) ; 10.5281/zenodo.16417026 (jeu de données) ; étude d'origine à retrouver | G2: CC BY 4.0 (base Ghadim) | H2: 2026-10-19 | I2: à vérifier | J2: Étude primaire non consultée
A3: Actual LCOH | B3: Ghadim | C3: Actual LCOH (étude compilée par Ghadim et al.) | D3: Voir Supplementary Table 1 de Ghadim et al. 2025 | F3: 10.1038/s41597-025-05951-4 (article) ; 10.5281/zenodo.16417026 (jeu de données) ; étude d'origine à retrouver | G3: CC BY 4.0 (base Ghadim) | H3: 2026-10-19 | I3: à vérifier | J3: Étude primaire non consultée
A4: BNEF 2020 (China) | B4: Ghadim | C4: BNEF 2020 (China) (étude compilée par Ghadim et al.) | D4: Voir Supplementary Table 1 de Ghadim et al. 2025 | F4: 10.1038/s41597-025-05951-4 (article) ; 10.5281/zenodo.16417026 (jeu de données) ; étude d'origine à retrouver | G4: CC BY 4.0 (base Ghadim) | H4: 2026-10-19 | I4: à vérifier | J4: Étude primaire non consultée
A5: BNEF 2020 (World) | B5: Ghadim | C5: BNEF 2020 (World) (étude compilée par Ghadim et al.) | D5: Voir Supplementary Table 1 de Ghadim et al. 2025 | F5: 10.1038/s41597-025-05951-4 (article) ; 10.5281/zenodo.16417026 (jeu de données) ; étude d'origine à retrouver | G5: CC BY 4.0 (base Ghadim) | H5: 2026-10-19 | I5: à vérifier | J5: Étude primaire non consultée
A6: Brandle et al. 2021 (World) | B6: Ghadim | C6: Brandle et al. 2021 (World) (étude compilée par Ghadim et al.) | D6: Voir Supplementary Table 1 de Ghadim et al. 2025 | F6: 10.1038/s41597-025-05951-4 (article) ; 10.5281/zenodo.16417026 (jeu de données) ; étude d'origine à retrouver | G6: CC BY 4.0 (base Ghadim) | H6: 2026-10-19 | I6: à vérifier | J6: Étude primaire non consultée
A7: DEA 2025 (Denmark) - 10 MW | B7: Ghadim | C7: DEA 2025 (Denmark) - 10 MW (étude compilée par Ghadim et al.) | D7: Voir Supplementary Table 1 de Ghadim et al. 2025 | F7: 10.1038/s41597-025-05951-4 (article) ; 10.5281/zenodo.16417026 (jeu de données) ; étude d'origine à retrouver | G7: CC BY 4.0 (base Ghadim) | H7: 2026-10-19 | I7: à vérifier | J7: Étude primaire non consultée
A8: DEA 2025 (Denmark) - 100 MW | B8: Ghadim | C8: DEA 2025 (Denmark) - 100 MW (étude compilée par Ghadim et al.) | D8: Voir Supplementary Table 1 de Ghadim et al. 2025 | F8: 10.1038/s41597-025-05951-4 (article) ; 10.5281/zenodo.16417026 (jeu de données) ; étude d'origine à retrouver | G8: CC BY 4.0 (base Ghadim) | H8: 2026-10-19 | I8: à vérifier | J8: Étude primaire non consultée
A9: DEA 2025 (Denmark) - 1000 MW | B9: Ghadim | C9: DEA 2025 (Denmark) - 1000 MW (étude compilée par Ghadim et al.) | D9: Voir Supplementary Table 1 de Ghadim et al. 2025 | F9: 10.1038/s41597-025-05951-4 (article) ; 10.5281/zenodo.16417026 (jeu de données) ; étude d'origine à retrouver | G9: CC BY 4.0 (base Ghadim) | H9: 2026-10-19 | I9: à vérifier | J9: Étude primaire non consultée
A10: DNV 2022 (World) | B10: Ghadim | C10: DNV 2022 (World) (étude compilée par Ghadim et al.) | D10: Voir Supplementary Table 1 de Ghadim et al. 2025 | F10: 10.1038/s41597-025-05951-4 (article) ; 10.5281/zenodo.16417026 (jeu de données) ; étude d'origine à retrouver | G10: CC BY 4.0 (base Ghadim) | H10: 2026-10-19 | I10: à vérifier | J10: Étude primaire non consultée
A11: ETC 2019 (China) | B11: Ghadim | C11: ETC 2019 (China) (étude compilée par Ghadim et al.) | D11: Voir Supplementary Table 1 de Ghadim et al. 2025 | F11: 10.1038/s41597-025-05951-4 (article) ; 10.5281/zenodo.16417026 (jeu de données) ; étude d'origine à retrouver | G11: CC BY 4.0 (base Ghadim) | H11: 2026-10-19 | I11: à vérifier | J11: Étude primaire non consultée
A12: Gallardo et al. 2021 (Chile) | B12: Ghadim | C12: Gallardo et al. 2021 (Chile) (étude compilée par Ghadim et al.) | D12: Voir Supplementary Table 1 de Ghadim et al. 2025 | F12: 10.1038/s41597-025-05951-4 (article) ; 10.5281/zenodo.16417026 (jeu de données) ; étude d'origine à retrouver | G12: CC BY 4.0 (base Ghadim) | H12: 2026-10-19 | I12: à vérifier | J12: Étude primaire non consultée
A13: Gandhi et al 2022 (UAE) | B13: Ghadim | C13: Gandhi et al 2022 (UAE) (étude compilée par Ghadim et al.) | D13: Voir Supplementary Table 1 de Ghadim et al. 2025 | F13: 10.1038/s41597-025-05951-4 (article) ; 10.5281/zenodo.16417026 (jeu de données) ; étude d'origine à retrouver | G13: CC BY 4.0 (base Ghadim) | H13: 2026-10-19 | I13: à vérifier | J13: Étude primaire non consultée
... A35: WEC 2021 (World) | B35: Ghadim | C35: WEC 2021 (World) (étude compilée par Ghadim et al.) | D35: Voir Supplementary Table 1 de Ghadim et al. 2025 | F35: 10.1038/s41597-025-05951-4 (article) ; 10.5281/zenodo.16417026 (jeu de données) ; étude d'origine à retrouver | G35: CC BY 4.0 (base Ghadim) | H35: 2026-10-19 | I35: à vérifier | J35: Étude primaire non consultée
A36: Glenk & Reichelstein 2019 | B36: Delft | C36: Glenk G., Reichelstein S. | D36: Economics of converting renewable power to hydrogen | E36: 2019 | F36: Nature Energy (DOI à compléter) | G36: (à compléter) | H36: 2026-10-19 | I36: à vérifier | J36: Cité dans le classeur CAPEX_DATA de Delft (onglet CALC) ; page exacte indiquée dans CALC
A37: IEA The Future of Hydrogen 2019 | B37: Delft | C37: IEA | D37: The Future of Hydrogen | E37: 2019 | F37: (lien IEA à compléter) | G37: (à compléter) | H37: 2026-10-19 | I37: à vérifier | J37: Cité dans le classeur CAPEX_DATA de Delft (onglet CALC) ; page exacte indiquée dans CALC
A38: IEA Global Hydrogen Review 2021 | B38: Delft | C38: IEA | D38: Global Hydrogen Review 2021 | E38: 2021 | F38: (lien IEA à compléter) | G38: (à compléter) | H38: 2026-10-19 | I38: à vérifier | J38: Cité dans le classeur CAPEX_DATA de Delft (onglet CALC) ; page exacte indiquée dans CALC
A39: IEA Global Hydrogen Review 2022 | B39: Delft | C39: IEA | D39: Global Hydrogen Review 2022 | E39: 2022 | F39: (lien IEA à compléter) | G39: (à compléter) | H39: 2026-10-19 | I39: à vérifier | J39: Cité dans le classeur CAPEX_DATA de Delft (onglet CALC) ; page exacte indiquée dans CALC
A40: IEA Global Hydrogen Review 2023 | B40: Delft | C40: IEA | D40: Global Hydrogen Review 2023 | E40: 2023 | F40: (lien IEA à compléter) | G40: (à compléter) | H40: 2026-10-19 | I40: à vérifier | J40: Cité dans le classeur CAPEX_DATA de Delft (onglet CALC) ; page exacte indiquée dans CALC
A41: IEA Global Hydrogen Review 2024 | B41: Delft | C41: IEA | D41: Global Hydrogen Review 2024 | E41: 2024 | F41: (lien IEA à compléter) | G41: (à compléter) | H41: 2026-10-19 | I41: à vérifier | J41: Cité dans le classeur CAPEX_DATA de Delft (onglet CALC) ; page exacte indiquée dans CALC
A42: Muñoz-Peña et al. 2024 | B42: Microgrid | C42: Muñoz-Peña et al. | D42: Optimal design of a hydrogen system of grid-connected flexible industrial microgrids (23rd Wind & Solar Integration Workshop, Helsinki) | E42: 2024 | F42: (DOI à compléter) | G42: (à compléter) | H42: 2026-10-19 | I42: à vérifier | J42: Tableaux 2 et 3 ; valeurs reprises de Marocco et al. 2023 (J. Clean. Prod. 388, 135969) et 2024 (J. Clean. Prod. 434, 140007)
A43: Potsdam (base) | B43: Potsdam | C43: Jeu de données « Electrolyser Data Complete » (Efuels JE FU) | D43: Electrolyser_Data_Complete_Efuels_JE_FU : revue de coûts et rendements d'électrolyseurs (AEC, PEMEC, SOEC) | F43: (voir README Potsdam) | G43: CC BY 4.0 (selon vos notes) | H43: 2026-10-19 | I43: à vérifier | J43: Importé depuis une copie texte de la table Data (72 lignes). L'onglet Sources de Potsdam (DOI par source) n'a pas été fourni : à compléter.
A44: Brynolf | B44: Potsdam | C44: Brynolf (source citée par Potsdam) | D44: Voir l'onglet Sources de Potsdam | E44: 2018 | F44: (à compléter depuis Sources de Potsdam) | G44: (à compléter) | H44: 2026-10-19 | I44: à vérifier | J44: Journal_Article ; Method_Lit : Original_Review_Multiple_Sources
A45: IndWEDE | B45: Potsdam | C45: IndWEDE (source citée par Potsdam) | D45: Voir l'onglet Sources de Potsdam | E45: 2018 | F45: (à compléter depuis Sources de Potsdam) | G45: (à compléter) | H45: 2026-10-19 | I45: à vérifier | J45: Report ; Method_Lit : Original_Analysis_w_Industry_Sources
A46: FCH | B46: Potsdam | C46: FCH (source citée par Potsdam) | D46: Voir l'onglet Sources de Potsdam | E46: 2017 | F46: (à compléter depuis Sources de Potsdam) | G46: (à compléter) | H46: 2026-10-19 | I46: à vérifier | J46: Report ; Method_Lit : Original_Analysis_w_Industry_Sources
A47: Matute | B47: Potsdam | C47: Matute (source citée par Potsdam) | D47: Voir l'onglet Sources de Potsdam | E47: 2019 | F47: (à compléter depuis Sources de Potsdam) | G47: (à compléter) | H47: 2026-10-19 | I47: à vérifier | J47: Journal_Article ; Method_Lit : Secondary_Source
A48: Siemens | B48: Potsdam | C48: Siemens (source citée par Potsdam) | D48: Voir l'onglet Sources de Potsdam | E48: 2017 | F48: (à compléter depuis Sources de Potsdam) | G48: (à compléter) | H48: 2026-10-19 | I48: à vérifier | J48: Interview ; Method_Lit : Original_Review_Multiple_Sources
A49: Microbenergy | B49: Potsdam | C49: Microbenergy (source citée par Potsdam) | D49: Voir l'onglet Sources de Potsdam | E49: 2017 | F49: (à compléter depuis Sources de Potsdam) | G49: (à compléter) | H49: 2026-10-19 | I49: à vérifier | J49: Interview ; Method_Lit : Original_Review_Multiple_Sources
A50: Proost | B50: Potsdam | C50: Proost (source citée par Potsdam) | D50: Voir l'onglet Sources de Potsdam | E50: 2018 | F50: (à compléter depuis Sources de Potsdam) | G50: (à compléter) | H50: 2026-10-19 | I50: à vérifier | J50: Journal_Article ; Method_Lit : Original_Analysis_w_Industry_Sources
A51: CSIRO | B51: Potsdam | C51: CSIRO (source citée par Potsdam) | D51: Voir l'onglet Sources de Potsdam | E51: 2018 | F51: (à compléter depuis Sources de Potsdam) | G51: (à compléter) | H51: 2026-10-19 | I51: à vérifier | J51: Report ; Method_Lit : Original_Analysis_w_Industry_Sources
A52: Nel | B52: Potsdam | C52: Nel (source citée par Potsdam) | D52: Voir l'onglet Sources de Potsdam | E52: 2017 | F52: (à compléter depuis Sources de Potsdam) | G52: (à compléter) | H52: 2026-10-19 | I52: à vérifier | J52: Report ; Method_Lit : Original_Analysis_w_Industry_Sources
A53: Michalski | B53: Potsdam | C53: Michalski (source citée par Potsdam) | D53: Voir l'onglet Sources de Potsdam | E53: 2017 | F53: (à compléter depuis Sources de Potsdam) | G53: (à compléter) | H53: 2026-10-19 | I53: à vérifier | J53: Journal_Article ; Method_Lit : Original_Review_Multiple_Sources
A54: Agora | B54: Potsdam | C54: Agora (source citée par Potsdam) | D54: Voir l'onglet Sources de Potsdam | E54: 2018 | F54: (à compléter depuis Sources de Potsdam) | G54: (à compléter) | H54: 2026-10-19 | I54: à vérifier | J54: Report ; Method_Lit : Original_Analysis_w_Industry_Sources
A55: Schmidt | B55: Potsdam | C55: Schmidt (source citée par Potsdam) | D55: Voir l'onglet Sources de Potsdam | E55: 2017 | F55: (à compléter depuis Sources de Potsdam) | G55: (à compléter) | H55: 2026-10-19 | I55: à vérifier | J55: Journal_Article ; Method_Lit : Original_Analysis_w_Industry_Sources
... A58: Milzani | B58: Potsdam | C58: Milzani (source citée par Potsdam) | D58: Voir l'onglet Sources de Potsdam | E58: 2018 | F58: (à compléter depuis Sources de Potsdam) | G58: (à compléter) | H58: 2026-10-19 | I58: à vérifier | J58: Journal_Article ; Method_Lit : Original_Review_Multiple_Sources

Sheet Données
A1: ID | B1: Base de données | C1: Source | D1: Technologie | E1: Paramètre | F1: Type de donnée | G1: Valeur min | H1: Valeur typique | I1: Valeur max | J1: Unité | K1: Année de la valeur | L1: Horizon | M1: Taille | N1: Périmètre | O1: Base énergétique | P1: Région | Q1: Clé de conversion | R1: Facteur de conversion | S1: Min normalisé | T1: Typique normalisé | U1: Max normalisé | V1: Unité normalisée | W1: Statut | X1: Commentaire | Y1: Horizon imposé (optionnel) | Z1: Qualité de la méthode (Method_Lit) | AA1: Inclure dans la synthèse (1/0)
A2: D0001 | B2: Ghadim | C2: Actual CAPEX | D2: Alcalin | E2: CAPEX | F2: Observé | G2: 837.45901 | H2: 1164.5901 | I2: 1596.4073 | J2: USD 2024/kW | K2: 2015 | L2: =IF(Y2<>"",Y2,IF(AND(K2>=Hypothèses!$B$9,K2<=Hypothèses!$B$10),"actuel",IF(K2=2030,"2030",IF(K2=2050,"2050","autre")))) -> autre | N2: non précisé (varie selon l'étude) | P2: Marché | Q2: USD2024 | R2: =INDEX(Hypothèses!$B$14:$B$22,MATCH(Q2,Hypothèses!$A$14:$A$22,0)) -> 1 | S2: =IF(G2="","",G2*R2) -> 837.45901 | T2: =IF(H2="","",H2*R2) -> 1164.5901 | U2: =IF(I2="","",I2*R2) -> 1596.4073 | V2: USD 2024/kW | W2: à vérifier | X2: Base Ghadim et al. 2025 (USD 2024, déjà corrigé de l'inflation). | AA2: =IF(AND(Hypothèses!$B$12=1,Z2="Secondary_Source"),0,1) -> 1
A3: D0002 | B3: Ghadim | C3: Actual CAPEX | D3: Alcalin | E3: CAPEX | F3: Observé | G3: 850.54413 | H3: 1138.4178 | I3: 1478.6371 | J3: USD 2024/kW | K3: 2016 | L3: =IF(Y3<>"",Y3,IF(AND(K3>=Hypothèses!$B$9,K3<=Hypothèses!$B$10),"actuel",IF(K3=2030,"2030",IF(K3=2050,"2050","autre")))) -> autre | N3: non précisé (varie selon l'étude) | P3: Marché | Q3: USD2024 | R3: =INDEX(Hypothèses!$B$14:$B$22,MATCH(Q3,Hypothèses!$A$14:$A$22,0)) -> 1 | S3: =IF(G3="","",G3*R3) -> 850.54413 | T3: =IF(H3="","",H3*R3) -> 1138.4178 | U3: =IF(I3="","",I3*R3) -> 1478.6371 | V3: USD 2024/kW | W3: à vérifier | X3: Base Ghadim et al. 2025 (USD 2024, déjà corrigé de l'inflation). | AA3: =IF(AND(Hypothèses!$B$12=1,Z3="Secondary_Source"),0,1) -> 1
A4: D0003 | B4: Ghadim | C4: Actual CAPEX | D4: Alcalin | E4: CAPEX | F4: Observé | G4: 1417.6096 | H4: 978.5 | I4: 1498.9178 | J4: USD 2024/kW | K4: 2017 | L4: =IF(Y4<>"",Y4,IF(AND(K4>=Hypothèses!$B$9,K4<=Hypothèses!$B$10),"actuel",IF(K4=2030,"2030",IF(K4=2050,"2050","autre")))) -> autre | N4: non précisé (varie selon l'étude) | P4: Marché | Q4: USD2024 | R4: =INDEX(Hypothèses!$B$14:$B$22,MATCH(Q4,Hypothèses!$A$14:$A$22,0)) -> 1 | S4: =IF(G4="","",G4*R4) -> 1417.6096 | T4: =IF(H4="","",H4*R4) -> 978.5 | U4: =IF(I4="","",I4*R4) -> 1498.9178 | V4: USD 2024/kW | W4: à vérifier | X4: Base Ghadim et al. 2025 (USD 2024, déjà corrigé de l'inflation). | AA4: =IF(AND(Hypothèses!$B$12=1,Z4="Secondary_Source"),0,1) -> 1
A5: D0004 | B5: Ghadim | C5: Actual CAPEX | D5: Alcalin | E5: CAPEX | F5: Observé | G5: 824 | H5: 1184.5 | I5: 1545 | J5: USD 2024/kW | K5: 2019 | L5: =IF(Y5<>"",Y5,IF(AND(K5>=Hypothèses!$B$9,K5<=Hypothèses!$B$10),"actuel",IF(K5=2030,"2030",IF(K5=2050,"2050","autre")))) -> autre | N5: non précisé (varie selon l'étude) | P5: Marché | Q5: USD2024 | R5: =INDEX(Hypothèses!$B$14:$B$22,MATCH(Q5,Hypothèses!$A$14:$A$22,0)) -> 1 | S5: =IF(G5="","",G5*R5) -> 824 | T5: =IF(H5="","",H5*R5) -> 1184.5 | U5: =IF(I5="","",I5*R5) -> 1545 | V5: USD 2024/kW | W5: à vérifier | X5: Base Ghadim et al. 2025 (USD 2024, déjà corrigé de l'inflation). | AA5: =IF(AND(Hypothèses!$B$12=1,Z5="Secondary_Source"),0,1) -> 1
A6: D0005 | B6: Ghadim | C6: Actual CAPEX | D6: Alcalin | E6: CAPEX | F6: Observé | G6: 772.5 | H6: 983.65 | I6: 1194.8 | J6: USD 2024/kW | K6: 2020 | L6: =IF(Y6<>"",Y6,IF(AND(K6>=Hypothèses!$B$9,K6<=Hypothèses!$B$10),"actuel",IF(K6=2030,"2030",IF(K6=2050,"2050","autre")))) -> actuel | N6: non précisé (varie selon l'étude) | P6: Marché | Q6: USD2024 | R6: =INDEX(Hypothèses!$B$14:$B$22,MATCH(Q6,Hypothèses!$A$14:$A$22,0)) -> 1 | S6: =IF(G6="","",G6*R6) -> 772.5 | T6: =IF(H6="","",H6*R6) -> 983.65 | U6: =IF(I6="","",I6*R6) -> 1194.8 | V6: USD 2024/kW | W6: à vérifier | X6: Base Ghadim et al. 2025 (USD 2024, déjà corrigé de l'inflation). | AA6: =IF(AND(Hypothèses!$B$12=1,Z6="Secondary_Source"),0,1) -> 1
A7: D0006 | B7: Ghadim | C7: Actual CAPEX | D7: Alcalin | E7: CAPEX | F7: Observé | G7: 613.88 | H7: 965.625 | I7: 1317.37 | J7: USD 2024/kW | K7: 2021 | L7: =IF(Y7<>"",Y7,IF(AND(K7>=Hypothèses!$B$9,K7<=Hypothèses!$B$10),"actuel",IF(K7=2030,"2030",IF(K7=2050,"2050","autre")))) -> actuel | N7: non précisé (varie selon l'étude) | P7: Marché | Q7: USD2024 | R7: =INDEX(Hypothèses!$B$14:$B$22,MATCH(Q7,Hypothèses!$A$14:$A$22,0)) -> 1 | S7: =IF(G7="","",G7*R7) -> 613.88 | T7: =IF(H7="","",H7*R7) -> 965.625 | U7: =IF(I7="","",I7*R7) -> 1317.37 | V7: USD 2024/kW | W7: à vérifier | X7: Base Ghadim et al. 2025 (USD 2024, déjà corrigé de l'inflation). | AA7: =IF(AND(Hypothèses!$B$12=1,Z7="Secondary_Source"),0,1) -> 1
A8: D0007 | B8: Ghadim | C8: Actual CAPEX | D8: Alcalin | E8: CAPEX | F8: Observé | G8: 515 | H8: 978.5 | I8: 1442 | J8: USD 2024/kW | K8: 2022 | L8: =IF(Y8<>"",Y8,IF(AND(K8>=Hypothèses!$B$9,K8<=Hypothèses!$B$10),"actuel",IF(K8=2030,"2030",IF(K8=2050,"2050","autre")))) -> actuel | N8: non précisé (varie selon l'étude) | P8: Marché | Q8: USD2024 | R8: =INDEX(Hypothèses!$B$14:$B$22,MATCH(Q8,Hypothèses!$A$14:$A$22,0)) -> 1 | S8: =IF(G8="","",G8*R8) -> 515 | T8: =IF(H8="","",H8*R8) -> 978.5 | U8: =IF(I8="","",I8*R8) -> 1442 | V8: USD 2024/kW | W8: à vérifier | X8: Base Ghadim et al. 2025 (USD 2024, déjà corrigé de l'inflation). | AA8: =IF(AND(Hypothèses!$B$12=1,Z8="Secondary_Source"),0,1) -> 1
A9: D0008 | B9: Ghadim | C9: BNEF 2020 (China) | D9: Alcalin | E9: CAPEX | F9: Projection | H9: 206 | J9: USD 2024/kW | K9: 2020 | L9: =IF(Y9<>"",Y9,IF(AND(K9>=Hypothèses!$B$9,K9<=Hypothèses!$B$10),"actuel",IF(K9=2030,"2030",IF(K9=2050,"2050","autre")))) -> actuel | N9: non précisé (varie selon l'étude) | P9: China | Q9: USD2024 | R9: =INDEX(Hypothèses!$B$14:$B$22,MATCH(Q9,Hypothèses!$A$14:$A$22,0)) -> 1 | S9: =IF(G9="","",G9*R9) | T9: =IF(H9="","",H9*R9) -> 206 | U9: =IF(I9="","",I9*R9) | V9: USD 2024/kW | W9: à vérifier | X9: Base Ghadim et al. 2025 (USD 2024, déjà corrigé de l'inflation). | AA9: =IF(AND(Hypothèses!$B$12=1,Z9="Secondary_Source"),0,1) -> 1
A10: D0009 | B10: Ghadim | C10: BNEF 2020 (China) | D10: Alcalin | E10: CAPEX | F10: Projection | H10: 128.75 | J10: USD 2024/kW | K10: 2030 | L10: =IF(Y10<>"",Y10,IF(AND(K10>=Hypothèses!$B$9,K10<=Hypothèses!$B$10),"actuel",IF(K10=2030,"2030",IF(K10=2050,"2050","autre")))) -> 2030 | N10: non précisé (varie selon l'étude) | P10: China | Q10: USD2024 | R10: =INDEX(Hypothèses!$B$14:$B$22,MATCH(Q10,Hypothèses!$A$14:$A$22,0)) -> 1 | S10: =IF(G10="","",G10*R10) | T10: =IF(H10="","",H10*R10) -> 128.75 | U10: =IF(I10="","",I10*R10) | V10: USD 2024/kW | W10: à vérifier | X10: Base Ghadim et al. 2025 (USD 2024, déjà corrigé de l'inflation). | AA10: =IF(AND(Hypothèses!$B$12=1,Z10="Secondary_Source"),0,1) -> 1
A11: D0010 | B11: Ghadim | C11: BNEF 2020 (China) | D11: Alcalin | E11: CAPEX | F11: Projection | H11: 92.7 | J11: USD 2024/kW | K11: 2050 | L11: =IF(Y11<>"",Y11,IF(AND(K11>=Hypothèses!$B$9,K11<=Hypothèses!$B$10),"actuel",IF(K11=2030,"2030",IF(K11=2050,"2050","autre")))) -> 2050 | N11: non précisé (varie selon l'étude) | P11: China | Q11: USD2024 | R11: =INDEX(Hypothèses!$B$14:$B$22,MATCH(Q11,Hypothèses!$A$14:$A$22,0)) -> 1 | S11: =IF(G11="","",G11*R11) | T11: =IF(H11="","",H11*R11) -> 92.7 | U11: =IF(I11="","",I11*R11) | V11: USD 2024/kW | W11: à vérifier | X11: Base Ghadim et al. 2025 (USD 2024, déjà corrigé de l'inflation). | AA11: =IF(AND(Hypothèses!$B$12=1,Z11="Secondary_Source"),0,1) -> 1
A12: D0011 | B12: Ghadim | C12: DEA 2025 (Denmark) - 10 MW | D12: Alcalin | E12: CAPEX | F12: Projection | G12: 1647 | H12: 2052 | I12: 2457 | J12: USD 2024/kW | K12: 2020 | L12: =IF(Y12<>"",Y12,IF(AND(K12>=Hypothèses!$B$9,K12<=Hypothèses!$B$10),"actuel",IF(K12=2030,"2030",IF(K12=2050,"2050","autre")))) -> actuel | M12: 10 MW | N12: non précisé (varie selon l'étude) | P12: Denmark | Q12: USD2024 | R12: =INDEX(Hypothèses!$B$14:$B$22,MATCH(Q12,Hypothèses!$A$14:$A$22,0)) -> 1 | S12: =IF(G12="","",G12*R12) -> 1647 | T12: =IF(H12="","",H12*R12) -> 2052 | U12: =IF(I12="","",I12*R12) -> 2457 | V12: USD 2024/kW | W12: à vérifier | X12: Base Ghadim et al. 2025 (USD 2024, déjà corrigé de l'inflation). | AA12: =IF(AND(Hypothèses!$B$12=1,Z12="Secondary_Source"),0,1) -> 1
A13: D0012 | B13: Ghadim | C13: DEA 2025 (Denmark) - 10 MW | D13: Alcalin | E13: CAPEX | F13: Projection | H13: 1512 | J13: USD 2024/kW | K13: 2025 | L13: =IF(Y13<>"",Y13,IF(AND(K13>=Hypothèses!$B$9,K13<=Hypothèses!$B$10),"actuel",IF(K13=2030,"2030",IF(K13=2050,"2050","autre")))) -> actuel | M13: 10 MW | N13: non précisé (varie selon l'étude) | P13: Denmark | Q13: USD2024 | R13: =INDEX(Hypothèses!$B$14:$B$22,MATCH(Q13,Hypothèses!$A$14:$A$22,0)) -> 1 | S13: =IF(G13="","",G13*R13) | T13: =IF(H13="","",H13*R13) -> 1512 | U13: =IF(I13="","",I13*R13) | V13: USD 2024/kW | W13: à vérifier | X13: Base Ghadim et al. 2025 (USD 2024, déjà corrigé de l'inflation). | AA13: =IF(AND(Hypothèses!$B$12=1,Z13="Secondary_Source"),0,1) -> 1
A14: D0013 | B14: Ghadim | C14: DEA 2025 (Denmark) - 10 MW | D14: Alcalin | E14: CAPEX | F14: Projection | H14: 945 | J14: USD 2024/kW | K14: 2030 | L14: =IF(Y14<>"",Y14,IF(AND(K14>=Hypothèses!$B$9,K14<=Hypothèses!$B$10),"actuel",IF(K14=2030,"2030",IF(K14=2050,"2050","autre")))) -> 2030 | M14: 10 MW | N14: non précisé (varie selon l'étude) | P14: Denmark | Q14: USD2024 | R14: =INDEX(Hypothèses!$B$14:$B$22,MATCH(Q14,Hypothèses!$A$14:$A$22,0)) -> 1 | S14: =IF(G14="","",G14*R14) | T14: =IF(H14="","",H14*R14) -> 945 | U14: =IF(I14="","",I14*R14) | V14: USD 2024/kW | W14: à vérifier | X14: Base Ghadim et al. 2025 (USD 2024, déjà corrigé de l'inflation). | AA14: =IF(AND(Hypothèses!$B$12=1,Z14="Secondary_Source"),0,1) -> 1
A15: D0014 | B15: Ghadim | C15: DEA 2025 (Denmark) - 10 MW | D15: Alcalin | E15: CAPEX | F15: Projection | H15: 729 | J15: USD 2024/kW | K15: 2040 | L15: =IF(Y15<>"",Y15,IF(AND(K15>=Hypothèses!$B$9,K15<=Hypothèses!$B$10),"actuel",IF(K15=2030,"2030",IF(K15=2050,"2050","autre")))) -> autre | M15: 10 MW | N15: non précisé (varie selon l'étude) | P15: Denmark | Q15: USD2024 | R15: =INDEX(Hypothèses!$B$14:$B$22,MATCH(Q15,Hypothèses!$A$14:$A$22,0)) -> 1 | S15: =IF(G15="","",G15*R15) | T15: =IF(H15="","",H15*R15) -> 729 | U15: =IF(I15="","",I15*R15) | V15: USD 2024/kW | W15: à vérifier | X15: Base Ghadim et al. 2025 (USD 2024, déjà corrigé de l'inflation). | AA15: =IF(AND(Hypothèses!$B$12=1,Z15="Secondary_Source"),0,1) -> 1
A16: D0015 | B16: Ghadim | C16: DEA 2025 (Denmark) - 10 MW | D16: Alcalin | E16: CAPEX | F16: Projection | G16: 405 | H16: 513 | I16: 621 | J16: USD 2024/kW | K16: 2050 | L16: =IF(Y16<>"",Y16,IF(AND(K16>=Hypothèses!$B$9,K16<=Hypothèses!$B$10),"actuel",IF(K16=2030,"2030",IF(K16=2050,"2050","autre")))) -> 2050 | M16: 10 MW | N16: non précisé (varie selon l'étude) | P16: Denmark | Q16: USD2024 | R16: =INDEX(Hypothèses!$B$14:$B$22,MATCH(Q16,Hypothèses!$A$14:$A$22,0)) -> 1 | S16: =IF(G16="","",G16*R16) -> 405 | T16: =IF(H16="","",H16*R16) -> 513 | U16: =IF(I16="","",I16*R16) -> 621 | V16: USD 2024/kW | W16: à vérifier | X16: Base Ghadim et al. 2025 (USD 2024, déjà corrigé de l'inflation). | AA16: =IF(AND(Hypothèses!$B$12=1,Z16="Secondary_Source"),0,1) -> 1
A17: D0016 | B17: Ghadim | C17: DEA 2025 (Denmark) - 100 MW | D17: Alcalin | E17: CAPEX | F17: Projection | G17: 1026 | H17: 1296 | I17: 1566 | J17: USD 2024/kW | K17: 2020 | L17: =IF(Y17<>"",Y17,IF(AND(K17>=Hypothèses!$B$9,K17<=Hypothèses!$B$10),"actuel",IF(K17=2030,"2030",IF(K17=2050,"2050","autre")))) -> actuel | M17: 100 MW | N17: non précisé (varie selon l'étude) | P17: Denmark | Q17: USD2024 | R17: =INDEX(Hypothèses!$B$14:$B$22,MATCH(Q17,Hypothèses!$A$14:$A$22,0)) -> 1 | S17: =IF(G17="","",G17*R17) -> 1026 | T17: =IF(H17="","",H17*R17) -> 1296 | U17: =IF(I17="","",I17*R17) -> 1566 | V17: USD 2024/kW | W17: à vérifier | X17: Base Ghadim et al. 2025 (USD 2024, déjà corrigé de l'inflation). | AA17: =IF(AND(Hypothèses!$B$12=1,Z17="Secondary_Source"),0,1) -> 1
A18: D0017 | B18: Ghadim | C18: DEA 2025 (Denmark) - 100 MW | D18: Alcalin | E18: CAPEX | F18: Projection | H18: 945 | J18: USD 2024/kW | K18: 2025 | L18: =IF(Y18<>"",Y18,IF(AND(K18>=Hypothèses!$B$9,K18<=Hypothèses!$B$10),"actuel",IF(K18=2030,"2030",IF(K18=2050,"2050","autre")))) -> actuel | M18: 100 MW | N18: non précisé (varie selon l'étude) | P18: Denmark | Q18: USD2024 | R18: =INDEX(Hypothèses!$B$14:$B$22,MATCH(Q18,Hypothèses!$A$14:$A$22,0)) -> 1 | S18: =IF(G18="","",G18*R18) | T18: =IF(H18="","",H18*R18) -> 945 | U18: =IF(I18="","",I18*R18) | V18: USD 2024/kW | W18: à vérifier | X18: Base Ghadim et al. 2025 (USD 2024, déjà corrigé de l'inflation). | AA18: =IF(AND(Hypothèses!$B$12=1,Z18="Secondary_Source"),0,1) -> 1
A19: D0018 | B19: Ghadim | C19: DEA 2025 (Denmark) - 100 MW | D19: Alcalin | E19: CAPEX | F19: Projection | H19: 594 | J19: USD 2024/kW | K19: 2030 | L19: =IF(Y19<>"",Y19,IF(AND(K19>=Hypothèses!$B$9,K19<=Hypothèses!$B$10),"actuel",IF(K19=2030,"2030",IF(K19=2050,"2050","autre")))) -> 2030 | M19: 100 MW | N19: non précisé (varie selon l'étude) | P19: Denmark | Q19: USD2024 | R19: =INDEX(Hypothèses!$B$14:$B$22,MATCH(Q19,Hypothèses!$A$14:$A$22,0)) -> 1 | S19: =IF(G19="","",G19*R19) | T19: =IF(H19="","",H19*R19) -> 594 | U19: =IF(I19="","",I19*R19) | V19: USD 2024/kW | W19: à vérifier | X19: Base Ghadim et al. 2025 (USD 2024, déjà corrigé de l'inflation). | AA19: =IF(AND(Hypothèses!$B$12=1,Z19="Secondary_Source"),0,1) -> 1
A20: D0019 | B20: Ghadim | C20: DEA 2025 (Denmark) - 100 MW | D20: Alcalin | E20: CAPEX | F20: Projection | H20: 459 | J20: USD 2024/kW | K20: 2040 | L20: =IF(Y20<>"",Y20,IF(AND(K20>=Hypothèses!$B$9,K20<=Hypothèses!$B$10),"actuel",IF(K20=2030,"2030",IF(K20=2050,"2050","autre")))) -> autre | M20: 100 MW | N20: non précisé (varie selon l'étude) | P20: Denmark | Q20: USD2024 | R20: =INDEX(Hypothèses!$B$14:$B$22,MATCH(Q20,Hypothèses!$A$14:$A$22,0)) -> 1 | S20: =IF(G20="","",G20*R20) | T20: =IF(H20="","",H20*R20) -> 459 | U20: =IF(I20="","",I20*R20) | V20: USD 2024/kW | W20: à vérifier | X20: Base Ghadim et al. 2025 (USD 2024, déjà corrigé de l'inflation). | AA20: =IF(AND(Hypothèses!$B$12=1,Z20="Secondary_Source"),0,1) -> 1
A21: D0020 | B21: Ghadim | C21: DEA 2025 (Denmark) - 100 MW | D21: Alcalin | E21: CAPEX | F21: Projection | G21: 270 | H21: 324 | I21: 378 | J21: USD 2024/kW | K21: 2050 | L21: =IF(Y21<>"",Y21,IF(AND(K21>=Hypothèses!$B$9,K21<=Hypothèses!$B$10),"actuel",IF(K21=2030,"2030",IF(K21=2050,"2050","autre")))) -> 2050 | M21: 100 MW | N21: non précisé (varie selon l'étude) | P21: Denmark | Q21: USD2024 | R21: =INDEX(Hypothèses!$B$14:$B$22,MATCH(Q21,Hypothèses!$A$14:$A$22,0)) -> 1 | S21: =IF(G21="","",G21*R21) -> 270 | T21: =IF(H21="","",H21*R21) -> 324 | U21: =IF(I21="","",I21*R21) -> 378 | V21: USD 2024/kW | W21: à vérifier | X21: Base Ghadim et al. 2025 (USD 2024, déjà corrigé de l'inflation). | AA21: =IF(AND(Hypothèses!$B$12=1,Z21="Secondary_Source"),0,1) -> 1
A22: D0021 | B22: Ghadim | C22: DEA 2025 (Denmark) - 1000 MW | D22: Alcalin | E22: CAPEX | F22: Projection | G22: 945 | H22: 1188 | I22: 1431 | J22: USD 2024/kW | K22: 2020 | L22: =IF(Y22<>"",Y22,IF(AND(K22>=Hypothèses!$B$9,K22<=Hypothèses!$B$10),"actuel",IF(K22=2030,"2030",IF(K22=2050,"2050","autre")))) -> actuel | M22: 1000 MW | N22: non précisé (varie selon l'étude) | P22: Denmark | Q22: USD2024 | R22: =INDEX(Hypothèses!$B$14:$B$22,MATCH(Q22,Hypothèses!$A$14:$A$22,0)) -> 1 | S22: =IF(G22="","",G22*R22) -> 945 | T22: =IF(H22="","",H22*R22) -> 1188 | U22: =IF(I22="","",I22*R22) -> 1431 | V22: USD 2024/kW | W22: à vérifier | X22: Base Ghadim et al. 2025 (USD 2024, déjà corrigé de l'inflation). | AA22: =IF(AND(Hypothèses!$B$12=1,Z22="Secondary_Source"),0,1) -> 1
A23: D0022 | B23: Ghadim | C23: DEA 2025 (Denmark) - 1000 MW | D23: Alcalin | E23: CAPEX | F23: Projection | H23: 864 | J23: USD 2024/kW | K23: 2025 | L23: =IF(Y23<>"",Y23,IF(AND(K23>=Hypothèses!$B$9,K23<=Hypothèses!$B$10),"actuel",IF(K23=2030,"2030",IF(K23=2050,"2050","autre")))) -> actuel | M23: 1000 MW | N23: non précisé (varie selon l'étude) | P23: Denmark | Q23: USD2024 | R23: =INDEX(Hypothèses!$B$14:$B$22,MATCH(Q23,Hypothèses!$A$14:$A$22,0)) -> 1 | S23: =IF(G23="","",G23*R23) | T23: =IF(H23="","",H23*R23) -> 864 | U23: =IF(I23="","",I23*R23) | V23: USD 2024/kW | W23: à vérifier | X23: Base Ghadim et al. 2025 (USD 2024, déjà corrigé de l'inflation). | AA23: =IF(AND(Hypothèses!$B$12=1,Z23="Secondary_Source"),0,1) -> 1
A24: D0023 | B24: Ghadim | C24: DEA 2025 (Denmark) - 1000 MW | D24: Alcalin | E24: CAPEX | F24: Projection | H24: 540 | J24: USD 2024/kW | K24: 2030 | L24: =IF(Y24<>"",Y24,IF(AND(K24>=Hypothèses!$B$9,K24<=Hypothèses!$B$10),"actuel",IF(K24=2030,"2030",IF(K24=2050,"2050","autre")))) -> 2030 | M24: 1000 MW | N24: non précisé (varie selon l'étude) | P24: Denmark | Q24: USD2024 | R24: =INDEX(Hypothèses!$B$14:$B$22,MATCH(Q24,Hypothèses!$A$14:$A$22,0)) -> 1 | S24: =IF(G24="","",G24*R24) | T24: =IF(H24="","",H24*R24) -> 540 | U24: =IF(I24="","",I24*R24) | V24: USD 2024/kW | W24: à vérifier | X24: Base Ghadim et al. 2025 (USD 2024, déjà corrigé de l'inflation). | AA24: =IF(AND(Hypothèses!$B$12=1,Z24="Secondary_Source"),0,1) -> 1
A25: D0024 | B25: Ghadim | C25: DEA 2025 (Denmark) - 1000 MW | D25: Alcalin | E25: CAPEX | F25: Projection | H25: 432 | J25: USD 2024/kW | K25: 2040 | L25: =IF(Y25<>"",Y25,IF(AND(K25>=Hypothèses!$B$9,K25<=Hypothèses!$B$10),"actuel",IF(K25=2030,"2030",IF(K25=2050,"2050","autre")))) -> autre | M25: 1000 MW | N25: non précisé (varie selon l'étude) | P25: Denmark | Q25: USD2024 | R25: =INDEX(Hypothèses!$B$14:$B$22,MATCH(Q25,Hypothèses!$A$14:$A$22,0)) -> 1 | S25: =IF(G25="","",G25*R25) | T25: =IF(H25="","",H25*R25) -> 432 | U25: =IF(I25="","",I25*R25) | V25: USD 2024/kW | W25: à vérifier | X25: Base Ghadim et al. 2025 (USD 2024, déjà corrigé de l'inflation). | AA25: =IF(AND(Hypothèses!$B$12=1,Z25="Secondary_Source"),0,1) -> 1
A26: D0025 | B26: Ghadim | C26: DEA 2025 (Denmark) - 1000 MW | D26: Alcalin | E26: CAPEX | F26: Projection | G26: 243 | H26: 297 | I26: 351 | J26: USD 2024/kW | K26: 2050 | L26: =IF(Y26<>"",Y26,IF(AND(K26>=Hypothèses!$B$9,K26<=Hypothèses!$B$10),"actuel",IF(K26=2030,"2030",IF(K26=2050,"2050","autre")))) -> 2050 | M26: 1000 MW | N26: non précisé (varie selon l'étude) | P26: Denmark | Q26: USD2024 | R26: =INDEX(Hypothèses!$B$14:$B$22,MATCH(Q26,Hypothèses!$A$14:$A$22,0)) -> 1 | S26: =IF(G26="","",G26*R26) -> 243 | T26: =IF(H26="","",H26*R26) -> 297 | U26: =IF(I26="","",I26*R26) -> 351 | V26: USD 2024/kW | W26: à vérifier | X26: Base Ghadim et al. 2025 (USD 2024, déjà corrigé de l'inflation). | AA26: =IF(AND(Hypothèses!$B$12=1,Z26="Secondary_Source"),0,1) -> 1
A27: D0026 | B27: Ghadim | C27: DNV 2022 (World) | D27: Alcalin | E27: CAPEX | F27: Projection | G27: 926.28518 | H27: 1051.4549 | I27: 1166.6192 | J27: USD 2024/kW | K27: 2020 | L27: =IF(Y27<>"",Y27,IF(AND(K27>=Hypothèses!$B$9,K27<=Hypothèses!$B$10),"actuel",IF(K27=2030,"2030",IF(K27=2050,"2050","autre")))) -> actuel | N27: non précisé (varie selon l'étude) | P27: World | Q27: USD2024 | R27: =INDEX(Hypothèses!$B$14:$B$22,MATCH(Q27,Hypothèses!$A$14:$A$22,0)) -> 1 | S27: =IF(G27="","",G27*R27) -> 926.28518 | T27: =IF(H27="","",H27*R27) -> 1051.4549 | U27: =IF(I27="","",I27*R27) -> 1166.6192 | V27: USD 2024/kW | W27: à vérifier | X27: Base Ghadim et al. 2025 (USD 2024, déjà corrigé de l'inflation). | AA27: =IF(AND(Hypothèses!$B$12=1,Z27="Secondary_Source"),0,1) -> 1
A28: D0027 | B28: Ghadim | C28: DNV 2022 (World) | D28: Alcalin | E28: CAPEX | F28: Projection | G28: 841.16701 | H28: 936.29884 | I28: 1031.4317 | J28: USD 2024/kW | K28: 2025 | L28: =IF(Y28<>"",Y28,IF(AND(K28>=Hypothèses!$B$9,K28<=Hypothèses!$B$10),"actuel",IF(K28=2030,"2030",IF(K28=2050,"2050","autre")))) -> actuel | N28: non précisé (varie selon l'étude) | P28: World | Q28: USD2024 | R28: =INDEX(Hypothèses!$B$14:$B$22,MATCH(Q28,Hypothèses!$A$14:$A$22,0)) -> 1 | S28: =IF(G28="","",G28*R28) -> 841.16701 | T28: =IF(H28="","",H28*R28) -> 936.29884 | U28: =IF(I28="","",I28*R28) -> 1031.4317 | V28: USD 2024/kW | W28: à vérifier | X28: Base Ghadim et al. 2025 (USD 2024, déjà corrigé de l'inflation). | AA28: =IF(AND(Hypothèses!$B$12=1,Z28="Secondary_Source"),0,1) -> 1
A29: D0028 | B29: Ghadim | C29: DNV 2022 (World) | D29: Alcalin | E29: CAPEX | F29: Projection | G29: 736.02049 | H29: 836.16018 | I29: 941.30567 | J29: USD 2024/kW | K29: 2030 | L29: =IF(Y29<>"",Y29,IF(AND(K29>=Hypothèses!$B$9,K29<=Hypothèses!$B$10),"actuel",IF(K29=2030,"2030",IF(K29=2050,"2050","autre")))) -> 2030 | N29: non précisé (varie selon l'étude) | P29: World | Q29: USD2024 | R29: =INDEX(Hypothèses!$B$14:$B$22,MATCH(Q29,Hypothèses!$A$14:$A$22,0)) -> 1 | S29: =IF(G29="","",G29*R29) -> 736.02049 | T29: =IF(H29="","",H29*R29) -> 836.16018 | U29: =IF(I29="","",I29*R29) -> 941.30567 | V29: USD 2024/kW | W29: à vérifier | X29: Base Ghadim et al. 2025 (USD 2024, déjà corrigé de l'inflation). | AA29: =IF(AND(Hypothèses!$B$12=1,Z29="Secondary_Source"),0,1) -> 1
A30: D0029 | B30: Ghadim | C30: DNV 2022 (World) | D30: Alcalin | E30: CAPEX | F30: Projection | G30: 620.86134 | H30: 751.04201 | I30: 881.22268 | J30: USD 2024/kW | K30: 2035 | L30: =IF(Y30<>"",Y30,IF(AND(K30>=Hypothèses!$B$9,K30<=Hypothèses!$B$10),"actuel",IF(K30=2030,"2030",IF(K30=2050,"2050","autre")))) -> autre | N30: non précisé (varie selon l'étude) | P30: World | Q30: USD2024 | R30: =INDEX(Hypothèses!$B$14:$B$22,MATCH(Q30,Hypothèses!$A$14:$A$22,0)) -> 1 | S30: =IF(G30="","",G30*R30) -> 620.86134 | T30: =IF(H30="","",H30*R30) -> 751.04201 | U30: =IF(I30="","",I30*R30) -> 881.22268 | V30: USD 2024/kW | W30: à vérifier | X30: Base Ghadim et al. 2025 (USD 2024, déjà corrigé de l'inflation). | AA30: =IF(AND(Hypothèses!$B$12=1,Z30="Secondary_Source"),0,1) -> 1
A31: D0030 | B31: Ghadim | C31: DNV 2022 (World) | D31: Alcalin | E31: CAPEX | F31: Projection | G31: 520.72268 | H31: 670.93067 | I31: 826.14549 | J31: USD 2024/kW | K31: 2040 | L31: =IF(Y31<>"",Y31,IF(AND(K31>=Hypothèses!$B$9,K31<=Hypothèses!$B$10),"actuel",IF(K31=2030,"2030",IF(K31=2050,"2050","autre")))) -> autre | N31: non précisé (varie selon l'étude) | P31: World | Q31: USD2024 | R31: =INDEX(Hypothèses!$B$14:$B$22,MATCH(Q31,Hypothèses!$A$14:$A$22,0)) -> 1 | S31: =IF(G31="","",G31*R31) -> 520.72268 | T31: =IF(H31="","",H31*R31) -> 670.93067 | U31: =IF(I31="","",I31*R31) -> 826.14549 | V31: USD 2024/kW | W31: à vérifier | X31: Base Ghadim et al. 2025 (USD 2024, déjà corrigé de l'inflation). | AA31: =IF(AND(Hypothèses!$B$12=1,Z31="Secondary_Source"),0,1) -> 1
A32: D0031 | B32: Ghadim | C32: DNV 2022 (World) | D32: Alcalin | E32: CAPEX | F32: Projection | G32: 430.59768 | H32: 600.83299 | I32: 776.07616 | J32: USD 2024/kW | K32: 2045 | L32: =IF(Y32<>"",Y32,IF(AND(K32>=Hypothèses!$B$9,K32<=Hypothèses!$B$10),"actuel",IF(K32=2030,"2030",IF(K32=2050,"2050","autre")))) -> autre | N32: non précisé (varie selon l'étude) | P32: World | Q32: USD2024 | R32: =INDEX(Hypothèses!$B$14:$B$22,MATCH(Q32,Hypothèses!$A$14:$A$22,0)) -> 1 | S32: =IF(G32="","",G32*R32) -> 430.59768 | T32: =IF(H32="","",H32*R32) -> 600.83299 | U32: =IF(I32="","",I32*R32) -> 776.07616 | V32: USD 2024/kW | W32: à vérifier | X32: Base Ghadim et al. 2025 (USD 2024, déjà corrigé de l'inflation). | AA32: =IF(AND(Hypothèses!$B$12=1,Z32="Secondary_Source"),0,1) -> 1
A33: D0032 | B33: Ghadim | C33: DNV 2022 (World) | D33: Alcalin | E33: CAPEX | F33: Projection | G33: 355.49317 | H33: 535.74317 | I33: 731.01366 | J33: USD 2024/kW | K33: 2050 | L33: =IF(Y33<>"",Y33,IF(AND(K33>=Hypothèses!$B$9,K33<=Hypothèses!$B$10),"actuel",IF(K33=2030,"2030",IF(K33=2050,"2050","autre")))) -> 2050 | N33: non précisé (varie selon l'étude) | P33: World | Q33: USD2024 | R33: =INDEX(Hypothèses!$B$14:$B$22,MATCH(Q33,Hypothèses!$A$14:$A$22,0)) -> 1 | S33: =IF(G33="","",G33*R33) -> 355.49317 | T33: =IF(H33="","",H33*R33) -> 535.74317 | U33: =IF(I33="","",I33*R33) -> 731.01366 | V33: USD 2024/kW | W33: à vérifier | X33: Base Ghadim et al. 2025 (USD 2024, déjà corrigé de l'inflation). | AA33: =IF(AND(Hypothèses!$B$12=1,Z33="Secondary_Source"),0,1) -> 1
A34: D0033 | B34: Ghadim | C34: Gandhi et al 2022 (UAE) | D34: Alcalin | E34: CAPEX | F34: Projection | G34: 824 | J34: USD 2024/kW | K34: 2020 | L34: =IF(Y34<>"",Y34,IF(AND(K34>=Hypothèses!$B$9,K34<=Hypothèses!$B$10),"actuel",IF(K34=2030,"2030",IF(K34=2050,"2050","autre")))) -> actuel | N34: non précisé (varie selon l'étude) | P34: UAE | Q34: USD2024 | R34: =INDEX(Hypothèses!$B$14:$B$22,MATCH(Q34,Hypothèses!$A$14:$A$22,0)) -> 1 | S34: =IF(G34="","",G34*R34) -> 824 | T34: =IF(H34="","",H34*R34) | U34: =IF(I34="","",I34*R34) | V34: USD 2024/kW | W34: à vérifier | X34: Base Ghadim et al. 2025 (USD 2024, déjà corrigé de l'inflation). | AA34: =IF(AND(Hypothèses!$B$12=1,Z34="Secondary_Source"),0,1) -> 1
A35: D0034 | B35: Ghadim | C35: Gandhi et al 2022 (UAE) | D35: Alcalin | E35: CAPEX | F35: Projection | G35: 352.26 | J35: USD 2024/kW | K35: 2025 | L35: =IF(Y35<>"",Y35,IF(AND(K35>=Hypothèses!$B$9,K35<=Hypothèses!$B$10),"actuel",IF(K35=2030,"2030",IF(K35=2050,"2050","autre")))) -> actuel | N35: non précisé (varie selon l'étude) | P35: UAE | Q35: USD2024 | R35: =INDEX(Hypothèses!$B$14:$B$22,MATCH(Q35,Hypothèses!$A$14:$A$22,0)) -> 1 | S35: =IF(G35="","",G35*R35) -> 352.26 | T35: =IF(H35="","",H35*R35) | U35: =IF(I35="","",I35*R35) | V35: USD 2024/kW | W35: à vérifier | X35: Base Ghadim et al. 2025 (USD 2024, déjà corrigé de l'inflation). | AA35: =IF(AND(Hypothèses!$B$12=1,Z35="Secondary_Source"),0,1) -> 1
A36: D0035 | B36: Ghadim | C36: Gandhi et al 2022 (UAE) | D36: Alcalin | E36: CAPEX | F36: Projection | G36: 196.73 | J36: USD 2024/kW | K36: 2030 | L36: =IF(Y36<>"",Y36,IF(AND(K36>=Hypothèses!$B$9,K36<=Hypothèses!$B$10),"actuel",IF(K36=2030,"2030",IF(K36=2050,"2050","autre")))) -> 2030 | N36: non précisé (varie selon l'étude) | P36: UAE | Q36: USD2024 | R36: =INDEX(Hypothèses!$B$14:$B$22,MATCH(Q36,Hypothèses!$A$14:$A$22,0)) -> 1 | S36: =IF(G36="","",G36*R36) -> 196.73 | T36: =IF(H36="","",H36*R36) | U36: =IF(I36="","",I36*R36) | V36: USD 2024/kW | W36: à vérifier | X36: Base Ghadim et al. 2025 (USD 2024, déjà corrigé de l'inflation). | AA36: =IF(AND(Hypothèses!$B$12=1,Z36="Secondary_Source"),0,1) -> 1
A37: D0036 | B37: Ghadim | C37: Gandhi et al 2022 (UAE) | D37: Alcalin | E37: CAPEX | F37: Projection | G37: 76.22 | J37: USD 2024/kW | K37: 2050 | L37: =IF(Y37<>"",Y37,IF(AND(K37>=Hypothèses!$B$9,K37<=Hypothèses!$B$10),"actuel",IF(K37=2030,"2030",IF(K37=2050,"2050","autre")))) -> 2050 | N37: non précisé (varie selon l'étude) | P37: UAE | Q37: USD2024 | R37: =INDEX(Hypothèses!$B$14:$B$22,MATCH(Q37,Hypothèses!$A$14:$A$22,0)) -> 1 | S37: =IF(G37="","",G37*R37) -> 76.22 | T37: =IF(H37="","",H37*R37) | U37: =IF(I37="","",I37*R37) | V37: USD 2024/kW | W37: à vérifier | X37: Base Ghadim et al. 2025 (USD 2024, déjà corrigé de l'inflation). | AA37: =IF(AND(Hypothèses!$B$12=1,Z37="Secondary_Source"),0,1) -> 1
A38: D0037 | B38: Ghadim | C38: George et al. 2022 (Germany) | D38: Alcalin | E38: CAPEX | F38: Projection | G38: 667.36374 | H38: 742.78846 | I38: 811.33793 | J38: USD 2024/kW | K38: 2020 | L38: =IF(Y38<>"",Y38,IF(AND(K38>=Hypothèses!$B$9,K38<=Hypothèses!$B$10),"actuel",IF(K38=2030,"2030",IF(K38=2050,"2050","autre")))) -> actuel | N38: non précisé (varie selon l'étude) | P38: Germany | Q38: USD2024 | R38: =INDEX(Hypothèses!$B$14:$B$22,MATCH(Q38,Hypothèses!$A$14:$A$22,0)) -> 1 | S38: =IF(G38="","",G38*R38) -> 667.36374 | T38: =IF(H38="","",H38*R38) -> 742.78846 | U38: =IF(I38="","",I38*R38) -> 811.33793 | V38: USD 2024/kW | W38: à vérifier | X38: Base Ghadim et al. 2025 (USD 2024, déjà corrigé de l'inflation). | AA38: =IF(AND(Hypothèses!$B$12=1,Z38="Secondary_Source"),0,1) -> 1
A39: D0038 | B39: Ghadim | C39: George et al. 2022 (Germany) | D39: Alcalin | E39: CAPEX | F39: Projection | G39: 397.19969 | H39: 575.89776 | I39: 775.76827 | J39: USD 2024/kW | K39: 2025 | L39: =IF(Y39<>"",Y39,IF(AND(K39>=Hypothèses!$B$9,K39<=Hypothèses!$B$10),"actuel",IF(K39=2030,"2030",IF(K39=2050,"2050","autre")))) -> actuel | N39: non précisé (varie selon l'étude) | P39: Germany | Q39: USD2024 | R39: =INDEX(Hypothèses!$B$14:$B$22,MATCH(Q39,Hypothèses!$A$14:$A$22,0)) -> 1 | S39: =IF(G39="","",G39*R39) -> 397.19969 | T39: =IF(H39="","",H39*R39) -> 575.89776 | U39: =IF(I39="","",I39*R39) -> 775.76827 | V39: USD 2024/kW | W39: à vérifier | X39: Base Ghadim et al. 2025 (USD 2024, déjà corrigé de l'inflation). | AA39: =IF(AND(Hypothèses!$B$12=1,Z39="Secondary_Source"),0,1) -> 1
A40: D0039 | B40: Ghadim | C40: George et al. 2022 (Germany) | D40: Alcalin | E40: CAPEX | F40: Projection | G40: 245.6035 | H40: 444.62723 | I40: 744.4325 | J40: USD 2024/kW | K40: 2030 | L40: =IF(Y40<>"",Y40,IF(AND(K40>=Hypothèses!$B$9,K40<=Hypothèses!$B$10),"actuel",IF(K40=2030,"2030",IF(K40=2050,"2050","autre")))) -> 2030 | N40: non précisé (varie selon l'étude) | P40: Germany | Q40: USD2024 | R40: =INDEX(Hypothèses!$B$14:$B$22,MATCH(Q40,Hypothèses!$A$14:$A$22,0)) -> 1 | S40: =IF(G40="","",G40*R40) -> 245.6035 | T40: =IF(H40="","",H40*R40) -> 444.62723 | U40: =IF(I40="","",I40*R40) -> 744.4325 | V40: USD 2024/kW | W40: à vérifier | X40: Base Ghadim et al. 2025 (USD 2024, déjà corrigé de l'inflation). | AA40: =IF(AND(Hypothèses!$B$12=1,Z40="Secondary_Source"),0,1) -> 1
A41: D0040 | B41: Ghadim | C41: George et al. 2022 (Germany) | D41: Alcalin | E41: CAPEX | F41: Projection | G41: 177.8503 | H41: 379.41536 | I41: 720.71873 | J41: USD 2024/kW | K41: 2035 | L41: =IF(Y41<>"",Y41,IF(AND(K41>=Hypothèses!$B$9,K41<=Hypothèses!$B$10),"actuel",IF(K41=2030,"2030",IF(K41=2050,"2050","autre")))) -> autre | N41: non précisé (varie selon l'étude) | P41: Germany | Q41: USD2024 | R41: =INDEX(Hypothèses!$B$14:$B$22,MATCH(Q41,Hypothèses!$A$14:$A$22,0)) -> 1 | S41: =IF(G41="","",G41*R41) -> 177.8503 | T41: =IF(H41="","",H41*R41) -> 379.41536 | U41: =IF(I41="","",I41*R41) -> 720.71873 | V41: USD 2024/kW | W41: à vérifier | X41: Base Ghadim et al. 2025 (USD 2024, déjà corrigé de l'inflation). | AA41: =IF(AND(Hypothèses!$B$12=1,Z41="Secondary_Source"),0,1) -> 1
A42: D0041 | B42: Ghadim | C42: George et al. 2022 (Germany) | D42: Alcalin | E42: CAPEX | F42: Projection | G42: 150.74941 | H42: 343.8447 | I42: 701.23985 | J42: USD 2024/kW | K42: 2040 | L42: =IF(Y42<>"",Y42,IF(AND(K42>=Hypothèses!$B$9,K42<=Hypothèses!$B$10),"actuel",IF(K42=2030,"2030",IF(K42=2050,"2050","autre")))) -> autre | N42: non précisé (varie selon l'étude) | P42: Germany | Q42: USD2024 | R42: =INDEX(Hypothèses!$B$14:$B$22,MATCH(Q42,Hypothèses!$A$14:$A$22,0)) -> 1 | S42: =IF(G42="","",G42*R42) -> 150.74941 | T42: =IF(H42="","",H42*R42) -> 343.8447 | U42: =IF(I42="","",I42*R42) -> 701.23985 | V42: USD 2024/kW | W42: à vérifier | X42: Base Ghadim et al. 2025 (USD 2024, déjà corrigé de l'inflation). | AA42: =IF(AND(Hypothèses!$B$12=1,Z42="Secondary_Source"),0,1) -> 1
A43: D0042 | B43: Ghadim | C43: George et al. 2022 (Germany) | D43: Alcalin | E43: CAPEX | F43: Projection | G43: 133.81186 | H43: 321.82548 | I43: 685.99585 | J43: USD 2024/kW | K43: 2045 | L43: =IF(Y43<>"",Y43,IF(AND(K43>=Hypothèses!$B$9,K43<=Hypothèses!$B$10),"actuel",IF(K43=2030,"2030",IF(K43=2050,"2050","autre")))) -> autre | N43: non précisé (varie selon l'étude) | P43: Germany | Q43: USD2024 | R43: =INDEX(Hypothèses!$B$14:$B$22,MATCH(Q43,Hypothèses!$A$14:$A$22,0)) -> 1 | S43: =IF(G43="","",G43*R43) -> 133.81186 | T43: =IF(H43="","",H43*R43) -> 321.82548 | U43: =IF(I43="","",I43*R43) -> 685.99585 | V43: USD 2024/kW | W43: à vérifier | X43: Base Ghadim et al. 2025 (USD 2024, déjà corrigé de l'inflation). | AA43: =IF(AND(Hypothèses!$B$12=1,Z43="Secondary_Source"),0,1) -> 1
A44: D0043 | B44: Ghadim | C44: George et al. 2022 (Germany) | D44: Alcalin | E44: CAPEX | F44: Projection | G44: 129.57697 | H44: 308.00962 | I44: 673.29218 | J44: USD 2024/kW | K44: 2050 | L44: =IF(Y44<>"",Y44,IF(AND(K44>=Hypothèses!$B$9,K44<=Hypothèses!$B$10),"actuel",IF(K44=2030,"2030",IF(K44=2050,"2050","autre")))) -> 2050 | N44: non précisé (varie selon l'étude) | P44: Germany | Q44: USD2024 | R44: =INDEX(Hypothèses!$B$14:$B$22,MATCH(Q44,Hypothèses!$A$14:$A$22,0)) -> 1 | S44: =IF(G44="","",G44*R44) -> 129.57697 | T44: =IF(H44="","",H44*R44) -> 308.00962 | U44: =IF(I44="","",I44*R44) -> 673.29218 | V44: USD 2024/kW | W44: à vérifier | X44: Base Ghadim et al. 2025 (USD 2024, déjà corrigé de l'inflation). | AA44: =IF(AND(Hypothèses!$B$12=1,Z44="Secondary_Source"),0,1) -> 1
A45: D0044 | B45: Ghadim | C45: Graham et al. 2021 (Australia) | D45: Alcalin | E45: CAPEX | F45: Projection | H45: 1661.2903 | J45: USD 2024/kW | K45: 2020 | L45: =IF(Y45<>"",Y45,IF(AND(K45>=Hypothèses!$B$9,K45<=Hypothèses!$B$10),"actuel",IF(K45=2030,"2030",IF(K45=2050,"2050","autre")))) -> actuel | N45: non précisé (varie selon l'étude) | P45: Australia | Q45: USD2024 | R45: =INDEX(Hypothèses!$B$14:$B$22,MATCH(Q45,Hypothèses!$A$14:$A$22,0)) -> 1 | S45: =IF(G45="","",G45*R45) | T45: =IF(H45="","",H45*R45) -> 1661.2903 | U45: =IF(I45="","",I45*R45) | V45: USD 2024/kW | W45: à vérifier | X45: Base Ghadim et al. 2025 (USD 2024, déjà corrigé de l'inflation). | AA45: =IF(AND(Hypothèses!$B$12=1,Z45="Secondary_Source"),0,1) -> 1
A46: D0045 | B46: Ghadim | C46: Graham et al. 2021 (Australia) | D46: Alcalin | E46: CAPEX | F46: Projection | H46: 1228.6505 | J46: USD 2024/kW | K46: 2021 | L46: =IF(Y46<>"",Y46,IF(AND(K46>=Hypothèses!$B$9,K46<=Hypothèses!$B$10),"actuel",IF(K46=2030,"2030",IF(K46=2050,"2050","autre")))) -> actuel | N46: non précisé (varie selon l'étude) | P46: Australia | Q46: USD2024 | R46: =INDEX(Hypothèses!$B$14:$B$22,MATCH(Q46,Hypothèses!$A$14:$A$22,0)) -> 1 | S46: =IF(G46="","",G46*R46) | T46: =IF(H46="","",H46*R46) -> 1228.6505 | U46: =IF(I46="","",I46*R46) | V46: USD 2024/kW | W46: à vérifier | X46: Base Ghadim et al. 2025 (USD 2024, déjà corrigé de l'inflation). | AA46: =IF(AND(Hypothèses!$B$12=1,Z46="Secondary_Source"),0,1) -> 1
A47: D0046 | B47: Ghadim | C47: Graham et al. 2021 (Australia) | D47: Alcalin | E47: CAPEX | F47: Projection | H47: 1084.1049 | J47: USD 2024/kW | K47: 2022 | L47: =IF(Y47<>"",Y47,IF(AND(K47>=Hypothèses!$B$9,K47<=Hypothèses!$B$10),"actuel",IF(K47=2030,"2030",IF(K47=2050,"2050","autre")))) -> actuel | N47: non précisé (varie selon l'étude) | P47: Australia | Q47: USD2024 | R47: =INDEX(Hypothèses!$B$14:$B$22,MATCH(Q47,Hypothèses!$A$14:$A$22,0)) -> 1 | S47: =IF(G47="","",G47*R47) | T47: =IF(H47="","",H47*R47) -> 1084.1049 | U47: =IF(I47="","",I47*R47) | V47: USD 2024/kW | W47: à vérifier | X47: Base Ghadim et al. 2025 (USD 2024, déjà corrigé de l'inflation). | AA47: =IF(AND(Hypothèses!$B$12=1,Z47="Secondary_Source"),0,1) -> 1
A48: D0047 | B48: Ghadim | C48: Graham et al. 2021 (Australia) | D48: Alcalin | E48: CAPEX | F48: Projection | H48: 991.7571 | J48: USD 2024/kW | K48: 2023 | L48: =IF(Y48<>"",Y48,IF(AND(K48>=Hypothèses!$B$9,K48<=Hypothèses!$B$10),"actuel",IF(K48=2030,"2030",IF(K48=2050,"2050","autre")))) -> actuel | N48: non précisé (varie selon l'étude) | P48: Australia | Q48: USD2024 | R48: =INDEX(Hypothèses!$B$14:$B$22,MATCH(Q48,Hypothèses!$A$14:$A$22,0)) -> 1 | S48: =IF(G48="","",G48*R48) | T48: =IF(H48="","",H48*R48) -> 991.7571 | U48: =IF(I48="","",I48*R48) | V48: USD 2024/kW | W48: à vérifier | X48: Base Ghadim et al. 2025 (USD 2024, déjà corrigé de l'inflation). | AA48: =IF(AND(Hypothèses!$B$12=1,Z48="Secondary_Source"),0,1) -> 1
A49: D0048 | B49: Ghadim | C49: Graham et al. 2021 (Australia) | D49: Alcalin | E49: CAPEX | F49: Projection | H49: 935.53903 | J49: USD 2024/kW | K49: 2024 | L49: =IF(Y49<>"",Y49,IF(AND(K49>=Hypothèses!$B$9,K49<=Hypothèses!$B$10),"actuel",IF(K49=2030,"2030",IF(K49=2050,"2050","autre")))) -> actuel | N49: non précisé (varie selon l'étude) | P49: Australia | Q49: USD2024 | R49: =INDEX(Hypothèses!$B$14:$B$22,MATCH(Q49,Hypothèses!$A$14:$A$22,0)) -> 1 | S49: =IF(G49="","",G49*R49) | T49: =IF(H49="","",H49*R49) -> 935.53903 | U49: =IF(I49="","",I49*R49) | V49: USD 2024/kW | W49: à vérifier | X49: Base Ghadim et al. 2025 (USD 2024, déjà corrigé de l'inflation). | AA49: =IF(AND(Hypothèses!$B$12=1,Z49="Secondary_Source"),0,1) -> 1
A50: D0049 | B50: Ghadim | C50: Graham et al. 2021 (Australia) | D50: Alcalin | E50: CAPEX | F50: Projection | H50: 911.45032 | J50: USD 2024/kW | K50: 2025 | L50: =IF(Y50<>"",Y50,IF(AND(K50>=Hypothèses!$B$9,K50<=Hypothèses!$B$10),"actuel",IF(K50=2030,"2030",IF(K50=2050,"2050","autre")))) -> actuel | N50: non précisé (varie selon l'étude) | P50: Australia | Q50: USD2024 | R50: =INDEX(Hypothèses!$B$14:$B$22,MATCH(Q50,Hypothèses!$A$14:$A$22,0)) -> 1 | S50: =IF(G50="","",G50*R50) | T50: =IF(H50="","",H50*R50) -> 911.45032 | U50: =IF(I50="","",I50*R50) | V50: USD 2024/kW | W50: à vérifier | X50: Base Ghadim et al. 2025 (USD 2024, déjà corrigé de l'inflation). | AA50: =IF(AND(Hypothèses!$B$12=1,Z50="Secondary_Source"),0,1) -> 1
A51: D0050 | B51: Ghadim | C51: Graham et al. 2021 (Australia) | D51: Alcalin | E51: CAPEX | F51: Projection | H51: 895.38897 | J51: USD 2024/kW | K51: 2026 | L51: =IF(Y51<>"",Y51,IF(AND(K51>=Hypothèses!$B$9,K51<=Hypothèses!$B$10),"actuel",IF(K51=2030,"2030",IF(K51=2050,"2050","autre")))) -> autre | N51: non précisé (varie selon l'étude) | P51: Australia | Q51: USD2024 | R51: =INDEX(Hypothèses!$B$14:$B$22,MATCH(Q51,Hypothèses!$A$14:$A$22,0)) -> 1 | S51: =IF(G51="","",G51*R51) | T51: =IF(H51="","",H51*R51) -> 895.38897 | U51: =IF(I51="","",I51*R51) | V51: USD 2024/kW | W51: à vérifier | X51: Base Ghadim et al. 2025 (USD 2024, déjà corrigé de l'inflation). | AA51: =IF(AND(Hypothèses!$B$12=1,Z51="Secondary_Source"),0,1) -> 1
A52: D0051 | B52: Ghadim | C52: Graham et al. 2021 (Australia) | D52: Alcalin | E52: CAPEX | F52: Projection | H52: 875.31394 | J52: USD 2024/kW | K52: 2027 | L52: =IF(Y52<>"",Y52,IF(AND(K52>=Hypothèses!$B$9,K52<=Hypothèses!$B$10),"actuel",IF(K52=2030,"2030",IF(K52=2050,"2050","autre")))) -> autre | N52: non précisé (varie selon l'étude) | P52: Australia | Q52: USD2024 | R52: =INDEX(Hypothèses!$B$14:$B$22,MATCH(Q52,Hypothèses!$A$14:$A$22,0)) -> 1 | S52: =IF(G52="","",G52*R52) | T52: =IF(H52="","",H52*R52) -> 875.31394 | U52: =IF(I52="","",I52*R52) | V52: USD 2024/kW | W52: à vérifier | X52: Base Ghadim et al. 2025 (USD 2024, déjà corrigé de l'inflation). | AA52: =IF(AND(Hypothèses!$B$12=1,Z52="Secondary_Source"),0,1) -> 1
A53: D0052 | B53: Ghadim | C53: Graham et al. 2021 (Australia) | D53: Alcalin | E53: CAPEX | F53: Projection | H53: 847.2049 | J53: USD 2024/kW | K53: 2028 | L53: =IF(Y53<>"",Y53,IF(AND(K53>=Hypothèses!$B$9,K53<=Hypothèses!$B$10),"actuel",IF(K53=2030,"2030",IF(K53=2050,"2050","autre")))) -> autre | N53: non précisé (varie selon l'étude) | P53: Australia | Q53: USD2024 | R53: =INDEX(Hypothèses!$B$14:$B$22,MATCH(Q53,Hypothèses!$A$14:$A$22,0)) -> 1 | S53: =IF(G53="","",G53*R53) | T53: =IF(H53="","",H53*R53) -> 847.2049 | U53: =IF(I53="","",I53*R53) | V53: USD 2024/kW | W53: à vérifier | X53: Base Ghadim et al. 2025 (USD 2024, déjà corrigé de l'inflation). | AA53: =IF(AND(Hypothèses!$B$12=1,Z53="Secondary_Source"),0,1) -> 1
A54: D0053 | B54: Ghadim | C54: Graham et al. 2021 (Australia) | D54: Alcalin | E54: CAPEX | F54: Projection | H54: 827.12987 | J54: USD 2024/kW | K54: 2029 | L54: =IF(Y54<>"",Y54,IF(AND(K54>=Hypothèses!$B$9,K54<=Hypothèses!$B$10),"actuel",IF(K54=2030,"2030",IF(K54=2050,"2050","autre")))) -> autre | N54: non précisé (varie selon l'étude) | P54: Australia | Q54: USD2024 | R54: =INDEX(Hypothèses!$B$14:$B$22,MATCH(Q54,Hypothèses!$A$14:$A$22,0)) -> 1 | S54: =IF(G54="","",G54*R54) | T54: =IF(H54="","",H54*R54) -> 827.12987 | U54: =IF(I54="","",I54*R54) | V54: USD 2024/kW | W54: à vérifier | X54: Base Ghadim et al. 2025 (USD 2024, déjà corrigé de l'inflation). | AA54: =IF(AND(Hypothèses!$B$12=1,Z54="Secondary_Source"),0,1) -> 1
A55: D0054 | B55: Ghadim | C55: Graham et al. 2021 (Australia) | D55: Alcalin | E55: CAPEX | F55: Projection | H55: 803.04116 | J55: USD 2024/kW | K55: 2030 | L55: =IF(Y55<>"",Y55,IF(AND(K55>=Hypothèses!$B$9,K55<=Hypothèses!$B$10),"actuel",IF(K55=2030,"2030",IF(K55=2050,"2050","autre")))) -> 2030 | N55: non précisé (varie selon l'étude) | P55: Australia | Q55: USD2024 | R55: =INDEX(Hypothèses!$B$14:$B$22,MATCH(Q55,Hypothèses!$A$14:$A$22,0)) -> 1 | S55: =IF(G55="","",G55*R55) | T55: =IF(H55="","",H55*R55) -> 803.04116 | U55: =IF(I55="","",I55*R55) | V55: USD 2024/kW | W55: à vérifier | X55: Base Ghadim et al. 2025 (USD 2024, déjà corrigé de l'inflation). | AA55: =IF(AND(Hypothèses!$B$12=1,Z55="Secondary_Source"),0,1) -> 1
A56: D0055 | B56: Ghadim | C56: Graham et al. 2021 (Australia) | D56: Alcalin | E56: CAPEX | F56: Projection | H56: 770.91845 | J56: USD 2024/kW | K56: 2031 | L56: =IF(Y56<>"",Y56,IF(AND(K56>=Hypothèses!$B$9,K56<=Hypothèses!$B$10),"actuel",IF(K56=2030,"2030",IF(K56=2050,"2050","autre")))) -> autre | N56: non précisé (varie selon l'étude) | P56: Australia | Q56: USD2024 | R56: =INDEX(Hypothèses!$B$14:$B$22,MATCH(Q56,Hypothèses!$A$14:$A$22,0)) -> 1 | S56: =IF(G56="","",G56*R56) | T56: =IF(H56="","",H56*R56) -> 770.91845 | U56: =IF(I56="","",I56*R56) | V56: USD 2024/kW | W56: à vérifier | X56: Base Ghadim et al. 2025 (USD 2024, déjà corrigé de l'inflation). | AA56: =IF(AND(Hypothèses!$B$12=1,Z56="Secondary_Source"),0,1) -> 1
... A78: D0077 | B78: Ghadim | C78: Hall et al. 2020 (India) | D78: Alcalin | E78: CAPEX | F78: Projection | H78: 186.1004 | J78: USD 2024/kW | K78: 2050 | L78: =IF(Y78<>"",Y78,IF(AND(K78>=Hypothèses!$B$9,K78<=Hypothèses!$B$10),"actuel",IF(K78=2030,"2030",IF(K78=2050,"2050","autre")))) -> 2050 | N78: non précisé (varie selon l'étude) | P78: India | Q78: USD2024 | R78: =INDEX(Hypothèses!$B$14:$B$22,MATCH(Q78,Hypothèses!$A$14:$A$22,0)) -> 1 | S78: =IF(G78="","",G78*R78) | T78: =IF(H78="","",H78*R78) -> 186.1004 | U78: =IF(I78="","",I78*R78) | V78: USD 2024/kW | W78: à vérifier | X78: Base Ghadim et al. 2025 (USD 2024, déjà corrigé de l'inflation). | AA78: =IF(AND(Hypothèses!$B$12=1,Z78="Secondary_Source"),0,1) -> 1
A79: D0078 | B79: Ghadim | C79: IEA 2021 - H2 (Latin America) | D79: Alcalin | E79: CAPEX | F79: Projection | G79: 1103.13 | J79: USD 2024/kW | K79: 2020 | L79: =IF(Y79<>"",Y79,IF(AND(K79>=Hypothèses!$B$9,K79<=Hypothèses!$B$10),"actuel",IF(K79=2030,"2030",IF(K79=2050,"2050","autre")))) -> actuel | N79: non précisé (varie selon l'étude) | P79: Latin America | Q79: USD2024 | R79: =INDEX(Hypothèses!$B$14:$B$22,MATCH(Q79,Hypothèses!$A$14:$A$22,0)) -> 1 | S79: =IF(G79="","",G79*R79) -> 1103.13 | T79: =IF(H79="","",H79*R79) | U79: =IF(I79="","",I79*R79) | V79: USD 2024/kW | W79: à vérifier | X79: Base Ghadim et al. 2025 (USD 2024, déjà corrigé de l'inflation). | AA79: =IF(AND(Hypothèses!$B$12=1,Z79="Secondary_Source"),0,1) -> 1
A80: D0079 | B80: Ghadim | C80: IEA 2021 - H2 (Latin America) | D80: Alcalin | E80: CAPEX | F80: Projection | G80: 306.94 | J80: USD 2024/kW | K80: 2030 | L80: =IF(Y80<>"",Y80,IF(AND(K80>=Hypothèses!$B$9,K80<=Hypothèses!$B$10),"actuel",IF(K80=2030,"2030",IF(K80=2050,"2050","autre")))) -> 2030 | N80: non précisé (varie selon l'étude) | P80: Latin America | Q80: USD2024 | R80: =INDEX(Hypothèses!$B$14:$B$22,MATCH(Q80,Hypothèses!$A$14:$A$22,0)) -> 1 | S80: =IF(G80="","",G80*R80) -> 306.94 | T80: =IF(H80="","",H80*R80) | U80: =IF(I80="","",I80*R80) | V80: USD 2024/kW | W80: à vérifier | X80: Base Ghadim et al. 2025 (USD 2024, déjà corrigé de l'inflation). | AA80: =IF(AND(Hypothèses!$B$12=1,Z80="Secondary_Source"),0,1) -> 1
A81: D0080 | B81: Ghadim | C81: IEA 2021 - H2 (Latin America) | D81: Alcalin | E81: CAPEX | F81: Projection | G81: 238.96 | J81: USD 2024/kW | K81: 2050 | L81: =IF(Y81<>"",Y81,IF(AND(K81>=Hypothèses!$B$9,K81<=Hypothèses!$B$10),"actuel",IF(K81=2030,"2030",IF(K81=2050,"2050","autre")))) -> 2050 | N81: non précisé (varie selon l'étude) | P81: Latin America | Q81: USD2024 | R81: =INDEX(Hypothèses!$B$14:$B$22,MATCH(Q81,Hypothèses!$A$14:$A$22,0)) -> 1 | S81: =IF(G81="","",G81*R81) -> 238.96 | T81: =IF(H81="","",H81*R81) | U81: =IF(I81="","",I81*R81) | V81: USD 2024/kW | W81: à vérifier | X81: Base Ghadim et al. 2025 (USD 2024, déjà corrigé de l'inflation). | AA81: =IF(AND(Hypothèses!$B$12=1,Z81="Secondary_Source"),0,1) -> 1
A82: D0081 | B82: Ghadim | C82: IRENA 2020 (World) | D82: Alcalin | E82: CAPEX | F82: Projection | H82: 793.1 | J82: USD 2024/kW | K82: 2020 | L82: =IF(Y82<>"",Y82,IF(AND(K82>=Hypothèses!$B$9,K82<=Hypothèses!$B$10),"actuel",IF(K82=2030,"2030",IF(K82=2050,"2050","autre")))) -> actuel | N82: non précisé (varie selon l'étude) | P82: World | Q82: USD2024 | R82: =INDEX(Hypothèses!$B$14:$B$22,MATCH(Q82,Hypothèses!$A$14:$A$22,0)) -> 1 | S82: =IF(G82="","",G82*R82) | T82: =IF(H82="","",H82*R82) -> 793.1 | U82: =IF(I82="","",I82*R82) | V82: USD 2024/kW | W82: à vérifier | X82: Base Ghadim et al. 2025 (USD 2024, déjà corrigé de l'inflation). | AA82: =IF(AND(Hypothèses!$B$12=1,Z82="Secondary_Source"),0,1) -> 1
A83: D0082 | B83: Ghadim | C83: IRENA 2020 (World) | D83: Alcalin | E83: CAPEX | F83: Projection | H83: 556.2 | J83: USD 2024/kW | K83: 2030 | L83: =IF(Y83<>"",Y83,IF(AND(K83>=Hypothèses!$B$9,K83<=Hypothèses!$B$10),"actuel",IF(K83=2030,"2030",IF(K83=2050,"2050","autre")))) -> 2030 | N83: non précisé (varie selon l'étude) | P83: World | Q83: USD2024 | R83: =INDEX(Hypothèses!$B$14:$B$22,MATCH(Q83,Hypothèses!$A$14:$A$22,0)) -> 1 | S83: =IF(G83="","",G83*R83) | T83: =IF(H83="","",H83*R83) -> 556.2 | U83: =IF(I83="","",I83*R83) | V83: USD 2024/kW | W83: à vérifier | X83: Base Ghadim et al. 2025 (USD 2024, déjà corrigé de l'inflation). | AA83: =IF(AND(Hypothèses!$B$12=1,Z83="Secondary_Source"),0,1) -> 1
A84: D0083 | B84: Ghadim | C84: IRENA 2020 (World) | D84: Alcalin | E84: CAPEX | F84: Projection | H84: 448.05 | J84: USD 2024/kW | K84: 2040 | L84: =IF(Y84<>"",Y84,IF(AND(K84>=Hypothèses!$B$9,K84<=Hypothèses!$B$10),"actuel",IF(K84=2030,"2030",IF(K84=2050,"2050","autre")))) -> autre | N84: non précisé (varie selon l'étude) | P84: World | Q84: USD2024 | R84: =INDEX(Hypothèses!$B$14:$B$22,MATCH(Q84,Hypothèses!$A$14:$A$22,0)) -> 1 | S84: =IF(G84="","",G84*R84) | T84: =IF(H84="","",H84*R84) -> 448.05 | U84: =IF(I84="","",I84*R84) | V84: USD 2024/kW | W84: à vérifier | X84: Base Ghadim et al. 2025 (USD 2024, déjà corrigé de l'inflation). | AA84: =IF(AND(Hypothèses!$B$12=1,Z84="Secondary_Source"),0,1) -> 1
A85: D0084 | B85: Ghadim | C85: IRENA 2020 (World) | D85: Alcalin | E85: CAPEX | F85: Projection | H85: 381.1 | J85: USD 2024/kW | K85: 2050 | L85: =IF(Y85<>"",Y85,IF(AND(K85>=Hypothèses!$B$9,K85<=Hypothèses!$B$10),"actuel",IF(K85=2030,"2030",IF(K85=2050,"2050","autre")))) -> 2050 | N85: non précisé (varie selon l'étude) | P85: World | Q85: USD2024 | R85: =INDEX(Hypothèses!$B$14:$B$22,MATCH(Q85,Hypothèses!$A$14:$A$22,0)) -> 1 | S85: =IF(G85="","",G85*R85) | T85: =IF(H85="","",H85*R85) -> 381.1 | U85: =IF(I85="","",I85*R85) | V85: USD 2024/kW | W85: à vérifier | X85: Base Ghadim et al. 2025 (USD 2024, déjà corrigé de l'inflation). | AA85: =IF(AND(Hypothèses!$B$12=1,Z85="Secondary_Source"),0,1) -> 1
A86: D0085 | B86: Ghadim | C86: Janssen et al. 2022 (Denmark, Portugal, Netherlands) | D86: Alcalin | E86: CAPEX | F86: Projection | H86: 693.26923 | J86: USD 2024/kW | K86: 2020 | L86: =IF(Y86<>"",Y86,IF(AND(K86>=Hypothèses!$B$9,K86<=Hypothèses!$B$10),"actuel",IF(K86=2030,"2030",IF(K86=2050,"2050","autre")))) -> actuel | N86: non précisé (varie selon l'étude) | P86: Denmark, Portugal, Netherlands | Q86: USD2024 | R86: =INDEX(Hypothèses!$B$14:$B$22,MATCH(Q86,Hypothèses!$A$14:$A$22,0)) -> 1 | S86: =IF(G86="","",G86*R86) | T86: =IF(H86="","",H86*R86) -> 693.26923 | U86: =IF(I86="","",I86*R86) | V86: USD 2024/kW | W86: à vérifier | X86: Base Ghadim et al. 2025 (USD 2024, déjà corrigé de l'inflation). | AA86: =IF(AND(Hypothèses!$B$12=1,Z86="Secondary_Source"),0,1) -> 1
A87: D0086 | B87: Ghadim | C87: Janssen et al. 2022 (Denmark, Portugal, Netherlands) | D87: Alcalin | E87: CAPEX | F87: Projection | H87: 594.23077 | J87: USD 2024/kW | K87: 2030 | L87: =IF(Y87<>"",Y87,IF(AND(K87>=Hypothèses!$B$9,K87<=Hypothèses!$B$10),"actuel",IF(K87=2030,"2030",IF(K87=2050,"2050","autre")))) -> 2030 | N87: non précisé (varie selon l'étude) | P87: Denmark, Portugal, Netherlands | Q87: USD2024 | R87: =INDEX(Hypothèses!$B$14:$B$22,MATCH(Q87,Hypothèses!$A$14:$A$22,0)) -> 1 | S87: =IF(G87="","",G87*R87) | T87: =IF(H87="","",H87*R87) -> 594.23077 | U87: =IF(I87="","",I87*R87) | V87: USD 2024/kW | W87: à vérifier | X87: Base Ghadim et al. 2025 (USD 2024, déjà corrigé de l'inflation). | AA87: =IF(AND(Hypothèses!$B$12=1,Z87="Secondary_Source"),0,1) -> 1
A88: D0087 | B88: Ghadim | C88: Janssen et al. 2022 (Denmark, Portugal, Netherlands) | D88: Alcalin | E88: CAPEX | F88: Projection | H88: 515 | J88: USD 2024/kW | K88: 2040 | L88: =IF(Y88<>"",Y88,IF(AND(K88>=Hypothèses!$B$9,K88<=Hypothèses!$B$10),"actuel",IF(K88=2030,"2030",IF(K88=2050,"2050","autre")))) -> autre | N88: non précisé (varie selon l'étude) | P88: Denmark, Portugal, Netherlands | Q88: USD2024 | R88: =INDEX(Hypothèses!$B$14:$B$22,MATCH(Q88,Hypothèses!$A$14:$A$22,0)) -> 1 | S88: =IF(G88="","",G88*R88) | T88: =IF(H88="","",H88*R88) -> 515 | U88: =IF(I88="","",I88*R88) | V88: USD 2024/kW | W88: à vérifier | X88: Base Ghadim et al. 2025 (USD 2024, déjà corrigé de l'inflation). | AA88: =IF(AND(Hypothèses!$B$12=1,Z88="Secondary_Source"),0,1) -> 1
A89: D0088 | B89: Ghadim | C89: Janssen et al. 2022 (Denmark, Portugal, Netherlands) | D89: Alcalin | E89: CAPEX | F89: Projection | H89: 445.67308 | J89: USD 2024/kW | K89: 2050 | L89: =IF(Y89<>"",Y89,IF(AND(K89>=Hypothèses!$B$9,K89<=Hypothèses!$B$10),"actuel",IF(K89=2030,"2030",IF(K89=2050,"2050","autre")))) -> 2050 | N89: non précisé (varie selon l'étude) | P89: Denmark, Portugal, Netherlands | Q89: USD2024 | R89: =INDEX(Hypothèses!$B$14:$B$22,MATCH(Q89,Hypothèses!$A$14:$A$22,0)) -> 1 | S89: =IF(G89="","",G89*R89) | T89: =IF(H89="","",H89*R89) -> 445.67308 | U89: =IF(I89="","",I89*R89) | V89: USD 2024/kW | W89: à vérifier | X89: Base Ghadim et al. 2025 (USD 2024, déjà corrigé de l'inflation). | AA89: =IF(AND(Hypothèses!$B$12=1,Z89="Secondary_Source"),0,1) -> 1
A90: D0089 | B90: Ghadim | C90: Mahone et al. 2020 (U.S.) | D90: Alcalin | E90: CAPEX | F90: Projection | G90: 1138.9328 | H90: 1145.4012 | I90: 1151.8696 | J90: USD 2024/kW | K90: 2020 | L90: =IF(Y90<>"",Y90,IF(AND(K90>=Hypothèses!$B$9,K90<=Hypothèses!$B$10),"actuel",IF(K90=2030,"2030",IF(K90=2050,"2050","autre")))) -> actuel | N90: non précisé (varie selon l'étude) | P90: U.S. | Q90: USD2024 | R90: =INDEX(Hypothèses!$B$14:$B$22,MATCH(Q90,Hypothèses!$A$14:$A$22,0)) -> 1 | S90: =IF(G90="","",G90*R90) -> 1138.9328 | T90: =IF(H90="","",H90*R90) -> 1145.4012 | U90: =IF(I90="","",I90*R90) -> 1151.8696 | V90: USD 2024/kW | W90: à vérifier | X90: Base Ghadim et al. 2025 (USD 2024, déjà corrigé de l'inflation). | AA90: =IF(AND(Hypothèses!$B$12=1,Z90="Secondary_Source"),0,1) -> 1
A91: D0090 | B91: Ghadim | C91: Mahone et al. 2020 (U.S.) | D91: Alcalin | E91: CAPEX | F91: Projection | G91: 718.30346 | H91: 905.96843 | I91: 1093.6334 | J91: USD 2024/kW | K91: 2025 | L91: =IF(Y91<>"",Y91,IF(AND(K91>=Hypothèses!$B$9,K91<=Hypothèses!$B$10),"actuel",IF(K91=2030,"2030",IF(K91=2050,"2050","autre")))) -> actuel | N91: non précisé (varie selon l'étude) | P91: U.S. | Q91: USD2024 | R91: =INDEX(Hypothèses!$B$14:$B$22,MATCH(Q91,Hypothèses!$A$14:$A$22,0)) -> 1 | S91: =IF(G91="","",G91*R91) -> 718.30346 | T91: =IF(H91="","",H91*R91) -> 905.96843 | U91: =IF(I91="","",I91*R91) -> 1093.6334 | V91: USD 2024/kW | W91: à vérifier | X91: Base Ghadim et al. 2025 (USD 2024, déjà corrigé de l'inflation). | AA91: =IF(AND(Hypothèses!$B$12=1,Z91="Secondary_Source"),0,1) -> 1
A92: D0091 | B92: Ghadim | C92: Mahone et al. 2020 (U.S.) | D92: Alcalin | E92: CAPEX | F92: Projection | G92: 533.87475 | H92: 757.13085 | I92: 980.38696 | J92: USD 2024/kW | K92: 2030 | L92: =IF(Y92<>"",Y92,IF(AND(K92>=Hypothèses!$B$9,K92<=Hypothèses!$B$10),"actuel",IF(K92=2030,"2030",IF(K92=2050,"2050","autre")))) -> 2030 | N92: non précisé (varie selon l'étude) | P92: U.S. | Q92: USD2024 | R92: =INDEX(Hypothèses!$B$14:$B$22,MATCH(Q92,Hypothèses!$A$14:$A$22,0)) -> 1 | S92: =IF(G92="","",G92*R92) -> 533.87475 | T92: =IF(H92="","",H92*R92) -> 757.13085 | U92: =IF(I92="","",I92*R92) -> 980.38696 | V92: USD 2024/kW | W92: à vérifier | X92: Base Ghadim et al. 2025 (USD 2024, déjà corrigé de l'inflation). | AA92: =IF(AND(Hypothèses!$B$12=1,Z92="Secondary_Source"),0,1) -> 1
A93: D0092 | B93: Ghadim | C93: Mahone et al. 2020 (U.S.) | D93: Alcalin | E93: CAPEX | F93: Projection | G93: 339.73829 | H93: 618 | I93: 896.26171 | J93: USD 2024/kW | K93: 2035 | L93: =IF(Y93<>"",Y93,IF(AND(K93>=Hypothèses!$B$9,K93<=Hypothèses!$B$10),"actuel",IF(K93=2030,"2030",IF(K93=2050,"2050","autre")))) -> autre | N93: non précisé (varie selon l'étude) | P93: U.S. | Q93: USD2024 | R93: =INDEX(Hypothèses!$B$14:$B$22,MATCH(Q93,Hypothèses!$A$14:$A$22,0)) -> 1 | S93: =IF(G93="","",G93*R93) -> 339.73829 | T93: =IF(H93="","",H93*R93) -> 618 | U93: =IF(I93="","",I93*R93) -> 896.26171 | V93: USD 2024/kW | W93: à vérifier | X93: Base Ghadim et al. 2025 (USD 2024, déjà corrigé de l'inflation). | AA93: =IF(AND(Hypothèses!$B$12=1,Z93="Secondary_Source"),0,1) -> 1
A94: D0093 | B94: Ghadim | C94: Mahone et al. 2020 (U.S.) | D94: Alcalin | E94: CAPEX | F94: Projection | G94: 236.19857 | H94: 506.37169 | I94: 776.54481 | J94: USD 2024/kW | K94: 2040 | L94: =IF(Y94<>"",Y94,IF(AND(K94>=Hypothèses!$B$9,K94<=Hypothèses!$B$10),"actuel",IF(K94=2030,"2030",IF(K94=2050,"2050","autre")))) -> autre | N94: non précisé (varie selon l'étude) | P94: U.S. | Q94: USD2024 | R94: =INDEX(Hypothèses!$B$14:$B$22,MATCH(Q94,Hypothèses!$A$14:$A$22,0)) -> 1 | S94: =IF(G94="","",G94*R94) -> 236.19857 | T94: =IF(H94="","",H94*R94) -> 506.37169 | U94: =IF(I94="","",I94*R94) -> 776.54481 | V94: USD 2024/kW | W94: à vérifier | X94: Base Ghadim et al. 2025 (USD 2024, déjà corrigé de l'inflation). | AA94: =IF(AND(Hypothèses!$B$12=1,Z94="Secondary_Source"),0,1) -> 1
A95: D0094 | B95: Ghadim | C95: Mahone et al. 2020 (U.S.) | D95: Alcalin | E95: CAPEX | F95: Projection | G95: 171.48676 | H95: 430.33503 | I95: 689.1833 | J95: USD 2024/kW | K95: 2045 | L95: =IF(Y95<>"",Y95,IF(AND(K95>=Hypothèses!$B$9,K95<=Hypothèses!$B$10),"actuel",IF(K95=2030,"2030",IF(K95=2050,"2050","autre")))) -> autre | N95: non précisé (varie selon l'étude) | P95: U.S. | Q95: USD2024 | R95: =INDEX(Hypothèses!$B$14:$B$22,MATCH(Q95,Hypothèses!$A$14:$A$22,0)) -> 1 | S95: =IF(G95="","",G95*R95) -> 171.48676 | T95: =IF(H95="","",H95*R95) -> 430.33503 | U95: =IF(I95="","",I95*R95) -> 689.1833 | V95: USD 2024/kW | W95: à vérifier | X95: Base Ghadim et al. 2025 (USD 2024, déjà corrigé de l'inflation). | AA95: =IF(AND(Hypothèses!$B$12=1,Z95="Secondary_Source"),0,1) -> 1
A96: D0095 | B96: Ghadim | C96: Mahone et al. 2020 (U.S.) | D96: Alcalin | E96: CAPEX | F96: Projection | G96: 135.89511 | H96: 368.85845 | I96: 601.82179 | J96: USD 2024/kW | K96: 2050 | L96: =IF(Y96<>"",Y96,IF(AND(K96>=Hypothèses!$B$9,K96<=Hypothèses!$B$10),"actuel",IF(K96=2030,"2030",IF(K96=2050,"2050","autre")))) -> 2050 | N96: non précisé (varie selon l'étude) | P96: U.S. | Q96: USD2024 | R96: =INDEX(Hypothèses!$B$14:$B$22,MATCH(Q96,Hypothèses!$A$14:$A$22,0)) -> 1 | S96: =IF(G96="","",G96*R96) -> 135.89511 | T96: =IF(H96="","",H96*R96) -> 368.85845 | U96: =IF(I96="","",I96*R96) -> 601.82179 | V96: USD 2024/kW | W96: à vérifier | X96: Base Ghadim et al. 2025 (USD 2024, déjà corrigé de l'inflation). | AA96: =IF(AND(Hypothèses!$B$12=1,Z96="Secondary_Source"),0,1) -> 1
A97: D0096 | B97: Ghadim | C97: UK BEIS 2021 (UK) | D97: Alcalin | E97: CAPEX | F97: Projection | G97: 850.18073 | H97: 1001.5825 | I97: 1380.083 | J97: USD 2024/kW | K97: 2020 | L97: =IF(Y97<>"",Y97,IF(AND(K97>=Hypothèses!$B$9,K97<=Hypothèses!$B$10),"actuel",IF(K97=2030,"2030",IF(K97=2050,"2050","autre")))) -> actuel | N97: non précisé (varie selon l'étude) | P97: UK | Q97: USD2024 | R97: =INDEX(Hypothèses!$B$14:$B$22,MATCH(Q97,Hypothèses!$A$14:$A$22,0)) -> 1 | S97: =IF(G97="","",G97*R97) -> 850.18073 | T97: =IF(H97="","",H97*R97) -> 1001.5825 | U97: =IF(I97="","",I97*R97) -> 1380.083 | V97: USD 2024/kW | W97: à vérifier | X97: Base Ghadim et al. 2025 (USD 2024, déjà corrigé de l'inflation). | AA97: =IF(AND(Hypothèses!$B$12=1,Z97="Secondary_Source"),0,1) -> 1
A98: D0097 | B98: Ghadim | C98: UK BEIS 2021 (UK) | D98: Alcalin | E98: CAPEX | F98: Projection | G98: 675.4857 | H98: 867.65093 | I98: 1211.2215 | J98: USD 2024/kW | K98: 2025 | L98: =IF(Y98<>"",Y98,IF(AND(K98>=Hypothèses!$B$9,K98<=Hypothèses!$B$10),"actuel",IF(K98=2030,"2030",IF(K98=2050,"2050","autre")))) -> actuel | N98: non précisé (varie selon l'étude) | P98: UK | Q98: USD2024 | R98: =INDEX(Hypothèses!$B$14:$B$22,MATCH(Q98,Hypothèses!$A$14:$A$22,0)) -> 1 | S98: =IF(G98="","",G98*R98) -> 675.4857 | T98: =IF(H98="","",H98*R98) -> 867.65093 | U98: =IF(I98="","",I98*R98) -> 1211.2215 | V98: USD 2024/kW | W98: à vérifier | X98: Base Ghadim et al. 2025 (USD 2024, déjà corrigé de l'inflation). | AA98: =IF(AND(Hypothèses!$B$12=1,Z98="Secondary_Source"),0,1) -> 1
A99: D0098 | B99: Ghadim | C99: UK BEIS 2021 (UK) | D99: Alcalin | E99: CAPEX | F99: Projection | G99: 576.49217 | H99: 786.12643 | I99: 1141.3383 | J99: USD 2024/kW | K99: 2030 | L99: =IF(Y99<>"",Y99,IF(AND(K99>=Hypothèses!$B$9,K99<=Hypothèses!$B$10),"actuel",IF(K99=2030,"2030",IF(K99=2050,"2050","autre")))) -> 2030 | N99: non précisé (varie selon l'étude) | P99: UK | Q99: USD2024 | R99: =INDEX(Hypothèses!$B$14:$B$22,MATCH(Q99,Hypothèses!$A$14:$A$22,0)) -> 1 | S99: =IF(G99="","",G99*R99) -> 576.49217 | T99: =IF(H99="","",H99*R99) -> 786.12643 | U99: =IF(I99="","",I99*R99) -> 1141.3383 | V99: USD 2024/kW | W99: à vérifier | X99: Base Ghadim et al. 2025 (USD 2024, déjà corrigé de l'inflation). | AA99: =IF(AND(Hypothèses!$B$12=1,Z99="Secondary_Source"),0,1) -> 1
A100: D0099 | B100: Ghadim | C100: UK BEIS 2021 (UK) | D100: Alcalin | E100: CAPEX | F100: Projection | G100: 547.37711 | H100: 757.0102 | I100: 1100.5772 | J100: USD 2024/kW | K100: 2035 | L100: =IF(Y100<>"",Y100,IF(AND(K100>=Hypothèses!$B$9,K100<=Hypothèses!$B$10),"actuel",IF(K100=2030,"2030",IF(K100=2050,"2050","autre")))) -> autre | N100: non précisé (varie selon l'étude) | P100: UK | Q100: USD2024 | R100: =INDEX(Hypothèses!$B$14:$B$22,MATCH(Q100,Hypothèses!$A$14:$A$22,0)) -> 1 | S100: =IF(G100="","",G100*R100) -> 547.37711 | T100: =IF(H100="","",H100*R100) -> 757.0102 | U100: =IF(I100="","",I100*R100) -> 1100.5772 | V100: USD 2024/kW | W100: à vérifier | X100: Base Ghadim et al. 2025 (USD 2024, déjà corrigé de l'inflation). | AA100: =IF(AND(Hypothèses!$B$12=1,Z100="Secondary_Source"),0,1) -> 1
A101: D0100 | B101: Ghadim | C101: UK BEIS 2021 (UK) | D101: Alcalin | E101: CAPEX | F101: Projection | G101: 518.26089 | H101: 739.54117 | I101: 1065.638 | J101: USD 2024/kW | K101: 2040 | L101: =IF(Y101<>"",Y101,IF(AND(K101>=Hypothèses!$B$9,K101<=Hypothèses!$B$10),"actuel",IF(K101=2030,"2030",IF(K101=2050,"2050","autre")))) -> autre | N101: non précisé (varie selon l'étude) | P101: UK | Q101: USD2024 | R101: =INDEX(Hypothèses!$B$14:$B$22,MATCH(Q101,Hypothèses!$A$14:$A$22,0)) -> 1 | S101: =IF(G101="","",G101*R101) -> 518.26089 | T101: =IF(H101="","",H101*R101) -> 739.54117 | U101: =IF(I101="","",I101*R101) -> 1065.638 | V101: USD 2024/kW | W101: à vérifier | X101: Base Ghadim et al. 2025 (USD 2024, déjà corrigé de l'inflation). | AA101: =IF(AND(Hypothèses!$B$12=1,Z101="Secondary_Source"),0,1) -> 1
... A103: D0102 | B103: Ghadim | C103: UK BEIS 2021 (UK) | D103: Alcalin | E103: CAPEX | F103: Projection | G103: 494.96884 | H103: 710.42494 | I103: 1024.8757 | J103: USD 2024/kW | K103: 2050 | L103: =IF(Y103<>"",Y103,IF(AND(K103>=Hypothèses!$B$9,K103<=Hypothèses!$B$10),"actuel",IF(K103=2030,"2030",IF(K103=2050,"2050","autre")))) -> 2050 | N103: non précisé (varie selon l'étude) | P103: UK | Q103: USD2024 | R103: =INDEX(Hypothèses!$B$14:$B$22,MATCH(Q103,Hypothèses!$A$14:$A$22,0)) -> 1 | S103: =IF(G103="","",G103*R103) -> 494.96884 | T103: =IF(H103="","",H103*R103) -> 710.42494 | U103: =IF(I103="","",I103*R103) -> 1024.8757 | V103: USD 2024/kW | W103: à vérifier | X103: Base Ghadim et al. 2025 (USD 2024, déjà corrigé de l'inflation). | AA103: =IF(AND(Hypothèses!$B$12=1,Z103="Secondary_Source"),0,1) -> 1
A104: D0103 | B104: Ghadim | C104: Vartiainen et al. 2020 (EU) | D104: Alcalin | E104: CAPEX | F104: Projection | H104: 396.15385 | J104: USD 2024/kW | K104: 2021 | L104: =IF(Y104<>"",Y104,IF(AND(K104>=Hypothèses!$B$9,K104<=Hypothèses!$B$10),"actuel",IF(K104=2030,"2030",IF(K104=2050,"2050","autre")))) -> actuel | N104: non précisé (varie selon l'étude) | P104: EU | Q104: USD2024 | R104: =INDEX(Hypothèses!$B$14:$B$22,MATCH(Q104,Hypothèses!$A$14:$A$22,0)) -> 1 | S104: =IF(G104="","",G104*R104) | T104: =IF(H104="","",H104*R104) -> 396.15385 | U104: =IF(I104="","",I104*R104) | V104: USD 2024/kW | W104: à vérifier | X104: Base Ghadim et al. 2025 (USD 2024, déjà corrigé de l'inflation). | AA104: =IF(AND(Hypothèses!$B$12=1,Z104="Secondary_Source"),0,1) -> 1
A105: D0104 | B105: Ghadim | C105: Vartiainen et al. 2020 (EU) | D105: Alcalin | E105: CAPEX | F105: Projection | H105: 237.69231 | J105: USD 2024/kW | K105: 2030 | L105: =IF(Y105<>"",Y105,IF(AND(K105>=Hypothèses!$B$9,K105<=Hypothèses!$B$10),"actuel",IF(K105=2030,"2030",IF(K105=2050,"2050","autre")))) -> 2030 | N105: non précisé (varie selon l'étude) | P105: EU | Q105: USD2024 | R105: =INDEX(Hypothèses!$B$14:$B$22,MATCH(Q105,Hypothèses!$A$14:$A$22,0)) -> 1 | S105: =IF(G105="","",G105*R105) | T105: =IF(H105="","",H105*R105) -> 237.69231 | U105: =IF(I105="","",I105*R105) | V105: USD 2024/kW | W105: à vérifier | X105: Base Ghadim et al. 2025 (USD 2024, déjà corrigé de l'inflation). | AA105: =IF(AND(Hypothèses!$B$12=1,Z105="Secondary_Source"),0,1) -> 1
A106: D0105 | B106: Ghadim | C106: Vartiainen et al. 2020 (EU) | D106: Alcalin | E106: CAPEX | F106: Projection | H106: 79.230769 | J106: USD 2024/kW | K106: 2050 | L106: =IF(Y106<>"",Y106,IF(AND(K106>=Hypothèses!$B$9,K106<=Hypothèses!$B$10),"actuel",IF(K106=2030,"2030",IF(K106=2050,"2050","autre")))) -> 2050 | N106: non précisé (varie selon l'étude) | P106: EU | Q106: USD2024 | R106: =INDEX(Hypothèses!$B$14:$B$22,MATCH(Q106,Hypothèses!$A$14:$A$22,0)) -> 1 | S106: =IF(G106="","",G106*R106) | T106: =IF(H106="","",H106*R106) -> 79.230769 | U106: =IF(I106="","",I106*R106) | V106: USD 2024/kW | W106: à vérifier | X106: Base Ghadim et al. 2025 (USD 2024, déjà corrigé de l'inflation). | AA106: =IF(AND(Hypothèses!$B$12=1,Z106="Secondary_Source"),0,1) -> 1
A107: D0106 | B107: Ghadim | C107: Actual LCOH | D107: Alcalin | E107: LCOH | F107: Observé | G107: 2.575 | H107: 6.4375 | I107: 10.3 | J107: USD 2024/kg H2 | K107: 2016 | L107: =IF(Y107<>"",Y107,IF(AND(K107>=Hypothèses!$B$9,K107<=Hypothèses!$B$10),"actuel",IF(K107=2030,"2030",IF(K107=2050,"2050","autre")))) -> autre | N107: non précisé (varie selon l'étude) | P107: Marché | Q107: USD2024 | R107: =INDEX(Hypothèses!$B$14:$B$22,MATCH(Q107,Hypothèses!$A$14:$A$22,0)) -> 1 | S107: =IF(G107="","",G107*R107) -> 2.575 | T107: =IF(H107="","",H107*R107) -> 6.4375 | U107: =IF(I107="","",I107*R107) -> 10.3 | V107: USD 2024/kg H2 | W107: à vérifier | X107: Base Ghadim et al. 2025 (USD 2024, déjà corrigé de l'inflation). | AA107: =IF(AND(Hypothèses!$B$12=1,Z107="Secondary_Source"),0,1) -> 1
A108: D0107 | B108: Ghadim | C108: Actual LCOH | D108: Alcalin | E108: LCOH | F108: Observé | G108: 1.751 | H108: 5.459 | I108: 9.167 | J108: USD 2024/kg H2 | K108: 2017 | L108: =IF(Y108<>"",Y108,IF(AND(K108>=Hypothèses!$B$9,K108<=Hypothèses!$B$10),"actuel",IF(K108=2030,"2030",IF(K108=2050,"2050","autre")))) -> autre | N108: non précisé (varie selon l'étude) | P108: Marché | Q108: USD2024 | R108: =INDEX(Hypothèses!$B$14:$B$22,MATCH(Q108,Hypothèses!$A$14:$A$22,0)) -> 1 | S108: =IF(G108="","",G108*R108) -> 1.751 | T108: =IF(H108="","",H108*R108) -> 5.459 | U108: =IF(I108="","",I108*R108) -> 9.167 | V108: USD 2024/kg H2 | W108: à vérifier | X108: Base Ghadim et al. 2025 (USD 2024, déjà corrigé de l'inflation). | AA108: =IF(AND(Hypothèses!$B$12=1,Z108="Secondary_Source"),0,1) -> 1
A109: D0108 | B109: Ghadim | C109: Actual LCOH | D109: Alcalin | E109: LCOH | F109: Observé | G109: 3.09 | H109: 5.4075 | I109: 7.725 | J109: USD 2024/kg H2 | K109: 2018 | L109: =IF(Y109<>"",Y109,IF(AND(K109>=Hypothèses!$B$9,K109<=Hypothèses!$B$10),"actuel",IF(K109=2030,"2030",IF(K109=2050,"2050","autre")))) -> autre | N109: non précisé (varie selon l'étude) | P109: Marché | Q109: USD2024 | R109: =INDEX(Hypothèses!$B$14:$B$22,MATCH(Q109,Hypothèses!$A$14:$A$22,0)) -> 1 | S109: =IF(G109="","",G109*R109) -> 3.09 | T109: =IF(H109="","",H109*R109) -> 5.4075 | U109: =IF(I109="","",I109*R109) -> 7.725 | V109: USD 2024/kg H2 | W109: à vérifier | X109: Base Ghadim et al. 2025 (USD 2024, déjà corrigé de l'inflation). | AA109: =IF(AND(Hypothèses!$B$12=1,Z109="Secondary_Source"),0,1) -> 1
A110: D0109 | B110: Ghadim | C110: Actual LCOH | D110: Alcalin | E110: LCOH | F110: Observé | G110: 2.9046 | H110: 4.9852 | I110: 7.0658 | J110: USD 2024/kg H2 | K110: 2019 | L110: =IF(Y110<>"",Y110,IF(AND(K110>=Hypothèses!$B$9,K110<=Hypothèses!$B$10),"actuel",IF(K110=2030,"2030",IF(K110=2050,"2050","autre")))) -> autre | N110: non précisé (varie selon l'étude) | P110: Marché | Q110: USD2024 | R110: =INDEX(Hypothèses!$B$14:$B$22,MATCH(Q110,Hypothèses!$A$14:$A$22,0)) -> 1 | S110: =IF(G110="","",G110*R110) -> 2.9046 | T110: =IF(H110="","",H110*R110) -> 4.9852 | U110: =IF(I110="","",I110*R110) -> 7.0658 | V110: USD 2024/kg H2 | W110: à vérifier | X110: Base Ghadim et al. 2025 (USD 2024, déjà corrigé de l'inflation). | AA110: =IF(AND(Hypothèses!$B$12=1,Z110="Secondary_Source"),0,1) -> 1
A111: D0110 | B111: Ghadim | C111: Actual LCOH | D111: Alcalin | E111: LCOH | F111: Observé | G111: 3.502 | H111: 5.15 | I111: 6.798 | J111: USD 2024/kg H2 | K111: 2020 | L111: =IF(Y111<>"",Y111,IF(AND(K111>=Hypothèses!$B$9,K111<=Hypothèses!$B$10),"actuel",IF(K111=2030,"2030",IF(K111=2050,"2050","autre")))) -> actuel | N111: non précisé (varie selon l'étude) | P111: Marché | Q111: USD2024 | R111: =INDEX(Hypothèses!$B$14:$B$22,MATCH(Q111,Hypothèses!$A$14:$A$22,0)) -> 1 | S111: =IF(G111="","",G111*R111) -> 3.502 | T111: =IF(H111="","",H111*R111) -> 5.15 | U111: =IF(I111="","",I111*R111) -> 6.798 | V111: USD 2024/kg H2 | W111: à vérifier | X111: Base Ghadim et al. 2025 (USD 2024, déjà corrigé de l'inflation). | AA111: =IF(AND(Hypothèses!$B$12=1,Z111="Secondary_Source"),0,1) -> 1
A112: D0111 | B112: Ghadim | C112: Actual LCOH | D112: Alcalin | E112: LCOH | F112: Observé | G112: 3.2754 | H112: 4.59895 | I112: 5.9225 | J112: USD 2024/kg H2 | K112: 2021 | L112: =IF(Y112<>"",Y112,IF(AND(K112>=Hypothèses!$B$9,K112<=Hypothèses!$B$10),"actuel",IF(K112=2030,"2030",IF(K112=2050,"2050","autre")))) -> actuel | N112: non précisé (varie selon l'étude) | P112: Marché | Q112: USD2024 | R112: =INDEX(Hypothèses!$B$14:$B$22,MATCH(Q112,Hypothèses!$A$14:$A$22,0)) -> 1 | S112: =IF(G112="","",G112*R112) -> 3.2754 | T112: =IF(H112="","",H112*R112) -> 4.59895 | U112: =IF(I112="","",I112*R112) -> 5.9225 | V112: USD 2024/kg H2 | W112: à vérifier | X112: Base Ghadim et al. 2025 (USD 2024, déjà corrigé de l'inflation). | AA112: =IF(AND(Hypothèses!$B$12=1,Z112="Secondary_Source"),0,1) -> 1
A113: D0112 | B113: Ghadim | C113: Actual LCOH | D113: Alcalin | E113: LCOH | F113: Observé | G113: 3.1003 | H113: 3.8728 | I113: 4.6453 | J113: USD 2024/kg H2 | K113: 2022 | L113: =IF(Y113<>"",Y113,IF(AND(K113>=Hypothèses!$B$9,K113<=Hypothèses!$B$10),"actuel",IF(K113=2030,"2030",IF(K113=2050,"2050","autre")))) -> actuel | N113: non précisé (varie selon l'étude) | P113: Marché | Q113: USD2024 | R113: =INDEX(Hypothèses!$B$14:$B$22,MATCH(Q113,Hypothèses!$A$14:$A$22,0)) -> 1 | S113: =IF(G113="","",G113*R113) -> 3.1003 | T113: =IF(H113="","",H113*R113) -> 3.8728 | U113: =IF(I113="","",I113*R113) -> 4.6453 | V113: USD 2024/kg H2 | W113: à vérifier | X113: Base Ghadim et al. 2025 (USD 2024, déjà corrigé de l'inflation). | AA113: =IF(AND(Hypothèses!$B$12=1,Z113="Secondary_Source"),0,1) -> 1
A114: D0113 | B114: Ghadim | C114: BNEF 2020 (China) | D114: Alcalin | E114: LCOH | F114: Projection | H114: 4.841 | J114: USD 2024/kg H2 | K114: 2019 | L114: =IF(Y114<>"",Y114,IF(AND(K114>=Hypothèses!$B$9,K114<=Hypothèses!$B$10),"actuel",IF(K114=2030,"2030",IF(K114=2050,"2050","autre")))) -> autre | N114: non précisé (varie selon l'étude) | P114: China | Q114: USD2024 | R114: =INDEX(Hypothèses!$B$14:$B$22,MATCH(Q114,Hypothèses!$A$14:$A$22,0)) -> 1 | S114: =IF(G114="","",G114*R114) | T114: =IF(H114="","",H114*R114) -> 4.841 | U114: =IF(I114="","",I114*R114) | V114: USD 2024/kg H2 | W114: à vérifier | X114: Base Ghadim et al. 2025 (USD 2024, déjà corrigé de l'inflation). | AA114: =IF(AND(Hypothèses!$B$12=1,Z114="Secondary_Source"),0,1) -> 1
A115: D0114 | B115: Ghadim | C115: BNEF 2020 (China) | D115: Alcalin | E115: LCOH | F115: Projection | H115: 2.0291 | J115: USD 2024/kg H2 | K115: 2030 | L115: =IF(Y115<>"",Y115,IF(AND(K115>=Hypothèses!$B$9,K115<=Hypothèses!$B$10),"actuel",IF(K115=2030,"2030",IF(K115=2050,"2050","autre")))) -> 2030 | N115: non précisé (varie selon l'étude) | P115: China | Q115: USD2024 | R115: =INDEX(Hypothèses!$B$14:$B$22,MATCH(Q115,Hypothèses!$A$14:$A$22,0)) -> 1 | S115: =IF(G115="","",G115*R115) | T115: =IF(H115="","",H115*R115) -> 2.0291 | U115: =IF(I115="","",I115*R115) | V115: USD 2024/kg H2 | W115: à vérifier | X115: Base Ghadim et al. 2025 (USD 2024, déjà corrigé de l'inflation). | AA115: =IF(AND(Hypothèses!$B$12=1,Z115="Secondary_Source"),0,1) -> 1
A116: D0115 | B116: Ghadim | C116: BNEF 2020 (China) | D116: Alcalin | E116: LCOH | F116: Projection | H116: 1.133 | J116: USD 2024/kg H2 | K116: 2050 | L116: =IF(Y116<>"",Y116,IF(AND(K116>=Hypothèses!$B$9,K116<=Hypothèses!$B$10),"actuel",IF(K116=2030,"2030",IF(K116=2050,"2050","autre")))) -> 2050 | N116: non précisé (varie selon l'étude) | P116: China | Q116: USD2024 | R116: =INDEX(Hypothèses!$B$14:$B$22,MATCH(Q116,Hypothèses!$A$14:$A$22,0)) -> 1 | S116: =IF(G116="","",G116*R116) | T116: =IF(H116="","",H116*R116) -> 1.133 | U116: =IF(I116="","",I116*R116) | V116: USD 2024/kg H2 | W116: à vérifier | X116: Base Ghadim et al. 2025 (USD 2024, déjà corrigé de l'inflation). | AA116: =IF(AND(Hypothèses!$B$12=1,Z116="Secondary_Source"),0,1) -> 1
A117: D0116 | B117: Ghadim | C117: DNV 2022 (World) | D117: Alcalin | E117: LCOH | F117: Projection | G117: 3.4114939 | H117: 5.1315733 | I117: 7.21 | J117: USD 2024/kg H2 | K117: 2020 | L117: =IF(Y117<>"",Y117,IF(AND(K117>=Hypothèses!$B$9,K117<=Hypothèses!$B$10),"actuel",IF(K117=2030,"2030",IF(K117=2050,"2050","autre")))) -> actuel | N117: non précisé (varie selon l'étude) | P117: World | Q117: USD2024 | R117: =INDEX(Hypothèses!$B$14:$B$22,MATCH(Q117,Hypothèses!$A$14:$A$22,0)) -> 1 | S117: =IF(G117="","",G117*R117) -> 3.4114939 | T117: =IF(H117="","",H117*R117) -> 5.1315733 | U117: =IF(I117="","",I117*R117) -> 7.21 | V117: USD 2024/kg H2 | W117: à vérifier | X117: Base Ghadim et al. 2025 (USD 2024, déjà corrigé de l'inflation). | AA117: =IF(AND(Hypothèses!$B$12=1,Z117="Secondary_Source"),0,1) -> 1
A118: D0117 | B118: Ghadim | C118: DNV 2022 (World) | D118: Alcalin | E118: LCOH | F118: Projection | G118: 1.734417 | H118: 2.4081091 | I118: 7.1096574 | J118: USD 2024/kg H2 | K118: 2030 | L118: =IF(Y118<>"",Y118,IF(AND(K118>=Hypothèses!$B$9,K118<=Hypothèses!$B$10),"actuel",IF(K118=2030,"2030",IF(K118=2050,"2050","autre")))) -> 2030 | N118: non précisé (varie selon l'étude) | P118: World | Q118: USD2024 | R118: =INDEX(Hypothèses!$B$14:$B$22,MATCH(Q118,Hypothèses!$A$14:$A$22,0)) -> 1 | S118: =IF(G118="","",G118*R118) -> 1.734417 | T118: =IF(H118="","",H118*R118) -> 2.4081091 | U118: =IF(I118="","",I118*R118) -> 7.1096574 | V118: USD 2024/kg H2 | W118: à vérifier | X118: Base Ghadim et al. 2025 (USD 2024, déjà corrigé de l'inflation). | AA118: =IF(AND(Hypothèses!$B$12=1,Z118="Secondary_Source"),0,1) -> 1
A119: D0118 | B119: Ghadim | C119: DNV 2022 (World) | D119: Alcalin | E119: LCOH | F119: Projection | G119: 1.3760594 | H119: 2.0640994 | I119: 6.1779503 | J119: USD 2024/kg H2 | K119: 2050 | L119: =IF(Y119<>"",Y119,IF(AND(K119>=Hypothèses!$B$9,K119<=Hypothèses!$B$10),"actuel",IF(K119=2030,"2030",IF(K119=2050,"2050","autre")))) -> 2050 | N119: non précisé (varie selon l'étude) | P119: World | Q119: USD2024 | R119: =INDEX(Hypothèses!$B$14:$B$22,MATCH(Q119,Hypothèses!$A$14:$A$22,0)) -> 1 | S119: =IF(G119="","",G119*R119) -> 1.3760594 | T119: =IF(H119="","",H119*R119) -> 2.0640994 | U119: =IF(I119="","",I119*R119) -> 6.1779503 | V119: USD 2024/kg H2 | W119: à vérifier | X119: Base Ghadim et al. 2025 (USD 2024, déjà corrigé de l'inflation). | AA119: =IF(AND(Hypothèses!$B$12=1,Z119="Secondary_Source"),0,1) -> 1
A120: D0119 | B120: Ghadim | C120: Gandhi et al 2022 (UAE) | D120: Alcalin | E120: LCOH | F120: Projection | H120: 3.798637 | J120: USD 2024/kg H2 | K120: 2020 | L120: =IF(Y120<>"",Y120,IF(AND(K120>=Hypothèses!$B$9,K120<=Hypothèses!$B$10),"actuel",IF(K120=2030,"2030",IF(K120=2050,"2050","autre")))) -> actuel | N120: non précisé (varie selon l'étude) | P120: UAE | Q120: USD2024 | R120: =INDEX(Hypothèses!$B$14:$B$22,MATCH(Q120,Hypothèses!$A$14:$A$22,0)) -> 1 | S120: =IF(G120="","",G120*R120) | T120: =IF(H120="","",H120*R120) -> 3.798637 | U120: =IF(I120="","",I120*R120) | V120: USD 2024/kg H2 | W120: à vérifier | X120: Base Ghadim et al. 2025 (USD 2024, déjà corrigé de l'inflation). | AA120: =IF(AND(Hypothèses!$B$12=1,Z120="Secondary_Source"),0,1) -> 1
A121: D0120 | B121: Ghadim | C121: Gandhi et al 2022 (UAE) | D121: Alcalin | E121: LCOH | F121: Projection | H121: 1.7426383 | J121: USD 2024/kg H2 | K121: 2025 | L121: =IF(Y121<>"",Y121,IF(AND(K121>=Hypothèses!$B$9,K121<=Hypothèses!$B$10),"actuel",IF(K121=2030,"2030",IF(K121=2050,"2050","autre")))) -> actuel | N121: non précisé (varie selon l'étude) | P121: UAE | Q121: USD2024 | R121: =INDEX(Hypothèses!$B$14:$B$22,MATCH(Q121,Hypothèses!$A$14:$A$22,0)) -> 1 | S121: =IF(G121="","",G121*R121) | T121: =IF(H121="","",H121*R121) -> 1.7426383 | U121: =IF(I121="","",I121*R121) | V121: USD 2024/kg H2 | W121: à vérifier | X121: Base Ghadim et al. 2025 (USD 2024, déjà corrigé de l'inflation). | AA121: =IF(AND(Hypothèses!$B$12=1,Z121="Secondary_Source"),0,1) -> 1
A122: D0121 | B122: Ghadim | C122: Gandhi et al 2022 (UAE) | D122: Alcalin | E122: LCOH | F122: Projection | H122: 1.164704 | J122: USD 2024/kg H2 | K122: 2030 | L122: =IF(Y122<>"",Y122,IF(AND(K122>=Hypothèses!$B$9,K122<=Hypothèses!$B$10),"actuel",IF(K122=2030,"2030",IF(K122=2050,"2050","autre")))) -> 2030 | N122: non précisé (varie selon l'étude) | P122: UAE | Q122: USD2024 | R122: =INDEX(Hypothèses!$B$14:$B$22,MATCH(Q122,Hypothèses!$A$14:$A$22,0)) -> 1 | S122: =IF(G122="","",G122*R122) | T122: =IF(H122="","",H122*R122) -> 1.164704 | U122: =IF(I122="","",I122*R122) | V122: USD 2024/kg H2 | W122: à vérifier | X122: Base Ghadim et al. 2025 (USD 2024, déjà corrigé de l'inflation). | AA122: =IF(AND(Hypothèses!$B$12=1,Z122="Secondary_Source"),0,1) -> 1
...

Sheet Synthèse
A1: Synthèse CAPEX et rendement par technologie et horizon
A2: CAPEX en USD 2024/kW (conversion : onglet Hypothèses) ; rendement en % base PCI. Statistiques sur les valeurs typiques (moyenne de chaque étude). « Bornes études » = plus petit min et plus grand max publiés par les études qui donnent une fourchette.
A4: Technologie | B4: Horizon | C4: CAPEX Nb valeurs | D4: CAPEX Nb sources | E4: CAPEX Min | F4: CAPEX Médiane | G4: CAPEX Max | H4: CAPEX Borne basse études | I4: CAPEX Borne haute études | J4: Rendement Nb valeurs | K4: Rendement Nb sources | L4: Rendement Min | M4: Rendement Médiane | N4: Rendement Max
A5: Alcalin | B5: actuel | C5: =SUMPRODUCT((Données!$D$2:$D$800=$A5)*(Données!$E$2:$E$800="CAPEX")*(Données!$L$2:$L$800=$B5)*ISNUMBER(Données!$T$2:$T$800)*(Données!$AA$2:$AA$800=1)) -> 50 | D5: =SUMPRODUCT(((Données!$D$2:$D$800=$A5)*(Données!$E$2:$E$800="CAPEX")*(Données!$L$2:$L$800=$B5)*ISNUMBER(Données!$T$2:$T$800)*(Données!$AA$2:$AA$800=1))/(COUNTIFS(Données!$C$2:$C$800,Données!$C$2:$C$800,Données!$D$2:$D$800,Données!$D$2:$D$800,Données!$E$2:$E$800,Données!$E$2:$E$800,Données!$L$2:$L$800,Données!$L$2:$L$800,Données!$AA$2:$AA$800,Données!$AA$2:$AA$800)+(Données!$C$2:$C$800=""))) -> 29 | E5: {=IF(C5=0,"—",MIN(IF((Données!$D$2:$D$800=$A5)*(Données!$E$2:$E$800="CAPEX")*(Données!$L$2:$L$800=$B5)*ISNUMBER(Données!$T$2:$T$800)*(Données!$AA$2:$AA$800=1),Données!$T$2:$T$800)))} -> 206 | F5: {=IF(C5=0,"—",MEDIAN(IF((Données!$D$2:$D$800=$A5)*(Données!$E$2:$E$800="CAPEX")*(Données!$L$2:$L$800=$B5)*ISNUMBER(Données!$T$2:$T$800)*(Données!$AA$2:$AA$800=1),Données!$T$2:$T$800)))} -> 996.66982 | G5: {=IF(C5=0,"—",MAX(IF((Données!$D$2:$D$800=$A5)*(Données!$E$2:$E$800="CAPEX")*(Données!$L$2:$L$800=$B5)*ISNUMBER(Données!$T$2:$T$800)*(Données!$AA$2:$AA$800=1),Données!$T$2:$T$800)))} -> 2146.12 | H5: {=IF(SUMPRODUCT((Données!$D$2:$D$800=$A5)*(Données!$E$2:$E$800="CAPEX")*(Données!$L$2:$L$800=$B5)*ISNUMBER(Données!$S$2:$S$800)*(Données!$AA$2:$AA$800=1))=0,"—",MIN(IF((Données!$D$2:$D$800=$A5)*(Données!$E$2:$E$800="CAPEX")*(Données!$L$2:$L$800=$B5)*ISNUMBER(Données!$S$2:$S$800)*(Données!$AA$2:$AA$800=1),Données!$S$2:$S$800)))} -> 352.26 | I5: {=IF(SUMPRODUCT((Données!$D$2:$D$800=$A5)*(Données!$E$2:$E$800="CAPEX")*(Données!$L$2:$L$800=$B5)*ISNUMBER(Données!$U$2:$U$800)*(Données!$AA$2:$AA$800=1))=0,"—",MAX(IF((Données!$D$2:$D$800=$A5)*(Données!$E$2:$E$800="CAPEX")*(Données!$L$2:$L$800=$B5)*ISNUMBER(Données!$U$2:$U$800)*(Données!$AA$2:$AA$800=1),Données!$U$2:$U$800)))} -> 2457 | J5: =SUMPRODUCT((Données!$D$2:$D$800=$A5)*(Données!$E$2:$E$800="Rendement (PCI)")*(Données!$L$2:$L$800=$B5)*ISNUMBER(Données!$T$2:$T$800)*(Données!$AA$2:$AA$800=1)) -> 10 | K5: =SUMPRODUCT(((Données!$D$2:$D$800=$A5)*(Données!$E$2:$E$800="Rendement (PCI)")*(Données!$L$2:$L$800=$B5)*ISNUMBER(Données!$T$2:$T$800)*(Données!$AA$2:$AA$800=1))/(COUNTIFS(Données!$C$2:$C$800,Données!$C$2:$C$800,Données!$D$2:$D$800,Données!$D$2:$D$800,Données!$E$2:$E$800,Données!$E$2:$E$800,Données!$L$2:$L$800,Données!$L$2:$L$800,Données!$AA$2:$AA$800,Données!$AA$2:$AA$800)+(Données!$C$2:$C$800=""))) -> 7 | L5: {=IF(J5=0,"—",MIN(IF((Données!$D$2:$D$800=$A5)*(Données!$E$2:$E$800="Rendement (PCI)")*(Données!$L$2:$L$800=$B5)*ISNUMBER(Données!$T$2:$T$800)*(Données!$AA$2:$AA$800=1),Données!$T$2:$T$800)))} -> 57 | M5: {=IF(J5=0,"—",MEDIAN(IF((Données!$D$2:$D$800=$A5)*(Données!$E$2:$E$800="Rendement (PCI)")*(Données!$L$2:$L$800=$B5)*ISNUMBER(Données!$T$2:$T$800)*(Données!$AA$2:$AA$800=1),Données!$T$2:$T$800)))} -> 61 | N5: {=IF(J5=0,"—",MAX(IF((Données!$D$2:$D$800=$A5)*(Données!$E$2:$E$800="Rendement (PCI)")*(Données!$L$2:$L$800=$B5)*ISNUMBER(Données!$T$2:$T$800)*(Données!$AA$2:$AA$800=1),Données!$T$2:$T$800)))} -> 70
A6: Alcalin | B6: 2030 | C6: =SUMPRODUCT((Données!$D$2:$D$800=$A6)*(Données!$E$2:$E$800="CAPEX")*(Données!$L$2:$L$800=$B6)*ISNUMBER(Données!$T$2:$T$800)*(Données!$AA$2:$AA$800=1)) -> 19 | D6: =SUMPRODUCT(((Données!$D$2:$D$800=$A6)*(Données!$E$2:$E$800="CAPEX")*(Données!$L$2:$L$800=$B6)*ISNUMBER(Données!$T$2:$T$800)*(Données!$AA$2:$AA$800=1))/(COUNTIFS(Données!$C$2:$C$800,Données!$C$2:$C$800,Données!$D$2:$D$800,Données!$D$2:$D$800,Données!$E$2:$E$800,Données!$E$2:$E$800,Données!$L$2:$L$800,Données!$L$2:$L$800,Données!$AA$2:$AA$800,Données!$AA$2:$AA$800)+(Données!$C$2:$C$800=""))) -> 19 | E6: {=IF(C6=0,"—",MIN(IF((Données!$D$2:$D$800=$A6)*(Données!$E$2:$E$800="CAPEX")*(Données!$L$2:$L$800=$B6)*ISNUMBER(Données!$T$2:$T$800)*(Données!$AA$2:$AA$800=1),Données!$T$2:$T$800)))} -> 128.75 | F6: {=IF(C6=0,"—",MEDIAN(IF((Données!$D$2:$D$800=$A6)*(Données!$E$2:$E$800="CAPEX")*(Données!$L$2:$L$800=$B6)*ISNUMBER(Données!$T$2:$T$800)*(Données!$AA$2:$AA$800=1),Données!$T$2:$T$800)))} -> 594.23077 | G6: {=IF(C6=0,"—",MAX(IF((Données!$D$2:$D$800=$A6)*(Données!$E$2:$E$800="CAPEX")*(Données!$L$2:$L$800=$B6)*ISNUMBER(Données!$T$2:$T$800)*(Données!$AA$2:$AA$800=1),Données!$T$2:$T$800)))} -> 999.768 | H6: {=IF(SUMPRODUCT((Données!$D$2:$D$800=$A6)*(Données!$E$2:$E$800="CAPEX")*(Données!$L$2:$L$800=$B6)*ISNUMBER(Données!$S$2:$S$800)*(Données!$AA$2:$AA$800=1))=0,"—",MIN(IF((Données!$D$2:$D$800=$A6)*(Données!$E$2:$E$800="CAPEX")*(Données!$L$2:$L$800=$B6)*ISNUMBER(Données!$S$2:$S$800)*(Données!$AA$2:$AA$800=1),Données!$S$2:$S$800)))} -> 196.73 | I6: {=IF(SUMPRODUCT((Données!$D$2:$D$800=$A6)*(Données!$E$2:$E$800="CAPEX")*(Données!$L$2:$L$800=$B6)*ISNUMBER(Données!$U$2:$U$800)*(Données!$AA$2:$AA$800=1))=0,"—",MAX(IF((Données!$D$2:$D$800=$A6)*(Données!$E$2:$E$800="CAPEX")*(Données!$L$2:$L$800=$B6)*ISNUMBER(Données!$U$2:$U$800)*(Données!$AA$2:$AA$800=1),Données!$U$2:$U$800)))} -> 1141.3383 | J6: =SUMPRODUCT((Données!$D$2:$D$800=$A6)*(Données!$E$2:$E$800="Rendement (PCI)")*(Données!$L$2:$L$800=$B6)*ISNUMBER(Données!$T$2:$T$800)*(Données!$AA$2:$AA$800=1)) -> 4 | K6: =SUMPRODUCT(((Données!$D$2:$D$800=$A6)*(Données!$E$2:$E$800="Rendement (PCI)")*(Données!$L$2:$L$800=$B6)*ISNUMBER(Données!$T$2:$T$800)*(Données!$AA$2:$AA$800=1))/(COUNTIFS(Données!$C$2:$C$800,Données!$C$2:$C$800,Données!$D$2:$D$800,Données!$D$2:$D$800,Données!$E$2:$E$800,Données!$E$2:$E$800,Données!$L$2:$L$800,Données!$L$2:$L$800,Données!$AA$2:$AA$800,Données!$AA$2:$AA$800)+(Données!$C$2:$C$800=""))) -> 4 | L6: {=IF(J6=0,"—",MIN(IF((Données!$D$2:$D$800=$A6)*(Données!$E$2:$E$800="Rendement (PCI)")*(Données!$L$2:$L$800=$B6)*ISNUMBER(Données!$T$2:$T$800)*(Données!$AA$2:$AA$800=1),Données!$T$2:$T$800)))} -> 61 | M6: {=IF(J6=0,"—",MEDIAN(IF((Données!$D$2:$D$800=$A6)*(Données!$E$2:$E$800="Rendement (PCI)")*(Données!$L$2:$L$800=$B6)*ISNUMBER(Données!$T$2:$T$800)*(Données!$AA$2:$AA$800=1),Données!$T$2:$T$800)))} -> 65.75 | N6: {=IF(J6=0,"—",MAX(IF((Données!$D$2:$D$800=$A6)*(Données!$E$2:$E$800="Rendement (PCI)")*(Données!$L$2:$L$800=$B6)*ISNUMBER(Données!$T$2:$T$800)*(Données!$AA$2:$AA$800=1),Données!$T$2:$T$800)))} -> 75
A7: Alcalin | B7: 2050 | C7: =SUMPRODUCT((Données!$D$2:$D$800=$A7)*(Données!$E$2:$E$800="CAPEX")*(Données!$L$2:$L$800=$B7)*ISNUMBER(Données!$T$2:$T$800)*(Données!$AA$2:$AA$800=1)) -> 17 | D7: =SUMPRODUCT(((Données!$D$2:$D$800=$A7)*(Données!$E$2:$E$800="CAPEX")*(Données!$L$2:$L$800=$B7)*ISNUMBER(Données!$T$2:$T$800)*(Données!$AA$2:$AA$800=1))/(COUNTIFS(Données!$C$2:$C$800,Données!$C$2:$C$800,Données!$D$2:$D$800,Données!$D$2:$D$800,Données!$E$2:$E$800,Données!$E$2:$E$800,Données!$L$2:$L$800,Données!$L$2:$L$800,Données!$AA$2:$AA$800,Données!$AA$2:$AA$800)+(Données!$C$2:$C$800=""))) -> 17 | E7: {=IF(C7=0,"—",MIN(IF((Données!$D$2:$D$800=$A7)*(Données!$E$2:$E$800="CAPEX")*(Données!$L$2:$L$800=$B7)*ISNUMBER(Données!$T$2:$T$800)*(Données!$AA$2:$AA$800=1),Données!$T$2:$T$800)))} -> 79.230769 | F7: {=IF(C7=0,"—",MEDIAN(IF((Données!$D$2:$D$800=$A7)*(Données!$E$2:$E$800="CAPEX")*(Données!$L$2:$L$800=$B7)*ISNUMBER(Données!$T$2:$T$800)*(Données!$AA$2:$AA$800=1),Données!$T$2:$T$800)))} -> 368.85845 | G7: {=IF(C7=0,"—",MAX(IF((Données!$D$2:$D$800=$A7)*(Données!$E$2:$E$800="CAPEX")*(Données!$L$2:$L$800=$B7)*ISNUMBER(Données!$T$2:$T$800)*(Données!$AA$2:$AA$800=1),Données!$T$2:$T$800)))} -> 840.67072 | H7: {=IF(SUMPRODUCT((Données!$D$2:$D$800=$A7)*(Données!$E$2:$E$800="CAPEX")*(Données!$L$2:$L$800=$B7)*ISNUMBER(Données!$S$2:$S$800)*(Données!$AA$2:$AA$800=1))=0,"—",MIN(IF((Données!$D$2:$D$800=$A7)*(Données!$E$2:$E$800="CAPEX")*(Données!$L$2:$L$800=$B7)*ISNUMBER(Données!$S$2:$S$800)*(Données!$AA$2:$AA$800=1),Données!$S$2:$S$800)))} -> 76.22 | I7: {=IF(SUMPRODUCT((Données!$D$2:$D$800=$A7)*(Données!$E$2:$E$800="CAPEX")*(Données!$L$2:$L$800=$B7)*ISNUMBER(Données!$U$2:$U$800)*(Données!$AA$2:$AA$800=1))=0,"—",MAX(IF((Données!$D$2:$D$800=$A7)*(Données!$E$2:$E$800="CAPEX")*(Données!$L$2:$L$800=$B7)*ISNUMBER(Données!$U$2:$U$800)*(Données!$AA$2:$AA$800=1),Données!$U$2:$U$800)))} -> 1024.8757 | J7: =SUMPRODUCT((Données!$D$2:$D$800=$A7)*(Données!$E$2:$E$800="Rendement (PCI)")*(Données!$L$2:$L$800=$B7)*ISNUMBER(Données!$T$2:$T$800)*(Données!$AA$2:$AA$800=1)) -> 3 | K7: =SUMPRODUCT(((Données!$D$2:$D$800=$A7)*(Données!$E$2:$E$800="Rendement (PCI)")*(Données!$L$2:$L$800=$B7)*ISNUMBER(Données!$T$2:$T$800)*(Données!$AA$2:$AA$800=1))/(COUNTIFS(Données!$C$2:$C$800,Données!$C$2:$C$800,Données!$D$2:$D$800,Données!$D$2:$D$800,Données!$E$2:$E$800,Données!$E$2:$E$800,Données!$L$2:$L$800,Données!$L$2:$L$800,Données!$AA$2:$AA$800,Données!$AA$2:$AA$800)+(Données!$C$2:$C$800=""))) -> 3 | L7: {=IF(J7=0,"—",MIN(IF((Données!$D$2:$D$800=$A7)*(Données!$E$2:$E$800="Rendement (PCI)")*(Données!$L$2:$L$800=$B7)*ISNUMBER(Données!$T$2:$T$800)*(Données!$AA$2:$AA$800=1),Données!$T$2:$T$800)))} -> 61 | M7: {=IF(J7=0,"—",MEDIAN(IF((Données!$D$2:$D$800=$A7)*(Données!$E$2:$E$800="Rendement (PCI)")*(Données!$L$2:$L$800=$B7)*ISNUMBER(Données!$T$2:$T$800)*(Données!$AA$2:$AA$800=1),Données!$T$2:$T$800)))} -> 61 | N7: {=IF(J7=0,"—",MAX(IF((Données!$D$2:$D$800=$A7)*(Données!$E$2:$E$800="Rendement (PCI)")*(Données!$L$2:$L$800=$B7)*ISNUMBER(Données!$T$2:$T$800)*(Données!$AA$2:$AA$800=1),Données!$T$2:$T$800)))} -> 72.2
A8: PEM | B8: actuel | C8: =SUMPRODUCT((Données!$D$2:$D$800=$A8)*(Données!$E$2:$E$800="CAPEX")*(Données!$L$2:$L$800=$B8)*ISNUMBER(Données!$T$2:$T$800)*(Données!$AA$2:$AA$800=1)) -> 64 | D8: =SUMPRODUCT(((Données!$D$2:$D$800=$A8)*(Données!$E$2:$E$800="CAPEX")*(Données!$L$2:$L$800=$B8)*ISNUMBER(Données!$T$2:$T$800)*(Données!$AA$2:$AA$800=1))/(COUNTIFS(Données!$C$2:$C$800,Données!$C$2:$C$800,Données!$D$2:$D$800,Données!$D$2:$D$800,Données!$E$2:$E$800,Données!$E$2:$E$800,Données!$L$2:$L$800,Données!$L$2:$L$800,Données!$AA$2:$AA$800,Données!$AA$2:$AA$800)+(Données!$C$2:$C$800=""))) -> 32 | E8: {=IF(C8=0,"—",MIN(IF((Données!$D$2:$D$800=$A8)*(Données!$E$2:$E$800="CAPEX")*(Données!$L$2:$L$800=$B8)*ISNUMBER(Données!$T$2:$T$800)*(Données!$AA$2:$AA$800=1),Données!$T$2:$T$800)))} -> 555.71075 | F8: {=IF(C8=0,"—",MEDIAN(IF((Données!$D$2:$D$800=$A8)*(Données!$E$2:$E$800="CAPEX")*(Données!$L$2:$L$800=$B8)*ISNUMBER(Données!$T$2:$T$800)*(Données!$AA$2:$AA$800=1),Données!$T$2:$T$800)))} -> 1338.8537 | G8: {=IF(C8=0,"—",MAX(IF((Données!$D$2:$D$800=$A8)*(Données!$E$2:$E$800="CAPEX")*(Données!$L$2:$L$800=$B8)*ISNUMBER(Données!$T$2:$T$800)*(Données!$AA$2:$AA$800=1),Données!$T$2:$T$800)))} -> 2837.004 | H8: {=IF(SUMPRODUCT((Données!$D$2:$D$800=$A8)*(Données!$E$2:$E$800="CAPEX")*(Données!$L$2:$L$800=$B8)*ISNUMBER(Données!$S$2:$S$800)*(Données!$AA$2:$AA$800=1))=0,"—",MIN(IF((Données!$D$2:$D$800=$A8)*(Données!$E$2:$E$800="CAPEX")*(Données!$L$2:$L$800=$B8)*ISNUMBER(Données!$S$2:$S$800)*(Données!$AA$2:$AA$800=1),Données!$S$2:$S$800)))} -> 357.72791 | I8: {=IF(SUMPRODUCT((Données!$D$2:$D$800=$A8)*(Données!$E$2:$E$800="CAPEX")*(Données!$L$2:$L$800=$B8)*ISNUMBER(Données!$U$2:$U$800)*(Données!$AA$2:$AA$800=1))=0,"—",MAX(IF((Données!$D$2:$D$800=$A8)*(Données!$E$2:$E$800="CAPEX")*(Données!$L$2:$L$800=$B8)*ISNUMBER(Données!$U$2:$U$800)*(Données!$AA$2:$AA$800=1),Données!$U$2:$U$800)))} -> 2769.876 | J8: =SUMPRODUCT((Données!$D$2:$D$800=$A8)*(Données!$E$2:$E$800="Rendement (PCI)")*(Données!$L$2:$L$800=$B8)*ISNUMBER(Données!$T$2:$T$800)*(Données!$AA$2:$AA$800=1)) -> 8 | K8: =SUMPRODUCT(((Données!$D$2:$D$800=$A8)*(Données!$E$2:$E$800="Rendement (PCI)")*(Données!$L$2:$L$800=$B8)*ISNUMBER(Données!$T$2:$T$800)*(Données!$AA$2:$AA$800=1))/(COUNTIFS(Données!$C$2:$C$800,Données!$C$2:$C$800,Données!$D$2:$D$800,Données!$D$2:$D$800,Données!$E$2:$E$800,Données!$E$2:$E$800,Données!$L$2:$L$800,Données!$L$2:$L$800,Données!$AA$2:$AA$800,Données!$AA$2:$AA$800)+(Données!$C$2:$C$800=""))) -> 7 | L8: {=IF(J8=0,"—",MIN(IF((Données!$D$2:$D$800=$A8)*(Données!$E$2:$E$800="Rendement (PCI)")*(Données!$L$2:$L$800=$B8)*ISNUMBER(Données!$T$2:$T$800)*(Données!$AA$2:$AA$800=1),Données!$T$2:$T$800)))} -> 54 | M8: {=IF(J8=0,"—",MEDIAN(IF((Données!$D$2:$D$800=$A8)*(Données!$E$2:$E$800="Rendement (PCI)")*(Données!$L$2:$L$800=$B8)*ISNUMBER(Données!$T$2:$T$800)*(Données!$AA$2:$AA$800=1),Données!$T$2:$T$800)))} -> 63.15 | N8: {=IF(J8=0,"—",MAX(IF((Données!$D$2:$D$800=$A8)*(Données!$E$2:$E$800="Rendement (PCI)")*(Données!$L$2:$L$800=$B8)*ISNUMBER(Données!$T$2:$T$800)*(Données!$AA$2:$AA$800=1),Données!$T$2:$T$800)))} -> 67
A9: PEM | B9: 2030 | C9: =SUMPRODUCT((Données!$D$2:$D$800=$A9)*(Données!$E$2:$E$800="CAPEX")*(Données!$L$2:$L$800=$B9)*ISNUMBER(Données!$T$2:$T$800)*(Données!$AA$2:$AA$800=1)) -> 22 | D9: =SUMPRODUCT(((Données!$D$2:$D$800=$A9)*(Données!$E$2:$E$800="CAPEX")*(Données!$L$2:$L$800=$B9)*ISNUMBER(Données!$T$2:$T$800)*(Données!$AA$2:$AA$800=1))/(COUNTIFS(Données!$C$2:$C$800,Données!$C$2:$C$800,Données!$D$2:$D$800,Données!$D$2:$D$800,Données!$E$2:$E$800,Données!$E$2:$E$800,Données!$L$2:$L$800,Données!$L$2:$L$800,Données!$AA$2:$AA$800,Données!$AA$2:$AA$800)+(Données!$C$2:$C$800=""))) -> 22 | E9: {=IF(C9=0,"—",MIN(IF((Données!$D$2:$D$800=$A9)*(Données!$E$2:$E$800="CAPEX")*(Données!$L$2:$L$800=$B9)*ISNUMBER(Données!$T$2:$T$800)*(Données!$AA$2:$AA$800=1),Données!$T$2:$T$800)))} -> 361.12691 | F9: {=IF(C9=0,"—",MEDIAN(IF((Données!$D$2:$D$800=$A9)*(Données!$E$2:$E$800="CAPEX")*(Données!$L$2:$L$800=$B9)*ISNUMBER(Données!$T$2:$T$800)*(Données!$AA$2:$AA$800=1),Données!$T$2:$T$800)))} -> 703.6514 | G9: {=IF(C9=0,"—",MAX(IF((Données!$D$2:$D$800=$A9)*(Données!$E$2:$E$800="CAPEX")*(Données!$L$2:$L$800=$B9)*ISNUMBER(Données!$T$2:$T$800)*(Données!$AA$2:$AA$800=1),Données!$T$2:$T$800)))} -> 1294.9376 | H9: {=IF(SUMPRODUCT((Données!$D$2:$D$800=$A9)*(Données!$E$2:$E$800="CAPEX")*(Données!$L$2:$L$800=$B9)*ISNUMBER(Données!$S$2:$S$800)*(Données!$AA$2:$AA$800=1))=0,"—",MIN(IF((Données!$D$2:$D$800=$A9)*(Données!$E$2:$E$800="CAPEX")*(Données!$L$2:$L$800=$B9)*ISNUMBER(Données!$S$2:$S$800)*(Données!$AA$2:$AA$800=1),Données!$S$2:$S$800)))} -> 197.13309 | I9: {=IF(SUMPRODUCT((Données!$D$2:$D$800=$A9)*(Données!$E$2:$E$800="CAPEX")*(Données!$L$2:$L$800=$B9)*ISNUMBER(Données!$U$2:$U$800)*(Données!$AA$2:$AA$800=1))=0,"—",MAX(IF((Données!$D$2:$D$800=$A9)*(Données!$E$2:$E$800="CAPEX")*(Données!$L$2:$L$800=$B9)*ISNUMBER(Données!$U$2:$U$800)*(Données!$AA$2:$AA$800=1),Données!$U$2:$U$800)))} -> 1405.95 | J9: =SUMPRODUCT((Données!$D$2:$D$800=$A9)*(Données!$E$2:$E$800="Rendement (PCI)")*(Données!$L$2:$L$800=$B9)*ISNUMBER(Données!$T$2:$T$800)*(Données!$AA$2:$AA$800=1)) -> 3 | K9: =SUMPRODUCT(((Données!$D$2:$D$800=$A9)*(Données!$E$2:$E$800="Rendement (PCI)")*(Données!$L$2:$L$800=$B9)*ISNUMBER(Données!$T$2:$T$800)*(Données!$AA$2:$AA$800=1))/(COUNTIFS(Données!$C$2:$C$800,Données!$C$2:$C$800,Données!$D$2:$D$800,Données!$D$2:$D$800,Données!$E$2:$E$800,Données!$E$2:$E$800,Données!$L$2:$L$800,Données!$L$2:$L$800,Données!$AA$2:$AA$800,Données!$AA$2:$AA$800)+(Données!$C$2:$C$800=""))) -> 3 | L9: {=IF(J9=0,"—",MIN(IF((Données!$D$2:$D$800=$A9)*(Données!$E$2:$E$800="Rendement (PCI)")*(Données!$L$2:$L$800=$B9)*ISNUMBER(Données!$T$2:$T$800)*(Données!$AA$2:$AA$800=1),Données!$T$2:$T$800)))} -> 65.5 | M9: {=IF(J9=0,"—",MEDIAN(IF((Données!$D$2:$D$800=$A9)*(Données!$E$2:$E$800="Rendement (PCI)")*(Données!$L$2:$L$800=$B9)*ISNUMBER(Données!$T$2:$T$800)*(Données!$AA$2:$AA$800=1),Données!$T$2:$T$800)))} -> 69 | N9: {=IF(J9=0,"—",MAX(IF((Données!$D$2:$D$800=$A9)*(Données!$E$2:$E$800="Rendement (PCI)")*(Données!$L$2:$L$800=$B9)*ISNUMBER(Données!$T$2:$T$800)*(Données!$AA$2:$AA$800=1),Données!$T$2:$T$800)))} -> 72
A10: PEM | B10: 2050 | C10: =SUMPRODUCT((Données!$D$2:$D$800=$A10)*(Données!$E$2:$E$800="CAPEX")*(Données!$L$2:$L$800=$B10)*ISNUMBER(Données!$T$2:$T$800)*(Données!$AA$2:$AA$800=1)) -> 18 | D10: =SUMPRODUCT(((Données!$D$2:$D$800=$A10)*(Données!$E$2:$E$800="CAPEX")*(Données!$L$2:$L$800=$B10)*ISNUMBER(Données!$T$2:$T$800)*(Données!$AA$2:$AA$800=1))/(COUNTIFS(Données!$C$2:$C$800,Données!$C$2:$C$800,Données!$D$2:$D$800,Données!$D$2:$D$800,Données!$E$2:$E$800,Données!$E$2:$E$800,Données!$L$2:$L$800,Données!$L$2:$L$800,Données!$AA$2:$AA$800,Données!$AA$2:$AA$800)+(Données!$C$2:$C$800=""))) -> 18 | E10: {=IF(C10=0,"—",MIN(IF((Données!$D$2:$D$800=$A10)*(Données!$E$2:$E$800="CAPEX")*(Données!$L$2:$L$800=$B10)*ISNUMBER(Données!$T$2:$T$800)*(Données!$AA$2:$AA$800=1),Données!$T$2:$T$800)))} -> 154.5 | F10: {=IF(C10=0,"—",MEDIAN(IF((Données!$D$2:$D$800=$A10)*(Données!$E$2:$E$800="CAPEX")*(Données!$L$2:$L$800=$B10)*ISNUMBER(Données!$T$2:$T$800)*(Données!$AA$2:$AA$800=1),Données!$T$2:$T$800)))} -> 351.115 | G10: {=IF(C10=0,"—",MAX(IF((Données!$D$2:$D$800=$A10)*(Données!$E$2:$E$800="CAPEX")*(Données!$L$2:$L$800=$B10)*ISNUMBER(Données!$T$2:$T$800)*(Données!$AA$2:$AA$800=1),Données!$T$2:$T$800)))} -> 731.01366 | H10: {=IF(SUMPRODUCT((Données!$D$2:$D$800=$A10)*(Données!$E$2:$E$800="CAPEX")*(Données!$L$2:$L$800=$B10)*ISNUMBER(Données!$S$2:$S$800)*(Données!$AA$2:$AA$800=1))=0,"—",MIN(IF((Données!$D$2:$D$800=$A10)*(Données!$E$2:$E$800="CAPEX")*(Données!$L$2:$L$800=$B10)*ISNUMBER(Données!$S$2:$S$800)*(Données!$AA$2:$AA$800=1),Données!$S$2:$S$800)))} -> 56.080925 | I10: {=IF(SUMPRODUCT((Données!$D$2:$D$800=$A10)*(Données!$E$2:$E$800="CAPEX")*(Données!$L$2:$L$800=$B10)*ISNUMBER(Données!$U$2:$U$800)*(Données!$AA$2:$AA$800=1))=0,"—",MAX(IF((Données!$D$2:$D$800=$A10)*(Données!$E$2:$E$800="CAPEX")*(Données!$L$2:$L$800=$B10)*ISNUMBER(Données!$U$2:$U$800)*(Données!$AA$2:$AA$800=1),Données!$U$2:$U$800)))} -> 1031.4317 | J10: =SUMPRODUCT((Données!$D$2:$D$800=$A10)*(Données!$E$2:$E$800="Rendement (PCI)")*(Données!$L$2:$L$800=$B10)*ISNUMBER(Données!$T$2:$T$800)*(Données!$AA$2:$AA$800=1)) -> 2 | K10: =SUMPRODUCT(((Données!$D$2:$D$800=$A10)*(Données!$E$2:$E$800="Rendement (PCI)")*(Données!$L$2:$L$800=$B10)*ISNUMBER(Données!$T$2:$T$800)*(Données!$AA$2:$AA$800=1))/(COUNTIFS(Données!$C$2:$C$800,Données!$C$2:$C$800,Données!$D$2:$D$800,Données!$D$2:$D$800,Données!$E$2:$E$800,Données!$E$2:$E$800,Données!$L$2:$L$800,Données!$L$2:$L$800,Données!$AA$2:$AA$800,Données!$AA$2:$AA$800)+(Données!$C$2:$C$800=""))) -> 2 | L10: {=IF(J10=0,"—",MIN(IF((Données!$D$2:$D$800=$A10)*(Données!$E$2:$E$800="Rendement (PCI)")*(Données!$L$2:$L$800=$B10)*ISNUMBER(Données!$T$2:$T$800)*(Données!$AA$2:$AA$800=1),Données!$T$2:$T$800)))} -> 70 | M10: {=IF(J10=0,"—",MEDIAN(IF((Données!$D$2:$D$800=$A10)*(Données!$E$2:$E$800="Rendement (PCI)")*(Données!$L$2:$L$800=$B10)*ISNUMBER(Données!$T$2:$T$800)*(Données!$AA$2:$AA$800=1),Données!$T$2:$T$800)))} -> 71.1 | N10: {=IF(J10=0,"—",MAX(IF((Données!$D$2:$D$800=$A10)*(Données!$E$2:$E$800="Rendement (PCI)")*(Données!$L$2:$L$800=$B10)*ISNUMBER(Données!$T$2:$T$800)*(Données!$AA$2:$AA$800=1),Données!$T$2:$T$800)))} -> 72.2
A11: SOEC | B11: actuel | C11: =SUMPRODUCT((Données!$D$2:$D$800=$A11)*(Données!$E$2:$E$800="CAPEX")*(Données!$L$2:$L$800=$B11)*ISNUMBER(Données!$T$2:$T$800)*(Données!$AA$2:$AA$800=1)) -> 3 | D11: =SUMPRODUCT(((Données!$D$2:$D$800=$A11)*(Données!$E$2:$E$800="CAPEX")*(Données!$L$2:$L$800=$B11)*ISNUMBER(Données!$T$2:$T$800)*(Données!$AA$2:$AA$800=1))/(COUNTIFS(Données!$C$2:$C$800,Données!$C$2:$C$800,Données!$D$2:$D$800,Données!$D$2:$D$800,Données!$E$2:$E$800,Données!$E$2:$E$800,Données!$L$2:$L$800,Données!$L$2:$L$800,Données!$AA$2:$AA$800,Données!$AA$2:$AA$800)+(Données!$C$2:$C$800=""))) -> 3 | E11: {=IF(C11=0,"—",MIN(IF((Données!$D$2:$D$800=$A11)*(Données!$E$2:$E$800="CAPEX")*(Données!$L$2:$L$800=$B11)*ISNUMBER(Données!$T$2:$T$800)*(Données!$AA$2:$AA$800=1),Données!$T$2:$T$800)))} -> 1907.025 | F11: {=IF(C11=0,"—",MEDIAN(IF((Données!$D$2:$D$800=$A11)*(Données!$E$2:$E$800="CAPEX")*(Données!$L$2:$L$800=$B11)*ISNUMBER(Données!$T$2:$T$800)*(Données!$AA$2:$AA$800=1),Données!$T$2:$T$800)))} -> 3167.4468 | G11: {=IF(C11=0,"—",MAX(IF((Données!$D$2:$D$800=$A11)*(Données!$E$2:$E$800="CAPEX")*(Données!$L$2:$L$800=$B11)*ISNUMBER(Données!$T$2:$T$800)*(Données!$AA$2:$AA$800=1),Données!$T$2:$T$800)))} -> 3462.4 | H11: {=IF(SUMPRODUCT((Données!$D$2:$D$800=$A11)*(Données!$E$2:$E$800="CAPEX")*(Données!$L$2:$L$800=$B11)*ISNUMBER(Données!$S$2:$S$800)*(Données!$AA$2:$AA$800=1))=0,"—",MIN(IF((Données!$D$2:$D$800=$A11)*(Données!$E$2:$E$800="CAPEX")*(Données!$L$2:$L$800=$B11)*ISNUMBER(Données!$S$2:$S$800)*(Données!$AA$2:$AA$800=1),Données!$S$2:$S$800)))} -> — | I11: {=IF(SUMPRODUCT((Données!$D$2:$D$800=$A11)*(Données!$E$2:$E$800="CAPEX")*(Données!$L$2:$L$800=$B11)*ISNUMBER(Données!$U$2:$U$800)*(Données!$AA$2:$AA$800=1))=0,"—",MAX(IF((Données!$D$2:$D$800=$A11)*(Données!$E$2:$E$800="CAPEX")*(Données!$L$2:$L$800=$B11)*ISNUMBER(Données!$U$2:$U$800)*(Données!$AA$2:$AA$800=1),Données!$U$2:$U$800)))} -> — | J11: =SUMPRODUCT((Données!$D$2:$D$800=$A11)*(Données!$E$2:$E$800="Rendement (PCI)")*(Données!$L$2:$L$800=$B11)*ISNUMBER(Données!$T$2:$T$800)*(Données!$AA$2:$AA$800=1)) -> 2 | K11: =SUMPRODUCT(((Données!$D$2:$D$800=$A11)*(Données!$E$2:$E$800="Rendement (PCI)")*(Données!$L$2:$L$800=$B11)*ISNUMBER(Données!$T$2:$T$800)*(Données!$AA$2:$AA$800=1))/(COUNTIFS(Données!$C$2:$C$800,Données!$C$2:$C$800,Données!$D$2:$D$800,Données!$D$2:$D$800,Données!$E$2:$E$800,Données!$E$2:$E$800,Données!$L$2:$L$800,Données!$L$2:$L$800,Données!$AA$2:$AA$800,Données!$AA$2:$AA$800)+(Données!$C$2:$C$800=""))) -> 2 | L11: {=IF(J11=0,"—",MIN(IF((Données!$D$2:$D$800=$A11)*(Données!$E$2:$E$800="Rendement (PCI)")*(Données!$L$2:$L$800=$B11)*ISNUMBER(Données!$T$2:$T$800)*(Données!$AA$2:$AA$800=1),Données!$T$2:$T$800)))} -> 81 | M11: {=IF(J11=0,"—",MEDIAN(IF((Données!$D$2:$D$800=$A11)*(Données!$E$2:$E$800="Rendement (PCI)")*(Données!$L$2:$L$800=$B11)*ISNUMBER(Données!$T$2:$T$800)*(Données!$AA$2:$AA$800=1),Données!$T$2:$T$800)))} -> 82 | N11: {=IF(J11=0,"—",MAX(IF((Données!$D$2:$D$800=$A11)*(Données!$E$2:$E$800="Rendement (PCI)")*(Données!$L$2:$L$800=$B11)*ISNUMBER(Données!$T$2:$T$800)*(Données!$AA$2:$AA$800=1),Données!$T$2:$T$800)))} -> 83
A12: SOEC | B12: 2030 | C12: =SUMPRODUCT((Données!$D$2:$D$800=$A12)*(Données!$E$2:$E$800="CAPEX")*(Données!$L$2:$L$800=$B12)*ISNUMBER(Données!$T$2:$T$800)*(Données!$AA$2:$AA$800=1)) -> 5 | D12: =SUMPRODUCT(((Données!$D$2:$D$800=$A12)*(Données!$E$2:$E$800="CAPEX")*(Données!$L$2:$L$800=$B12)*ISNUMBER(Données!$T$2:$T$800)*(Données!$AA$2:$AA$800=1))/(COUNTIFS(Données!$C$2:$C$800,Données!$C$2:$C$800,Données!$D$2:$D$800,Données!$D$2:$D$800,Données!$E$2:$E$800,Données!$E$2:$E$800,Données!$L$2:$L$800,Données!$L$2:$L$800,Données!$AA$2:$AA$800,Données!$AA$2:$AA$800)+(Données!$C$2:$C$800=""))) -> 5 | E12: {=IF(C12=0,"—",MIN(IF((Données!$D$2:$D$800=$A12)*(Données!$E$2:$E$800="CAPEX")*(Données!$L$2:$L$800=$B12)*ISNUMBER(Données!$T$2:$T$800)*(Données!$AA$2:$AA$800=1),Données!$T$2:$T$800)))} -> 904.9848 | F12: {=IF(C12=0,"—",MEDIAN(IF((Données!$D$2:$D$800=$A12)*(Données!$E$2:$E$800="CAPEX")*(Données!$L$2:$L$800=$B12)*ISNUMBER(Données!$T$2:$T$800)*(Données!$AA$2:$AA$800=1),Données!$T$2:$T$800)))} -> 1082 | G12: {=IF(C12=0,"—",MAX(IF((Données!$D$2:$D$800=$A12)*(Données!$E$2:$E$800="CAPEX")*(Données!$L$2:$L$800=$B12)*ISNUMBER(Données!$T$2:$T$800)*(Données!$AA$2:$AA$800=1),Données!$T$2:$T$800)))} -> 2215.936 | H12: {=IF(SUMPRODUCT((Données!$D$2:$D$800=$A12)*(Données!$E$2:$E$800="CAPEX")*(Données!$L$2:$L$800=$B12)*ISNUMBER(Données!$S$2:$S$800)*(Données!$AA$2:$AA$800=1))=0,"—",MIN(IF((Données!$D$2:$D$800=$A12)*(Données!$E$2:$E$800="CAPEX")*(Données!$L$2:$L$800=$B12)*ISNUMBER(Données!$S$2:$S$800)*(Données!$AA$2:$AA$800=1),Données!$S$2:$S$800)))} -> — | I12: {=IF(SUMPRODUCT((Données!$D$2:$D$800=$A12)*(Données!$E$2:$E$800="CAPEX")*(Données!$L$2:$L$800=$B12)*ISNUMBER(Données!$U$2:$U$800)*(Données!$AA$2:$AA$800=1))=0,"—",MAX(IF((Données!$D$2:$D$800=$A12)*(Données!$E$2:$E$800="CAPEX")*(Données!$L$2:$L$800=$B12)*ISNUMBER(Données!$U$2:$U$800)*(Données!$AA$2:$AA$800=1),Données!$U$2:$U$800)))} -> — | J12: =SUMPRODUCT((Données!$D$2:$D$800=$A12)*(Données!$E$2:$E$800="Rendement (PCI)")*(Données!$L$2:$L$800=$B12)*ISNUMBER(Données!$T$2:$T$800)*(Données!$AA$2:$AA$800=1)) -> 3 | K12: =SUMPRODUCT(((Données!$D$2:$D$800=$A12)*(Données!$E$2:$E$800="Rendement (PCI)")*(Données!$L$2:$L$800=$B12)*ISNUMBER(Données!$T$2:$T$800)*(Données!$AA$2:$AA$800=1))/(COUNTIFS(Données!$C$2:$C$800,Données!$C$2:$C$800,Données!$D$2:$D$800,Données!$D$2:$D$800,Données!$E$2:$E$800,Données!$E$2:$E$800,Données!$L$2:$L$800,Données!$L$2:$L$800,Données!$AA$2:$AA$800,Données!$AA$2:$AA$800)+(Données!$C$2:$C$800=""))) -> 3 | L12: {=IF(J12=0,"—",MIN(IF((Données!$D$2:$D$800=$A12)*(Données!$E$2:$E$800="Rendement (PCI)")*(Données!$L$2:$L$800=$B12)*ISNUMBER(Données!$T$2:$T$800)*(Données!$AA$2:$AA$800=1),Données!$T$2:$T$800)))} -> 81 | M12: {=IF(J12=0,"—",MEDIAN(IF((Données!$D$2:$D$800=$A12)*(Données!$E$2:$E$800="Rendement (PCI)")*(Données!$L$2:$L$800=$B12)*ISNUMBER(Données!$T$2:$T$800)*(Données!$AA$2:$AA$800=1),Données!$T$2:$T$800)))} -> 84 | N12: {=IF(J12=0,"—",MAX(IF((Données!$D$2:$D$800=$A12)*(Données!$E$2:$E$800="Rendement (PCI)")*(Données!$L$2:$L$800=$B12)*ISNUMBER(Données!$T$2:$T$800)*(Données!$AA$2:$AA$800=1),Données!$T$2:$T$800)))} -> 84.4
A13: SOEC | B13: 2050 | C13: =SUMPRODUCT((Données!$D$2:$D$800=$A13)*(Données!$E$2:$E$800="CAPEX")*(Données!$L$2:$L$800=$B13)*ISNUMBER(Données!$T$2:$T$800)*(Données!$AA$2:$AA$800=1)) -> 2 | D13: =SUMPRODUCT(((Données!$D$2:$D$800=$A13)*(Données!$E$2:$E$800="CAPEX")*(Données!$L$2:$L$800=$B13)*ISNUMBER(Données!$T$2:$T$800)*(Données!$AA$2:$AA$800=1))/(COUNTIFS(Données!$C$2:$C$800,Données!$C$2:$C$800,Données!$D$2:$D$800,Données!$D$2:$D$800,Données!$E$2:$E$800,Données!$E$2:$E$800,Données!$L$2:$L$800,Données!$L$2:$L$800,Données!$AA$2:$AA$800,Données!$AA$2:$AA$800)+(Données!$C$2:$C$800=""))) -> 2 | E13: {=IF(C13=0,"—",MIN(IF((Données!$D$2:$D$800=$A13)*(Données!$E$2:$E$800="CAPEX")*(Données!$L$2:$L$800=$B13)*ISNUMBER(Données!$T$2:$T$800)*(Données!$AA$2:$AA$800=1),Données!$T$2:$T$800)))} -> 565.6155 | F13: {=IF(C13=0,"—",MEDIAN(IF((Données!$D$2:$D$800=$A13)*(Données!$E$2:$E$800="CAPEX")*(Données!$L$2:$L$800=$B13)*ISNUMBER(Données!$T$2:$T$800)*(Données!$AA$2:$AA$800=1),Données!$T$2:$T$800)))} -> 698.29575 | G13: {=IF(C13=0,"—",MAX(IF((Données!$D$2:$D$800=$A13)*(Données!$E$2:$E$800="CAPEX")*(Données!$L$2:$L$800=$B13)*ISNUMBER(Données!$T$2:$T$800)*(Données!$AA$2:$AA$800=1),Données!$T$2:$T$800)))} -> 830.976 | H13: {=IF(SUMPRODUCT((Données!$D$2:$D$800=$A13)*(Données!$E$2:$E$800="CAPEX")*(Données!$L$2:$L$800=$B13)*ISNUMBER(Données!$S$2:$S$800)*(Données!$AA$2:$AA$800=1))=0,"—",MIN(IF((Données!$D$2:$D$800=$A13)*(Données!$E$2:$E$800="CAPEX")*(Données!$L$2:$L$800=$B13)*ISNUMBER(Données!$S$2:$S$800)*(Données!$AA$2:$AA$800=1),Données!$S$2:$S$800)))} -> — | I13: {=IF(SUMPRODUCT((Données!$D$2:$D$800=$A13)*(Données!$E$2:$E$800="CAPEX")*(Données!$L$2:$L$800=$B13)*ISNUMBER(Données!$U$2:$U$800)*(Données!$AA$2:$AA$800=1))=0,"—",MAX(IF((Données!$D$2:$D$800=$A13)*(Données!$E$2:$E$800="CAPEX")*(Données!$L$2:$L$800=$B13)*ISNUMBER(Données!$U$2:$U$800)*(Données!$AA$2:$AA$800=1),Données!$U$2:$U$800)))} -> — | J13: =SUMPRODUCT((Données!$D$2:$D$800=$A13)*(Données!$E$2:$E$800="Rendement (PCI)")*(Données!$L$2:$L$800=$B13)*ISNUMBER(Données!$T$2:$T$800)*(Données!$AA$2:$AA$800=1)) -> 1 | K13: =SUMPRODUCT(((Données!$D$2:$D$800=$A13)*(Données!$E$2:$E$800="Rendement (PCI)")*(Données!$L$2:$L$800=$B13)*ISNUMBER(Données!$T$2:$T$800)*(Données!$AA$2:$AA$800=1))/(COUNTIFS(Données!$C$2:$C$800,Données!$C$2:$C$800,Données!$D$2:$D$800,Données!$D$2:$D$800,Données!$E$2:$E$800,Données!$E$2:$E$800,Données!$L$2:$L$800,Données!$L$2:$L$800,Données!$AA$2:$AA$800,Données!$AA$2:$AA$800)+(Données!$C$2:$C$800=""))) -> 1 | L13: {=IF(J13=0,"—",MIN(IF((Données!$D$2:$D$800=$A13)*(Données!$E$2:$E$800="Rendement (PCI)")*(Données!$L$2:$L$800=$B13)*ISNUMBER(Données!$T$2:$T$800)*(Données!$AA$2:$AA$800=1),Données!$T$2:$T$800)))} -> 90 | M13: {=IF(J13=0,"—",MEDIAN(IF((Données!$D$2:$D$800=$A13)*(Données!$E$2:$E$800="Rendement (PCI)")*(Données!$L$2:$L$800=$B13)*ISNUMBER(Données!$T$2:$T$800)*(Données!$AA$2:$AA$800=1),Données!$T$2:$T$800)))} -> 90 | N13: {=IF(J13=0,"—",MAX(IF((Données!$D$2:$D$800=$A13)*(Données!$E$2:$E$800="Rendement (PCI)")*(Données!$L$2:$L$800=$B13)*ISNUMBER(Données!$T$2:$T$800)*(Données!$AA$2:$AA$800=1),Données!$T$2:$T$800)))} -> 90
A15: Lecture : « — » = aucune valeur pour cette combinaison. Le rendement vient surtout de Potsdam (Efficiency_LHV, base PCI) et d'un point du micro-réseau. Les lignes exclues (Secondary_Source) se règlent dans Hypothèses. L'horizon « actuel » dépend de la plage fixée dans Hypothèses.

Sheet Lacunes
A1: Lacunes : nombre de sources distinctes par paramètre et par technologie
A2: Compte aussi les lignes « Tous ». Objectif : au moins 2 sources par paramètre prioritaire. « Où chercher » reprend l'étape 8 du plan.
A4: Paramètre | B4: Alcalin | C4: PEM | D4: SOEC | E4: Statut global | F4: Où chercher
A5: CAPEX | B5: =SUMPRODUCT((((Données!$D$2:$D$800=B$4)+(Données!$D$2:$D$800="Tous")>0)*(Données!$E$2:$E$800=$A5)*((Données!$T$2:$T$800<>"")*ISNUMBER(Données!$T$2:$T$800))*(Données!$AA$2:$AA$800=1))/(COUNTIFS(Données!$C$2:$C$800,Données!$C$2:$C$800,Données!$E$2:$E$800,Données!$E$2:$E$800,Données!$D$2:$D$800,Données!$D$2:$D$800,Données!$AA$2:$AA$800,Données!$AA$2:$AA$800)+(Données!$C$2:$C$800=""))) -> 31 | C5: =SUMPRODUCT((((Données!$D$2:$D$800=C$4)+(Données!$D$2:$D$800="Tous")>0)*(Données!$E$2:$E$800=$A5)*((Données!$T$2:$T$800<>"")*ISNUMBER(Données!$T$2:$T$800))*(Données!$AA$2:$AA$800=1))/(COUNTIFS(Données!$C$2:$C$800,Données!$C$2:$C$800,Données!$E$2:$E$800,Données!$E$2:$E$800,Données!$D$2:$D$800,Données!$D$2:$D$800,Données!$AA$2:$AA$800,Données!$AA$2:$AA$800)+(Données!$C$2:$C$800=""))) -> 36 | D5: =SUMPRODUCT((((Données!$D$2:$D$800=D$4)+(Données!$D$2:$D$800="Tous")>0)*(Données!$E$2:$E$800=$A5)*((Données!$T$2:$T$800<>"")*ISNUMBER(Données!$T$2:$T$800))*(Données!$AA$2:$AA$800=1))/(COUNTIFS(Données!$C$2:$C$800,Données!$C$2:$C$800,Données!$E$2:$E$800,Données!$E$2:$E$800,Données!$D$2:$D$800,Données!$D$2:$D$800,Données!$AA$2:$AA$800,Données!$AA$2:$AA$800)+(Données!$C$2:$C$800=""))) -> 5 | E5: =IF(MIN(B5:D5)>=2,"Couvert (≥2 sources)",IF(MAX(B5:D5)=0,"Lacune","À compléter")) -> Couvert (≥2 sources) | F5: Potsdam (à importer) ; déjà Ghadim et Delft
A6: Rendement (PCI) | B6: =SUMPRODUCT((((Données!$D$2:$D$800=B$4)+(Données!$D$2:$D$800="Tous")>0)*(Données!$E$2:$E$800=$A6)*((Données!$T$2:$T$800<>"")*ISNUMBER(Données!$T$2:$T$800))*(Données!$AA$2:$AA$800=1))/(COUNTIFS(Données!$C$2:$C$800,Données!$C$2:$C$800,Données!$E$2:$E$800,Données!$E$2:$E$800,Données!$D$2:$D$800,Données!$D$2:$D$800,Données!$AA$2:$AA$800,Données!$AA$2:$AA$800)+(Données!$C$2:$C$800=""))) -> 8 | C6: =SUMPRODUCT((((Données!$D$2:$D$800=C$4)+(Données!$D$2:$D$800="Tous")>0)*(Données!$E$2:$E$800=$A6)*((Données!$T$2:$T$800<>"")*ISNUMBER(Données!$T$2:$T$800))*(Données!$AA$2:$AA$800=1))/(COUNTIFS(Données!$C$2:$C$800,Données!$C$2:$C$800,Données!$E$2:$E$800,Données!$E$2:$E$800,Données!$D$2:$D$800,Données!$D$2:$D$800,Données!$AA$2:$AA$800,Données!$AA$2:$AA$800)+(Données!$C$2:$C$800=""))) -> 8 | D6: =SUMPRODUCT((((Données!$D$2:$D$800=D$4)+(Données!$D$2:$D$800="Tous")>0)*(Données!$E$2:$E$800=$A6)*((Données!$T$2:$T$800<>"")*ISNUMBER(Données!$T$2:$T$800))*(Données!$AA$2:$AA$800=1))/(COUNTIFS(Données!$C$2:$C$800,Données!$C$2:$C$800,Données!$E$2:$E$800,Données!$E$2:$E$800,Données!$D$2:$D$800,Données!$D$2:$D$800,Données!$AA$2:$AA$800,Données!$AA$2:$AA$800)+(Données!$C$2:$C$800=""))) -> 4 | E6: =IF(MIN(B6:D6)>=2,"Couvert (≥2 sources)",IF(MAX(B6:D6)=0,"Lacune","À compléter")) -> Couvert (≥2 sources) | F6: Potsdam, Efficiency_LHV (à importer)
A7: OPEX annuel | B7: =SUMPRODUCT((((Données!$D$2:$D$800=B$4)+(Données!$D$2:$D$800="Tous")>0)*(Données!$E$2:$E$800=$A7)*((Données!$T$2:$T$800<>"")*ISNUMBER(Données!$T$2:$T$800))*(Données!$AA$2:$AA$800=1))/(COUNTIFS(Données!$C$2:$C$800,Données!$C$2:$C$800,Données!$E$2:$E$800,Données!$E$2:$E$800,Données!$D$2:$D$800,Données!$D$2:$D$800,Données!$AA$2:$AA$800,Données!$AA$2:$AA$800)+(Données!$C$2:$C$800=""))) -> 0 | C7: =SUMPRODUCT((((Données!$D$2:$D$800=C$4)+(Données!$D$2:$D$800="Tous")>0)*(Données!$E$2:$E$800=$A7)*((Données!$T$2:$T$800<>"")*ISNUMBER(Données!$T$2:$T$800))*(Données!$AA$2:$AA$800=1))/(COUNTIFS(Données!$C$2:$C$800,Données!$C$2:$C$800,Données!$E$2:$E$800,Données!$E$2:$E$800,Données!$D$2:$D$800,Données!$D$2:$D$800,Données!$AA$2:$AA$800,Données!$AA$2:$AA$800)+(Données!$C$2:$C$800=""))) -> 1 | D7: =SUMPRODUCT((((Données!$D$2:$D$800=D$4)+(Données!$D$2:$D$800="Tous")>0)*(Données!$E$2:$E$800=$A7)*((Données!$T$2:$T$800<>"")*ISNUMBER(Données!$T$2:$T$800))*(Données!$AA$2:$AA$800=1))/(COUNTIFS(Données!$C$2:$C$800,Données!$C$2:$C$800,Données!$E$2:$E$800,Données!$E$2:$E$800,Données!$D$2:$D$800,Données!$D$2:$D$800,Données!$AA$2:$AA$800,Données!$AA$2:$AA$800)+(Données!$C$2:$C$800=""))) -> 0 | E7: =IF(MIN(B7:D7)>=2,"Couvert (≥2 sources)",IF(MAX(B7:D7)=0,"Lacune","À compléter")) -> À compléter | F7: IRENA, IEA, NREL
A8: Charge minimale | B8: =SUMPRODUCT((((Données!$D$2:$D$800=B$4)+(Données!$D$2:$D$800="Tous")>0)*(Données!$E$2:$E$800=$A8)*((Données!$T$2:$T$800<>"")*ISNUMBER(Données!$T$2:$T$800))*(Données!$AA$2:$AA$800=1))/(COUNTIFS(Données!$C$2:$C$800,Données!$C$2:$C$800,Données!$E$2:$E$800,Données!$E$2:$E$800,Données!$D$2:$D$800,Données!$D$2:$D$800,Données!$AA$2:$AA$800,Données!$AA$2:$AA$800)+(Données!$C$2:$C$800=""))) -> 0 | C8: =SUMPRODUCT((((Données!$D$2:$D$800=C$4)+(Données!$D$2:$D$800="Tous")>0)*(Données!$E$2:$E$800=$A8)*((Données!$T$2:$T$800<>"")*ISNUMBER(Données!$T$2:$T$800))*(Données!$AA$2:$AA$800=1))/(COUNTIFS(Données!$C$2:$C$800,Données!$C$2:$C$800,Données!$E$2:$E$800,Données!$E$2:$E$800,Données!$D$2:$D$800,Données!$D$2:$D$800,Données!$AA$2:$AA$800,Données!$AA$2:$AA$800)+(Données!$C$2:$C$800=""))) -> 1 | D8: =SUMPRODUCT((((Données!$D$2:$D$800=D$4)+(Données!$D$2:$D$800="Tous")>0)*(Données!$E$2:$E$800=$A8)*((Données!$T$2:$T$800<>"")*ISNUMBER(Données!$T$2:$T$800))*(Données!$AA$2:$AA$800=1))/(COUNTIFS(Données!$C$2:$C$800,Données!$C$2:$C$800,Données!$E$2:$E$800,Données!$E$2:$E$800,Données!$D$2:$D$800,Données!$D$2:$D$800,Données!$AA$2:$AA$800,Données!$AA$2:$AA$800)+(Données!$C$2:$C$800=""))) -> 0 | E8: =IF(MIN(B8:D8)>=2,"Couvert (≥2 sources)",IF(MAX(B8:D8)=0,"Lacune","À compléter")) -> À compléter | F8: Fiches constructeurs : Nel, Sunfire, Siemens Energy, Thyssenkrupp Nucera, Plug, Cummins
A9: Durée de vie | B9: =SUMPRODUCT((((Données!$D$2:$D$800=B$4)+(Données!$D$2:$D$800="Tous")>0)*(Données!$E$2:$E$800=$A9)*((Données!$T$2:$T$800<>"")*ISNUMBER(Données!$T$2:$T$800))*(Données!$AA$2:$AA$800=1))/(COUNTIFS(Données!$C$2:$C$800,Données!$C$2:$C$800,Données!$E$2:$E$800,Données!$E$2:$E$800,Données!$D$2:$D$800,Données!$D$2:$D$800,Données!$AA$2:$AA$800,Données!$AA$2:$AA$800)+(Données!$C$2:$C$800=""))) -> 0 | C9: =SUMPRODUCT((((Données!$D$2:$D$800=C$4)+(Données!$D$2:$D$800="Tous")>0)*(Données!$E$2:$E$800=$A9)*((Données!$T$2:$T$800<>"")*ISNUMBER(Données!$T$2:$T$800))*(Données!$AA$2:$AA$800=1))/(COUNTIFS(Données!$C$2:$C$800,Données!$C$2:$C$800,Données!$E$2:$E$800,Données!$E$2:$E$800,Données!$D$2:$D$800,Données!$D$2:$D$800,Données!$AA$2:$AA$800,Données!$AA$2:$AA$800)+(Données!$C$2:$C$800=""))) -> 1 | D9: =SUMPRODUCT((((Données!$D$2:$D$800=D$4)+(Données!$D$2:$D$800="Tous")>0)*(Données!$E$2:$E$800=$A9)*((Données!$T$2:$T$800<>"")*ISNUMBER(Données!$T$2:$T$800))*(Données!$AA$2:$AA$800=1))/(COUNTIFS(Données!$C$2:$C$800,Données!$C$2:$C$800,Données!$E$2:$E$800,Données!$E$2:$E$800,Données!$D$2:$D$800,Données!$D$2:$D$800,Données!$AA$2:$AA$800,Données!$AA$2:$AA$800)+(Données!$C$2:$C$800=""))) -> 0 | E9: =IF(MIN(B9:D9)>=2,"Couvert (≥2 sources)",IF(MAX(B9:D9)=0,"Lacune","À compléter")) -> À compléter | F9: Fiches constructeurs (durée de vie du stack en heures) ; IRENA
A10: Coût de remplacement | B10: =SUMPRODUCT((((Données!$D$2:$D$800=B$4)+(Données!$D$2:$D$800="Tous")>0)*(Données!$E$2:$E$800=$A10)*((Données!$T$2:$T$800<>"")*ISNUMBER(Données!$T$2:$T$800))*(Données!$AA$2:$AA$800=1))/(COUNTIFS(Données!$C$2:$C$800,Données!$C$2:$C$800,Données!$E$2:$E$800,Données!$E$2:$E$800,Données!$D$2:$D$800,Données!$D$2:$D$800,Données!$AA$2:$AA$800,Données!$AA$2:$AA$800)+(Données!$C$2:$C$800=""))) -> 0 | C10: =SUMPRODUCT((((Données!$D$2:$D$800=C$4)+(Données!$D$2:$D$800="Tous")>0)*(Données!$E$2:$E$800=$A10)*((Données!$T$2:$T$800<>"")*ISNUMBER(Données!$T$2:$T$800))*(Données!$AA$2:$AA$800=1))/(COUNTIFS(Données!$C$2:$C$800,Données!$C$2:$C$800,Données!$E$2:$E$800,Données!$E$2:$E$800,Données!$D$2:$D$800,Données!$D$2:$D$800,Données!$AA$2:$AA$800,Données!$AA$2:$AA$800)+(Données!$C$2:$C$800=""))) -> 1 | D10: =SUMPRODUCT((((Données!$D$2:$D$800=D$4)+(Données!$D$2:$D$800="Tous")>0)*(Données!$E$2:$E$800=$A10)*((Données!$T$2:$T$800<>"")*ISNUMBER(Données!$T$2:$T$800))*(Données!$AA$2:$AA$800=1))/(COUNTIFS(Données!$C$2:$C$800,Données!$C$2:$C$800,Données!$E$2:$E$800,Données!$E$2:$E$800,Données!$D$2:$D$800,Données!$D$2:$D$800,Données!$AA$2:$AA$800,Données!$AA$2:$AA$800)+(Données!$C$2:$C$800=""))) -> 0 | E10: =IF(MIN(B10:D10)>=2,"Couvert (≥2 sources)",IF(MAX(B10:D10)=0,"Lacune","À compléter")) -> À compléter | F10: Articles technico-économiques ; fiches constructeurs
A11: Consommation d'eau | B11: =SUMPRODUCT((((Données!$D$2:$D$800=B$4)+(Données!$D$2:$D$800="Tous")>0)*(Données!$E$2:$E$800=$A11)*((Données!$T$2:$T$800<>"")*ISNUMBER(Données!$T$2:$T$800))*(Données!$AA$2:$AA$800=1))/(COUNTIFS(Données!$C$2:$C$800,Données!$C$2:$C$800,Données!$E$2:$E$800,Données!$E$2:$E$800,Données!$D$2:$D$800,Données!$D$2:$D$800,Données!$AA$2:$AA$800,Données!$AA$2:$AA$800)+(Données!$C$2:$C$800=""))) -> 1 | C11: =SUMPRODUCT((((Données!$D$2:$D$800=C$4)+(Données!$D$2:$D$800="Tous")>0)*(Données!$E$2:$E$800=$A11)*((Données!$T$2:$T$800<>"")*ISNUMBER(Données!$T$2:$T$800))*(Données!$AA$2:$AA$800=1))/(COUNTIFS(Données!$C$2:$C$800,Données!$C$2:$C$800,Données!$E$2:$E$800,Données!$E$2:$E$800,Données!$D$2:$D$800,Données!$D$2:$D$800,Données!$AA$2:$AA$800,Données!$AA$2:$AA$800)+(Données!$C$2:$C$800=""))) -> 1 | D11: =SUMPRODUCT((((Données!$D$2:$D$800=D$4)+(Données!$D$2:$D$800="Tous")>0)*(Données!$E$2:$E$800=$A11)*((Données!$T$2:$T$800<>"")*ISNUMBER(Données!$T$2:$T$800))*(Données!$AA$2:$AA$800=1))/(COUNTIFS(Données!$C$2:$C$800,Données!$C$2:$C$800,Données!$E$2:$E$800,Données!$E$2:$E$800,Données!$D$2:$D$800,Données!$D$2:$D$800,Données!$AA$2:$AA$800,Données!$AA$2:$AA$800)+(Données!$C$2:$C$800=""))) -> 1 | E11: =IF(MIN(B11:D11)>=2,"Couvert (≥2 sources)",IF(MAX(B11:D11)=0,"Lacune","À compléter")) -> À compléter | F11: Article de revue (valeur mesurée) vs 9 L/kg théorique
A12: Consommation compresseur | B12: =SUMPRODUCT((((Données!$D$2:$D$800=B$4)+(Données!$D$2:$D$800="Tous")>0)*(Données!$E$2:$E$800=$A12)*((Données!$T$2:$T$800<>"")*ISNUMBER(Données!$T$2:$T$800))*(Données!$AA$2:$AA$800=1))/(COUNTIFS(Données!$C$2:$C$800,Données!$C$2:$C$800,Données!$E$2:$E$800,Données!$E$2:$E$800,Données!$D$2:$D$800,Données!$D$2:$D$800,Données!$AA$2:$AA$800,Données!$AA$2:$AA$800)+(Données!$C$2:$C$800=""))) -> 1 | C12: =SUMPRODUCT((((Données!$D$2:$D$800=C$4)+(Données!$D$2:$D$800="Tous")>0)*(Données!$E$2:$E$800=$A12)*((Données!$T$2:$T$800<>"")*ISNUMBER(Données!$T$2:$T$800))*(Données!$AA$2:$AA$800=1))/(COUNTIFS(Données!$C$2:$C$800,Données!$C$2:$C$800,Données!$E$2:$E$800,Données!$E$2:$E$800,Données!$D$2:$D$800,Données!$D$2:$D$800,Données!$AA$2:$AA$800,Données!$AA$2:$AA$800)+(Données!$C$2:$C$800=""))) -> 1 | D12: =SUMPRODUCT((((Données!$D$2:$D$800=D$4)+(Données!$D$2:$D$800="Tous")>0)*(Données!$E$2:$E$800=$A12)*((Données!$T$2:$T$800<>"")*ISNUMBER(Données!$T$2:$T$800))*(Données!$AA$2:$AA$800=1))/(COUNTIFS(Données!$C$2:$C$800,Données!$C$2:$C$800,Données!$E$2:$E$800,Données!$E$2:$E$800,Données!$D$2:$D$800,Données!$D$2:$D$800,Données!$AA$2:$AA$800,Données!$AA$2:$AA$800)+(Données!$C$2:$C$800=""))) -> 1 | E12: =IF(MIN(B12:D12)>=2,"Couvert (≥2 sources)",IF(MAX(B12:D12)=0,"Lacune","À compléter")) -> À compléter | F12: Fiches constructeurs ; articles de revue
A13: CO₂ cycle de vie | B13: =SUMPRODUCT((((Données!$D$2:$D$800=B$4)+(Données!$D$2:$D$800="Tous")>0)*(Données!$E$2:$E$800=$A13)*((Données!$T$2:$T$800<>"")*ISNUMBER(Données!$T$2:$T$800))*(Données!$AA$2:$AA$800=1))/(COUNTIFS(Données!$C$2:$C$800,Données!$C$2:$C$800,Données!$E$2:$E$800,Données!$E$2:$E$800,Données!$D$2:$D$800,Données!$D$2:$D$800,Données!$AA$2:$AA$800,Données!$AA$2:$AA$800)+(Données!$C$2:$C$800=""))) -> 0 | C13: =SUMPRODUCT((((Données!$D$2:$D$800=C$4)+(Données!$D$2:$D$800="Tous")>0)*(Données!$E$2:$E$800=$A13)*((Données!$T$2:$T$800<>"")*ISNUMBER(Données!$T$2:$T$800))*(Données!$AA$2:$AA$800=1))/(COUNTIFS(Données!$C$2:$C$800,Données!$C$2:$C$800,Données!$E$2:$E$800,Données!$E$2:$E$800,Données!$D$2:$D$800,Données!$D$2:$D$800,Données!$AA$2:$AA$800,Données!$AA$2:$AA$800)+(Données!$C$2:$C$800=""))) -> 0 | D13: =SUMPRODUCT((((Données!$D$2:$D$800=D$4)+(Données!$D$2:$D$800="Tous")>0)*(Données!$E$2:$E$800=$A13)*((Données!$T$2:$T$800<>"")*ISNUMBER(Données!$T$2:$T$800))*(Données!$AA$2:$AA$800=1))/(COUNTIFS(Données!$C$2:$C$800,Données!$C$2:$C$800,Données!$E$2:$E$800,Données!$E$2:$E$800,Données!$D$2:$D$800,Données!$D$2:$D$800,Données!$AA$2:$AA$800,Données!$AA$2:$AA$800)+(Données!$C$2:$C$800=""))) -> 0 | E13: =IF(MIN(B13:D13)>=2,"Couvert (≥2 sources)",IF(MAX(B13:D13)=0,"Lacune","À compléter")) -> Lacune | F13: Articles ACV sur la fabrication d'électrolyseurs
A14: TRL | B14: =SUMPRODUCT((((Données!$D$2:$D$800=B$4)+(Données!$D$2:$D$800="Tous")>0)*(Données!$E$2:$E$800=$A14)*((Données!$T$2:$T$800<>"")*ISNUMBER(Données!$T$2:$T$800))*(Données!$AA$2:$AA$800=1))/(COUNTIFS(Données!$C$2:$C$800,Données!$C$2:$C$800,Données!$E$2:$E$800,Données!$E$2:$E$800,Données!$D$2:$D$800,Données!$D$2:$D$800,Données!$AA$2:$AA$800,Données!$AA$2:$AA$800)+(Données!$C$2:$C$800=""))) -> 0 | C14: =SUMPRODUCT((((Données!$D$2:$D$800=C$4)+(Données!$D$2:$D$800="Tous")>0)*(Données!$E$2:$E$800=$A14)*((Données!$T$2:$T$800<>"")*ISNUMBER(Données!$T$2:$T$800))*(Données!$AA$2:$AA$800=1))/(COUNTIFS(Données!$C$2:$C$800,Données!$C$2:$C$800,Données!$E$2:$E$800,Données!$E$2:$E$800,Données!$D$2:$D$800,Données!$D$2:$D$800,Données!$AA$2:$AA$800,Données!$AA$2:$AA$800)+(Données!$C$2:$C$800=""))) -> 0 | D14: =SUMPRODUCT((((Données!$D$2:$D$800=D$4)+(Données!$D$2:$D$800="Tous")>0)*(Données!$E$2:$E$800=$A14)*((Données!$T$2:$T$800<>"")*ISNUMBER(Données!$T$2:$T$800))*(Données!$AA$2:$AA$800=1))/(COUNTIFS(Données!$C$2:$C$800,Données!$C$2:$C$800,Données!$E$2:$E$800,Données!$E$2:$E$800,Données!$D$2:$D$800,Données!$D$2:$D$800,Données!$AA$2:$AA$800,Données!$AA$2:$AA$800)+(Données!$C$2:$C$800=""))) -> 0 | E14: =IF(MIN(B14:D14)>=2,"Couvert (≥2 sources)",IF(MAX(B14:D14)=0,"Lacune","À compléter")) -> Lacune | F14: IEA Global Hydrogen Review

Sheet Interface
A1: Interface du bloc électrolyseur (représentation systémique et modèle Python LCOF / émissions)
A3: Catégorie | B3: Variable | C3: Unité | D3: Origine dans ce classeur | E3: Commentaire
A4: Entrée | B4: Puissance électrique absorbée | C4: kW | D4: — | E4: Pilotée par le bloc production / réseau
A5: Entrée | B5: Eau | C5: L/h | D5: Paramètre « Consommation d'eau » | E5: 9 L/kg H2 théorique ; consommation mesurée à trouver
A6: Sortie | B6: Hydrogène produit | C6: kg/h | D6: Rendement (PCI) | E6: H2 = P × rendement / PCI(H2) ; PCI H2 = 120 MJ/kg
A7: Sortie | B7: Oxygène | C7: kg/h | D7: Stœchiométrie | E7: ≈ 8 kg O2 par kg H2
A8: Sortie | B8: Chaleur | C8: kW | D8: Rendement | E8: Chaleur fatale = P × (1 − rendement)
A9: Paramètre | B9: CAPEX | C9: USD 2024/kW | D9: Synthèse / Données
A10: Paramètre | B10: OPEX | C10: % du CAPEX par an | D10: Données (Microgrid ; à compléter) | E10: Une seule source pour l'instant
A11: Paramètre | B11: Rendement | C11: % (PCI) | D11: Synthèse / Données | E11: Potsdam à importer
A12: Paramètre | B12: Charge minimale | C12: % de la puissance nominale | D12: Données (Microgrid ; à compléter) | E12: Une seule source pour l'instant
A13: Paramètre | B13: Durée de vie | C13: années (et heures de stack) | D13: Données (Microgrid ; à compléter) | E13: Durée en heures : fiches constructeurs
A14: Paramètre | B14: Coût de remplacement | C14: % du CAPEX | D14: Données (Microgrid) | E14: Une seule source pour l'instant

Sheet Déploiement
A1: Année | B1: Statut | C1: Technologie | D1: Capacité (fichier reçu) | E1: Capacité reconstruite | F1: Contrôle | G1: Source | H1: Unité | J1: Note
A2: 1965 | B2: Concept | C2: Alcalin | D2: 0 | E2: =IF(D2>1000000,D2/1000000000000000,IF(AND(D2>=1000,D2<1000000),D2/1000,D2)) -> 0 | F2: =IF(E2=D2,"tel quel","reconstruit") -> tel quel | G2: IEA Hydrogen Projects Database 2024 (via Delft) | H2: à confirmer (MW supposé) | J2: Le fichier deploiement_1.xlsx contient des capacités aberrantes (ex. 6,1E+16) : la virgule décimale a été perdue à l'import (25,828 devenu 2,58E+16 ; 30,988 devenu 30988).
A3: 1965 | B3: Etude de faisabilité | C3: Alcalin | D3: 0 | E3: =IF(D3>1000000,D3/1000000000000000,IF(AND(D3>=1000,D3<1000000),D3/1000,D3)) -> 0 | F3: =IF(E3=D3,"tel quel","reconstruit") -> tel quel | G3: IEA Hydrogen Projects Database 2024 (via Delft) | H3: à confirmer (MW supposé) | J3: La colonne « reconstruite » divise par 1E15 les valeurs > 1E6 et par 1 000 la valeur 30988 (2018, alcalin, opérationnel). Règle déduite des motifs, pas confirmée.
A4: 1965 | B4: FID/Construction | C4: Alcalin | D4: 0 | E4: =IF(D4>1000000,D4/1000000000000000,IF(AND(D4>=1000,D4<1000000),D4/1000,D4)) -> 0 | F4: =IF(E4=D4,"tel quel","reconstruit") -> tel quel | G4: IEA Hydrogen Projects Database 2024 (via Delft) | H4: à confirmer (MW supposé) | J4: Les séries ne sont pas monotones (alcalin opérationnel : 60,4 en 2020 puis 21,7 en 2021) : à comparer avec le fichier DEPLOYMENT_DATA.xlsx d'origine avant tout usage.
A5: 1965 | B5: Opérationnel | C5: Alcalin | D5: 25 | E5: =IF(D5>1000000,D5/1000000000000000,IF(AND(D5>=1000,D5<1000000),D5/1000,D5)) -> 25 | F5: =IF(E5=D5,"tel quel","reconstruit") -> tel quel | G5: IEA Hydrogen Projects Database 2024 (via Delft) | H5: à confirmer (MW supposé) | J5: Source indiquée : IEA Hydrogen Projects Database 2024 (via Delft).
A6: 2000 | B6: Concept | C6: Alcalin | D6: 0 | E6: =IF(D6>1000000,D6/1000000000000000,IF(AND(D6>=1000,D6<1000000),D6/1000,D6)) -> 0 | F6: =IF(E6=D6,"tel quel","reconstruit") -> tel quel | G6: IEA Hydrogen Projects Database 2024 (via Delft) | H6: à confirmer (MW supposé)
A7: 2000 | B7: Etude de faisabilité | C7: Alcalin | D7: 0 | E7: =IF(D7>1000000,D7/1000000000000000,IF(AND(D7>=1000,D7<1000000),D7/1000,D7)) -> 0 | F7: =IF(E7=D7,"tel quel","reconstruit") -> tel quel | G7: IEA Hydrogen Projects Database 2024 (via Delft) | H7: à confirmer (MW supposé)
A8: 2000 | B8: FID/Construction | C8: Alcalin | D8: 0 | E8: =IF(D8>1000000,D8/1000000000000000,IF(AND(D8>=1000,D8<1000000),D8/1000,D8)) -> 0 | F8: =IF(E8=D8,"tel quel","reconstruit") -> tel quel | G8: IEA Hydrogen Projects Database 2024 (via Delft) | H8: à confirmer (MW supposé)
A9: 2000 | B9: Opérationnel | C9: Alcalin | D9: 25 | E9: =IF(D9>1000000,D9/1000000000000000,IF(AND(D9>=1000,D9<1000000),D9/1000,D9)) -> 25 | F9: =IF(E9=D9,"tel quel","reconstruit") -> tel quel | G9: IEA Hydrogen Projects Database 2024 (via Delft) | H9: à confirmer (MW supposé)
A10: 2007 | B10: Concept | C10: Alcalin | D10: 0 | E10: =IF(D10>1000000,D10/1000000000000000,IF(AND(D10>=1000,D10<1000000),D10/1000,D10)) -> 0 | F10: =IF(E10=D10,"tel quel","reconstruit") -> tel quel | G10: IEA Hydrogen Projects Database 2024 (via Delft) | H10: à confirmer (MW supposé)
A11: 2007 | B11: Etude de faisabilité | C11: Alcalin | D11: 0 | E11: =IF(D11>1000000,D11/1000000000000000,IF(AND(D11>=1000,D11<1000000),D11/1000,D11)) -> 0 | F11: =IF(E11=D11,"tel quel","reconstruit") -> tel quel | G11: IEA Hydrogen Projects Database 2024 (via Delft) | H11: à confirmer (MW supposé)
A12: 2007 | B12: FID/Construction | C12: Alcalin | D12: 0 | E12: =IF(D12>1000000,D12/1000000000000000,IF(AND(D12>=1000,D12<1000000),D12/1000,D12)) -> 0 | F12: =IF(E12=D12,"tel quel","reconstruit") -> tel quel | G12: IEA Hydrogen Projects Database 2024 (via Delft) | H12: à confirmer (MW supposé)
A13: 2007 | B13: Opérationnel | C13: Alcalin | D13: 25 | E13: =IF(D13>1000000,D13/1000000000000000,IF(AND(D13>=1000,D13<1000000),D13/1000,D13)) -> 25 | F13: =IF(E13=D13,"tel quel","reconstruit") -> tel quel | G13: IEA Hydrogen Projects Database 2024 (via Delft) | H13: à confirmer (MW supposé)
A14: 2008 | B14: Concept | C14: Alcalin | D14: 0 | E14: =IF(D14>1000000,D14/1000000000000000,IF(AND(D14>=1000,D14<1000000),D14/1000,D14)) -> 0 | F14: =IF(E14=D14,"tel quel","reconstruit") -> tel quel | G14: IEA Hydrogen Projects Database 2024 (via Delft) | H14: à confirmer (MW supposé)
A15: 2008 | B15: Etude de faisabilité | C15: Alcalin | D15: 0 | E15: =IF(D15>1000000,D15/1000000000000000,IF(AND(D15>=1000,D15<1000000),D15/1000,D15)) -> 0 | F15: =IF(E15=D15,"tel quel","reconstruit") -> tel quel | G15: IEA Hydrogen Projects Database 2024 (via Delft) | H15: à confirmer (MW supposé)
A16: 2008 | B16: FID/Construction | C16: Alcalin | D16: 0 | E16: =IF(D16>1000000,D16/1000000000000000,IF(AND(D16>=1000,D16<1000000),D16/1000,D16)) -> 0 | F16: =IF(E16=D16,"tel quel","reconstruit") -> tel quel | G16: IEA Hydrogen Projects Database 2024 (via Delft) | H16: à confirmer (MW supposé)
A17: 2008 | B17: Opérationnel | C17: Alcalin | D17: 25 | E17: =IF(D17>1000000,D17/1000000000000000,IF(AND(D17>=1000,D17<1000000),D17/1000,D17)) -> 25 | F17: =IF(E17=D17,"tel quel","reconstruit") -> tel quel | G17: IEA Hydrogen Projects Database 2024 (via Delft) | H17: à confirmer (MW supposé)
... A177: 2030 | B177: Opérationnel | C177: PEM | D177: 2.1941959e+16 | E177: =IF(D177>1000000,D177/1000000000000000,IF(AND(D177>=1000,D177<1000000),D177/1000,D177)) -> 21.941959 | F177: =IF(E177=D177,"tel quel","reconstruit") -> reconstruit | G177: IEA Hydrogen Projects Database 2024 (via Delft) | H177: à confirmer (MW supposé)
